{"type": "Feature", "id": 22231963, "geometry": {"type": "Point", "coordinates": [6.8682, 50.93766]}, "properties": {"woe:id": 22231963, "woe:parent_id": 667931, "woe:name": "U Junkersdorf Bahnhof", "woe:placetype": 20, "woe:placetype_name": "POI", "woe:lang": "GER", "iso:country": "DE", "meta:provider": ["geoplanet:7.3.1", "geoplanet:7.3.2", "geoplanet:7.4.0", "geoplanet:7.4.1", "geoplanet:7.5.1", "geoplanet:7.5.2", "geoplanet:7.6.0", "geoplanet:7.8.1", "geoplanet:7.9.0", "geoplanet:7.10.0", "geoplanet:8.0.0", "woeplanet:8.0.0"], "meta:indexed": "2020-08-20T20:51:40.966593", "meta:updated": "2020-10-14T11:50:57.269476", "woe:alias_ENG_P": ["U Junkersdorf Station"], "woe:hierarchy": {"continent": 24865675, "country": 23424829, "town": 0, "planet": 1, "county": 12597059, "suburb": 0, "state": 2345487, "region": 0, "localadmin": 26822762}, "woe:timezone_id": 28350890, "woe:hash": "u1hcu2cm2sj1", "woe:centroid": [6.8682, 50.93766], "geom:latitude": 50.93766, "geom:longitude": 6.8682, "geom:hash": "u1hcu2cm2sj1", "woe:latitude": 50.93766, "geom:centroid": [6.8682, 50.93766], "woe:longitude": 6.8682, "woe:repo": "woeplanet-poi-de", "geom:area": 0.0, "woe:scale": 19}}