{"type": "Feature", "id": 22242555, "geometry": {"type": "Point", "coordinates": [7.77074, 48.152]}, "properties": {"woe:id": 22242555, "woe:parent_id": 673622, "woe:name": "Riegel Bahnhof", "woe:placetype": 20, "woe:placetype_name": "POI", "woe:lang": "GER", "iso:country": "DE", "meta:provider": ["geoplanet:7.3.1", "geoplanet:7.3.2", "geoplanet:7.4.0", "geoplanet:7.4.1", "geoplanet:7.5.1", "geoplanet:7.5.2", "geoplanet:7.6.0", "geoplanet:7.8.1", "geoplanet:7.9.0", "geoplanet:7.10.0", "geoplanet:8.0.0", "woeplanet:8.0.0"], "meta:indexed": "2020-08-20T20:51:41.493359", "meta:updated": "2020-10-14T11:50:57.528275", "woe:alias_ENG_P": ["Riegel Station"], "woe:hierarchy": {"continent": 24865675, "country": 23424829, "town": 0, "planet": 1, "county": 12596970, "suburb": 0, "state": 2345481, "region": 0, "localadmin": 12623373}, "woe:timezone_id": 28350890, "woe:hash": "u0t9bvf3xr7s", "woe:centroid": [7.77074, 48.152], "geom:latitude": 48.152, "geom:longitude": 7.77074, "geom:hash": "u0t9bvf3xr7s", "woe:latitude": 48.152, "geom:centroid": [7.77074, 48.152], "woe:longitude": 7.77074, "woe:repo": "woeplanet-poi-de", "geom:area": 0.0, "woe:scale": 19}}