{"type": "Feature", "id": 22286269, "geometry": {"type": "Point", "coordinates": [7.11942, 49.951302]}, "properties": {"woe:id": 22286269, "woe:parent_id": 29349086, "woe:name": "Traben-Trarbach Bahnhof", "woe:placetype": 20, "woe:placetype_name": "POI", "woe:lang": "GER", "iso:country": "DE", "meta:provider": ["geoplanet:7.3.1", "geoplanet:7.3.2", "geoplanet:7.4.0", "geoplanet:7.4.1", "geoplanet:7.5.1", "geoplanet:7.5.2", "geoplanet:7.6.0", "geoplanet:7.8.1", "geoplanet:7.9.0", "geoplanet:7.10.0", "geoplanet:8.0.0", "woeplanet:8.0.0"], "meta:indexed": "2020-08-20T20:51:43.177163", "meta:updated": "2020-10-14T11:50:59.486339", "woe:alias_ENG_P": ["Traben-Trarbach Station"], "woe:hierarchy": {"continent": 24865675, "country": 23424829, "town": 0, "planet": 1, "county": 12597031, "suburb": 0, "state": 2345488, "region": 0, "localadmin": 12628976}, "woe:timezone_id": 28350890, "woe:hash": "u0vh4j25qt86", "woe:centroid": [7.11942, 49.951302], "geom:latitude": 49.951302, "geom:longitude": 7.11942, "geom:hash": "u0vh4j25qt86", "woe:latitude": 49.951302, "geom:centroid": [7.11942, 49.951302], "woe:longitude": 7.11942, "woe:repo": "woeplanet-poi-de", "geom:area": 0.0, "woe:scale": 19}}