{"type": "Feature", "id": 22243028, "geometry": {"type": "Point", "coordinates": [8.46565, 49.487549]}, "properties": {"woe:id": 22243028, "woe:parent_id": 673711, "woe:name": "Mannheim-Paradeplatz Bahnhof", "woe:placetype": 20, "woe:placetype_name": "POI", "woe:lang": "GER", "iso:country": "DE", "meta:provider": ["geoplanet:7.3.1", "geoplanet:7.3.2", "geoplanet:7.4.0", "geoplanet:7.4.1", "geoplanet:7.5.1", "geoplanet:7.5.2", "geoplanet:7.6.0", "geoplanet:7.8.1", "geoplanet:7.9.0", "geoplanet:7.10.0", "geoplanet:8.0.0", "woeplanet:8.0.0"], "meta:indexed": "2020-08-20T20:51:41.503530", "meta:updated": "2020-10-14T11:50:58.477782", "woe:alias_ENG_P": ["Mannheim-Paradeplatz Station"], "woe:hierarchy": {"continent": 24865675, "country": 23424829, "town": 0, "planet": 1, "county": 12597108, "suburb": 0, "state": 2345481, "region": 0, "localadmin": 26823003}, "woe:timezone_id": 28350890, "woe:hash": "u0y188umzgy0", "woe:centroid": [8.46565, 49.487549], "geom:latitude": 49.487549, "geom:longitude": 8.46565, "geom:hash": "u0y188umzgy0", "woe:latitude": 49.487549, "geom:centroid": [8.46565, 49.487549], "woe:longitude": 8.46565, "woe:repo": "woeplanet-poi-de", "geom:area": 0.0, "woe:scale": 19}}