{"type": "Feature", "id": 22266463, "properties": {"woe:id": 22266463, "woe:parent_id": 639950, "woe:name": "B\u00f6hringen-Rickelshausen Bahnhof", "woe:placetype": 20, "woe:placetype_name": "POI", "woe:lang": "GER", "iso:country": "DE", "meta:provider": ["geoplanet:7.3.1", "geoplanet:7.3.2", "geoplanet:7.4.0", "geoplanet:7.4.1", "geoplanet:7.5.1", "geoplanet:7.5.2", "geoplanet:7.6.0", "geoplanet:7.8.1", "geoplanet:7.9.0", "geoplanet:7.10.0", "geoplanet:8.0.0", "woeplanet:8.0.0"], "meta:indexed": "2020-08-20T20:51:42.329436", "meta:updated": "2020-08-22T01:51:41.089324", "woe:alias_ENG_S": ["Bohringen-Rickelshausen Station"], "woe:alias_GER_S": ["Boehringen-Rickelshausen Bahnhof", "Bohringen-Rickelshausen Bahnhof"], "woe:alias_ENG_P": ["Bohringen-Rickelshausen Station"], "woe:hierarchy": {"continent": 24865675, "country": 23424829, "town": 0, "planet": 1, "county": 12596692, "suburb": 0, "state": 2345481, "region": 0, "localadmin": 12623526}, "woe:timezone_id": 28350890, "woe:hash": "u0qreh6zrk4u", "woe:centroid": [8.92499, 47.749222], "geom:latitude": 47.749222, "geom:longitude": 8.92499, "geom:hash": "u0qreh6zrk4u", "woe:latitude": 47.749222, "geom:centroid": [8.92499, 47.749222], "woe:longitude": 8.92499, "woe:repo": "woeplanet-poi-de"}, "geometry": {"coordinates": [8.92499, 47.749222], "type": "Point"}}