{"type": "Feature", "id": 22194568, "geometry": {"type": "Point", "coordinates": [6.94284, 51.483608]}, "properties": {"woe:id": 22194568, "woe:parent_id": 648820, "woe:name": "Essen-Gerschede Bahnhof", "woe:placetype": 20, "woe:placetype_name": "POI", "woe:lang": "GER", "iso:country": "DE", "meta:provider": ["geoplanet:7.3.1", "geoplanet:7.3.2", "geoplanet:7.4.0", "geoplanet:7.4.1", "geoplanet:7.5.1", "geoplanet:7.5.2", "geoplanet:7.6.0", "geoplanet:7.8.1", "geoplanet:7.9.0", "geoplanet:7.10.0", "geoplanet:8.0.0", "woeplanet:8.0.0"], "meta:indexed": "2020-08-20T20:51:39.537771", "meta:updated": "2020-10-14T11:50:27.639010", "woe:alias_ENG_P": ["Essen-Gerschede Station"], "woe:hierarchy": {"continent": 24865675, "country": 23424829, "town": 0, "planet": 1, "county": 12597009, "suburb": 0, "state": 2345487, "region": 0, "localadmin": 26822341}, "woe:timezone_id": 28350890, "woe:hash": "u1huvur9gbhs", "woe:centroid": [6.94284, 51.483608], "geom:latitude": 51.483608, "geom:longitude": 6.94284, "geom:hash": "u1huvur9gbhs", "woe:latitude": 51.483608, "geom:centroid": [6.94284, 51.483608], "woe:longitude": 6.94284, "woe:repo": "woeplanet-poi-de", "geom:area": 0.0, "woe:scale": 19}}