{"type": "Feature", "id": 56055753, "geometry": {"type": "Point", "coordinates": [6.43985, 51.179131]}, "properties": {"woe:id": 56055753, "woe:parent_id": 675922, "woe:name": "Hochschule Niederrhein", "woe:placetype": 20, "woe:placetype_name": "POI", "woe:lang": "GER", "iso:country": "DE", "meta:provider": ["geoplanet:7.3.1", "geoplanet:7.3.2", "geoplanet:7.4.0", "geoplanet:7.4.1", "geoplanet:7.5.1", "geoplanet:7.5.2", "geoplanet:7.6.0", "geoplanet:7.8.1", "geoplanet:7.9.0", "geoplanet:7.10.0", "geoplanet:8.0.0", "woeplanet:8.0.0"], "meta:indexed": "2020-08-20T20:51:45.982839", "meta:updated": "2020-10-14T11:50:35.534061", "woe:hierarchy": {"continent": 24865675, "country": 23424829, "town": 0, "planet": 1, "county": 12596896, "suburb": 0, "state": 2345487, "region": 0, "localadmin": 26823040}, "woe:timezone_id": 28350890, "woe:hash": "u1he4sck53s0", "woe:centroid": [6.43985, 51.179131], "geom:latitude": 51.179131, "geom:longitude": 6.43985, "geom:hash": "u1he4sck53s0", "woe:latitude": 51.179131, "geom:centroid": [6.43985, 51.179131], "woe:longitude": 6.43985, "woe:repo": "woeplanet-poi-de", "geom:area": 0.0, "woe:scale": 19}}