{"type": "Feature", "id": 22171700, "geometry": {"type": "Point", "coordinates": [12.96034, 47.651588]}, "properties": {"woe:id": 22171700, "woe:parent_id": 639254, "woe:name": "Bischofswiesen Bahnhof", "woe:placetype": 20, "woe:placetype_name": "POI", "woe:lang": "GER", "iso:country": "DE", "meta:provider": ["geoplanet:7.3.1", "geoplanet:7.3.2", "geoplanet:7.4.0", "geoplanet:7.4.1", "geoplanet:7.5.1", "geoplanet:7.5.2", "geoplanet:7.6.0", "geoplanet:7.8.1", "geoplanet:7.9.0", "geoplanet:7.10.0", "geoplanet:8.0.0", "woeplanet:8.0.0"], "meta:indexed": "2020-08-20T20:51:38.510540", "meta:updated": "2020-10-14T11:50:27.227069", "woe:alias_ENG_P": ["Bischofswiesen Station"], "woe:hierarchy": {"continent": 24865675, "country": 23424829, "town": 0, "planet": 1, "county": 12596739, "suburb": 0, "state": 2345482, "region": 0, "localadmin": 12622722}, "woe:timezone_id": 28350890, "woe:hash": "u23pnftqtgcf", "woe:centroid": [12.96034, 47.651588], "geom:latitude": 47.651588, "geom:longitude": 12.96034, "geom:hash": "u23pnftqtgcf", "woe:latitude": 47.651588, "geom:centroid": [12.96034, 47.651588], "woe:longitude": 12.96034, "woe:repo": "woeplanet-poi-de", "geom:area": 0.0, "woe:scale": 19}}