{"type": "Feature", "id": 22286485, "properties": {"woe:id": 22286485, "woe:parent_id": 699981, "woe:name": "Treuen Bahnhof", "woe:placetype": 20, "woe:placetype_name": "POI", "woe:lang": "GER", "iso:country": "DE", "meta:provider": ["geoplanet:7.3.1", "geoplanet:7.3.2", "geoplanet:7.4.0", "geoplanet:7.4.1", "geoplanet:7.5.1", "geoplanet:7.5.2", "geoplanet:7.6.0", "geoplanet:7.8.1", "geoplanet:7.9.0", "geoplanet:7.10.0", "geoplanet:8.0.0", "woeplanet:8.0.0"], "meta:indexed": "2020-08-20T20:51:43.192363", "meta:updated": "2020-08-22T01:51:41.444553", "woe:alias_ENG_P": ["Treuen Station"], "woe:hierarchy": {"continent": 24865675, "country": 23424829, "town": 0, "planet": 1, "county": 22526000, "suburb": 0, "state": 2345493, "region": 0, "localadmin": 12636512}, "woe:timezone_id": 28350890, "woe:hash": "u2bxxcyqur4x", "woe:centroid": [12.30247, 50.54792], "geom:latitude": 50.54792, "geom:longitude": 12.30247, "geom:hash": "u2bxxcyqur4x", "woe:latitude": 50.54792, "geom:centroid": [12.30247, 50.54792], "woe:longitude": 12.30247, "woe:repo": "woeplanet-poi-de"}, "geometry": {"coordinates": [12.30247, 50.54792], "type": "Point"}}