{"type": "Feature", "id": 22190410, "geometry": {"type": "Point", "coordinates": [6.84273, 51.200062]}, "properties": {"woe:id": 22190410, "woe:parent_id": 646099, "woe:name": "U Alt Eller Bahnhof", "woe:placetype": 20, "woe:placetype_name": "POI", "woe:lang": "GER", "iso:country": "DE", "meta:provider": ["geoplanet:7.3.1", "geoplanet:7.3.2", "geoplanet:7.4.0", "geoplanet:7.4.1", "geoplanet:7.5.1", "geoplanet:7.5.2", "geoplanet:7.6.0", "geoplanet:7.8.1", "geoplanet:7.9.0", "geoplanet:7.10.0", "geoplanet:8.0.0", "woeplanet:8.0.0"], "meta:indexed": "2020-08-20T20:51:39.300810", "meta:updated": "2020-10-14T11:50:27.769962", "woe:alias_ENG_P": ["U Alt Eller Station"], "woe:hierarchy": {"continent": 24865675, "country": 23424829, "town": 0, "planet": 1, "county": 12596700, "suburb": 0, "state": 2345487, "region": 0, "localadmin": 26822282}, "woe:timezone_id": 28350890, "woe:hash": "u1hg78wtzpm6", "woe:centroid": [6.84273, 51.200062], "geom:latitude": 51.200062, "geom:longitude": 6.84273, "geom:hash": "u1hg78wtzpm6", "woe:latitude": 51.200062, "geom:centroid": [6.84273, 51.200062], "woe:longitude": 6.84273, "woe:repo": "woeplanet-poi-de", "geom:area": 0.0, "woe:scale": 19}}