{"type": "Feature", "id": 23007569, "properties": {"woe:id": 23007569, "woe:parent_id": 709028, "woe:name": "Heimatmuseum Haus Morgensonne", "woe:placetype": 20, "woe:placetype_name": "POI", "woe:lang": "GER", "iso:country": "DE", "meta:provider": ["geoplanet:7.3.1", "geoplanet:7.3.2", "geoplanet:7.4.0", "geoplanet:7.4.1", "geoplanet:7.5.1", "geoplanet:7.5.2", "geoplanet:7.6.0", "geoplanet:7.8.1", "geoplanet:7.9.0", "geoplanet:7.10.0", "geoplanet:8.0.0", "woeplanet:8.0.0"], "meta:indexed": "2020-08-20T20:51:45.413782", "meta:updated": "2020-08-22T01:51:42.603444", "woe:hierarchy": {"continent": 24865675, "country": 23424829, "town": 0, "planet": 1, "county": 12596758, "suburb": 0, "state": 2345492, "region": 0, "localadmin": 12635744}, "woe:timezone_id": 28350890, "woe:hash": "u39j8tger7rn", "woe:centroid": [12.68335, 54.436459], "geom:latitude": 54.436459, "geom:longitude": 12.68335, "geom:hash": "u39j8tger7rn", "woe:latitude": 54.436459, "geom:centroid": [12.68335, 54.436459], "woe:longitude": 12.68335, "woe:repo": "woeplanet-poi-de"}, "geometry": {"coordinates": [12.68335, 54.436459], "type": "Point"}}