{"type": "Feature", "id": 22255645, "geometry": {"type": "Point", "coordinates": [13.02321, 50.863171]}, "properties": {"woe:id": 22255645, "woe:parent_id": 679991, "woe:name": "Niederwiesa Bahnhof", "woe:placetype": 20, "woe:placetype_name": "POI", "woe:lang": "GER", "iso:country": "DE", "meta:provider": ["geoplanet:7.3.1", "geoplanet:7.3.2", "geoplanet:7.4.0", "geoplanet:7.4.1", "geoplanet:7.5.1", "geoplanet:7.5.2", "geoplanet:7.6.0", "geoplanet:7.8.1", "geoplanet:7.9.0", "geoplanet:7.10.0", "geoplanet:8.0.0", "woeplanet:8.0.0"], "meta:indexed": "2020-08-20T20:51:41.935669", "meta:updated": "2020-10-14T11:50:59.793943", "woe:alias_ENG_P": ["Niederwiesa Station"], "woe:hierarchy": {"continent": 24865675, "country": 23424829, "town": 0, "planet": 1, "county": 56448168, "suburb": 0, "state": 2345493, "region": 0, "localadmin": 12636318}, "woe:timezone_id": 28350890, "woe:hash": "u3132775qy31", "woe:centroid": [13.02321, 50.863171], "geom:latitude": 50.863171, "geom:longitude": 13.02321, "geom:hash": "u3132775qy31", "woe:latitude": 50.863171, "geom:centroid": [13.02321, 50.863171], "woe:longitude": 13.02321, "woe:repo": "woeplanet-poi-de", "geom:area": 0.0, "woe:scale": 19}}