{"type": "Feature", "id": 22221253, "geometry": {"type": "Point", "coordinates": [13.57429, 51.49839]}, "properties": {"woe:id": 22221253, "woe:parent_id": 661241, "woe:name": "Hohenleipisch Bahnhof", "woe:placetype": 20, "woe:placetype_name": "POI", "woe:lang": "GER", "iso:country": "DE", "meta:provider": ["geoplanet:7.3.1", "geoplanet:7.3.2", "geoplanet:7.4.0", "geoplanet:7.4.1", "geoplanet:7.5.1", "geoplanet:7.5.2", "geoplanet:7.6.0", "geoplanet:7.8.1", "geoplanet:7.9.0", "geoplanet:7.10.0", "geoplanet:8.0.0", "woeplanet:8.0.0"], "meta:indexed": "2020-08-20T20:51:40.553137", "meta:updated": "2020-10-14T11:50:57.561430", "woe:alias_ENG_P": ["Hohenleipisch Station"], "woe:hierarchy": {"continent": 24865675, "country": 23424829, "town": 0, "planet": 1, "county": 12596891, "suburb": 0, "state": 2345491, "region": 0, "localadmin": 12633088}, "woe:timezone_id": 28350890, "woe:hash": "u31suyurzgsn", "woe:centroid": [13.57429, 51.49839], "geom:latitude": 51.49839, "geom:longitude": 13.57429, "geom:hash": "u31suyurzgsn", "woe:latitude": 51.49839, "geom:centroid": [13.57429, 51.49839], "woe:longitude": 13.57429, "woe:repo": "woeplanet-poi-de", "geom:area": 0.0, "woe:scale": 19}}