{"type": "Feature", "id": 22239169, "properties": {"woe:id": 22239169, "woe:parent_id": 672536, "woe:name": "Lohr Bahnhof", "woe:placetype": 20, "woe:placetype_name": "POI", "woe:lang": "GER", "iso:country": "DE", "meta:provider": ["geoplanet:7.3.1", "geoplanet:7.3.2", "geoplanet:7.4.0", "geoplanet:7.4.1", "geoplanet:7.5.1", "geoplanet:7.5.2", "geoplanet:7.6.0", "geoplanet:7.8.1", "geoplanet:7.9.0", "geoplanet:7.10.0", "geoplanet:8.0.0", "woeplanet:8.0.0"], "meta:indexed": "2020-08-20T20:51:41.352953", "meta:updated": "2020-08-22T01:51:40.701271", "woe:hierarchy": {"continent": 24865675, "country": 23424829, "town": 0, "planet": 1, "county": 12596810, "suburb": 0, "state": 2345482, "region": 0, "localadmin": 12636137}, "woe:timezone_id": 28350890, "woe:hash": "u0yu6nbw990e", "woe:centroid": [9.58083, 50.004021], "geom:latitude": 50.004021, "geom:longitude": 9.58083, "geom:hash": "u0yu6nbw990e", "woe:latitude": 50.004021, "geom:centroid": [9.58083, 50.004021], "woe:longitude": 9.58083, "woe:repo": "woeplanet-poi-de"}, "geometry": {"coordinates": [9.58083, 50.004021], "type": "Point"}}