{"type": "Feature", "id": 22161174, "geometry": {"type": "Point", "coordinates": [8.78412, 49.357948]}, "properties": {"woe:id": 22161174, "woe:parent_id": 636775, "woe:name": "Heimatmuseum Bammental", "woe:placetype": 20, "woe:placetype_name": "POI", "woe:lang": "GER", "iso:country": "DE", "meta:provider": ["geoplanet:7.3.1", "geoplanet:7.3.2", "geoplanet:7.4.0", "geoplanet:7.4.1", "geoplanet:7.5.1", "geoplanet:7.5.2", "geoplanet:7.6.0", "geoplanet:7.8.1", "geoplanet:7.9.0", "geoplanet:7.10.0", "geoplanet:8.0.0", "woeplanet:8.0.0"], "meta:indexed": "2020-08-20T20:51:38.187028", "meta:updated": "2020-10-14T11:50:27.917248", "woe:hierarchy": {"continent": 24865675, "country": 23424829, "town": 0, "planet": 1, "county": 12596830, "suburb": 0, "state": 2345481, "region": 0, "localadmin": 12623952}, "woe:timezone_id": 28350890, "woe:hash": "u0y0zck6uu6s", "woe:centroid": [8.78412, 49.357948], "geom:latitude": 49.357948, "geom:longitude": 8.78412, "geom:hash": "u0y0zck6uu6s", "woe:latitude": 49.357948, "geom:centroid": [8.78412, 49.357948], "woe:longitude": 8.78412, "woe:repo": "woeplanet-poi-de", "geom:area": 0.0, "woe:scale": 19}}