{"type": "Feature", "id": 22966999, "properties": {"woe:id": 22966999, "woe:parent_id": 26821894, "woe:name": "Krumme Lanke Bahnhof", "woe:placetype": 20, "woe:placetype_name": "POI", "woe:lang": "GER", "iso:country": "DE", "meta:provider": ["geoplanet:7.3.1", "geoplanet:7.3.2", "geoplanet:7.4.0", "geoplanet:7.4.1", "geoplanet:7.5.1", "geoplanet:7.5.2", "geoplanet:7.6.0", "geoplanet:7.8.1", "geoplanet:7.9.0", "geoplanet:7.10.0", "geoplanet:8.0.0", "woeplanet:8.0.0"], "meta:indexed": "2020-08-20T20:51:44.692685", "meta:updated": "2020-08-22T01:51:42.192571", "woe:alias_ENG_P": ["Krumme Lanke Station"], "woe:hierarchy": {"continent": 24865675, "country": 23424829, "town": 0, "planet": 1, "county": 12596838, "suburb": 0, "state": 2345496, "region": 0, "localadmin": 26821894}, "woe:timezone_id": 28350890, "woe:hash": "u336m6czxgq8", "woe:centroid": [13.24127, 52.443169], "geom:latitude": 52.443169, "geom:longitude": 13.24127, "geom:hash": "u336m6czxgq8", "woe:latitude": 52.443169, "geom:centroid": [13.24127, 52.443169], "woe:longitude": 13.24127, "woe:repo": "woeplanet-poi-de"}, "geometry": {"coordinates": [13.24127, 52.443169], "type": "Point"}}