{"type": "Feature", "id": 22266582, "properties": {"woe:id": 22266582, "woe:parent_id": 686690, "woe:name": "Raisting Bahnhof", "woe:placetype": 20, "woe:placetype_name": "POI", "woe:lang": "GER", "iso:country": "DE", "meta:provider": ["geoplanet:7.3.1", "geoplanet:7.3.2", "geoplanet:7.4.0", "geoplanet:7.4.1", "geoplanet:7.5.1", "geoplanet:7.5.2", "geoplanet:7.6.0", "geoplanet:7.8.1", "geoplanet:7.9.0", "geoplanet:7.10.0", "geoplanet:8.0.0", "woeplanet:8.0.0"], "meta:indexed": "2020-08-20T20:51:42.335403", "meta:updated": "2020-08-22T01:51:41.091544", "woe:alias_ENG_P": ["Raisting Station"], "woe:hierarchy": {"continent": 24865675, "country": 23424829, "town": 0, "planet": 1, "county": 12596765, "suburb": 0, "state": 2345482, "region": 0, "localadmin": 12634709}, "woe:timezone_id": 28350890, "woe:hash": "u0xbsfj4j60m", "woe:centroid": [11.11427, 47.911732], "geom:latitude": 47.911732, "geom:longitude": 11.11427, "geom:hash": "u0xbsfj4j60m", "woe:latitude": 47.911732, "geom:centroid": [11.11427, 47.911732], "woe:longitude": 11.11427, "woe:repo": "woeplanet-poi-de"}, "geometry": {"coordinates": [11.11427, 47.911732], "type": "Point"}}