{"type": "Feature", "id": 22291957, "geometry": {"type": "Point", "coordinates": [9.9059, 49.478191]}, "properties": {"woe:id": 22291957, "woe:parent_id": 704661, "woe:name": "Weikersheim Bahnhof", "woe:placetype": 20, "woe:placetype_name": "POI", "woe:lang": "GER", "iso:country": "DE", "meta:provider": ["geoplanet:7.3.1", "geoplanet:7.3.2", "geoplanet:7.4.0", "geoplanet:7.4.1", "geoplanet:7.5.1", "geoplanet:7.5.2", "geoplanet:7.6.0", "geoplanet:7.8.1", "geoplanet:7.9.0", "geoplanet:7.10.0", "geoplanet:8.0.0", "woeplanet:8.0.0"], "meta:indexed": "2020-08-20T20:51:43.508908", "meta:updated": "2020-10-14T11:50:59.354513", "woe:alias_ENG_P": ["Weikersheim Station"], "woe:hierarchy": {"continent": 24865675, "country": 23424829, "town": 0, "planet": 1, "county": 12596849, "suburb": 0, "state": 2345481, "region": 0, "localadmin": 12624185}, "woe:timezone_id": 28350890, "woe:hash": "u0z13rjr25q3", "woe:centroid": [9.9059, 49.478191], "geom:latitude": 49.478191, "geom:longitude": 9.9059, "geom:hash": "u0z13rjr25q3", "woe:latitude": 49.478191, "geom:centroid": [9.9059, 49.478191], "woe:longitude": 9.9059, "woe:repo": "woeplanet-poi-de", "geom:area": 0.0, "woe:scale": 19}}