{"type": "Feature", "id": 22288189, "properties": {"woe:id": 22288189, "woe:parent_id": 701224, "woe:name": "Unterl\u00fc\u00df Bahnhof", "woe:placetype": 20, "woe:placetype_name": "POI", "woe:lang": "GER", "iso:country": "DE", "meta:provider": ["geoplanet:7.3.1", "geoplanet:7.3.2", "geoplanet:7.4.0", "geoplanet:7.4.1", "geoplanet:7.5.1", "geoplanet:7.5.2", "geoplanet:7.6.0", "geoplanet:7.8.1", "geoplanet:7.9.0", "geoplanet:7.10.0", "geoplanet:8.0.0", "woeplanet:8.0.0"], "meta:indexed": "2020-08-20T20:51:43.282827", "meta:updated": "2020-08-22T01:51:41.484675", "woe:alias_ENG_S": ["Unterluss Station"], "woe:alias_GER_S": ["Unterluess Bahnhof", "Unterluss Bahnhof"], "woe:alias_ENG_P": ["Unterluss Station"], "woe:hierarchy": {"continent": 24865675, "country": 23424829, "town": 0, "planet": 1, "county": 12596807, "suburb": 0, "state": 2345486, "region": 0, "localadmin": 12629589}, "woe:timezone_id": 28350890, "woe:hash": "u1rkd65qn1x2", "woe:centroid": [10.29892, 52.83429], "geom:latitude": 52.83429, "geom:longitude": 10.29892, "geom:hash": "u1rkd65qn1x2", "woe:latitude": 52.83429, "geom:centroid": [10.29892, 52.83429], "woe:longitude": 10.29892, "woe:repo": "woeplanet-poi-de"}, "geometry": {"coordinates": [10.29892, 52.83429], "type": "Point"}}