{"type": "Feature", "id": 22265672, "geometry": {"type": "Point", "coordinates": [12.34578, 52.528252]}, "properties": {"woe:id": 22265672, "woe:parent_id": 685908, "woe:name": "Premnitz S\u00fcd Bahnhof", "woe:placetype": 20, "woe:placetype_name": "POI", "woe:lang": "GER", "iso:country": "DE", "meta:provider": ["geoplanet:7.3.1", "geoplanet:7.3.2", "geoplanet:7.4.0", "geoplanet:7.4.1", "geoplanet:7.5.1", "geoplanet:7.5.2", "geoplanet:7.6.0", "geoplanet:7.8.1", "geoplanet:7.9.0", "geoplanet:7.10.0", "geoplanet:8.0.0", "woeplanet:8.0.0"], "meta:indexed": "2020-08-20T20:51:42.274910", "meta:updated": "2020-10-14T11:51:00.060780", "woe:alias_ENG_S": ["Premnitz Sud Station"], "woe:alias_GER_S": ["Premnitz Sued Bahnhof", "Premnitz Sud Bahnhof"], "woe:alias_ENG_P": ["Premnitz Sud Station"], "woe:hierarchy": {"continent": 24865675, "country": 23424829, "town": 0, "planet": 1, "county": 12596986, "suburb": 0, "state": 2345491, "region": 0, "localadmin": 24547248}, "woe:timezone_id": 28350890, "woe:hash": "u32fbfmzjxbu", "woe:centroid": [12.34578, 52.528252], "geom:latitude": 52.528252, "geom:longitude": 12.34578, "geom:hash": "u32fbfmzjxbu", "woe:latitude": 52.528252, "geom:centroid": [12.34578, 52.528252], "woe:longitude": 12.34578, "woe:repo": "woeplanet-poi-de", "geom:area": 0.0, "woe:scale": 19}}