{"type": "Feature", "id": 22229164, "properties": {"woe:id": 22229164, "woe:parent_id": 708752, "woe:name": "Zeppelinheim Bahnhof", "woe:placetype": 20, "woe:placetype_name": "POI", "woe:lang": "GER", "iso:country": "DE", "meta:provider": ["geoplanet:7.3.1", "geoplanet:7.3.2", "geoplanet:7.4.0", "geoplanet:7.4.1", "geoplanet:7.5.1", "geoplanet:7.5.2", "geoplanet:7.6.0", "geoplanet:7.8.1", "geoplanet:7.9.0", "geoplanet:7.10.0", "geoplanet:8.0.0", "woeplanet:8.0.0"], "meta:indexed": "2020-08-20T20:51:40.883867", "meta:updated": "2020-08-22T01:51:40.507235", "woe:alias_ENG_P": ["Zeppelinheim Station"], "woe:hierarchy": {"continent": 24865675, "country": 23424829, "town": 0, "planet": 1, "county": 12597040, "suburb": 0, "state": 2345485, "region": 0, "localadmin": 12632633}, "woe:timezone_id": 28350890, "woe:hash": "u0yheufh7qnw", "woe:centroid": [8.60519, 50.036621], "geom:latitude": 50.036621, "geom:longitude": 8.60519, "geom:hash": "u0yheufh7qnw", "woe:latitude": 50.036621, "geom:centroid": [8.60519, 50.036621], "woe:longitude": 8.60519, "woe:repo": "woeplanet-poi-de"}, "geometry": {"coordinates": [8.60519, 50.036621], "type": "Point"}}