{"type": "Feature", "id": 22250023, "geometry": {"type": "Point", "coordinates": [11.52701, 48.079342]}, "properties": {"woe:id": 22250023, "woe:parent_id": 676757, "woe:name": "M\u00fcnchen-Solln Bahnhof", "woe:placetype": 20, "woe:placetype_name": "POI", "woe:lang": "GER", "iso:country": "DE", "meta:provider": ["geoplanet:7.3.1", "geoplanet:7.3.2", "geoplanet:7.4.0", "geoplanet:7.4.1", "geoplanet:7.5.1", "geoplanet:7.5.2", "geoplanet:7.6.0", "geoplanet:7.8.1", "geoplanet:7.9.0", "geoplanet:7.10.0", "geoplanet:8.0.0", "woeplanet:8.0.0"], "meta:indexed": "2020-08-20T20:51:41.772455", "meta:updated": "2020-10-14T11:50:58.073400", "woe:alias_ENG_S": ["Munchen-Solln Station"], "woe:alias_GER_S": ["Muenchen-Solln Bahnhof", "Munchen-Solln Bahnhof"], "woe:alias_ENG_P": ["Munchen-Solln Station"], "woe:hierarchy": {"continent": 24865675, "country": 23424829, "town": 0, "planet": 1, "county": 20071093, "suburb": 0, "state": 2345482, "region": 0, "localadmin": 26823076}, "woe:timezone_id": 28350890, "woe:hash": "u281w29dqycw", "woe:centroid": [11.52701, 48.079342], "geom:latitude": 48.079342, "geom:longitude": 11.52701, "geom:hash": "u281w29dqycw", "woe:latitude": 48.079342, "geom:centroid": [11.52701, 48.079342], "woe:longitude": 11.52701, "woe:repo": "woeplanet-poi-de", "geom:area": 0.0, "woe:scale": 19}}