{"type": "Feature", "id": 22297566, "properties": {"woe:id": 22297566, "woe:parent_id": 634467, "woe:name": "Altenhasungen Bahnhof", "woe:placetype": 20, "woe:placetype_name": "POI", "woe:lang": "GER", "iso:country": "DE", "meta:provider": ["geoplanet:7.3.1", "geoplanet:7.3.2", "geoplanet:7.4.0", "geoplanet:7.4.1", "geoplanet:7.5.1", "geoplanet:7.5.2", "geoplanet:7.6.0", "geoplanet:7.8.1", "geoplanet:7.9.0", "geoplanet:7.10.0", "geoplanet:8.0.0", "woeplanet:8.0.0"], "meta:indexed": "2020-08-20T20:51:43.720583", "meta:updated": "2020-08-22T01:51:41.709391", "woe:alias_ENG_P": ["Altenhasungen Station"], "woe:hierarchy": {"continent": 24865675, "country": 23424829, "town": 0, "planet": 1, "county": 12596885, "suburb": 0, "state": 2345485, "region": 0, "localadmin": 12632803}, "woe:timezone_id": 28350890, "woe:hash": "u1ns1fy43kj2", "woe:centroid": [9.22583, 51.343639], "geom:latitude": 51.343639, "geom:longitude": 9.22583, "geom:hash": "u1ns1fy43kj2", "woe:latitude": 51.343639, "geom:centroid": [9.22583, 51.343639], "woe:longitude": 9.22583, "woe:repo": "woeplanet-poi-de"}, "geometry": {"coordinates": [9.22583, 51.343639], "type": "Point"}}