{"type": "Feature", "id": 22244645, "properties": {"woe:id": 22244645, "woe:parent_id": 683571, "woe:name": "U Hoterheide Bahnhof", "woe:placetype": 20, "woe:placetype_name": "POI", "woe:lang": "GER", "iso:country": "DE", "meta:provider": ["geoplanet:7.3.1", "geoplanet:7.3.2", "geoplanet:7.4.0", "geoplanet:7.4.1", "geoplanet:7.5.1", "geoplanet:7.5.2", "geoplanet:7.6.0", "geoplanet:7.8.1", "geoplanet:7.9.0", "geoplanet:7.10.0", "geoplanet:8.0.0", "woeplanet:8.0.0"], "meta:indexed": "2020-08-20T20:51:41.573753", "meta:updated": "2020-08-22T01:51:40.782348", "woe:alias_ENG_P": ["U Hoterheide Station"], "woe:hierarchy": {"continent": 24865675, "country": 23424829, "town": 0, "planet": 1, "county": 12596955, "suburb": 0, "state": 2345487, "region": 0, "localadmin": 12624452}, "woe:timezone_id": 28350890, "woe:hash": "u1hewy65wbmc", "woe:centroid": [6.6278, 51.275169], "geom:latitude": 51.275169, "geom:longitude": 6.6278, "geom:hash": "u1hewy65wbmc", "woe:latitude": 51.275169, "geom:centroid": [6.6278, 51.275169], "woe:longitude": 6.6278, "woe:repo": "woeplanet-poi-de"}, "geometry": {"coordinates": [6.6278, 51.275169], "type": "Point"}}