{"type": "Feature", "id": 22210091, "properties": {"woe:id": 22210091, "woe:parent_id": 685410, "woe:name": "Pl\u00fcschow Bahnhof", "woe:placetype": 20, "woe:placetype_name": "POI", "woe:lang": "GER", "iso:country": "DE", "meta:provider": ["geoplanet:7.3.1", "geoplanet:7.3.2", "geoplanet:7.4.0", "geoplanet:7.4.1", "geoplanet:7.5.1", "geoplanet:7.5.2", "geoplanet:7.6.0", "geoplanet:7.8.1", "geoplanet:7.9.0", "geoplanet:7.10.0", "geoplanet:8.0.0", "woeplanet:8.0.0"], "meta:indexed": "2020-08-20T20:51:40.184624", "meta:updated": "2020-08-22T01:51:40.225749", "woe:alias_ENG_S": ["Pluschow Station"], "woe:alias_GER_S": ["Plueschow Bahnhof", "Pluschow Bahnhof"], "woe:alias_ENG_P": ["Pluschow Station"], "woe:hierarchy": {"continent": 24865675, "country": 23424829, "town": 0, "planet": 1, "county": 12596988, "suburb": 0, "state": 2345492, "region": 0, "localadmin": 12631067}, "woe:timezone_id": 28350890, "woe:hash": "u3842b8x6mtg", "woe:centroid": [11.28375, 53.837029], "geom:latitude": 53.837029, "geom:longitude": 11.28375, "geom:hash": "u3842b8x6mtg", "woe:latitude": 53.837029, "geom:centroid": [11.28375, 53.837029], "woe:longitude": 11.28375, "woe:repo": "woeplanet-poi-de"}, "geometry": {"coordinates": [11.28375, 53.837029], "type": "Point"}}