{"type": "Feature", "id": 22980649, "properties": {"woe:id": 22980649, "woe:parent_id": 676423, "woe:name": "M\u00fcgeln Bahnhof", "woe:placetype": 20, "woe:placetype_name": "POI", "woe:lang": "GER", "iso:country": "DE", "meta:provider": ["geoplanet:7.3.1", "geoplanet:7.3.2", "geoplanet:7.4.0", "geoplanet:7.4.1", "geoplanet:7.5.1", "geoplanet:7.5.2", "geoplanet:7.6.0", "geoplanet:7.8.1", "geoplanet:7.9.0", "geoplanet:7.10.0", "geoplanet:8.0.0", "woeplanet:8.0.0"], "meta:indexed": "2020-08-20T20:51:44.964125", "meta:updated": "2020-08-22T01:51:42.348081", "woe:alias_ENG_S": ["Mugeln Station"], "woe:alias_GER_S": ["Muegeln Bahnhof", "Mugeln Bahnhof"], "woe:alias_ENG_P": ["Mugeln Station"], "woe:hierarchy": {"continent": 24865675, "country": 23424829, "town": 0, "planet": 1, "county": 56448170, "suburb": 0, "state": 2345493, "region": 0, "localadmin": 12625715}, "woe:timezone_id": 28350890, "woe:hash": "u3173pk6m9zj", "woe:centroid": [13.05784, 51.236511], "geom:latitude": 51.236511, "geom:longitude": 13.05784, "geom:hash": "u3173pk6m9zj", "woe:latitude": 51.236511, "geom:centroid": [13.05784, 51.236511], "woe:longitude": 13.05784, "woe:repo": "woeplanet-poi-de"}, "geometry": {"coordinates": [13.05784, 51.236511], "type": "Point"}}