{"type": "Feature", "id": 22150798, "properties": {"woe:id": 22150798, "woe:parent_id": 633175, "woe:name": "Couven-Museum", "woe:placetype": 20, "woe:placetype_name": "POI", "woe:lang": "GER", "iso:country": "DE", "meta:provider": ["geoplanet:7.3.1", "geoplanet:7.3.2", "geoplanet:7.4.0", "geoplanet:7.4.1", "geoplanet:7.5.1", "geoplanet:7.5.2", "geoplanet:7.6.0", "geoplanet:7.8.1", "geoplanet:7.9.0", "geoplanet:7.10.0", "geoplanet:8.0.0", "woeplanet:8.0.0"], "meta:indexed": "2020-08-20T20:51:37.815468", "meta:updated": "2020-08-22T01:51:39.027838", "woe:hierarchy": {"continent": 24865675, "country": 23424829, "town": 0, "planet": 1, "county": 20071103, "suburb": 0, "state": 2345487, "region": 0, "localadmin": 26821833}, "woe:timezone_id": 28350890, "woe:hash": "u1h2f7qy9us6", "woe:centroid": [6.08479, 50.775829], "geom:latitude": 50.775829, "geom:longitude": 6.08479, "geom:hash": "u1h2f7qy9us6", "woe:latitude": 50.775829, "geom:centroid": [6.08479, 50.775829], "woe:longitude": 6.08479, "woe:repo": "woeplanet-poi-de"}, "geometry": {"coordinates": [6.08479, 50.775829], "type": "Point"}}