{"type": "Feature", "id": 22203400, "properties": {"woe:id": 22203400, "woe:parent_id": 652038, "woe:name": "Gelsenkirchen-Rotthausen Bahnhof", "woe:placetype": 20, "woe:placetype_name": "POI", "woe:lang": "GER", "iso:country": "DE", "meta:provider": ["geoplanet:7.3.1", "geoplanet:7.3.2", "geoplanet:7.4.0", "geoplanet:7.4.1", "geoplanet:7.5.1", "geoplanet:7.5.2", "geoplanet:7.6.0", "geoplanet:7.8.1", "geoplanet:7.9.0", "geoplanet:7.10.0", "geoplanet:8.0.0", "woeplanet:8.0.0"], "meta:indexed": "2020-08-20T20:51:39.819552", "meta:updated": "2020-08-22T01:51:40.062512", "woe:alias_ENG_P": ["Gelsenkirchen-Rotthausen Station"], "woe:alias_GER_V": ["S-Bahn-Gelsenkirchen-Rotthausen"], "woe:hierarchy": {"continent": 24865675, "country": 23424829, "town": 0, "planet": 1, "county": 12597080, "suburb": 0, "state": 2345487, "region": 0, "localadmin": 26822455}, "woe:timezone_id": 28350890, "woe:hash": "u1jhcmfmkcgk", "woe:centroid": [7.08948, 51.492458], "geom:latitude": 51.492458, "geom:longitude": 7.08948, "geom:hash": "u1jhcmfmkcgk", "woe:latitude": 51.492458, "geom:centroid": [7.08948, 51.492458], "woe:longitude": 7.08948, "woe:repo": "woeplanet-poi-de"}, "geometry": {"coordinates": [7.08948, 51.492458], "type": "Point"}}