{"type": "Feature", "id": 22975403, "geometry": {"type": "Point", "coordinates": [13.16202, 50.648312]}, "properties": {"woe:id": 22975403, "woe:parent_id": 673860, "woe:name": "Marienberg Bahnhof", "woe:placetype": 20, "woe:placetype_name": "POI", "woe:lang": "GER", "iso:country": "DE", "meta:provider": ["geoplanet:7.3.1", "geoplanet:7.3.2", "geoplanet:7.4.0", "geoplanet:7.4.1", "geoplanet:7.5.1", "geoplanet:7.5.2", "geoplanet:7.6.0", "geoplanet:7.8.1", "geoplanet:7.9.0", "geoplanet:7.10.0", "geoplanet:8.0.0", "woeplanet:8.0.0"], "meta:indexed": "2020-08-20T20:51:44.873110", "meta:updated": "2020-10-14T11:50:28.592676", "woe:alias_ENG_P": ["Marienberg Station"], "woe:hierarchy": {"continent": 24865675, "country": 23424829, "town": 0, "planet": 1, "county": 56448166, "suburb": 0, "state": 2345493, "region": 0, "localadmin": 24547356}, "woe:timezone_id": 28350890, "woe:hash": "u3125s0rc39m", "woe:centroid": [13.16202, 50.648312], "geom:latitude": 50.648312, "geom:longitude": 13.16202, "geom:hash": "u3125s0rc39m", "woe:latitude": 50.648312, "geom:centroid": [13.16202, 50.648312], "woe:longitude": 13.16202, "woe:repo": "woeplanet-poi-de", "geom:area": 0.0, "woe:scale": 19}}