{"type": "Feature", "id": 22190225, "geometry": {"type": "Point", "coordinates": [6.87141, 51.163052]}, "properties": {"woe:id": 22190225, "woe:parent_id": 646099, "woe:name": "Schlo\u00df Benrath", "woe:placetype": 20, "woe:placetype_name": "POI", "woe:lang": "GER", "iso:country": "DE", "meta:provider": ["geoplanet:7.3.1", "geoplanet:7.3.2", "geoplanet:7.4.0", "geoplanet:7.4.1", "geoplanet:7.5.1", "geoplanet:7.5.2", "geoplanet:7.6.0", "geoplanet:7.8.1", "geoplanet:7.9.0", "geoplanet:7.10.0", "geoplanet:8.0.0", "woeplanet:8.0.0"], "meta:indexed": "2020-08-20T20:51:39.298405", "meta:updated": "2020-10-14T11:50:26.866319", "woe:alias_GER_S": ["Schloss Benrath"], "woe:hierarchy": {"continent": 24865675, "country": 23424829, "town": 0, "planet": 1, "county": 12596700, "suburb": 0, "state": 2345487, "region": 0, "localadmin": 26822288}, "woe:timezone_id": 28350890, "woe:hash": "u1hgh3gw7knt", "woe:centroid": [6.87141, 51.163052], "geom:latitude": 51.163052, "geom:longitude": 6.87141, "geom:hash": "u1hgh3gw7knt", "woe:latitude": 51.163052, "geom:centroid": [6.87141, 51.163052], "woe:longitude": 6.87141, "woe:repo": "woeplanet-poi-de", "geom:area": 0.0, "woe:scale": 19}}