{"type": "Feature", "id": 22243643, "properties": {"woe:id": 22243643, "woe:parent_id": 673963, "woe:name": "Bauernhausstra\u00dfe Bodenseekreis", "woe:placetype": 20, "woe:placetype_name": "POI", "woe:lang": "GER", "iso:country": "DE", "meta:provider": ["geoplanet:7.3.1", "geoplanet:7.3.2", "geoplanet:7.4.0", "geoplanet:7.4.1", "geoplanet:7.5.1", "geoplanet:7.5.2", "geoplanet:7.6.0", "geoplanet:7.8.1", "geoplanet:7.9.0", "geoplanet:7.10.0", "geoplanet:8.0.0", "woeplanet:8.0.0"], "meta:indexed": "2020-08-20T20:51:41.518718", "meta:updated": "2020-08-22T01:51:40.761967", "woe:alias_GER_S": ["Bauernhausstrasse Bodenseekreis"], "woe:hierarchy": {"continent": 24865675, "country": 23424829, "town": 0, "planet": 1, "county": 12596879, "suburb": 0, "state": 2345481, "region": 0, "localadmin": 12623789}, "woe:timezone_id": 28350890, "woe:hash": "u0qxmz731z0c", "woe:centroid": [9.39785, 47.720699], "geom:latitude": 47.720699, "geom:longitude": 9.39785, "geom:hash": "u0qxmz731z0c", "woe:latitude": 47.720699, "geom:centroid": [9.39785, 47.720699], "woe:longitude": 9.39785, "woe:repo": "woeplanet-poi-de"}, "geometry": {"coordinates": [9.39785, 47.720699], "type": "Point"}}