{"type": "Feature", "id": 22202465, "properties": {"woe:id": 22202465, "woe:parent_id": 651339, "woe:name": "Gaildorfer Heimatmuseum", "woe:placetype": 20, "woe:placetype_name": "POI", "woe:lang": "GER", "iso:country": "DE", "meta:provider": ["geoplanet:7.3.1", "geoplanet:7.3.2", "geoplanet:7.4.0", "geoplanet:7.4.1", "geoplanet:7.5.1", "geoplanet:7.5.2", "geoplanet:7.6.0", "geoplanet:7.8.1", "geoplanet:7.9.0", "geoplanet:7.10.0", "geoplanet:8.0.0", "woeplanet:8.0.0"], "meta:indexed": "2020-08-20T20:51:39.777788", "meta:updated": "2020-08-22T01:51:40.040619", "woe:hierarchy": {"continent": 24865675, "country": 23424829, "town": 0, "planet": 1, "county": 12596799, "suburb": 0, "state": 2345481, "region": 0, "localadmin": 12624149}, "woe:timezone_id": 28350890, "woe:hash": "u0wyy3xn8rry", "woe:centroid": [9.77648, 49.008419], "geom:latitude": 49.008419, "geom:longitude": 9.77648, "geom:hash": "u0wyy3xn8rry", "woe:latitude": 49.008419, "geom:centroid": [9.77648, 49.008419], "woe:longitude": 9.77648, "woe:repo": "woeplanet-poi-de"}, "geometry": {"coordinates": [9.77648, 49.008419], "type": "Point"}}