{"type": "Feature", "id": 22235796, "properties": {"woe:id": 22235796, "woe:parent_id": 670225, "woe:name": "Langenlonsheim Bahnhof", "woe:placetype": 20, "woe:placetype_name": "POI", "woe:lang": "GER", "iso:country": "DE", "meta:provider": ["geoplanet:7.3.1", "geoplanet:7.3.2", "geoplanet:7.4.0", "geoplanet:7.4.1", "geoplanet:7.5.1", "geoplanet:7.5.2", "geoplanet:7.6.0", "geoplanet:7.8.1", "geoplanet:7.9.0", "geoplanet:7.10.0", "geoplanet:8.0.0", "woeplanet:8.0.0"], "meta:indexed": "2020-08-20T20:51:41.181758", "meta:updated": "2020-08-22T01:51:40.632829", "woe:alias_ENG_P": ["Langenlonsheim Station"], "woe:hierarchy": {"continent": 24865675, "country": 23424829, "town": 0, "planet": 1, "county": 12596762, "suburb": 0, "state": 2345488, "region": 0, "localadmin": 12628016}, "woe:timezone_id": 28350890, "woe:hash": "u0vegfg11xum", "woe:centroid": [7.90336, 49.89325], "geom:latitude": 49.89325, "geom:longitude": 7.90336, "geom:hash": "u0vegfg11xum", "woe:latitude": 49.89325, "geom:centroid": [7.90336, 49.89325], "woe:longitude": 7.90336, "woe:repo": "woeplanet-poi-de"}, "geometry": {"coordinates": [7.90336, 49.89325], "type": "Point"}}