{"type": "Feature", "id": 22224290, "geometry": {"type": "Point", "coordinates": [6.46605, 51.103142]}, "properties": {"woe:id": 22224290, "woe:parent_id": 660574, "woe:name": "Hochneukirch Bahnhof", "woe:placetype": 20, "woe:placetype_name": "POI", "woe:lang": "GER", "iso:country": "DE", "meta:provider": ["geoplanet:7.3.1", "geoplanet:7.3.2", "geoplanet:7.4.0", "geoplanet:7.4.1", "geoplanet:7.5.1", "geoplanet:7.5.2", "geoplanet:7.6.0", "geoplanet:7.8.1", "geoplanet:7.9.0", "geoplanet:7.10.0", "geoplanet:8.0.0", "woeplanet:8.0.0"], "meta:indexed": "2020-08-20T20:51:40.709418", "meta:updated": "2020-10-14T11:50:57.603393", "woe:alias_ENG_P": ["Hochneukirch Station"], "woe:hierarchy": {"continent": 24865675, "country": 23424829, "town": 0, "planet": 1, "county": 12596955, "suburb": 0, "state": 2345487, "region": 0, "localadmin": 12624449}, "woe:timezone_id": 28350890, "woe:hash": "u1hdeph3muhk", "woe:centroid": [6.46605, 51.103142], "geom:latitude": 51.103142, "geom:longitude": 6.46605, "geom:hash": "u1hdeph3muhk", "woe:latitude": 51.103142, "geom:centroid": [6.46605, 51.103142], "woe:longitude": 6.46605, "woe:repo": "woeplanet-poi-de", "geom:area": 0.0, "woe:scale": 19}}