{"type": "Feature", "id": 22182256, "geometry": {"type": "Point", "coordinates": [7.61517, 50.2453]}, "properties": {"woe:id": 22182256, "woe:parent_id": 683728, "woe:name": "Osterspai Bahnhof", "woe:placetype": 20, "woe:placetype_name": "POI", "woe:lang": "GER", "iso:country": "DE", "meta:provider": ["geoplanet:7.3.1", "geoplanet:7.3.2", "geoplanet:7.4.0", "geoplanet:7.4.1", "geoplanet:7.5.1", "geoplanet:7.5.2", "geoplanet:7.6.0", "geoplanet:7.8.1", "geoplanet:7.9.0", "geoplanet:7.10.0", "geoplanet:8.0.0", "woeplanet:8.0.0"], "meta:indexed": "2020-08-20T20:51:38.940319", "meta:updated": "2020-10-14T11:50:27.216246", "woe:alias_ENG_P": ["Osterspai Station"], "woe:hierarchy": {"continent": 24865675, "country": 23424829, "town": 0, "planet": 1, "county": 12596791, "suburb": 0, "state": 2345488, "region": 0, "localadmin": 12628571}, "woe:timezone_id": 28350890, "woe:hash": "u0vmv6chn6f3", "woe:centroid": [7.61517, 50.2453], "geom:latitude": 50.2453, "geom:longitude": 7.61517, "geom:hash": "u0vmv6chn6f3", "woe:latitude": 50.2453, "geom:centroid": [7.61517, 50.2453], "woe:longitude": 7.61517, "woe:repo": "woeplanet-poi-de", "geom:area": 0.0, "woe:scale": 19}}