{"type": "Feature", "id": 22188816, "geometry": {"type": "Point", "coordinates": [12.02055, 49.401279]}, "properties": {"woe:id": 22188816, "woe:parent_id": 650485, "woe:name": "Freih\u00f6ls Bahnhof", "woe:placetype": 20, "woe:placetype_name": "POI", "woe:lang": "GER", "iso:country": "DE", "meta:provider": ["geoplanet:7.3.1", "geoplanet:7.3.2", "geoplanet:7.4.0", "geoplanet:7.4.1", "geoplanet:7.5.1", "geoplanet:7.5.2", "geoplanet:7.6.0", "geoplanet:7.8.1", "geoplanet:7.9.0", "geoplanet:7.10.0", "geoplanet:8.0.0", "woeplanet:8.0.0"], "meta:indexed": "2020-08-20T20:51:39.272171", "meta:updated": "2020-10-14T11:50:27.185969", "woe:alias_ENG_S": ["Freihols Station"], "woe:alias_GER_S": ["Freihoels Bahnhof", "Freihols Bahnhof"], "woe:alias_ENG_P": ["Freihols Station"], "woe:hierarchy": {"continent": 24865675, "country": 23424829, "town": 0, "planet": 1, "county": 12596931, "suburb": 0, "state": 2345482, "region": 0, "localadmin": 12634303}, "woe:timezone_id": 28350890, "woe:hash": "u2b9191p71ge", "woe:centroid": [12.02055, 49.401279], "geom:latitude": 49.401279, "geom:longitude": 12.02055, "geom:hash": "u2b9191p71ge", "woe:latitude": 49.401279, "geom:centroid": [12.02055, 49.401279], "woe:longitude": 12.02055, "woe:repo": "woeplanet-poi-de", "geom:area": 0.0, "woe:scale": 19}}