{"type": "Feature", "id": 22187159, "properties": {"woe:id": 22187159, "woe:parent_id": 653974, "woe:name": "Schillerh\u00e4uschen", "woe:placetype": 20, "woe:placetype_name": "POI", "woe:lang": "GER", "iso:country": "DE", "meta:provider": ["geoplanet:7.3.1", "geoplanet:7.3.2", "geoplanet:7.4.0", "geoplanet:7.4.1", "geoplanet:7.5.1", "geoplanet:7.5.2", "geoplanet:7.6.0", "geoplanet:7.8.1", "geoplanet:7.9.0", "geoplanet:7.10.0", "geoplanet:8.0.0", "woeplanet:8.0.0"], "meta:indexed": "2020-08-20T20:51:39.211019", "meta:updated": "2020-08-22T01:51:39.757115", "woe:alias_GER_S": ["Schillerhaeuschen", "Schillerhauschen"], "woe:hierarchy": {"continent": 24865675, "country": 23424829, "town": 0, "planet": 1, "county": 12596943, "suburb": 0, "state": 2345493, "region": 0, "localadmin": 26822180}, "woe:timezone_id": 28350890, "woe:hash": "u31f6qf3v2zt", "woe:centroid": [13.81314, 51.057892], "geom:latitude": 51.057892, "geom:longitude": 13.81314, "geom:hash": "u31f6qf3v2zt", "woe:latitude": 51.057892, "geom:centroid": [13.81314, 51.057892], "woe:longitude": 13.81314, "woe:repo": "woeplanet-poi-de"}, "geometry": {"coordinates": [13.81314, 51.057892], "type": "Point"}}