{"type": "Feature", "id": 22182010, "properties": {"woe:id": 22182010, "woe:parent_id": 693010, "woe:name": "Sch\u00f6nmark Bahnhof", "woe:placetype": 20, "woe:placetype_name": "POI", "woe:lang": "GER", "iso:country": "DE", "meta:provider": ["geoplanet:7.3.1", "geoplanet:7.3.2", "geoplanet:7.4.0", "geoplanet:7.4.1", "geoplanet:7.5.1", "geoplanet:7.5.2", "geoplanet:7.6.0", "geoplanet:7.8.1", "geoplanet:7.9.0", "geoplanet:7.10.0", "geoplanet:8.0.0", "woeplanet:8.0.0"], "meta:indexed": "2020-08-20T20:51:38.929854", "meta:updated": "2020-08-22T01:51:39.629588", "woe:alias_ENG_S": ["Schonmark Station"], "woe:alias_GER_S": ["Schoenmark Bahnhof", "Schonmark Bahnhof"], "woe:alias_ENG_P": ["Schonmark Station"], "woe:hierarchy": {"continent": 24865675, "country": 23424829, "town": 0, "planet": 1, "county": 12596890, "suburb": 0, "state": 2345491, "region": 0, "localadmin": 24547193}, "woe:timezone_id": 28350890, "woe:hash": "u33yp7esqe6d", "woe:centroid": [14.03463, 53.105911], "geom:latitude": 53.105911, "geom:longitude": 14.03463, "geom:hash": "u33yp7esqe6d", "woe:latitude": 53.105911, "geom:centroid": [14.03463, 53.105911], "woe:longitude": 14.03463, "woe:repo": "woeplanet-poi-de"}, "geometry": {"coordinates": [14.03463, 53.105911], "type": "Point"}}