{"type": "Feature", "id": 22211639, "properties": {"woe:id": 22211639, "woe:parent_id": 26822565, "woe:name": "Hamburg-Wandsbek Bahnhof", "woe:placetype": 20, "woe:placetype_name": "POI", "woe:lang": "GER", "iso:country": "DE", "meta:provider": ["geoplanet:7.3.1", "geoplanet:7.3.2", "geoplanet:7.4.0", "geoplanet:7.4.1", "geoplanet:7.5.1", "geoplanet:7.5.2", "geoplanet:7.6.0", "geoplanet:7.8.1", "geoplanet:7.9.0", "geoplanet:7.10.0", "geoplanet:8.0.0", "woeplanet:8.0.0"], "meta:indexed": "2020-08-20T20:51:40.232116", "meta:updated": "2020-08-22T01:51:40.251650", "woe:alias_ENG_P": ["Hamburg-Wandsbek Station"], "woe:hierarchy": {"continent": 24865675, "country": 23424829, "town": 0, "planet": 1, "county": 12596781, "suburb": 0, "state": 2345484, "region": 0, "localadmin": 26822565}, "woe:timezone_id": 28350890, "woe:hash": "u1x0v21gdfkr", "woe:centroid": [10.07699, 53.56995], "geom:latitude": 53.56995, "geom:longitude": 10.07699, "geom:hash": "u1x0v21gdfkr", "woe:latitude": 53.56995, "geom:centroid": [10.07699, 53.56995], "woe:longitude": 10.07699, "woe:repo": "woeplanet-poi-de"}, "geometry": {"coordinates": [10.07699, 53.56995], "type": "Point"}}