{"type": "Feature", "id": 22280389, "properties": {"woe:id": 22280389, "woe:parent_id": 20163114, "woe:name": "Philippsheim Bahnhof", "woe:placetype": 20, "woe:placetype_name": "POI", "woe:lang": "GER", "iso:country": "DE", "meta:provider": ["geoplanet:7.3.1", "geoplanet:7.3.2", "geoplanet:7.4.0", "geoplanet:7.4.1", "geoplanet:7.5.1", "geoplanet:7.5.2", "geoplanet:7.6.0", "geoplanet:7.8.1", "geoplanet:7.9.0", "geoplanet:7.10.0", "geoplanet:8.0.0", "woeplanet:8.0.0"], "meta:indexed": "2020-08-20T20:51:42.974895", "meta:updated": "2020-08-22T01:51:41.338857", "woe:alias_ENG_P": ["Philippsheim Station"], "woe:hierarchy": {"continent": 24865675, "country": 23424829, "town": 0, "planet": 1, "county": 12596867, "suburb": 0, "state": 2345488, "region": 0, "localadmin": 12629096}, "woe:timezone_id": 28350890, "woe:hash": "u0usnvbbk11y", "woe:centroid": [6.62596, 49.95351], "geom:latitude": 49.95351, "geom:longitude": 6.62596, "geom:hash": "u0usnvbbk11y", "woe:latitude": 49.95351, "geom:centroid": [6.62596, 49.95351], "woe:longitude": 6.62596, "woe:repo": "woeplanet-poi-de"}, "geometry": {"coordinates": [6.62596, 49.95351], "type": "Point"}}