{"type": "Feature", "id": 22172064, "geometry": {"type": "Point", "coordinates": [9.78498, 48.411469]}, "properties": {"woe:id": 22172064, "woe:parent_id": 639416, "woe:name": "Urgeschichtliches Museum", "woe:placetype": 20, "woe:placetype_name": "POI", "woe:lang": "GER", "iso:country": "DE", "meta:provider": ["geoplanet:7.3.1", "geoplanet:7.3.2", "geoplanet:7.4.0", "geoplanet:7.4.1", "geoplanet:7.5.1", "geoplanet:7.5.2", "geoplanet:7.6.0", "geoplanet:7.8.1", "geoplanet:7.9.0", "geoplanet:7.10.0", "geoplanet:8.0.0", "woeplanet:8.0.0"], "meta:indexed": "2020-08-20T20:51:38.524855", "meta:updated": "2020-10-14T11:50:27.673328", "woe:hierarchy": {"continent": 24865675, "country": 23424829, "town": 0, "planet": 1, "county": 12596912, "suburb": 0, "state": 2345481, "region": 0, "localadmin": 12623688}, "woe:timezone_id": 28350890, "woe:hash": "u0wgqtj1nxcv", "woe:centroid": [9.78498, 48.411469], "geom:latitude": 48.411469, "geom:longitude": 9.78498, "geom:hash": "u0wgqtj1nxcv", "woe:latitude": 48.411469, "geom:centroid": [9.78498, 48.411469], "woe:longitude": 9.78498, "woe:repo": "woeplanet-poi-de", "geom:area": 0.0, "woe:scale": 19}}