{"type": "Feature", "id": 22241690, "properties": {"woe:id": 22241690, "woe:parent_id": 673513, "woe:name": "Heimat-Museum Maintal", "woe:placetype": 20, "woe:placetype_name": "POI", "woe:lang": "GER", "iso:country": "DE", "meta:provider": ["geoplanet:7.3.1", "geoplanet:7.3.2", "geoplanet:7.4.0", "geoplanet:7.4.1", "geoplanet:7.5.1", "geoplanet:7.5.2", "geoplanet:7.6.0", "geoplanet:7.8.1", "geoplanet:7.9.0", "geoplanet:7.10.0", "geoplanet:8.0.0", "woeplanet:8.0.0"], "meta:indexed": "2020-08-20T20:51:41.470982", "meta:updated": "2020-08-22T01:51:40.744728", "woe:hierarchy": {"continent": 24865675, "country": 23424829, "town": 0, "planet": 1, "county": 12596883, "suburb": 0, "state": 2345485, "region": 0, "localadmin": 12632531}, "woe:timezone_id": 28350890, "woe:hash": "u0ym341tyk7p", "woe:centroid": [8.83534, 50.153599], "geom:latitude": 50.153599, "geom:longitude": 8.83534, "geom:hash": "u0ym341tyk7p", "woe:latitude": 50.153599, "geom:centroid": [8.83534, 50.153599], "woe:longitude": 8.83534, "woe:repo": "woeplanet-poi-de"}, "geometry": {"coordinates": [8.83534, 50.153599], "type": "Point"}}