{"type": "Feature", "id": 22182000, "geometry": {"type": "Point", "coordinates": [14.00413, 53.017429]}, "properties": {"woe:id": 22182000, "woe:parent_id": 635170, "woe:name": "Heimatmuseum Angerm\u00fcnde", "woe:placetype": 20, "woe:placetype_name": "POI", "woe:lang": "GER", "iso:country": "DE", "meta:provider": ["geoplanet:7.3.1", "geoplanet:7.3.2", "geoplanet:7.4.0", "geoplanet:7.4.1", "geoplanet:7.5.1", "geoplanet:7.5.2", "geoplanet:7.6.0", "geoplanet:7.8.1", "geoplanet:7.9.0", "geoplanet:7.10.0", "geoplanet:8.0.0", "woeplanet:8.0.0"], "meta:indexed": "2020-08-20T20:51:38.928137", "meta:updated": "2020-10-14T11:50:26.983550", "woe:alias_GER_S": ["Heimatmuseum Angermuende", "Heimatmuseum Angermunde"], "woe:hierarchy": {"continent": 24865675, "country": 23424829, "town": 0, "planet": 1, "county": 12596890, "suburb": 0, "state": 2345491, "region": 0, "localadmin": 12636251}, "woe:timezone_id": 28350890, "woe:hash": "u33vwet2zvh4", "woe:centroid": [14.00413, 53.017429], "geom:latitude": 53.017429, "geom:longitude": 14.00413, "geom:hash": "u33vwet2zvh4", "woe:latitude": 53.017429, "geom:centroid": [14.00413, 53.017429], "woe:longitude": 14.00413, "woe:repo": "woeplanet-poi-de", "geom:area": 0.0, "woe:scale": 19}}