{"type": "Feature", "id": 22942133, "properties": {"woe:id": 22942133, "woe:parent_id": 689801, "woe:name": "R\u00f6tenbach Bahnhof", "woe:placetype": 20, "woe:placetype_name": "POI", "woe:lang": "GER", "iso:country": "DE", "meta:provider": ["geoplanet:7.3.1", "geoplanet:7.3.2", "geoplanet:7.4.0", "geoplanet:7.4.1", "geoplanet:7.5.1", "geoplanet:7.5.2", "geoplanet:7.6.0", "geoplanet:7.8.1", "geoplanet:7.9.0", "geoplanet:7.10.0", "geoplanet:8.0.0", "woeplanet:8.0.0"], "meta:indexed": "2020-08-20T20:51:44.171925", "meta:updated": "2020-08-22T01:51:41.931447", "woe:alias_ENG_S": ["Rotenbach Station"], "woe:alias_GER_S": ["Roetenbach Bahnhof", "Rotenbach Bahnhof"], "woe:alias_ENG_P": ["Rotenbach Station"], "woe:hierarchy": {"continent": 24865675, "country": 23424829, "town": 0, "planet": 1, "county": 12596773, "suburb": 0, "state": 2345481, "region": 0, "localadmin": 12623327}, "woe:timezone_id": 28350890, "woe:hash": "u0tbkws61hyz", "woe:centroid": [8.28958, 47.892521], "geom:latitude": 47.892521, "geom:longitude": 8.28958, "geom:hash": "u0tbkws61hyz", "woe:latitude": 47.892521, "geom:centroid": [8.28958, 47.892521], "woe:longitude": 8.28958, "woe:repo": "woeplanet-poi-de"}, "geometry": {"coordinates": [8.28958, 47.892521], "type": "Point"}}