{"type": "Feature", "id": 22297245, "properties": {"woe:id": 22297245, "woe:parent_id": 15002846, "woe:name": "Wittighausen Bahnhof", "woe:placetype": 20, "woe:placetype_name": "POI", "woe:lang": "GER", "iso:country": "DE", "meta:provider": ["geoplanet:7.3.1", "geoplanet:7.3.2", "geoplanet:7.4.0", "geoplanet:7.4.1", "geoplanet:7.5.1", "geoplanet:7.5.2", "geoplanet:7.6.0", "geoplanet:7.8.1", "geoplanet:7.9.0", "geoplanet:7.10.0", "geoplanet:8.0.0", "woeplanet:8.0.0"], "meta:indexed": "2020-08-20T20:51:43.700953", "meta:updated": "2020-08-22T01:51:41.698489", "woe:alias_ENG_P": ["Wittighausen Station"], "woe:hierarchy": {"continent": 24865675, "country": 23424829, "town": 0, "planet": 1, "county": 12596849, "suburb": 0, "state": 2345481, "region": 0, "localadmin": 12624188}, "woe:timezone_id": 28350890, "woe:hash": "u0z420cb1t9u", "woe:centroid": [9.84622, 49.618408], "geom:latitude": 49.618408, "geom:longitude": 9.84622, "geom:hash": "u0z420cb1t9u", "woe:latitude": 49.618408, "geom:centroid": [9.84622, 49.618408], "woe:longitude": 9.84622, "woe:repo": "woeplanet-poi-de"}, "geometry": {"coordinates": [9.84622, 49.618408], "type": "Point"}}