{"type": "Feature", "id": 22296490, "geometry": {"type": "Point", "coordinates": [7.64378, 50.77322]}, "properties": {"woe:id": 22296490, "woe:parent_id": 20169749, "woe:name": "Geilhausen Bahnhof", "woe:placetype": 20, "woe:placetype_name": "POI", "woe:lang": "GER", "iso:country": "DE", "meta:provider": ["geoplanet:7.3.1", "geoplanet:7.3.2", "geoplanet:7.4.0", "geoplanet:7.4.1", "geoplanet:7.5.1", "geoplanet:7.5.2", "geoplanet:7.6.0", "geoplanet:7.8.1", "geoplanet:7.9.0", "geoplanet:7.10.0", "geoplanet:8.0.0", "woeplanet:8.0.0"], "meta:indexed": "2020-08-20T20:51:43.673649", "meta:updated": "2020-10-14T11:51:00.286263", "woe:alias_ENG_P": ["Geilhausen Station"], "woe:hierarchy": {"continent": 24865675, "country": 23424829, "town": 0, "planet": 1, "county": 12596828, "suburb": 0, "state": 2345487, "region": 0, "localadmin": 12624381}, "woe:timezone_id": 28350890, "woe:hash": "u1j2vfyp2ypq", "woe:centroid": [7.64378, 50.77322], "geom:latitude": 50.77322, "geom:longitude": 7.64378, "geom:hash": "u1j2vfyp2ypq", "woe:latitude": 50.77322, "geom:centroid": [7.64378, 50.77322], "woe:longitude": 7.64378, "woe:repo": "woeplanet-poi-de", "geom:area": 0.0, "woe:scale": 19}}