{"type": "Feature", "id": 22247145, "geometry": {"type": "Point", "coordinates": [6.41524, 51.130169]}, "properties": {"woe:id": 22247145, "woe:parent_id": 675922, "woe:name": "Vogelkundliches Museum", "woe:placetype": 20, "woe:placetype_name": "POI", "woe:lang": "GER", "iso:country": "DE", "meta:provider": ["geoplanet:7.3.1", "geoplanet:7.3.2", "geoplanet:7.4.0", "geoplanet:7.4.1", "geoplanet:7.5.1", "geoplanet:7.5.2", "geoplanet:7.6.0", "geoplanet:7.8.1", "geoplanet:7.9.0", "geoplanet:7.10.0", "geoplanet:8.0.0", "woeplanet:8.0.0"], "meta:indexed": "2020-08-20T20:51:41.693065", "meta:updated": "2020-10-14T11:50:57.958040", "woe:hierarchy": {"continent": 24865675, "country": 23424829, "town": 0, "planet": 1, "county": 12596896, "suburb": 0, "state": 2345487, "region": 0, "localadmin": 26823027}, "woe:timezone_id": 28350890, "woe:hash": "u1hdcgzqvfmd", "woe:centroid": [6.41524, 51.130169], "geom:latitude": 51.130169, "geom:longitude": 6.41524, "geom:hash": "u1hdcgzqvfmd", "woe:latitude": 51.130169, "geom:centroid": [6.41524, 51.130169], "woe:longitude": 6.41524, "woe:repo": "woeplanet-poi-de", "geom:area": 0.0, "woe:scale": 19}}