{"type": "Feature", "id": 22270531, "geometry": {"type": "Point", "coordinates": [12.14094, 47.855122]}, "properties": {"woe:id": 22270531, "woe:parent_id": 689632, "woe:name": "Inn-Museum", "woe:placetype": 20, "woe:placetype_name": "POI", "woe:lang": "GER", "iso:country": "DE", "meta:provider": ["geoplanet:7.3.1", "geoplanet:7.3.2", "geoplanet:7.4.0", "geoplanet:7.4.1", "geoplanet:7.5.1", "geoplanet:7.5.2", "geoplanet:7.6.0", "geoplanet:7.8.1", "geoplanet:7.9.0", "geoplanet:7.10.0", "geoplanet:8.0.0", "woeplanet:8.0.0"], "meta:indexed": "2020-08-20T20:51:42.521227", "meta:updated": "2020-10-14T11:50:57.206576", "woe:hierarchy": {"continent": 24865675, "country": 23424829, "town": 0, "planet": 1, "county": 20071086, "suburb": 0, "state": 2345482, "region": 0, "localadmin": 12635674}, "woe:timezone_id": 28350890, "woe:hash": "u288hrbb23m4", "woe:centroid": [12.14094, 47.855122], "geom:latitude": 47.855122, "geom:longitude": 12.14094, "geom:hash": "u288hrbb23m4", "woe:latitude": 47.855122, "geom:centroid": [12.14094, 47.855122], "woe:longitude": 12.14094, "woe:repo": "woeplanet-poi-de", "geom:area": 0.0, "woe:scale": 19}}