{"type": "Feature", "id": 23000145, "properties": {"woe:id": 23000145, "woe:parent_id": 663336, "woe:name": "Illingen Bahnhof", "woe:placetype": 20, "woe:placetype_name": "POI", "woe:lang": "GER", "iso:country": "DE", "meta:provider": ["geoplanet:7.3.1", "geoplanet:7.3.2", "geoplanet:7.4.0", "geoplanet:7.4.1", "geoplanet:7.5.1", "geoplanet:7.5.2", "geoplanet:7.6.0", "geoplanet:7.8.1", "geoplanet:7.9.0", "geoplanet:7.10.0", "geoplanet:8.0.0", "woeplanet:8.0.0"], "meta:indexed": "2020-08-20T20:51:45.345823", "meta:updated": "2020-08-22T01:51:42.565702", "woe:alias_ENG_P": ["Illingen Station"], "woe:hierarchy": {"continent": 24865675, "country": 23424829, "town": 0, "planet": 1, "county": 12597099, "suburb": 0, "state": 2345489, "region": 0, "localadmin": 12627103}, "woe:timezone_id": 28350890, "woe:hash": "u0v0bksz4q6g", "woe:centroid": [7.04886, 49.376541], "geom:latitude": 49.376541, "geom:longitude": 7.04886, "geom:hash": "u0v0bksz4q6g", "woe:latitude": 49.376541, "geom:centroid": [7.04886, 49.376541], "woe:longitude": 7.04886, "woe:repo": "woeplanet-poi-de"}, "geometry": {"coordinates": [7.04886, 49.376541], "type": "Point"}}