{"type": "Feature", "id": 22201665, "geometry": {"type": "Point", "coordinates": [7.76331, 51.47147]}, "properties": {"woe:id": 22201665, "woe:parent_id": 650987, "woe:name": "Fr\u00f6ndenberg Bahnhof", "woe:placetype": 20, "woe:placetype_name": "POI", "woe:lang": "GER", "iso:country": "DE", "meta:provider": ["geoplanet:7.3.1", "geoplanet:7.3.2", "geoplanet:7.4.0", "geoplanet:7.4.1", "geoplanet:7.5.1", "geoplanet:7.5.2", "geoplanet:7.6.0", "geoplanet:7.8.1", "geoplanet:7.9.0", "geoplanet:7.10.0", "geoplanet:8.0.0", "woeplanet:8.0.0"], "meta:indexed": "2020-08-20T20:51:39.751105", "meta:updated": "2020-10-14T11:51:00.025661", "woe:alias_ENG_S": ["Frondenberg Station"], "woe:alias_GER_S": ["Froendenberg Bahnhof", "Frondenberg Bahnhof"], "woe:alias_ENG_P": ["Frondenberg Station"], "woe:hierarchy": {"continent": 24865675, "country": 23424829, "town": 0, "planet": 1, "county": 12596864, "suburb": 0, "state": 2345487, "region": 0, "localadmin": 12624492}, "woe:timezone_id": 28350890, "woe:hash": "u1jsbdj541rq", "woe:centroid": [7.76331, 51.47147], "geom:latitude": 51.47147, "geom:longitude": 7.76331, "geom:hash": "u1jsbdj541rq", "woe:latitude": 51.47147, "geom:centroid": [7.76331, 51.47147], "woe:longitude": 7.76331, "woe:repo": "woeplanet-poi-de", "geom:area": 0.0, "woe:scale": 19}}