{"type": "Feature", "id": 23030978, "geometry": {"type": "Point", "coordinates": [7.04186, 50.929241]}, "properties": {"woe:id": 23030978, "woe:parent_id": 667931, "woe:name": "Ostheim Bahnhof", "woe:placetype": 20, "woe:placetype_name": "POI", "woe:lang": "GER", "iso:country": "DE", "meta:provider": ["geoplanet:7.3.1", "geoplanet:7.3.2", "geoplanet:7.4.0", "geoplanet:7.4.1", "geoplanet:7.5.1", "geoplanet:7.5.2", "geoplanet:7.6.0", "geoplanet:7.8.1", "geoplanet:7.9.0", "geoplanet:7.10.0", "geoplanet:8.0.0", "woeplanet:8.0.0"], "meta:indexed": "2020-08-20T20:51:45.612638", "meta:updated": "2020-10-14T11:50:26.791149", "woe:alias_ENG_P": ["Ostheim Station"], "woe:hierarchy": {"continent": 24865675, "country": 23424829, "town": 0, "planet": 1, "county": 12597059, "suburb": 0, "state": 2345487, "region": 0, "localadmin": 26822829}, "woe:timezone_id": 28350890, "woe:hash": "u1j18prsr4xk", "woe:centroid": [7.04186, 50.929241], "geom:latitude": 50.929241, "geom:longitude": 7.04186, "geom:hash": "u1j18prsr4xk", "woe:latitude": 50.929241, "geom:centroid": [7.04186, 50.929241], "woe:longitude": 7.04186, "woe:repo": "woeplanet-poi-de", "geom:area": 0.0, "woe:scale": 19}}