{"type": "Feature", "id": 22924614, "properties": {"woe:id": 22924614, "woe:parent_id": 704107, "woe:name": "Imagin\u00e4res Museum", "woe:placetype": 20, "woe:placetype_name": "POI", "woe:lang": "GER", "iso:country": "DE", "meta:provider": ["geoplanet:7.3.1", "geoplanet:7.3.2", "geoplanet:7.4.0", "geoplanet:7.4.1", "geoplanet:7.5.1", "geoplanet:7.5.2", "geoplanet:7.6.0", "geoplanet:7.8.1", "geoplanet:7.9.0", "geoplanet:7.10.0", "geoplanet:8.0.0", "woeplanet:8.0.0"], "meta:indexed": "2020-08-20T20:51:43.923572", "meta:updated": "2020-08-22T01:51:41.816706", "woe:alias_GER_S": ["Imaginaeres Museum", "Imaginares Museum"], "woe:hierarchy": {"continent": 24865675, "country": 23424829, "town": 0, "planet": 1, "county": 12596730, "suburb": 0, "state": 2345482, "region": 0, "localadmin": 12635771}, "woe:timezone_id": 28350890, "woe:hash": "u289qm5he3js", "woe:centroid": [12.23205, 48.060471], "geom:latitude": 48.060471, "geom:longitude": 12.23205, "geom:hash": "u289qm5he3js", "woe:latitude": 48.060471, "geom:centroid": [12.23205, 48.060471], "woe:longitude": 12.23205, "woe:repo": "woeplanet-poi-de"}, "geometry": {"coordinates": [12.23205, 48.060471], "type": "Point"}}