{"type": "Feature", "id": 23685989, "properties": {"woe:id": 23685989, "woe:parent_id": 26821854, "woe:name": "Zoo Berlin", "woe:placetype": 20, "woe:placetype_name": "POI", "woe:lang": "GER", "iso:country": "DE", "meta:provider": ["geoplanet:7.3.1", "geoplanet:7.3.2", "geoplanet:7.4.0", "geoplanet:7.4.1", "geoplanet:7.5.1", "geoplanet:7.5.2", "geoplanet:7.6.0", "geoplanet:7.8.1", "geoplanet:7.9.0", "geoplanet:7.10.0", "geoplanet:8.0.0", "woeplanet:8.0.0"], "meta:indexed": "2020-08-20T20:51:45.742115", "meta:updated": "2020-08-22T01:51:42.948177", "woe:alias_ENG_V": ["Berlin Zoological Garden"], "woe:alias_ENG_P": ["Berlin Zoo"], "woe:alias_GER_V": ["Zoologischer Garten Berlin"], "woe:supersedes": [22169462], "woe:hierarchy": {"continent": 24865675, "country": 23424829, "town": 0, "planet": 1, "county": 12596838, "suburb": 0, "state": 2345496, "region": 0, "localadmin": 26821854}, "woe:timezone_id": 28350890, "woe:hash": "u336xwb54q2g", "woe:centroid": [13.3375, 52.508331], "geom:latitude": 52.508331, "geom:longitude": 13.3375, "geom:hash": "u336xwb54q2g", "woe:latitude": 52.508331, "geom:centroid": [13.3375, 52.508331], "woe:longitude": 13.3375, "woe:repo": "woeplanet-poi-de"}, "geometry": {"coordinates": [13.3375, 52.508331], "type": "Point"}}