{"type": "Feature", "id": 22182210, "properties": {"woe:id": 22182210, "woe:parent_id": 643442, "woe:name": "Dachau Bahnhof", "woe:placetype": 20, "woe:placetype_name": "POI", "woe:lang": "GER", "iso:country": "DE", "meta:provider": ["geoplanet:7.3.1", "geoplanet:7.3.2", "geoplanet:7.4.0", "geoplanet:7.4.1", "geoplanet:7.5.1", "geoplanet:7.5.2", "geoplanet:7.6.0", "geoplanet:7.8.1", "geoplanet:7.9.0", "geoplanet:7.10.0", "geoplanet:8.0.0", "woeplanet:8.0.0"], "meta:indexed": "2020-08-20T20:51:38.937645", "meta:updated": "2020-08-22T01:51:39.633423", "woe:hierarchy": {"continent": 24865675, "country": 23424829, "town": 0, "planet": 1, "county": 12596917, "suburb": 0, "state": 2345482, "region": 0, "localadmin": 12635070}, "woe:timezone_id": 28350890, "woe:hash": "u284s2mhjfyc", "woe:centroid": [11.44389, 48.254028], "geom:latitude": 48.254028, "geom:longitude": 11.44389, "geom:hash": "u284s2mhjfyc", "woe:latitude": 48.254028, "geom:centroid": [11.44389, 48.254028], "woe:longitude": 11.44389, "woe:repo": "woeplanet-poi-de"}, "geometry": {"coordinates": [11.44389, 48.254028], "type": "Point"}}