{"type": "Feature", "id": 22206441, "properties": {"woe:id": 22206441, "woe:parent_id": 654035, "woe:name": "Gustaf-Dalman-Sammlung", "woe:placetype": 20, "woe:placetype_name": "POI", "woe:lang": "GER", "iso:country": "DE", "meta:provider": ["geoplanet:7.3.1", "geoplanet:7.3.2", "geoplanet:7.4.0", "geoplanet:7.4.1", "geoplanet:7.5.1", "geoplanet:7.5.2", "geoplanet:7.6.0", "geoplanet:7.8.1", "geoplanet:7.9.0", "geoplanet:7.10.0", "geoplanet:8.0.0", "woeplanet:8.0.0"], "meta:indexed": "2020-08-20T20:51:39.992369", "meta:updated": "2020-08-22T01:51:40.141050", "woe:hierarchy": {"continent": 24865675, "country": 23424829, "town": 0, "planet": 1, "county": 12597106, "suburb": 0, "state": 2345492, "region": 0, "localadmin": 12635722}, "woe:timezone_id": 28350890, "woe:hash": "u39e8req78ec", "woe:centroid": [13.37498, 54.095009], "geom:latitude": 54.095009, "geom:longitude": 13.37498, "geom:hash": "u39e8req78ec", "woe:latitude": 54.095009, "geom:centroid": [13.37498, 54.095009], "woe:longitude": 13.37498, "woe:repo": "woeplanet-poi-de"}, "geometry": {"coordinates": [13.37498, 54.095009], "type": "Point"}}