{"type": "Feature", "id": 22200013, "geometry": {"type": "Point", "coordinates": [13.30003, 48.987808]}, "properties": {"woe:id": 22200013, "woe:parent_id": 650313, "woe:name": "Frauenau Bahnhof", "woe:placetype": 20, "woe:placetype_name": "POI", "woe:lang": "GER", "iso:country": "DE", "meta:provider": ["geoplanet:7.3.1", "geoplanet:7.3.2", "geoplanet:7.4.0", "geoplanet:7.4.1", "geoplanet:7.5.1", "geoplanet:7.5.2", "geoplanet:7.6.0", "geoplanet:7.8.1", "geoplanet:7.9.0", "geoplanet:7.10.0", "geoplanet:8.0.0", "woeplanet:8.0.0"], "meta:indexed": "2020-08-20T20:51:39.688138", "meta:updated": "2020-10-14T11:50:58.223865", "woe:alias_ENG_P": ["Frauenau Station"], "woe:hierarchy": {"continent": 24865675, "country": 23424829, "town": 0, "planet": 1, "county": 12596755, "suburb": 0, "state": 2345482, "region": 0, "localadmin": 12622969}, "woe:timezone_id": 28350890, "woe:hash": "u29qwtuy9jm1", "woe:centroid": [13.30003, 48.987808], "geom:latitude": 48.987808, "geom:longitude": 13.30003, "geom:hash": "u29qwtuy9jm1", "woe:latitude": 48.987808, "geom:centroid": [13.30003, 48.987808], "woe:longitude": 13.30003, "woe:repo": "woeplanet-poi-de", "geom:area": 0.0, "woe:scale": 19}}