{"type": "Feature", "id": 22291888, "properties": {"woe:id": 22291888, "woe:parent_id": 704512, "woe:name": "Weidenberg Bahnhof", "woe:placetype": 20, "woe:placetype_name": "POI", "woe:lang": "GER", "iso:country": "DE", "meta:provider": ["geoplanet:7.3.1", "geoplanet:7.3.2", "geoplanet:7.4.0", "geoplanet:7.4.1", "geoplanet:7.5.1", "geoplanet:7.5.2", "geoplanet:7.6.0", "geoplanet:7.8.1", "geoplanet:7.9.0", "geoplanet:7.10.0", "geoplanet:8.0.0", "woeplanet:8.0.0"], "meta:indexed": "2020-08-20T20:51:43.500226", "meta:updated": "2020-08-22T01:51:41.591141", "woe:alias_ENG_P": ["Weidenberg Station"], "woe:hierarchy": {"continent": 24865675, "country": 23424829, "town": 0, "planet": 1, "county": 12596699, "suburb": 0, "state": 2345482, "region": 0, "localadmin": 12635279}, "woe:timezone_id": 28350890, "woe:hash": "u2bk4gbx3hn5", "woe:centroid": [11.72315, 49.943741], "geom:latitude": 49.943741, "geom:longitude": 11.72315, "geom:hash": "u2bk4gbx3hn5", "woe:latitude": 49.943741, "geom:centroid": [11.72315, 49.943741], "woe:longitude": 11.72315, "woe:repo": "woeplanet-poi-de"}, "geometry": {"coordinates": [11.72315, 49.943741], "type": "Point"}}