{"type": "Feature", "id": 22963182, "geometry": {"type": "Point", "coordinates": [13.38985, 52.510391]}, "properties": {"woe:id": 22963182, "woe:parent_id": 26821864, "woe:name": "Stadtmitte Bahnhof", "woe:placetype": 20, "woe:placetype_name": "POI", "woe:lang": "GER", "iso:country": "DE", "meta:provider": ["geoplanet:7.3.1", "geoplanet:7.3.2", "geoplanet:7.4.0", "geoplanet:7.4.1", "geoplanet:7.5.1", "geoplanet:7.5.2", "geoplanet:7.6.0", "geoplanet:7.8.1", "geoplanet:7.9.0", "geoplanet:7.10.0", "geoplanet:8.0.0", "woeplanet:8.0.0"], "meta:indexed": "2020-08-20T20:51:44.604414", "meta:updated": "2020-10-14T11:50:28.470302", "woe:alias_ENG_P": ["Stadtmitte Station"], "woe:hierarchy": {"continent": 24865675, "country": 23424829, "town": 0, "planet": 1, "county": 12596838, "suburb": 0, "state": 2345496, "region": 0, "localadmin": 26821864}, "woe:timezone_id": 28350890, "woe:hash": "u33d8xnpnn7g", "woe:centroid": [13.38985, 52.510391], "geom:latitude": 52.510391, "geom:longitude": 13.38985, "geom:hash": "u33d8xnpnn7g", "woe:latitude": 52.510391, "geom:centroid": [13.38985, 52.510391], "woe:longitude": 13.38985, "woe:repo": "woeplanet-poi-de", "geom:area": 0.0, "woe:scale": 19}}