{"type": "Feature", "id": 22992599, "properties": {"woe:id": 22992599, "woe:parent_id": 664119, "woe:name": "Je\u00dfnitz Bahnhof", "woe:placetype": 20, "woe:placetype_name": "POI", "woe:lang": "GER", "iso:country": "DE", "meta:provider": ["geoplanet:7.3.1", "geoplanet:7.3.2", "geoplanet:7.4.0", "geoplanet:7.4.1", "geoplanet:7.5.1", "geoplanet:7.5.2", "geoplanet:7.6.0", "geoplanet:7.8.1", "geoplanet:7.9.0", "geoplanet:7.10.0", "geoplanet:8.0.0", "woeplanet:8.0.0"], "meta:indexed": "2020-08-20T20:51:45.213021", "meta:updated": "2020-08-22T01:51:42.490644", "woe:alias_ENG_S": ["Jessnitz Station"], "woe:alias_GER_S": ["Jessnitz Bahnhof"], "woe:alias_ENG_P": ["Jessnitz Station"], "woe:hierarchy": {"continent": 24865675, "country": 23424829, "town": 0, "planet": 1, "county": 12597028, "suburb": 0, "state": 2345494, "region": 0, "localadmin": 12625969}, "woe:timezone_id": 28350890, "woe:hash": "u30wp2sn4y24", "woe:centroid": [12.27734, 51.683498], "geom:latitude": 51.683498, "geom:longitude": 12.27734, "geom:hash": "u30wp2sn4y24", "woe:latitude": 51.683498, "geom:centroid": [12.27734, 51.683498], "woe:longitude": 12.27734, "woe:repo": "woeplanet-poi-de"}, "geometry": {"coordinates": [12.27734, 51.683498], "type": "Point"}}