{"type": "Feature", "id": 22171295, "properties": {"woe:id": 22171295, "woe:parent_id": 705183, "woe:name": "Welsleben Bahnhof", "woe:placetype": 20, "woe:placetype_name": "POI", "woe:lang": "GER", "iso:country": "DE", "meta:provider": ["geoplanet:7.3.1", "geoplanet:7.3.2", "geoplanet:7.4.0", "geoplanet:7.4.1", "geoplanet:7.5.1", "geoplanet:7.5.2", "geoplanet:7.6.0", "geoplanet:7.8.1", "geoplanet:7.9.0", "geoplanet:7.10.0", "geoplanet:8.0.0", "woeplanet:8.0.0"], "meta:indexed": "2020-08-20T20:51:38.489718", "meta:updated": "2020-08-22T01:51:39.417542", "woe:alias_ENG_P": ["Welsleben Station"], "woe:hierarchy": {"continent": 24865675, "country": 23424829, "town": 0, "planet": 1, "county": 12597062, "suburb": 0, "state": 2345494, "region": 0, "localadmin": 12626929}, "woe:timezone_id": 28350890, "woe:hash": "u30rc583spmm", "woe:centroid": [11.64603, 52.006828], "geom:latitude": 52.006828, "geom:longitude": 11.64603, "geom:hash": "u30rc583spmm", "woe:latitude": 52.006828, "geom:centroid": [11.64603, 52.006828], "woe:longitude": 11.64603, "woe:repo": "woeplanet-poi-de"}, "geometry": {"coordinates": [11.64603, 52.006828], "type": "Point"}}