{"type": "Feature", "id": 22269934, "properties": {"woe:id": 22269934, "woe:parent_id": 637398, "woe:name": "Schuhmachermuseum", "woe:placetype": 20, "woe:placetype_name": "POI", "woe:lang": "GER", "iso:country": "DE", "meta:provider": ["geoplanet:7.3.1", "geoplanet:7.3.2", "geoplanet:7.4.0", "geoplanet:7.4.1", "geoplanet:7.5.1", "geoplanet:7.5.2", "geoplanet:7.6.0", "geoplanet:7.8.1", "geoplanet:7.9.0", "geoplanet:7.10.0", "geoplanet:8.0.0", "woeplanet:8.0.0"], "meta:indexed": "2020-08-20T20:51:42.475916", "meta:updated": "2020-08-22T01:51:41.145749", "woe:hierarchy": {"continent": 24865675, "country": 23424829, "town": 0, "planet": 1, "county": 12596716, "suburb": 0, "state": 2345486, "region": 0, "localadmin": 12630141}, "woe:timezone_id": 28350890, "woe:hash": "u1w314rvc6k0", "woe:centroid": [8.84371, 53.62664], "geom:latitude": 53.62664, "geom:longitude": 8.84371, "geom:hash": "u1w314rvc6k0", "woe:latitude": 53.62664, "geom:centroid": [8.84371, 53.62664], "woe:longitude": 8.84371, "woe:repo": "woeplanet-poi-de"}, "geometry": {"coordinates": [8.84371, 53.62664], "type": "Point"}}