{"type": "Feature", "id": 22286678, "properties": {"woe:id": 22286678, "woe:parent_id": 700029, "woe:name": "Quint Bahnhof", "woe:placetype": 20, "woe:placetype_name": "POI", "woe:lang": "GER", "iso:country": "DE", "meta:provider": ["geoplanet:7.3.1", "geoplanet:7.3.2", "geoplanet:7.4.0", "geoplanet:7.4.1", "geoplanet:7.5.1", "geoplanet:7.5.2", "geoplanet:7.6.0", "geoplanet:7.8.1", "geoplanet:7.9.0", "geoplanet:7.10.0", "geoplanet:8.0.0", "woeplanet:8.0.0"], "meta:indexed": "2020-08-20T20:51:43.201043", "meta:updated": "2020-08-22T01:51:41.448588", "woe:alias_ENG_P": ["Quint Station"], "woe:hierarchy": {"continent": 24865675, "country": 23424829, "town": 0, "planet": 1, "county": 12596694, "suburb": 0, "state": 2345488, "region": 0, "localadmin": 12628884}, "woe:timezone_id": 28350890, "woe:hash": "u0ug2wd385pk", "woe:centroid": [6.70476, 49.826019], "geom:latitude": 49.826019, "geom:longitude": 6.70476, "geom:hash": "u0ug2wd385pk", "woe:latitude": 49.826019, "geom:centroid": [6.70476, 49.826019], "woe:longitude": 6.70476, "woe:repo": "woeplanet-poi-de"}, "geometry": {"coordinates": [6.70476, 49.826019], "type": "Point"}}