{"type": "Feature", "id": 23003106, "properties": {"woe:id": 23003106, "woe:parent_id": 685620, "woe:name": "P\u00f6nitz Bahnhof", "woe:placetype": 20, "woe:placetype_name": "POI", "woe:lang": "GER", "iso:country": "DE", "meta:provider": ["geoplanet:7.3.1", "geoplanet:7.3.2", "geoplanet:7.4.0", "geoplanet:7.4.1", "geoplanet:7.5.1", "geoplanet:7.5.2", "geoplanet:7.6.0", "geoplanet:7.8.1", "geoplanet:7.9.0", "geoplanet:7.10.0", "geoplanet:8.0.0", "woeplanet:8.0.0"], "meta:indexed": "2020-08-20T20:51:45.371060", "meta:updated": "2020-08-22T01:51:42.578796", "woe:alias_ENG_P": ["Ponitz Station"], "woe:alias_GER_S": ["Poenitz Bahnhof", "Ponitz Bahnhof"], "woe:hierarchy": {"continent": 24865675, "country": 23424829, "town": 0, "planet": 1, "county": 12596898, "suburb": 0, "state": 2345490, "region": 0, "localadmin": 12632323}, "woe:timezone_id": 28350890, "woe:hash": "u1xe6yf66ftd", "woe:centroid": [10.67094, 54.046268], "geom:latitude": 54.046268, "geom:longitude": 10.67094, "geom:hash": "u1xe6yf66ftd", "woe:latitude": 54.046268, "geom:centroid": [10.67094, 54.046268], "woe:longitude": 10.67094, "woe:repo": "woeplanet-poi-de"}, "geometry": {"coordinates": [10.67094, 54.046268], "type": "Point"}}