{"type": "Feature", "id": 22290755, "properties": {"woe:id": 22290755, "woe:parent_id": 703606, "woe:name": "Walkenried Bahnhof", "woe:placetype": 20, "woe:placetype_name": "POI", "woe:lang": "GER", "iso:country": "DE", "meta:provider": ["geoplanet:7.3.1", "geoplanet:7.3.2", "geoplanet:7.4.0", "geoplanet:7.4.1", "geoplanet:7.5.1", "geoplanet:7.5.2", "geoplanet:7.6.0", "geoplanet:7.8.1", "geoplanet:7.9.0", "geoplanet:7.10.0", "geoplanet:8.0.0", "woeplanet:8.0.0"], "meta:indexed": "2020-08-20T20:51:43.429573", "meta:updated": "2020-08-22T01:51:41.555108", "woe:alias_ENG_P": ["Walkenried Station"], "woe:hierarchy": {"continent": 24865675, "country": 23424829, "town": 0, "planet": 1, "county": 12597042, "suburb": 0, "state": 2345486, "region": 0, "localadmin": 12630414}, "woe:timezone_id": 28350890, "woe:hash": "u1pt3qudx5fr", "woe:centroid": [10.60829, 51.585381], "geom:latitude": 51.585381, "geom:longitude": 10.60829, "geom:hash": "u1pt3qudx5fr", "woe:latitude": 51.585381, "geom:centroid": [10.60829, 51.585381], "woe:longitude": 10.60829, "woe:repo": "woeplanet-poi-de"}, "geometry": {"coordinates": [10.60829, 51.585381], "type": "Point"}}