{"type": "Feature", "id": 22243685, "properties": {"woe:id": 22243685, "woe:parent_id": 673999, "woe:name": "Markkleeberg Bahnhof", "woe:placetype": 20, "woe:placetype_name": "POI", "woe:lang": "GER", "iso:country": "DE", "meta:provider": ["geoplanet:7.3.1", "geoplanet:7.3.2", "geoplanet:7.4.0", "geoplanet:7.4.1", "geoplanet:7.5.1", "geoplanet:7.5.2", "geoplanet:7.6.0", "geoplanet:7.8.1", "geoplanet:7.9.0", "geoplanet:7.10.0", "geoplanet:8.0.0", "woeplanet:8.0.0"], "meta:indexed": "2020-08-20T20:51:41.520398", "meta:updated": "2020-08-22T01:51:40.762635", "woe:alias_ENG_P": ["Markkleeberg Station"], "woe:hierarchy": {"continent": 24865675, "country": 23424829, "town": 0, "planet": 1, "county": 56448169, "suburb": 0, "state": 2345493, "region": 0, "localadmin": 12625698}, "woe:timezone_id": 28350890, "woe:hash": "u30g9wcnx225", "woe:centroid": [12.37229, 51.278431], "geom:latitude": 51.278431, "geom:longitude": 12.37229, "geom:hash": "u30g9wcnx225", "woe:latitude": 51.278431, "geom:centroid": [12.37229, 51.278431], "woe:longitude": 12.37229, "woe:repo": "woeplanet-poi-de"}, "geometry": {"coordinates": [12.37229, 51.278431], "type": "Point"}}