{"type": "Feature", "id": 22201659, "geometry": {"type": "Point", "coordinates": [7.72729, 51.481281]}, "properties": {"woe:id": 22201659, "woe:parent_id": 635391, "woe:name": "Ardey Bahnhof", "woe:placetype": 20, "woe:placetype_name": "POI", "woe:lang": "GER", "iso:country": "DE", "meta:provider": ["geoplanet:7.3.1", "geoplanet:7.3.2", "geoplanet:7.4.0", "geoplanet:7.4.1", "geoplanet:7.5.1", "geoplanet:7.5.2", "geoplanet:7.6.0", "geoplanet:7.8.1", "geoplanet:7.9.0", "geoplanet:7.10.0", "geoplanet:8.0.0", "woeplanet:8.0.0"], "meta:indexed": "2020-08-20T20:51:39.749429", "meta:updated": "2020-10-14T11:51:00.021723", "woe:alias_ENG_P": ["Ardey Station"], "woe:hierarchy": {"continent": 24865675, "country": 23424829, "town": 0, "planet": 1, "county": 12596864, "suburb": 0, "state": 2345487, "region": 0, "localadmin": 12624492}, "woe:timezone_id": 28350890, "woe:hash": "u1jkzgfu4ym5", "woe:centroid": [7.72729, 51.481281], "geom:latitude": 51.481281, "geom:longitude": 7.72729, "geom:hash": "u1jkzgfu4ym5", "woe:latitude": 51.481281, "geom:centroid": [7.72729, 51.481281], "woe:longitude": 7.72729, "woe:repo": "woeplanet-poi-de", "geom:area": 0.0, "woe:scale": 19}}