{"type": "Feature", "id": 22164983, "properties": {"woe:id": 22164983, "woe:parent_id": 26821896, "woe:name": "Deutsch-Russisches-Museum", "woe:placetype": 20, "woe:placetype_name": "POI", "woe:lang": "GER", "iso:country": "DE", "meta:provider": ["geoplanet:7.3.1", "geoplanet:7.3.2", "geoplanet:7.4.0", "geoplanet:7.4.1", "geoplanet:7.5.1", "geoplanet:7.5.2", "geoplanet:7.6.0", "geoplanet:7.8.1", "geoplanet:7.9.0", "geoplanet:7.10.0", "geoplanet:8.0.0", "woeplanet:8.0.0"], "meta:indexed": "2020-08-20T20:51:38.376271", "meta:updated": "2020-08-22T01:51:39.354857", "woe:alias_GER_V": ["Deutsch-Russisches Museum"], "woe:hierarchy": {"continent": 24865675, "country": 23424829, "town": 0, "planet": 1, "county": 12596838, "suburb": 0, "state": 2345496, "region": 0, "localadmin": 26821896}, "woe:timezone_id": 28350890, "woe:hash": "u33ds4fdkwjx", "woe:centroid": [13.53879, 52.486229], "geom:latitude": 52.486229, "geom:longitude": 13.53879, "geom:hash": "u33ds4fdkwjx", "woe:latitude": 52.486229, "geom:centroid": [13.53879, 52.486229], "woe:longitude": 13.53879, "woe:repo": "woeplanet-poi-de"}, "geometry": {"coordinates": [13.53879, 52.486229], "type": "Point"}}