{"type": "Feature", "id": 23014422, "properties": {"woe:id": 23014422, "woe:parent_id": 672034, "woe:name": "Lindhorst Bahnhof", "woe:placetype": 20, "woe:placetype_name": "POI", "woe:lang": "GER", "iso:country": "DE", "meta:provider": ["geoplanet:7.3.1", "geoplanet:7.3.2", "geoplanet:7.4.0", "geoplanet:7.4.1", "geoplanet:7.5.1", "geoplanet:7.5.2", "geoplanet:7.6.0", "geoplanet:7.8.1", "geoplanet:7.9.0", "geoplanet:7.10.0", "geoplanet:8.0.0", "woeplanet:8.0.0"], "meta:indexed": "2020-08-20T20:51:45.473894", "meta:updated": "2020-08-22T01:51:42.636044", "woe:alias_ENG_P": ["Lindhorst Station"], "woe:hierarchy": {"continent": 24865675, "country": 23424829, "town": 0, "planet": 1, "county": 12596789, "suburb": 0, "state": 2345486, "region": 0, "localadmin": 12629568}, "woe:timezone_id": 28350890, "woe:hash": "u1q9g68tw7ju", "woe:centroid": [9.28441, 52.353561], "geom:latitude": 52.353561, "geom:longitude": 9.28441, "geom:hash": "u1q9g68tw7ju", "woe:latitude": 52.353561, "geom:centroid": [9.28441, 52.353561], "woe:longitude": 9.28441, "woe:repo": "woeplanet-poi-de"}, "geometry": {"coordinates": [9.28441, 52.353561], "type": "Point"}}