{"type": "Feature", "id": 22180410, "geometry": {"type": "Point", "coordinates": [10.88721, 49.465721]}, "properties": {"woe:id": 22180410, "woe:parent_id": 646619, "woe:name": "Egersdorf Bahnhof", "woe:placetype": 20, "woe:placetype_name": "POI", "woe:lang": "GER", "iso:country": "DE", "meta:provider": ["geoplanet:7.3.1", "geoplanet:7.3.2", "geoplanet:7.4.0", "geoplanet:7.4.1", "geoplanet:7.5.1", "geoplanet:7.5.2", "geoplanet:7.6.0", "geoplanet:7.8.1", "geoplanet:7.9.0", "geoplanet:7.10.0", "geoplanet:8.0.0", "woeplanet:8.0.0"], "meta:indexed": "2020-08-20T20:51:38.856587", "meta:updated": "2020-10-14T11:50:27.010183", "woe:alias_ENG_P": ["Egersdorf Station"], "woe:hierarchy": {"continent": 24865675, "country": 23424829, "town": 0, "planet": 1, "county": 12596815, "suburb": 0, "state": 2345482, "region": 0, "localadmin": 12634465}, "woe:timezone_id": 28350890, "woe:hash": "u0z9rszydqsp", "woe:centroid": [10.88721, 49.465721], "geom:latitude": 49.465721, "geom:longitude": 10.88721, "geom:hash": "u0z9rszydqsp", "woe:latitude": 49.465721, "geom:centroid": [10.88721, 49.465721], "woe:longitude": 10.88721, "woe:repo": "woeplanet-poi-de", "geom:area": 0.0, "woe:scale": 19}}