{"type": "Feature", "id": 22954963, "geometry": {"type": "Point", "coordinates": [8.6602, 49.059681]}, "properties": {"woe:id": 22954963, "woe:parent_id": 653263, "woe:name": "Gondelsheim Bahnhof", "woe:placetype": 20, "woe:placetype_name": "POI", "woe:lang": "GER", "iso:country": "DE", "meta:provider": ["geoplanet:7.3.1", "geoplanet:7.3.2", "geoplanet:7.4.0", "geoplanet:7.4.1", "geoplanet:7.5.1", "geoplanet:7.5.2", "geoplanet:7.6.0", "geoplanet:7.8.1", "geoplanet:7.9.0", "geoplanet:7.10.0", "geoplanet:8.0.0", "woeplanet:8.0.0"], "meta:indexed": "2020-08-20T20:51:44.449904", "meta:updated": "2020-10-14T11:50:28.448678", "woe:alias_ENG_P": ["Gondelsheim Station"], "woe:hierarchy": {"continent": 24865675, "country": 23424829, "town": 0, "planet": 1, "county": 12597063, "suburb": 0, "state": 2345481, "region": 0, "localadmin": 12623873}, "woe:timezone_id": 28350890, "woe:hash": "u0wpj541m73h", "woe:centroid": [8.6602, 49.059681], "geom:latitude": 49.059681, "geom:longitude": 8.6602, "geom:hash": "u0wpj541m73h", "woe:latitude": 49.059681, "geom:centroid": [8.6602, 49.059681], "woe:longitude": 8.6602, "woe:repo": "woeplanet-poi-de", "geom:area": 0.0, "woe:scale": 19}}