{"type": "Feature", "id": 22155362, "geometry": {"type": "Point", "coordinates": [8.94586, 49.92234]}, "properties": {"woe:id": 22155362, "woe:parent_id": 670354, "woe:name": "Langstadt Bahnhof", "woe:placetype": 20, "woe:placetype_name": "POI", "woe:lang": "GER", "iso:country": "DE", "meta:provider": ["geoplanet:7.3.1", "geoplanet:7.3.2", "geoplanet:7.4.0", "geoplanet:7.4.1", "geoplanet:7.5.1", "geoplanet:7.5.2", "geoplanet:7.6.0", "geoplanet:7.8.1", "geoplanet:7.9.0", "geoplanet:7.10.0", "geoplanet:8.0.0", "woeplanet:8.0.0"], "meta:indexed": "2020-08-20T20:51:37.997390", "meta:updated": "2020-10-14T11:50:27.364954", "woe:alias_ENG_P": ["Langstadt Station"], "woe:hierarchy": {"continent": 24865675, "country": 23424829, "town": 0, "planet": 1, "county": 12596968, "suburb": 0, "state": 2345485, "region": 0, "localadmin": 12632477}, "woe:timezone_id": 28350890, "woe:hash": "u0yk5844twst", "woe:centroid": [8.94586, 49.92234], "geom:latitude": 49.92234, "geom:longitude": 8.94586, "geom:hash": "u0yk5844twst", "woe:latitude": 49.92234, "geom:centroid": [8.94586, 49.92234], "woe:longitude": 8.94586, "woe:repo": "woeplanet-poi-de", "geom:area": 0.0, "woe:scale": 19}}