{"type": "Feature", "id": 22204078, "geometry": {"type": "Point", "coordinates": [12.04727, 50.91708]}, "properties": {"woe:id": 22204078, "woe:parent_id": 652153, "woe:name": "Gera-Langenberg Bahnhof", "woe:placetype": 20, "woe:placetype_name": "POI", "woe:lang": "GER", "iso:country": "DE", "meta:provider": ["geoplanet:7.3.1", "geoplanet:7.3.2", "geoplanet:7.4.0", "geoplanet:7.4.1", "geoplanet:7.5.1", "geoplanet:7.5.2", "geoplanet:7.6.0", "geoplanet:7.8.1", "geoplanet:7.9.0", "geoplanet:7.10.0", "geoplanet:8.0.0", "woeplanet:8.0.0"], "meta:indexed": "2020-08-20T20:51:39.842686", "meta:updated": "2020-10-14T11:50:58.515966", "woe:alias_ENG_P": ["Gera-Langenberg Station"], "woe:hierarchy": {"continent": 24865675, "country": 23424829, "town": 0, "planet": 1, "county": 12597089, "suburb": 0, "state": 2345495, "region": 0, "localadmin": 12624636}, "woe:timezone_id": 28350890, "woe:hash": "u309djht3xxt", "woe:centroid": [12.04727, 50.91708], "geom:latitude": 50.91708, "geom:longitude": 12.04727, "geom:hash": "u309djht3xxt", "woe:latitude": 50.91708, "geom:centroid": [12.04727, 50.91708], "woe:longitude": 12.04727, "woe:repo": "woeplanet-poi-de", "geom:area": 0.0, "woe:scale": 19}}