{"type": "Feature", "id": 22204076, "properties": {"woe:id": 22204076, "woe:parent_id": 652153, "woe:name": "Gera Hauptbahnhof", "woe:placetype": 20, "woe:placetype_name": "POI", "woe:lang": "GER", "iso:country": "DE", "meta:provider": ["geoplanet:7.3.1", "geoplanet:7.3.2", "geoplanet:7.4.0", "geoplanet:7.4.1", "geoplanet:7.5.1", "geoplanet:7.5.2", "geoplanet:7.6.0", "geoplanet:7.8.1", "geoplanet:7.9.0", "geoplanet:7.10.0", "geoplanet:8.0.0", "woeplanet:8.0.0"], "meta:indexed": "2020-08-20T20:51:39.840942", "meta:updated": "2020-08-22T01:51:56.395786", "woe:alias_ENG_P": ["Gera Central Station"], "woe:alias_ENG_V": ["Gera Railway Station", "Gera Station"], "woe:alias_GER_V": ["Gera Hbf", "Hauptbahnhof Gera", "Hbf Gera"], "woe:hierarchy": {"continent": 24865675, "country": 23424829, "town": 0, "planet": 1, "county": 12597089, "suburb": 0, "state": 2345495, "region": 0, "localadmin": 12624636}, "woe:timezone_id": 28350890, "woe:hash": "u3096yfk4ew0", "woe:centroid": [12.07718, 50.882511], "geom:latitude": 50.882511, "geom:longitude": 12.07718, "geom:hash": "u3096yfk4ew0", "woe:latitude": 50.882511, "geom:centroid": [12.07718, 50.882511], "woe:longitude": 12.07718, "woe:repo": "woeplanet-poi-de"}, "geometry": {"coordinates": [12.07718, 50.882511], "type": "Point"}}