{"type": "Feature", "id": 22295862, "properties": {"woe:id": 22295862, "woe:parent_id": 675928, "woe:name": "M\u00f6nchhagen Bahnhof", "woe:placetype": 20, "woe:placetype_name": "POI", "woe:lang": "GER", "iso:country": "DE", "meta:provider": ["geoplanet:7.3.1", "geoplanet:7.3.2", "geoplanet:7.4.0", "geoplanet:7.4.1", "geoplanet:7.5.1", "geoplanet:7.5.2", "geoplanet:7.6.0", "geoplanet:7.8.1", "geoplanet:7.9.0", "geoplanet:7.10.0", "geoplanet:8.0.0", "woeplanet:8.0.0"], "meta:indexed": "2020-08-20T20:51:43.646280", "meta:updated": "2020-08-22T01:51:41.668666", "woe:alias_ENG_S": ["Monchhagen Station"], "woe:alias_GER_S": ["Moenchhagen Bahnhof", "Monchhagen Bahnhof"], "woe:alias_ENG_P": ["Monchhagen Station"], "woe:hierarchy": {"continent": 24865675, "country": 23424829, "town": 0, "planet": 1, "county": 12596842, "suburb": 0, "state": 2345492, "region": 0, "localadmin": 12630508}, "woe:timezone_id": 28350890, "woe:hash": "u38sn0w1sp3q", "woe:centroid": [12.22521, 54.143669], "geom:latitude": 54.143669, "geom:longitude": 12.22521, "geom:hash": "u38sn0w1sp3q", "woe:latitude": 54.143669, "geom:centroid": [12.22521, 54.143669], "woe:longitude": 12.22521, "woe:repo": "woeplanet-poi-de"}, "geometry": {"coordinates": [12.22521, 54.143669], "type": "Point"}}