{"type": "Feature", "id": 23030697, "geometry": {"type": "Point", "coordinates": [6.94146, 50.907581]}, "properties": {"woe:id": 23030697, "woe:parent_id": 667931, "woe:name": "Kalscheurer Weg Bahnhof", "woe:placetype": 20, "woe:placetype_name": "POI", "woe:lang": "GER", "iso:country": "DE", "meta:provider": ["geoplanet:7.3.1", "geoplanet:7.3.2", "geoplanet:7.4.0", "geoplanet:7.4.1", "geoplanet:7.5.1", "geoplanet:7.5.2", "geoplanet:7.6.0", "geoplanet:7.8.1", "geoplanet:7.9.0", "geoplanet:7.10.0", "geoplanet:8.0.0", "woeplanet:8.0.0"], "meta:indexed": "2020-08-20T20:51:45.598929", "meta:updated": "2020-10-14T11:50:26.538138", "woe:alias_ENG_P": ["Kalscheurer Weg Station"], "woe:hierarchy": {"continent": 24865675, "country": 23424829, "town": 0, "planet": 1, "county": 12597059, "suburb": 0, "state": 2345487, "region": 0, "localadmin": 26822790}, "woe:timezone_id": 28350890, "woe:hash": "u1hctgqw5szt", "woe:centroid": [6.94146, 50.907581], "geom:latitude": 50.907581, "geom:longitude": 6.94146, "geom:hash": "u1hctgqw5szt", "woe:latitude": 50.907581, "geom:centroid": [6.94146, 50.907581], "woe:longitude": 6.94146, "woe:repo": "woeplanet-poi-de", "geom:area": 0.0, "woe:scale": 19}}