{"type": "Feature", "id": 22994264, "geometry": {"type": "Point", "coordinates": [11.92092, 51.581669]}, "properties": {"woe:id": 22994264, "woe:parent_id": 703746, "woe:name": "Wallwitz Bahnhof", "woe:placetype": 20, "woe:placetype_name": "POI", "woe:lang": "GER", "iso:country": "DE", "meta:provider": ["geoplanet:7.3.1", "geoplanet:7.3.2", "geoplanet:7.4.0", "geoplanet:7.4.1", "geoplanet:7.5.1", "geoplanet:7.5.2", "geoplanet:7.6.0", "geoplanet:7.8.1", "geoplanet:7.9.0", "geoplanet:7.10.0", "geoplanet:8.0.0", "woeplanet:8.0.0"], "meta:indexed": "2020-08-20T20:51:45.254554", "meta:updated": "2020-10-14T11:50:28.525655", "woe:alias_ENG_P": ["Wallwitz Station"], "woe:hierarchy": {"continent": 24865675, "country": 23424829, "town": 0, "planet": 1, "county": 12597061, "suburb": 0, "state": 2345494, "region": 0, "localadmin": 12635883}, "woe:timezone_id": 28350890, "woe:hash": "u30mrq0t1840", "woe:centroid": [11.92092, 51.581669], "geom:latitude": 51.581669, "geom:longitude": 11.92092, "geom:hash": "u30mrq0t1840", "woe:latitude": 51.581669, "geom:centroid": [11.92092, 51.581669], "woe:longitude": 11.92092, "woe:repo": "woeplanet-poi-de", "geom:area": 0.0, "woe:scale": 19}}