{"type": "Feature", "id": 22296383, "geometry": {"type": "Point", "coordinates": [14.37712, 51.806629]}, "properties": {"woe:id": 22296383, "woe:parent_id": 706742, "woe:name": "Cottbus-Willmersdorf Bahnhof", "woe:placetype": 20, "woe:placetype_name": "POI", "woe:lang": "GER", "iso:country": "DE", "meta:provider": ["geoplanet:7.3.1", "geoplanet:7.3.2", "geoplanet:7.4.0", "geoplanet:7.4.1", "geoplanet:7.5.1", "geoplanet:7.5.2", "geoplanet:7.6.0", "geoplanet:7.8.1", "geoplanet:7.9.0", "geoplanet:7.10.0", "geoplanet:8.0.0", "woeplanet:8.0.0"], "meta:indexed": "2020-08-20T20:51:43.668719", "meta:updated": "2020-10-14T11:50:59.881527", "woe:alias_ENG_P": ["Cottbus-Willmersdorf Station"], "woe:hierarchy": {"continent": 24865675, "country": 23424829, "town": 0, "planet": 1, "county": 12597095, "suburb": 0, "state": 2345491, "region": 0, "localadmin": 12632871}, "woe:timezone_id": 28350890, "woe:hash": "u34nxpj57pte", "woe:centroid": [14.37712, 51.806629], "geom:latitude": 51.806629, "geom:longitude": 14.37712, "geom:hash": "u34nxpj57pte", "woe:latitude": 51.806629, "geom:centroid": [14.37712, 51.806629], "woe:longitude": 14.37712, "woe:repo": "woeplanet-poi-de", "geom:area": 0.0, "woe:scale": 19}}