{"type": "Feature", "id": 22267059, "properties": {"woe:id": 22267059, "woe:parent_id": 646099, "woe:name": "U Prinzenallee Bahnhof", "woe:placetype": 20, "woe:placetype_name": "POI", "woe:lang": "GER", "iso:country": "DE", "meta:provider": ["geoplanet:7.3.1", "geoplanet:7.3.2", "geoplanet:7.4.0", "geoplanet:7.4.1", "geoplanet:7.5.1", "geoplanet:7.5.2", "geoplanet:7.6.0", "geoplanet:7.8.1", "geoplanet:7.9.0", "geoplanet:7.10.0", "geoplanet:8.0.0", "woeplanet:8.0.0"], "meta:indexed": "2020-08-20T20:51:42.355700", "meta:updated": "2020-08-22T01:51:41.100240", "woe:alias_ENG_P": ["U Prinzenallee Station"], "woe:hierarchy": {"continent": 24865675, "country": 23424829, "town": 0, "planet": 1, "county": 12596700, "suburb": 0, "state": 2345487, "region": 0, "localadmin": 26822251}, "woe:timezone_id": 28350890, "woe:hash": "u1hg3r852dxj", "woe:centroid": [6.73465, 51.23806], "geom:latitude": 51.23806, "geom:longitude": 6.73465, "geom:hash": "u1hg3r852dxj", "woe:latitude": 51.23806, "geom:centroid": [6.73465, 51.23806], "woe:longitude": 6.73465, "woe:repo": "woeplanet-poi-de"}, "geometry": {"coordinates": [6.73465, 51.23806], "type": "Point"}}