{"type": "Feature", "id": 22153937, "properties": {"woe:id": 22153937, "woe:parent_id": 635527, "woe:name": "Christian-Rauch-Gedenkst\u00e4tte", "woe:placetype": 20, "woe:placetype_name": "POI", "woe:lang": "GER", "iso:country": "DE", "meta:provider": ["geoplanet:7.3.1", "geoplanet:7.3.2", "geoplanet:7.4.0", "geoplanet:7.4.1", "geoplanet:7.5.1", "geoplanet:7.5.2", "geoplanet:7.6.0", "geoplanet:7.8.1", "geoplanet:7.9.0", "geoplanet:7.10.0", "geoplanet:8.0.0", "woeplanet:8.0.0"], "meta:indexed": "2020-08-20T20:51:37.953734", "meta:updated": "2020-08-22T01:51:39.107680", "woe:alias_GER_S": ["Christian-Rauch-Gedenkstaette", "Christian-Rauch-Gedenkstatte"], "woe:hierarchy": {"continent": 24865675, "country": 23424829, "town": 0, "planet": 1, "county": 12596852, "suburb": 0, "state": 2345485, "region": 0, "localadmin": 12632832}, "woe:timezone_id": 28350890, "woe:hash": "u1nkm48kd8bp", "woe:centroid": [9.00924, 51.386581], "geom:latitude": 51.386581, "geom:longitude": 9.00924, "geom:hash": "u1nkm48kd8bp", "woe:latitude": 51.386581, "geom:centroid": [9.00924, 51.386581], "woe:longitude": 9.00924, "woe:repo": "woeplanet-poi-de"}, "geometry": {"coordinates": [9.00924, 51.386581], "type": "Point"}}