{"type": "Feature", "id": 22206096, "geometry": {"type": "Point", "coordinates": [9.73356, 50.095379]}, "properties": {"woe:id": 22206096, "woe:parent_id": 707721, "woe:name": "Wolfsm\u00fcnster Bahnhof", "woe:placetype": 20, "woe:placetype_name": "POI", "woe:lang": "GER", "iso:country": "DE", "meta:provider": ["geoplanet:7.3.1", "geoplanet:7.3.2", "geoplanet:7.4.0", "geoplanet:7.4.1", "geoplanet:7.5.1", "geoplanet:7.5.2", "geoplanet:7.6.0", "geoplanet:7.8.1", "geoplanet:7.9.0", "geoplanet:7.10.0", "geoplanet:8.0.0", "woeplanet:8.0.0"], "meta:indexed": "2020-08-20T20:51:39.962824", "meta:updated": "2020-10-14T11:50:58.114909", "woe:alias_ENG_S": ["Wolfsmunster Station"], "woe:alias_GER_S": ["Wolfsmuenster Bahnhof", "Wolfsmunster Bahnhof"], "woe:alias_ENG_P": ["Wolfsmunster Station"], "woe:hierarchy": {"continent": 24865675, "country": 23424829, "town": 0, "planet": 1, "county": 12596810, "suburb": 0, "state": 2345482, "region": 0, "localadmin": 12635628}, "woe:timezone_id": 28350890, "woe:hash": "u0yuvrxf8rkr", "woe:centroid": [9.73356, 50.095379], "geom:latitude": 50.095379, "geom:longitude": 9.73356, "geom:hash": "u0yuvrxf8rkr", "woe:latitude": 50.095379, "geom:centroid": [9.73356, 50.095379], "woe:longitude": 9.73356, "woe:repo": "woeplanet-poi-de", "geom:area": 0.0, "woe:scale": 19}}