{"type": "Feature", "id": 22954769, "geometry": {"type": "Point", "coordinates": [8.70867, 49.030449]}, "properties": {"woe:id": 22954769, "woe:parent_id": 641231, "woe:name": "Bretten-Wannenweg Bahnhof", "woe:placetype": 20, "woe:placetype_name": "POI", "woe:lang": "GER", "iso:country": "DE", "meta:provider": ["geoplanet:7.3.1", "geoplanet:7.3.2", "geoplanet:7.4.0", "geoplanet:7.4.1", "geoplanet:7.5.1", "geoplanet:7.5.2", "geoplanet:7.6.0", "geoplanet:7.8.1", "geoplanet:7.9.0", "geoplanet:7.10.0", "geoplanet:8.0.0", "woeplanet:8.0.0"], "meta:indexed": "2020-08-20T20:51:44.446593", "meta:updated": "2020-10-14T11:50:28.494543", "woe:alias_ENG_P": ["Bretten-Wannenweg Station"], "woe:hierarchy": {"continent": 24865675, "country": 23424829, "town": 0, "planet": 1, "county": 12597063, "suburb": 0, "state": 2345481, "region": 0, "localadmin": 12623868}, "woe:timezone_id": 28350890, "woe:hash": "u0wnyjtrndph", "woe:centroid": [8.70867, 49.030449], "geom:latitude": 49.030449, "geom:longitude": 8.70867, "geom:hash": "u0wnyjtrndph", "woe:latitude": 49.030449, "geom:centroid": [8.70867, 49.030449], "woe:longitude": 8.70867, "woe:repo": "woeplanet-poi-de", "geom:area": 0.0, "woe:scale": 19}}