{"type": "Feature", "id": 22175971, "properties": {"woe:id": 22175971, "woe:parent_id": 20171397, "woe:name": "Borgholzhausen Bahnhof", "woe:placetype": 20, "woe:placetype_name": "POI", "woe:lang": "GER", "iso:country": "DE", "meta:provider": ["geoplanet:7.3.1", "geoplanet:7.3.2", "geoplanet:7.4.0", "geoplanet:7.4.1", "geoplanet:7.5.1", "geoplanet:7.5.2", "geoplanet:7.6.0", "geoplanet:7.8.1", "geoplanet:7.9.0", "geoplanet:7.10.0", "geoplanet:8.0.0", "woeplanet:8.0.0"], "meta:indexed": "2020-08-20T20:51:38.647832", "meta:updated": "2020-08-22T01:51:39.498101", "woe:alias_ENG_P": ["Borgholzhausen Station"], "woe:hierarchy": {"continent": 24865675, "country": 23424829, "town": 0, "planet": 1, "county": 12597048, "suburb": 0, "state": 2345487, "region": 0, "localadmin": 12624501}, "woe:timezone_id": 28350890, "woe:hash": "u1mbk1u4nxnu", "woe:centroid": [8.2675, 52.08519], "geom:latitude": 52.08519, "geom:longitude": 8.2675, "geom:hash": "u1mbk1u4nxnu", "woe:latitude": 52.08519, "geom:centroid": [8.2675, 52.08519], "woe:longitude": 8.2675, "woe:repo": "woeplanet-poi-de"}, "geometry": {"coordinates": [8.2675, 52.08519], "type": "Point"}}