{"type": "Feature", "id": 22205807, "properties": {"woe:id": 22205807, "woe:parent_id": 653545, "woe:name": "Gottenheim Bahnhof", "woe:placetype": 20, "woe:placetype_name": "POI", "woe:lang": "GER", "iso:country": "DE", "meta:provider": ["geoplanet:7.3.1", "geoplanet:7.3.2", "geoplanet:7.4.0", "geoplanet:7.4.1", "geoplanet:7.5.1", "geoplanet:7.5.2", "geoplanet:7.6.0", "geoplanet:7.8.1", "geoplanet:7.9.0", "geoplanet:7.10.0", "geoplanet:8.0.0", "woeplanet:8.0.0"], "meta:indexed": "2020-08-20T20:51:39.939685", "meta:updated": "2020-08-22T01:51:40.119072", "woe:alias_ENG_P": ["Gottenheim Station"], "woe:hierarchy": {"continent": 24865675, "country": 23424829, "town": 0, "planet": 1, "county": 12596773, "suburb": 0, "state": 2345481, "region": 0, "localadmin": 12623329}, "woe:timezone_id": 28350890, "woe:hash": "u0t3rge0mfeq", "woe:centroid": [7.72776, 48.05151], "geom:latitude": 48.05151, "geom:longitude": 7.72776, "geom:hash": "u0t3rge0mfeq", "woe:latitude": 48.05151, "geom:centroid": [7.72776, 48.05151], "woe:longitude": 7.72776, "woe:repo": "woeplanet-poi-de"}, "geometry": {"coordinates": [7.72776, 48.05151], "type": "Point"}}