{"type": "Feature", "id": 22275036, "geometry": {"type": "Point", "coordinates": [12.55639, 52.319351]}, "properties": {"woe:id": 22275036, "woe:parent_id": 668569, "woe:name": "Krahne Bahnhof", "woe:placetype": 20, "woe:placetype_name": "POI", "woe:lang": "GER", "iso:country": "DE", "meta:provider": ["geoplanet:7.3.1", "geoplanet:7.3.2", "geoplanet:7.4.0", "geoplanet:7.4.1", "geoplanet:7.5.1", "geoplanet:7.5.2", "geoplanet:7.6.0", "geoplanet:7.8.1", "geoplanet:7.9.0", "geoplanet:7.10.0", "geoplanet:8.0.0", "woeplanet:8.0.0"], "meta:indexed": "2020-08-20T20:51:42.686656", "meta:updated": "2020-10-14T11:50:59.589339", "woe:alias_ENG_P": ["Krahne Station"], "woe:hierarchy": {"continent": 24865675, "country": 23424829, "town": 0, "planet": 1, "county": 12596947, "suburb": 0, "state": 2345491, "region": 0, "localadmin": 24547172}, "woe:timezone_id": 28350890, "woe:hash": "u32ctsrq31fv", "woe:centroid": [12.55639, 52.319351], "geom:latitude": 52.319351, "geom:longitude": 12.55639, "geom:hash": "u32ctsrq31fv", "woe:latitude": 52.319351, "geom:centroid": [12.55639, 52.319351], "woe:longitude": 12.55639, "woe:repo": "woeplanet-poi-de", "geom:area": 0.0, "woe:scale": 19}}