{"type": "Feature", "id": 22232846, "properties": {"woe:id": 22232846, "woe:parent_id": 676783, "woe:name": "Heimatmuseum M\u00fcnchingen", "woe:placetype": 20, "woe:placetype_name": "POI", "woe:lang": "GER", "iso:country": "DE", "meta:provider": ["geoplanet:7.3.1", "geoplanet:7.3.2", "geoplanet:7.4.0", "geoplanet:7.4.1", "geoplanet:7.5.1", "geoplanet:7.5.2", "geoplanet:7.6.0", "geoplanet:7.8.1", "geoplanet:7.9.0", "geoplanet:7.10.0", "geoplanet:8.0.0", "woeplanet:8.0.0"], "meta:indexed": "2020-08-20T20:51:41.059287", "meta:updated": "2020-08-22T01:51:40.579884", "woe:alias_GER_S": ["Heimatmuseum Muenchingen", "Heimatmuseum Munchingen"], "woe:hierarchy": {"continent": 24865675, "country": 23424829, "town": 0, "planet": 1, "county": 12596746, "suburb": 0, "state": 2345481, "region": 0, "localadmin": 12623247}, "woe:timezone_id": 28350890, "woe:hash": "u0wmyv7t8sw6", "woe:centroid": [9.09053, 48.85305], "geom:latitude": 48.85305, "geom:longitude": 9.09053, "geom:hash": "u0wmyv7t8sw6", "woe:latitude": 48.85305, "geom:centroid": [9.09053, 48.85305], "woe:longitude": 9.09053, "woe:repo": "woeplanet-poi-de"}, "geometry": {"coordinates": [9.09053, 48.85305], "type": "Point"}}