{"type": "Feature", "id": 22941396, "properties": {"woe:id": 22941396, "woe:parent_id": 649066, "woe:name": "Hochdorf Bahnhof", "woe:placetype": 20, "woe:placetype_name": "POI", "woe:lang": "GER", "iso:country": "DE", "meta:provider": ["geoplanet:7.3.1", "geoplanet:7.3.2", "geoplanet:7.4.0", "geoplanet:7.4.1", "geoplanet:7.5.1", "geoplanet:7.5.2", "geoplanet:7.6.0", "geoplanet:7.8.1", "geoplanet:7.9.0", "geoplanet:7.10.0", "geoplanet:8.0.0", "woeplanet:8.0.0"], "meta:indexed": "2020-08-20T20:51:44.162290", "meta:updated": "2020-08-22T01:51:41.926576", "woe:alias_ENG_P": ["Hochdorf Station"], "woe:hierarchy": {"continent": 24865675, "country": 23424829, "town": 0, "planet": 1, "county": 12596691, "suburb": 0, "state": 2345481, "region": 0, "localadmin": 12623301}, "woe:timezone_id": 28350890, "woe:hash": "u0w5y3zt9bmh", "woe:centroid": [8.72254, 48.482239], "geom:latitude": 48.482239, "geom:longitude": 8.72254, "geom:hash": "u0w5y3zt9bmh", "woe:latitude": 48.482239, "geom:centroid": [8.72254, 48.482239], "woe:longitude": 8.72254, "woe:repo": "woeplanet-poi-de"}, "geometry": {"coordinates": [8.72254, 48.482239], "type": "Point"}}