{"type": "Feature", "id": 22976041, "properties": {"woe:id": 22976041, "woe:parent_id": 692795, "woe:name": "Wiesenburg Bahnhof", "woe:placetype": 20, "woe:placetype_name": "POI", "woe:lang": "GER", "iso:country": "DE", "meta:provider": ["geoplanet:7.3.1", "geoplanet:7.3.2", "geoplanet:7.4.0", "geoplanet:7.4.1", "geoplanet:7.5.1", "geoplanet:7.5.2", "geoplanet:7.6.0", "geoplanet:7.8.1", "geoplanet:7.9.0", "geoplanet:7.10.0", "geoplanet:8.0.0", "woeplanet:8.0.0"], "meta:indexed": "2020-08-20T20:51:44.897071", "meta:updated": "2020-08-22T01:51:42.309404", "woe:alias_ENG_P": ["Wiesenburg Station"], "woe:hierarchy": {"continent": 24865675, "country": 23424829, "town": 0, "planet": 1, "county": 56448167, "suburb": 0, "state": 2345493, "region": 0, "localadmin": 12636461}, "woe:timezone_id": 28350890, "woe:hash": "u30bjvjmecst", "woe:centroid": [12.56475, 50.653419], "geom:latitude": 50.653419, "geom:longitude": 12.56475, "geom:hash": "u30bjvjmecst", "woe:latitude": 50.653419, "geom:centroid": [12.56475, 50.653419], "woe:longitude": 12.56475, "woe:repo": "woeplanet-poi-de"}, "geometry": {"coordinates": [12.56475, 50.653419], "type": "Point"}}