{"type": "Feature", "id": 22176454, "properties": {"woe:id": 22176454, "woe:parent_id": 677912, "woe:name": "Max-Reger-Ged\u00e4chtniszimmer", "woe:placetype": 20, "woe:placetype_name": "POI", "woe:lang": "GER", "iso:country": "DE", "meta:provider": ["geoplanet:7.3.1", "geoplanet:7.3.2", "geoplanet:7.4.0", "geoplanet:7.4.1", "geoplanet:7.5.1", "geoplanet:7.5.2", "geoplanet:7.6.0", "geoplanet:7.8.1", "geoplanet:7.9.0", "geoplanet:7.10.0", "geoplanet:8.0.0", "woeplanet:8.0.0"], "meta:indexed": "2020-08-20T20:51:38.676690", "meta:updated": "2020-08-22T01:51:39.512192", "woe:alias_GER_S": ["Max-Reger-Gedaechtniszimmer", "Max-Reger-Gedachtniszimmer"], "woe:hierarchy": {"continent": 24865675, "country": 23424829, "town": 0, "planet": 1, "county": 12596744, "suburb": 0, "state": 2345482, "region": 0, "localadmin": 12634331}, "woe:timezone_id": 28350890, "woe:hash": "u2bkqbn7uj1q", "woe:centroid": [11.90695, 49.966492], "geom:latitude": 49.966492, "geom:longitude": 11.90695, "geom:hash": "u2bkqbn7uj1q", "woe:latitude": 49.966492, "geom:centroid": [11.90695, 49.966492], "woe:longitude": 11.90695, "woe:repo": "woeplanet-poi-de"}, "geometry": {"coordinates": [11.90695, 49.966492], "type": "Point"}}