{"type": "Feature", "id": 22289676, "geometry": {"type": "Point", "coordinates": [7.62516, 48.06805]}, "properties": {"woe:id": 22289676, "woe:parent_id": 633283, "woe:name": "Kaiserst\u00fchler Weinbaumuseum", "woe:placetype": 20, "woe:placetype_name": "POI", "woe:lang": "GER", "iso:country": "DE", "meta:provider": ["geoplanet:7.3.1", "geoplanet:7.3.2", "geoplanet:7.4.0", "geoplanet:7.4.1", "geoplanet:7.5.1", "geoplanet:7.5.2", "geoplanet:7.6.0", "geoplanet:7.8.1", "geoplanet:7.9.0", "geoplanet:7.10.0", "geoplanet:8.0.0", "woeplanet:8.0.0"], "meta:indexed": "2020-08-20T20:51:43.369495", "meta:updated": "2020-10-14T11:50:58.631160", "woe:alias_GER_V": ["Kaiserstuhler Weinbau-Museum", "Kaiserst\u00fchler Weinbau-Museum"], "woe:alias_GER_S": ["Kaiserstuehler Weinbaumuseum", "Kaiserstuhler Weinbaumuseum"], "woe:hierarchy": {"continent": 24865675, "country": 23424829, "town": 0, "planet": 1, "county": 12596773, "suburb": 0, "state": 2345481, "region": 0, "localadmin": 12623360}, "woe:timezone_id": 28350890, "woe:hash": "u0t3mw82xjgr", "woe:centroid": [7.62516, 48.06805], "geom:latitude": 48.06805, "geom:longitude": 7.62516, "geom:hash": "u0t3mw82xjgr", "woe:latitude": 48.06805, "geom:centroid": [7.62516, 48.06805], "woe:longitude": 7.62516, "woe:repo": "woeplanet-poi-de", "geom:area": 0.0, "woe:scale": 19}}