{"type": "Feature", "id": 22162072, "properties": {"woe:id": 22162072, "woe:parent_id": 682884, "woe:name": "Oegeln Bahnhof", "woe:placetype": 20, "woe:placetype_name": "POI", "woe:lang": "GER", "iso:country": "DE", "meta:provider": ["geoplanet:7.3.1", "geoplanet:7.3.2", "geoplanet:7.4.0", "geoplanet:7.4.1", "geoplanet:7.5.1", "geoplanet:7.5.2", "geoplanet:7.6.0", "geoplanet:7.8.1", "geoplanet:7.9.0", "geoplanet:7.10.0", "geoplanet:8.0.0", "woeplanet:8.0.0"], "meta:indexed": "2020-08-20T20:51:38.243516", "meta:updated": "2020-08-22T01:51:39.275275", "woe:alias_ENG_P": ["Oegeln Station"], "woe:hierarchy": {"continent": 24865675, "country": 23424829, "town": 0, "planet": 1, "county": 12596901, "suburb": 0, "state": 2345491, "region": 0, "localadmin": 12633487}, "woe:timezone_id": 28350890, "woe:hash": "u360u9xwfnxu", "woe:centroid": [14.27065, 52.17252], "geom:latitude": 52.17252, "geom:longitude": 14.27065, "geom:hash": "u360u9xwfnxu", "woe:latitude": 52.17252, "geom:centroid": [14.27065, 52.17252], "woe:longitude": 14.27065, "woe:repo": "woeplanet-poi-de"}, "geometry": {"coordinates": [14.27065, 52.17252], "type": "Point"}}