{"type": "Feature", "id": 22172129, "geometry": {"type": "Point", "coordinates": [7.2609, 49.23819]}, "properties": {"woe:id": 22172129, "woe:parent_id": 639519, "woe:name": "Blieskastel-Lautzkirchen Bahnhof", "woe:placetype": 20, "woe:placetype_name": "POI", "woe:lang": "GER", "iso:country": "DE", "meta:provider": ["geoplanet:7.3.1", "geoplanet:7.3.2", "geoplanet:7.4.0", "geoplanet:7.4.1", "geoplanet:7.5.1", "geoplanet:7.5.2", "geoplanet:7.6.0", "geoplanet:7.8.1", "geoplanet:7.9.0", "geoplanet:7.10.0", "geoplanet:8.0.0", "woeplanet:8.0.0"], "meta:indexed": "2020-08-20T20:51:38.528426", "meta:updated": "2020-10-14T11:50:27.503460", "woe:alias_ENG_P": ["Blieskastel-Lautzkirchen Station"], "woe:hierarchy": {"continent": 24865675, "country": 23424829, "town": 0, "planet": 1, "county": 12596978, "suburb": 0, "state": 2345489, "region": 0, "localadmin": 12635669}, "woe:timezone_id": 28350890, "woe:hash": "u0v0j5x1ppzk", "woe:centroid": [7.2609, 49.23819], "geom:latitude": 49.23819, "geom:longitude": 7.2609, "geom:hash": "u0v0j5x1ppzk", "woe:latitude": 49.23819, "geom:centroid": [7.2609, 49.23819], "woe:longitude": 7.2609, "woe:repo": "woeplanet-poi-de", "geom:area": 0.0, "woe:scale": 19}}