{"type": "Feature", "id": 22960781, "geometry": {"type": "Point", "coordinates": [10.73044, 50.686432]}, "properties": {"woe:id": 22960781, "woe:parent_id": 681428, "woe:name": "Oberhof Bahnhof", "woe:placetype": 20, "woe:placetype_name": "POI", "woe:lang": "GER", "iso:country": "DE", "meta:provider": ["geoplanet:7.3.1", "geoplanet:7.3.2", "geoplanet:7.4.0", "geoplanet:7.4.1", "geoplanet:7.5.1", "geoplanet:7.5.2", "geoplanet:7.6.0", "geoplanet:7.8.1", "geoplanet:7.9.0", "geoplanet:7.10.0", "geoplanet:8.0.0", "woeplanet:8.0.0"], "meta:indexed": "2020-08-20T20:51:44.535647", "meta:updated": "2020-10-14T11:50:28.922824", "woe:alias_ENG_P": ["Oberhof Station"], "woe:hierarchy": {"continent": 24865675, "country": 23424829, "town": 0, "planet": 1, "county": 12597005, "suburb": 0, "state": 2345495, "region": 0, "localadmin": 12624944}, "woe:timezone_id": 28350890, "woe:hash": "u1p8k5jtv7gb", "woe:centroid": [10.73044, 50.686432], "geom:latitude": 50.686432, "geom:longitude": 10.73044, "geom:hash": "u1p8k5jtv7gb", "woe:latitude": 50.686432, "geom:centroid": [10.73044, 50.686432], "woe:longitude": 10.73044, "woe:repo": "woeplanet-poi-de", "geom:area": 0.0, "woe:scale": 19}}