{"type": "Feature", "id": 23049190, "properties": {"woe:id": 23049190, "woe:parent_id": 694471, "woe:name": "Selm-Beifang Bahnhof", "woe:placetype": 20, "woe:placetype_name": "POI", "woe:lang": "GER", "iso:country": "DE", "meta:provider": ["geoplanet:7.3.1", "geoplanet:7.3.2", "geoplanet:7.4.0", "geoplanet:7.4.1", "geoplanet:7.5.1", "geoplanet:7.5.2", "geoplanet:7.6.0", "geoplanet:7.8.1", "geoplanet:7.9.0", "geoplanet:7.10.0", "geoplanet:8.0.0", "woeplanet:8.0.0"], "meta:indexed": "2020-08-20T20:51:45.739684", "meta:updated": "2020-08-22T01:51:42.947243", "woe:alias_ENG_P": ["Selm-Beifang Station"], "woe:hierarchy": {"continent": 24865675, "country": 23424829, "town": 0, "planet": 1, "county": 12596864, "suburb": 0, "state": 2345487, "region": 0, "localadmin": 12624497}, "woe:timezone_id": 28350890, "woe:hash": "u1jq1ds3x82u", "woe:centroid": [7.45489, 51.69368], "geom:latitude": 51.69368, "geom:longitude": 7.45489, "geom:hash": "u1jq1ds3x82u", "woe:latitude": 51.69368, "geom:centroid": [7.45489, 51.69368], "woe:longitude": 7.45489, "woe:repo": "woeplanet-poi-de"}, "geometry": {"coordinates": [7.45489, 51.69368], "type": "Point"}}