{"type": "Feature", "id": 22230731, "geometry": {"type": "Point", "coordinates": [6.9196, 50.951511]}, "properties": {"woe:id": 22230731, "woe:parent_id": 667931, "woe:name": "K\u00f6ln-Ehrenfeld Bahnhof", "woe:placetype": 20, "woe:placetype_name": "POI", "woe:lang": "GER", "iso:country": "DE", "meta:provider": ["geoplanet:7.3.1", "geoplanet:7.3.2", "geoplanet:7.4.0", "geoplanet:7.4.1", "geoplanet:7.5.1", "geoplanet:7.5.2", "geoplanet:7.6.0", "geoplanet:7.8.1", "geoplanet:7.9.0", "geoplanet:7.10.0", "geoplanet:8.0.0", "woeplanet:8.0.0"], "meta:indexed": "2020-08-20T20:51:40.912636", "meta:updated": "2020-10-14T11:50:57.763792", "woe:alias_ENG_S": ["Koln-Ehrenfeld Station"], "woe:alias_GER_S": ["Koeln-Ehrenfeld Bahnhof", "Koln-Ehrenfeld Bahnhof"], "woe:alias_ENG_P": ["Koln-Ehrenfeld Station"], "woe:hierarchy": {"continent": 24865675, "country": 23424829, "town": 0, "planet": 1, "county": 12597059, "suburb": 0, "state": 2345487, "region": 0, "localadmin": 26822778}, "woe:timezone_id": 28350890, "woe:hash": "u1hcv7qwn659", "woe:centroid": [6.9196, 50.951511], "geom:latitude": 50.951511, "geom:longitude": 6.9196, "geom:hash": "u1hcv7qwn659", "woe:latitude": 50.951511, "geom:centroid": [6.9196, 50.951511], "woe:longitude": 6.9196, "woe:repo": "woeplanet-poi-de", "geom:area": 0.0, "woe:scale": 19}}