{"type": "Feature", "id": 22277966, "geometry": {"type": "Point", "coordinates": [12.25227, 48.272968]}, "properties": {"woe:id": 22277966, "woe:parent_id": 693973, "woe:name": "Schwindegg Bahnhof", "woe:placetype": 20, "woe:placetype_name": "POI", "woe:lang": "GER", "iso:country": "DE", "meta:provider": ["geoplanet:7.3.1", "geoplanet:7.3.2", "geoplanet:7.4.0", "geoplanet:7.4.1", "geoplanet:7.5.1", "geoplanet:7.5.2", "geoplanet:7.6.0", "geoplanet:7.8.1", "geoplanet:7.9.0", "geoplanet:7.10.0", "geoplanet:8.0.0", "woeplanet:8.0.0"], "meta:indexed": "2020-08-20T20:51:42.839095", "meta:updated": "2020-10-14T11:50:57.521491", "woe:alias_ENG_P": ["Schwindegg Station"], "woe:hierarchy": {"continent": 24865675, "country": 23424829, "town": 0, "planet": 1, "county": 12596907, "suburb": 0, "state": 2345482, "region": 0, "localadmin": 12622754}, "woe:timezone_id": 28350890, "woe:hash": "u28dwgcf6t6w", "woe:centroid": [12.25227, 48.272968], "geom:latitude": 48.272968, "geom:longitude": 12.25227, "geom:hash": "u28dwgcf6t6w", "woe:latitude": 48.272968, "geom:centroid": [12.25227, 48.272968], "woe:longitude": 12.25227, "woe:repo": "woeplanet-poi-de", "geom:area": 0.0, "woe:scale": 19}}