{"type": "Feature", "id": 22226061, "properties": {"woe:id": 22226061, "woe:parent_id": 665005, "woe:name": "Karst\u00e4dt Bahnhof", "woe:placetype": 20, "woe:placetype_name": "POI", "woe:lang": "GER", "iso:country": "DE", "meta:provider": ["geoplanet:7.3.1", "geoplanet:7.3.2", "geoplanet:7.4.0", "geoplanet:7.4.1", "geoplanet:7.5.1", "geoplanet:7.5.2", "geoplanet:7.6.0", "geoplanet:7.8.1", "geoplanet:7.9.0", "geoplanet:7.10.0", "geoplanet:8.0.0", "woeplanet:8.0.0"], "meta:indexed": "2020-08-20T20:51:40.781799", "meta:updated": "2020-08-22T01:51:40.462944", "woe:alias_ENG_S": ["Karstadt Station"], "woe:alias_GER_S": ["Karstaedt Bahnhof", "Karstadt Bahnhof"], "woe:alias_ENG_P": ["Karstadt Station"], "woe:hierarchy": {"continent": 24865675, "country": 23424829, "town": 0, "planet": 1, "county": 12596708, "suburb": 0, "state": 2345491, "region": 0, "localadmin": 24547342}, "woe:timezone_id": 28350890, "woe:hash": "u32q7jecg719", "woe:centroid": [11.73869, 53.160412], "geom:latitude": 53.160412, "geom:longitude": 11.73869, "geom:hash": "u32q7jecg719", "woe:latitude": 53.160412, "geom:centroid": [11.73869, 53.160412], "woe:longitude": 11.73869, "woe:repo": "woeplanet-poi-de"}, "geometry": {"coordinates": [11.73869, 53.160412], "type": "Point"}}