{"type": "Feature", "id": 22176356, "geometry": {"type": "Point", "coordinates": [9.06522, 49.07774]}, "properties": {"woe:id": 22176356, "woe:parent_id": 640636, "woe:name": "Theodor-Heuss-Ged\u00e4chtnisst\u00e4tte", "woe:placetype": 20, "woe:placetype_name": "POI", "woe:lang": "GER", "iso:country": "DE", "meta:provider": ["geoplanet:7.3.1", "geoplanet:7.3.2", "geoplanet:7.4.0", "geoplanet:7.4.1", "geoplanet:7.5.1", "geoplanet:7.5.2", "geoplanet:7.6.0", "geoplanet:7.8.1", "geoplanet:7.9.0", "geoplanet:7.10.0", "geoplanet:8.0.0", "woeplanet:8.0.0"], "meta:indexed": "2020-08-20T20:51:38.673266", "meta:updated": "2020-10-14T11:50:26.986479", "woe:alias_GER_S": ["Theodor-Heuss-Gedaechtnisstaette", "Theodor-Heuss-Gedachtnisstatte"], "woe:hierarchy": {"continent": 24865675, "country": 23424829, "town": 0, "planet": 1, "county": 12596745, "suburb": 0, "state": 2345481, "region": 0, "localadmin": 12623275}, "woe:timezone_id": 28350890, "woe:hash": "u0wrnq34dcvf", "woe:centroid": [9.06522, 49.07774], "geom:latitude": 49.07774, "geom:longitude": 9.06522, "geom:hash": "u0wrnq34dcvf", "woe:latitude": 49.07774, "geom:centroid": [9.06522, 49.07774], "woe:longitude": 9.06522, "woe:repo": "woeplanet-poi-de", "geom:area": 0.0, "woe:scale": 19}}