{"type": "Feature", "id": 22948222, "properties": {"woe:id": 22948222, "woe:parent_id": 698064, "woe:name": "M\u00fcnster Rathaus Bahnhof", "woe:placetype": 20, "woe:placetype_name": "POI", "woe:lang": "GER", "iso:country": "DE", "meta:provider": ["geoplanet:7.3.1", "geoplanet:7.3.2", "geoplanet:7.4.0", "geoplanet:7.4.1", "geoplanet:7.5.1", "geoplanet:7.5.2", "geoplanet:7.6.0", "geoplanet:7.8.1", "geoplanet:7.9.0", "geoplanet:7.10.0", "geoplanet:8.0.0", "woeplanet:8.0.0"], "meta:indexed": "2020-08-20T20:51:44.276729", "meta:updated": "2020-08-22T01:51:41.987501", "woe:alias_ENG_S": ["Munster Rathaus Station"], "woe:alias_GER_S": ["Muenster Rathaus Bahnhof", "Munster Rathaus Bahnhof"], "woe:alias_ENG_P": ["Munster Rathaus Station"], "woe:hierarchy": {"continent": 24865675, "country": 23424829, "town": 0, "planet": 1, "county": 12597071, "suburb": 0, "state": 2345481, "region": 0, "localadmin": 26823292}, "woe:timezone_id": 28350890, "woe:hash": "u0wt9zwepg97", "woe:centroid": [9.22679, 48.82103], "geom:latitude": 48.82103, "geom:longitude": 9.22679, "geom:hash": "u0wt9zwepg97", "woe:latitude": 48.82103, "geom:centroid": [9.22679, 48.82103], "woe:longitude": 9.22679, "woe:repo": "woeplanet-poi-de"}, "geometry": {"coordinates": [9.22679, 48.82103], "type": "Point"}}