{"type": "Feature", "id": 56055738, "geometry": {"type": "Point", "coordinates": [9.71224, 49.27504]}, "properties": {"woe:id": 56055738, "woe:parent_id": 676230, "woe:name": "Fachhochschule Heilbronn", "woe:placetype": 20, "woe:placetype_name": "POI", "woe:lang": "GER", "iso:country": "DE", "meta:provider": ["geoplanet:7.3.1", "geoplanet:7.3.2", "geoplanet:7.4.0", "geoplanet:7.4.1", "geoplanet:7.5.1", "geoplanet:7.5.2", "geoplanet:7.6.0", "geoplanet:7.8.1", "geoplanet:7.9.0", "geoplanet:7.10.0", "geoplanet:8.0.0", "woeplanet:8.0.0"], "meta:indexed": "2020-08-20T20:51:45.969802", "meta:updated": "2020-10-14T11:50:35.524361", "woe:hierarchy": {"continent": 24865675, "country": 23424829, "town": 0, "planet": 1, "county": 12596848, "suburb": 0, "state": 2345481, "region": 0, "localadmin": 12624132}, "woe:timezone_id": 28350890, "woe:hash": "u0ybm40pzt5n", "woe:centroid": [9.71224, 49.27504], "geom:latitude": 49.27504, "geom:longitude": 9.71224, "geom:hash": "u0ybm40pzt5n", "woe:latitude": 49.27504, "geom:centroid": [9.71224, 49.27504], "woe:longitude": 9.71224, "woe:repo": "woeplanet-poi-de", "geom:area": 0.0, "woe:scale": 19}}