{"type": "Feature", "id": 22257664, "properties": {"woe:id": 22257664, "woe:parent_id": 680564, "woe:name": "Museum Industriekultur", "woe:placetype": 20, "woe:placetype_name": "POI", "woe:lang": "GER", "iso:country": "DE", "meta:provider": ["geoplanet:7.3.1", "geoplanet:7.3.2", "geoplanet:7.4.0", "geoplanet:7.4.1", "geoplanet:7.5.1", "geoplanet:7.5.2", "geoplanet:7.6.0", "geoplanet:7.8.1", "geoplanet:7.9.0", "geoplanet:7.10.0", "geoplanet:8.0.0", "woeplanet:8.0.0"], "meta:indexed": "2020-08-20T20:51:41.989431", "meta:updated": "2020-08-22T01:51:40.948385", "woe:hierarchy": {"continent": 24865675, "country": 23424829, "town": 0, "planet": 1, "county": 12596973, "suburb": 0, "state": 2345482, "region": 0, "localadmin": 26823114}, "woe:timezone_id": 28350890, "woe:hash": "u0zcku4zntt5", "woe:centroid": [11.11124, 49.461681], "geom:latitude": 49.461681, "geom:longitude": 11.11124, "geom:hash": "u0zcku4zntt5", "woe:latitude": 49.461681, "geom:centroid": [11.11124, 49.461681], "woe:longitude": 11.11124, "woe:repo": "woeplanet-poi-de"}, "geometry": {"coordinates": [11.11124, 49.461681], "type": "Point"}}