{"type": "Feature", "id": 22259657, "geometry": {"type": "Point", "coordinates": [12.47514, 50.76395]}, "properties": {"woe:id": 22259657, "woe:parent_id": 682146, "woe:name": "Oberrothenbach Bahnhof", "woe:placetype": 20, "woe:placetype_name": "POI", "woe:lang": "GER", "iso:country": "DE", "meta:provider": ["geoplanet:7.3.1", "geoplanet:7.3.2", "geoplanet:7.4.0", "geoplanet:7.4.1", "geoplanet:7.5.1", "geoplanet:7.5.2", "geoplanet:7.6.0", "geoplanet:7.8.1", "geoplanet:7.9.0", "geoplanet:7.10.0", "geoplanet:8.0.0", "woeplanet:8.0.0"], "meta:indexed": "2020-08-20T20:51:42.049027", "meta:updated": "2020-10-14T11:50:58.562054", "woe:alias_ENG_P": ["Oberrothenbach Station"], "woe:hierarchy": {"continent": 24865675, "country": 23424829, "town": 0, "planet": 1, "county": 56448167, "suburb": 0, "state": 2345493, "region": 0, "localadmin": 12636453}, "woe:timezone_id": 28350890, "woe:hash": "u30bgck17y4t", "woe:centroid": [12.47514, 50.76395], "geom:latitude": 50.76395, "geom:longitude": 12.47514, "geom:hash": "u30bgck17y4t", "woe:latitude": 50.76395, "geom:centroid": [12.47514, 50.76395], "woe:longitude": 12.47514, "woe:repo": "woeplanet-poi-de", "geom:area": 0.0, "woe:scale": 19}}