{"type": "Feature", "id": 22237061, "geometry": {"type": "Point", "coordinates": [12.26678, 51.31496]}, "properties": {"woe:id": 22237061, "woe:parent_id": 671072, "woe:name": "Leipzig-Miltitzer Allee Bahnhof", "woe:placetype": 20, "woe:placetype_name": "POI", "woe:lang": "GER", "iso:country": "DE", "meta:provider": ["geoplanet:7.3.1", "geoplanet:7.3.2", "geoplanet:7.4.0", "geoplanet:7.4.1", "geoplanet:7.5.1", "geoplanet:7.5.2", "geoplanet:7.6.0", "geoplanet:7.8.1", "geoplanet:7.9.0", "geoplanet:7.10.0", "geoplanet:8.0.0", "woeplanet:8.0.0"], "meta:indexed": "2020-08-20T20:51:41.253516", "meta:updated": "2020-10-14T11:50:59.396043", "woe:alias_ENG_P": ["Leipzig-Miltitzer Allee Station"], "woe:hierarchy": {"continent": 24865675, "country": 23424829, "town": 0, "planet": 1, "county": 12596753, "suburb": 0, "state": 2345493, "region": 0, "localadmin": 26822922}, "woe:timezone_id": 28350890, "woe:hash": "u30ezjs7k9y5", "woe:centroid": [12.26678, 51.31496], "geom:latitude": 51.31496, "geom:longitude": 12.26678, "geom:hash": "u30ezjs7k9y5", "woe:latitude": 51.31496, "geom:centroid": [12.26678, 51.31496], "woe:longitude": 12.26678, "woe:repo": "woeplanet-poi-de", "geom:area": 0.0, "woe:scale": 19}}