{"type": "Feature", "id": 22299382, "geometry": {"type": "Point", "coordinates": [12.739, 51.364689]}, "properties": {"woe:id": 22299382, "woe:parent_id": 708290, "woe:name": "Wurzen Bahnhof", "woe:placetype": 20, "woe:placetype_name": "POI", "woe:lang": "GER", "iso:country": "DE", "meta:provider": ["geoplanet:7.3.1", "geoplanet:7.3.2", "geoplanet:7.4.0", "geoplanet:7.4.1", "geoplanet:7.5.1", "geoplanet:7.5.2", "geoplanet:7.6.0", "geoplanet:7.8.1", "geoplanet:7.9.0", "geoplanet:7.10.0", "geoplanet:8.0.0", "woeplanet:8.0.0"], "meta:indexed": "2020-08-20T20:51:43.781760", "meta:updated": "2020-10-14T11:50:58.692306", "woe:alias_ENG_P": ["Wurzen Station"], "woe:hierarchy": {"continent": 24865675, "country": 23424829, "town": 0, "planet": 1, "county": 56448169, "suburb": 0, "state": 2345493, "region": 0, "localadmin": 12625714}, "woe:timezone_id": 28350890, "woe:hash": "u31h1ysm00nb", "woe:centroid": [12.739, 51.364689], "geom:latitude": 51.364689, "geom:longitude": 12.739, "geom:hash": "u31h1ysm00nb", "woe:latitude": 51.364689, "geom:centroid": [12.739, 51.364689], "woe:longitude": 12.739, "woe:repo": "woeplanet-poi-de", "geom:area": 0.0, "woe:scale": 19}}