{"type": "Feature", "id": 22224587, "properties": {"woe:id": 22224587, "woe:parent_id": 664474, "woe:name": "Kennelgarten Bahnhof", "woe:placetype": 20, "woe:placetype_name": "POI", "woe:lang": "GER", "iso:country": "DE", "meta:provider": ["geoplanet:7.3.1", "geoplanet:7.3.2", "geoplanet:7.4.0", "geoplanet:7.4.1", "geoplanet:7.5.1", "geoplanet:7.5.2", "geoplanet:7.6.0", "geoplanet:7.8.1", "geoplanet:7.9.0", "geoplanet:7.10.0", "geoplanet:8.0.0", "woeplanet:8.0.0"], "meta:indexed": "2020-08-20T20:51:40.733177", "meta:updated": "2020-08-22T01:51:40.441168", "woe:alias_ENG_P": ["Kennelgarten Station"], "woe:hierarchy": {"continent": 24865675, "country": 23424829, "town": 0, "planet": 1, "county": 20071104, "suburb": 0, "state": 2345488, "region": 0, "localadmin": 12627134}, "woe:timezone_id": 28350890, "woe:hash": "u0v3rbrnqequ", "woe:centroid": [7.73329, 49.440941], "geom:latitude": 49.440941, "geom:longitude": 7.73329, "geom:hash": "u0v3rbrnqequ", "woe:latitude": 49.440941, "geom:centroid": [7.73329, 49.440941], "woe:longitude": 7.73329, "woe:repo": "woeplanet-poi-de"}, "geometry": {"coordinates": [7.73329, 49.440941], "type": "Point"}}