{"type": "Feature", "id": 22157946, "geometry": {"type": "Point", "coordinates": [6.76274, 50.55452]}, "properties": {"woe:id": 22157946, "woe:parent_id": 636469, "woe:name": "H\u00fcrten-Heimatmuseum", "woe:placetype": 20, "woe:placetype_name": "POI", "woe:lang": "GER", "iso:country": "DE", "meta:provider": ["geoplanet:7.3.1", "geoplanet:7.3.2", "geoplanet:7.4.0", "geoplanet:7.4.1", "geoplanet:7.5.1", "geoplanet:7.5.2", "geoplanet:7.6.0", "geoplanet:7.8.1", "geoplanet:7.9.0", "geoplanet:7.10.0", "geoplanet:8.0.0", "woeplanet:8.0.0"], "meta:indexed": "2020-08-20T20:51:38.079838", "meta:updated": "2020-10-14T11:50:28.250787", "woe:alias_GER_S": ["Huerten-Heimatmuseum", "Hurten-Heimatmuseum"], "woe:hierarchy": {"continent": 24865675, "country": 23424829, "town": 0, "planet": 1, "county": 12596895, "suburb": 0, "state": 2345487, "region": 0, "localadmin": 12624590}, "woe:timezone_id": 28350890, "woe:hash": "u0uz9ghmrm86", "woe:centroid": [6.76274, 50.55452], "geom:latitude": 50.55452, "geom:longitude": 6.76274, "geom:hash": "u0uz9ghmrm86", "woe:latitude": 50.55452, "geom:centroid": [6.76274, 50.55452], "woe:longitude": 6.76274, "woe:repo": "woeplanet-poi-de", "geom:area": 0.0, "woe:scale": 19}}