{"type": "Feature", "id": 22224433, "geometry": {"type": "Point", "coordinates": [13.49521, 53.122211]}, "properties": {"woe:id": 22224433, "woe:parent_id": 698831, "woe:name": "Produktionsmuseum Klosterm\u00fchle", "woe:placetype": 20, "woe:placetype_name": "POI", "woe:lang": "GER", "iso:country": "DE", "meta:provider": ["geoplanet:7.3.1", "geoplanet:7.3.2", "geoplanet:7.4.0", "geoplanet:7.4.1", "geoplanet:7.5.1", "geoplanet:7.5.2", "geoplanet:7.6.0", "geoplanet:7.8.1", "geoplanet:7.9.0", "geoplanet:7.10.0", "geoplanet:8.0.0", "woeplanet:8.0.0"], "meta:indexed": "2020-08-20T20:51:40.723314", "meta:updated": "2020-10-14T11:50:58.327735", "woe:alias_GER_S": ["Produktionsmuseum Klostermuehle", "Produktionsmuseum Klostermuhle"], "woe:hierarchy": {"continent": 24865675, "country": 23424829, "town": 0, "planet": 1, "county": 12596890, "suburb": 0, "state": 2345491, "region": 0, "localadmin": 12634174}, "woe:timezone_id": 28350890, "woe:hash": "u33w5ndgm1vg", "woe:centroid": [13.49521, 53.122211], "geom:latitude": 53.122211, "geom:longitude": 13.49521, "geom:hash": "u33w5ndgm1vg", "woe:latitude": 53.122211, "geom:centroid": [13.49521, 53.122211], "woe:longitude": 13.49521, "woe:repo": "woeplanet-poi-de", "geom:area": 0.0, "woe:scale": 19}}