{"type": "Feature", "id": 22232522, "properties": {"woe:id": 22232522, "woe:parent_id": 663791, "woe:name": "International Museum Tibetan Traditions", "woe:placetype": 20, "woe:placetype_name": "POI", "woe:lang": "GER", "iso:country": "DE", "meta:provider": ["geoplanet:7.3.1", "geoplanet:7.3.2", "geoplanet:7.4.0", "geoplanet:7.4.1", "geoplanet:7.5.1", "geoplanet:7.5.2", "geoplanet:7.6.0", "geoplanet:7.8.1", "geoplanet:7.9.0", "geoplanet:7.10.0", "geoplanet:8.0.0", "woeplanet:8.0.0"], "meta:indexed": "2020-08-20T20:51:41.035212", "meta:updated": "2020-08-22T01:51:40.568442", "woe:hierarchy": {"continent": 24865675, "country": 23424829, "town": 0, "planet": 1, "county": 12596828, "suburb": 0, "state": 2345487, "region": 0, "localadmin": 12624368}, "woe:timezone_id": 28350890, "woe:hash": "u1j0m33yh809", "woe:centroid": [7.26456, 50.676842], "geom:latitude": 50.676842, "geom:longitude": 7.26456, "geom:hash": "u1j0m33yh809", "woe:latitude": 50.676842, "geom:centroid": [7.26456, 50.676842], "woe:longitude": 7.26456, "woe:repo": "woeplanet-poi-de"}, "geometry": {"coordinates": [7.26456, 50.676842], "type": "Point"}}