{"type": "Feature", "id": 22207998, "properties": {"woe:id": 22207998, "woe:parent_id": 655903, "woe:name": "G\u00fcnzach Bahnhof", "woe:placetype": 20, "woe:placetype_name": "POI", "woe:lang": "GER", "iso:country": "DE", "meta:provider": ["geoplanet:7.3.1", "geoplanet:7.3.2", "geoplanet:7.4.0", "geoplanet:7.4.1", "geoplanet:7.5.1", "geoplanet:7.5.2", "geoplanet:7.6.0", "geoplanet:7.8.1", "geoplanet:7.9.0", "geoplanet:7.10.0", "geoplanet:8.0.0", "woeplanet:8.0.0"], "meta:indexed": "2020-08-20T20:51:40.111871", "meta:updated": "2020-08-22T01:51:40.193268", "woe:alias_ENG_S": ["Gunzach Station"], "woe:alias_GER_S": ["Guenzach Bahnhof", "Gunzach Bahnhof"], "woe:alias_ENG_P": ["Gunzach Station"], "woe:hierarchy": {"continent": 24865675, "country": 23424829, "town": 0, "planet": 1, "county": 12596920, "suburb": 0, "state": 2345482, "region": 0, "localadmin": 12634900}, "woe:timezone_id": 28350890, "woe:hash": "u0x2j939s5hv", "woe:centroid": [10.43925, 47.819641], "geom:latitude": 47.819641, "geom:longitude": 10.43925, "geom:hash": "u0x2j939s5hv", "woe:latitude": 47.819641, "geom:centroid": [10.43925, 47.819641], "woe:longitude": 10.43925, "woe:repo": "woeplanet-poi-de"}, "geometry": {"coordinates": [10.43925, 47.819641], "type": "Point"}}