{"type": "Feature", "id": 22974924, "geometry": {"type": "Point", "coordinates": [13.48536, 50.770359]}, "properties": {"woe:id": 22974924, "woe:parent_id": 677148, "woe:name": "Nassau Bahnhof", "woe:placetype": 20, "woe:placetype_name": "POI", "woe:lang": "GER", "iso:country": "DE", "meta:provider": ["geoplanet:7.3.1", "geoplanet:7.3.2", "geoplanet:7.4.0", "geoplanet:7.4.1", "geoplanet:7.5.1", "geoplanet:7.5.2", "geoplanet:7.6.0", "geoplanet:7.8.1", "geoplanet:7.9.0", "geoplanet:7.10.0", "geoplanet:8.0.0", "woeplanet:8.0.0"], "meta:indexed": "2020-08-20T20:51:44.851180", "meta:updated": "2020-10-14T11:50:29.267673", "woe:alias_ENG_P": ["Nassau Station"], "woe:hierarchy": {"continent": 24865675, "country": 23424829, "town": 0, "planet": 1, "county": 56448168, "suburb": 0, "state": 2345493, "region": 0, "localadmin": 12625588}, "woe:timezone_id": 28350890, "woe:hash": "u318ff7wz8vh", "woe:centroid": [13.48536, 50.770359], "geom:latitude": 50.770359, "geom:longitude": 13.48536, "geom:hash": "u318ff7wz8vh", "woe:latitude": 50.770359, "geom:centroid": [13.48536, 50.770359], "woe:longitude": 13.48536, "woe:repo": "woeplanet-poi-de", "geom:area": 0.0, "woe:scale": 19}}