{"type": "Feature", "id": 22258465, "geometry": {"type": "Point", "coordinates": [9.3402, 48.620312]}, "properties": {"woe:id": 22258465, "woe:parent_id": 680566, "woe:name": "N\u00fcrtingen-Vorstadt Bahnhof", "woe:placetype": 20, "woe:placetype_name": "POI", "woe:lang": "GER", "iso:country": "DE", "meta:provider": ["geoplanet:7.3.1", "geoplanet:7.3.2", "geoplanet:7.4.0", "geoplanet:7.4.1", "geoplanet:7.5.1", "geoplanet:7.5.2", "geoplanet:7.6.0", "geoplanet:7.8.1", "geoplanet:7.9.0", "geoplanet:7.10.0", "geoplanet:8.0.0", "woeplanet:8.0.0"], "meta:indexed": "2020-08-20T20:51:42.013291", "meta:updated": "2020-10-14T11:50:59.259040", "woe:alias_ENG_S": ["Nurtingen-Vorstadt Station"], "woe:alias_GER_S": ["Nuertingen-Vorstadt Bahnhof", "Nurtingen-Vorstadt Bahnhof"], "woe:alias_ENG_P": ["Nurtingen-Vorstadt Station"], "woe:hierarchy": {"continent": 24865675, "country": 23424829, "town": 0, "planet": 1, "county": 12596908, "suburb": 0, "state": 2345481, "region": 0, "localadmin": 12623192}, "woe:timezone_id": 28350890, "woe:hash": "u0wsse13f7jf", "woe:centroid": [9.3402, 48.620312], "geom:latitude": 48.620312, "geom:longitude": 9.3402, "geom:hash": "u0wsse13f7jf", "woe:latitude": 48.620312, "geom:centroid": [9.3402, 48.620312], "woe:longitude": 9.3402, "woe:repo": "woeplanet-poi-de", "geom:area": 0.0, "woe:scale": 19}}