{"type": "Feature", "id": 22300728, "geometry": {"type": "Point", "coordinates": [12.83887, 50.666431]}, "properties": {"woe:id": 22300728, "woe:parent_id": 645212, "woe:name": "Museum Knochenstampfe", "woe:placetype": 20, "woe:placetype_name": "POI", "woe:lang": "GER", "iso:country": "DE", "meta:provider": ["geoplanet:7.3.1", "geoplanet:7.3.2", "geoplanet:7.4.0", "geoplanet:7.4.1", "geoplanet:7.5.1", "geoplanet:7.5.2", "geoplanet:7.6.0", "geoplanet:7.8.1", "geoplanet:7.9.0", "geoplanet:7.10.0", "geoplanet:8.0.0", "woeplanet:8.0.0"], "meta:indexed": "2020-08-20T20:51:43.834093", "meta:updated": "2020-10-14T11:50:35.475351", "woe:alias_GER_V": ["Heimatmuseum Knochenstampfe"], "woe:hierarchy": {"continent": 24865675, "country": 23424829, "town": 0, "planet": 1, "county": 56448166, "suburb": 0, "state": 2345493, "region": 0, "localadmin": 12636550}, "woe:timezone_id": 28350890, "woe:hash": "u310hpscr773", "woe:centroid": [12.83887, 50.666431], "geom:latitude": 50.666431, "geom:longitude": 12.83887, "geom:hash": "u310hpscr773", "woe:latitude": 50.666431, "geom:centroid": [12.83887, 50.666431], "woe:longitude": 12.83887, "woe:repo": "woeplanet-poi-de", "geom:area": 0.0, "woe:scale": 19}}