{"type": "Feature", "id": 22183805, "geometry": {"type": "Point", "coordinates": [10.52146, 49.547112]}, "properties": {"woe:id": 22183805, "woe:parent_id": 645498, "woe:name": "Dottenheim Bahnhof", "woe:placetype": 20, "woe:placetype_name": "POI", "woe:lang": "GER", "iso:country": "DE", "meta:provider": ["geoplanet:7.3.1", "geoplanet:7.3.2", "geoplanet:7.4.0", "geoplanet:7.4.1", "geoplanet:7.5.1", "geoplanet:7.5.2", "geoplanet:7.6.0", "geoplanet:7.8.1", "geoplanet:7.9.0", "geoplanet:7.10.0", "geoplanet:8.0.0", "woeplanet:8.0.0"], "meta:indexed": "2020-08-20T20:51:39.020293", "meta:updated": "2020-10-14T11:50:27.153766", "woe:alias_ENG_P": ["Dottenheim Station"], "woe:hierarchy": {"continent": 24865675, "country": 23424829, "town": 0, "planet": 1, "county": 12596757, "suburb": 0, "state": 2345482, "region": 0, "localadmin": 12634502}, "woe:timezone_id": 28350890, "woe:hash": "u0z3z7v2zg15", "woe:centroid": [10.52146, 49.547112], "geom:latitude": 49.547112, "geom:longitude": 10.52146, "geom:hash": "u0z3z7v2zg15", "woe:latitude": 49.547112, "geom:centroid": [10.52146, 49.547112], "woe:longitude": 10.52146, "woe:repo": "woeplanet-poi-de", "geom:area": 0.0, "woe:scale": 19}}