{"type": "Feature", "id": 22996102, "properties": {"woe:id": 22996102, "woe:parent_id": 639363, "woe:name": "Blankenburg-Westend Bahnhof", "woe:placetype": 20, "woe:placetype_name": "POI", "woe:lang": "GER", "iso:country": "DE", "meta:provider": ["geoplanet:7.3.1", "geoplanet:7.3.2", "geoplanet:7.4.0", "geoplanet:7.4.1", "geoplanet:7.5.1", "geoplanet:7.5.2", "geoplanet:7.6.0", "geoplanet:7.8.1", "geoplanet:7.9.0", "geoplanet:7.10.0", "geoplanet:8.0.0", "woeplanet:8.0.0"], "meta:indexed": "2020-08-20T20:51:45.289547", "meta:updated": "2020-08-22T01:51:42.534944", "woe:alias_ENG_P": ["Blankenburg-Westend Station"], "woe:hierarchy": {"continent": 24865675, "country": 23424829, "town": 0, "planet": 1, "county": 12596713, "suburb": 0, "state": 2345494, "region": 0, "localadmin": 12635909}, "woe:timezone_id": 28350890, "woe:hash": "u1py8vpytzdb", "woe:centroid": [10.94229, 51.7962], "geom:latitude": 51.7962, "geom:longitude": 10.94229, "geom:hash": "u1py8vpytzdb", "woe:latitude": 51.7962, "geom:centroid": [10.94229, 51.7962], "woe:longitude": 10.94229, "woe:repo": "woeplanet-poi-de"}, "geometry": {"coordinates": [10.94229, 51.7962], "type": "Point"}}