{"type": "Feature", "id": 22264492, "properties": {"woe:id": 22264492, "woe:parent_id": 684952, "woe:name": "Pfreimd Bahnhof", "woe:placetype": 20, "woe:placetype_name": "POI", "woe:lang": "GER", "iso:country": "DE", "meta:provider": ["geoplanet:7.3.1", "geoplanet:7.3.2", "geoplanet:7.4.0", "geoplanet:7.4.1", "geoplanet:7.5.1", "geoplanet:7.5.2", "geoplanet:7.6.0", "geoplanet:7.8.1", "geoplanet:7.9.0", "geoplanet:7.10.0", "geoplanet:8.0.0", "woeplanet:8.0.0"], "meta:indexed": "2020-08-20T20:51:42.226874", "meta:updated": "2020-08-22T01:51:41.045807", "woe:alias_ENG_P": ["Pfreimd Station"], "woe:hierarchy": {"continent": 24865675, "country": 23424829, "town": 0, "planet": 1, "county": 12596931, "suburb": 0, "state": 2345482, "region": 0, "localadmin": 12634314}, "woe:timezone_id": 28350890, "woe:hash": "u2b9sbeuf5nb", "woe:centroid": [12.16711, 49.486], "geom:latitude": 49.486, "geom:longitude": 12.16711, "geom:hash": "u2b9sbeuf5nb", "woe:latitude": 49.486, "geom:centroid": [12.16711, 49.486], "woe:longitude": 12.16711, "woe:repo": "woeplanet-poi-de"}, "geometry": {"coordinates": [12.16711, 49.486], "type": "Point"}}