{"type": "Feature", "id": 22176559, "geometry": {"type": "Point", "coordinates": [13.20059, 54.199379]}, "properties": {"woe:id": 22176559, "woe:parent_id": 675320, "woe:name": "Miltzow Bahnhof", "woe:placetype": 20, "woe:placetype_name": "POI", "woe:lang": "GER", "iso:country": "DE", "meta:provider": ["geoplanet:7.3.1", "geoplanet:7.3.2", "geoplanet:7.4.0", "geoplanet:7.4.1", "geoplanet:7.5.1", "geoplanet:7.5.2", "geoplanet:7.6.0", "geoplanet:7.8.1", "geoplanet:7.9.0", "geoplanet:7.10.0", "geoplanet:8.0.0", "woeplanet:8.0.0"], "meta:indexed": "2020-08-20T20:51:38.685761", "meta:updated": "2020-10-14T11:50:27.472437", "woe:alias_ENG_P": ["Miltzow Station"], "woe:hierarchy": {"continent": 24865675, "country": 23424829, "town": 0, "planet": 1, "county": 12596758, "suburb": 0, "state": 2345492, "region": 0, "localadmin": 12630972}, "woe:timezone_id": 28350890, "woe:hash": "u39kk6sqk093", "woe:centroid": [13.20059, 54.199379], "geom:latitude": 54.199379, "geom:longitude": 13.20059, "geom:hash": "u39kk6sqk093", "woe:latitude": 54.199379, "geom:centroid": [13.20059, 54.199379], "woe:longitude": 13.20059, "woe:repo": "woeplanet-poi-de", "geom:area": 0.0, "woe:scale": 19}}