{"type": "Feature", "id": 22990258, "geometry": {"type": "Point", "coordinates": [7.95155, 50.827148]}, "properties": {"woe:id": 22990258, "woe:parent_id": 676416, "woe:name": "Mudersbach Bahnhof", "woe:placetype": 20, "woe:placetype_name": "POI", "woe:lang": "GER", "iso:country": "DE", "meta:provider": ["geoplanet:7.3.1", "geoplanet:7.3.2", "geoplanet:7.4.0", "geoplanet:7.4.1", "geoplanet:7.5.1", "geoplanet:7.5.2", "geoplanet:7.6.0", "geoplanet:7.8.1", "geoplanet:7.9.0", "geoplanet:7.10.0", "geoplanet:8.0.0", "woeplanet:8.0.0"], "meta:indexed": "2020-08-20T20:51:45.170436", "meta:updated": "2020-10-14T11:50:28.387414", "woe:alias_ENG_P": ["Mudersbach Station"], "woe:hierarchy": {"continent": 24865675, "country": 23424829, "town": 0, "planet": 1, "county": 12596853, "suburb": 0, "state": 2345488, "region": 0, "localadmin": 12627915}, "woe:timezone_id": 28350890, "woe:hash": "u1j9huy1se17", "woe:centroid": [7.95155, 50.827148], "geom:latitude": 50.827148, "geom:longitude": 7.95155, "geom:hash": "u1j9huy1se17", "woe:latitude": 50.827148, "geom:centroid": [7.95155, 50.827148], "woe:longitude": 7.95155, "woe:repo": "woeplanet-poi-de", "geom:area": 0.0, "woe:scale": 19}}