{"type": "Feature", "id": 22159271, "properties": {"woe:id": 22159271, "woe:parent_id": 636506, "woe:name": "Bad Schwartau Bahnhof", "woe:placetype": 20, "woe:placetype_name": "POI", "woe:lang": "GER", "iso:country": "DE", "meta:provider": ["geoplanet:7.3.1", "geoplanet:7.3.2", "geoplanet:7.4.0", "geoplanet:7.4.1", "geoplanet:7.5.1", "geoplanet:7.5.2", "geoplanet:7.6.0", "geoplanet:7.8.1", "geoplanet:7.9.0", "geoplanet:7.10.0", "geoplanet:8.0.0", "woeplanet:8.0.0"], "meta:indexed": "2020-08-20T20:51:38.119423", "meta:updated": "2020-08-22T01:51:39.208007", "woe:alias_ENG_P": ["Bad Schwartau Station"], "woe:hierarchy": {"continent": 24865675, "country": 23424829, "town": 0, "planet": 1, "county": 12596898, "suburb": 0, "state": 2345490, "region": 0, "localadmin": 12632289}, "woe:timezone_id": 28350890, "woe:hash": "u1xdex1mfe1g", "woe:centroid": [10.70251, 53.916409], "geom:latitude": 53.916409, "geom:longitude": 10.70251, "geom:hash": "u1xdex1mfe1g", "woe:latitude": 53.916409, "geom:centroid": [10.70251, 53.916409], "woe:longitude": 10.70251, "woe:repo": "woeplanet-poi-de"}, "geometry": {"coordinates": [10.70251, 53.916409], "type": "Point"}}