{"type": "Feature", "id": 22155782, "geometry": {"type": "Point", "coordinates": [11.16983, 50.689079]}, "properties": {"woe:id": 22155782, "woe:parent_id": 690062, "woe:name": "Rottenbach Bahnhof", "woe:placetype": 20, "woe:placetype_name": "POI", "woe:lang": "GER", "iso:country": "DE", "meta:provider": ["geoplanet:7.3.1", "geoplanet:7.3.2", "geoplanet:7.4.0", "geoplanet:7.4.1", "geoplanet:7.5.1", "geoplanet:7.5.2", "geoplanet:7.6.0", "geoplanet:7.8.1", "geoplanet:7.9.0", "geoplanet:7.10.0", "geoplanet:8.0.0", "woeplanet:8.0.0"], "meta:indexed": "2020-08-20T20:51:38.009681", "meta:updated": "2020-10-14T11:50:27.038581", "woe:alias_ENG_P": ["Rottenbach Station"], "woe:hierarchy": {"continent": 24865675, "country": 23424829, "town": 0, "planet": 1, "county": 12596965, "suburb": 0, "state": 2345495, "region": 0, "localadmin": 12625300}, "woe:timezone_id": 28350890, "woe:hash": "u1pbq5tt7chy", "woe:centroid": [11.16983, 50.689079], "geom:latitude": 50.689079, "geom:longitude": 11.16983, "geom:hash": "u1pbq5tt7chy", "woe:latitude": 50.689079, "geom:centroid": [11.16983, 50.689079], "woe:longitude": 11.16983, "woe:repo": "woeplanet-poi-de", "geom:area": 0.0, "woe:scale": 19}}