{"type": "Feature", "id": 22927166, "properties": {"woe:id": 22927166, "woe:parent_id": 668851, "woe:name": "Blaibach Bahnhof", "woe:placetype": 20, "woe:placetype_name": "POI", "woe:lang": "GER", "iso:country": "DE", "meta:provider": ["geoplanet:7.3.1", "geoplanet:7.3.2", "geoplanet:7.4.0", "geoplanet:7.4.1", "geoplanet:7.5.1", "geoplanet:7.5.2", "geoplanet:7.6.0", "geoplanet:7.8.1", "geoplanet:7.9.0", "geoplanet:7.10.0", "geoplanet:8.0.0", "woeplanet:8.0.0"], "meta:indexed": "2020-08-20T20:51:43.948793", "meta:updated": "2020-08-22T01:51:41.829369", "woe:alias_ENG_P": ["Blaibach Station"], "woe:hierarchy": {"continent": 24865675, "country": 23424829, "town": 0, "planet": 1, "county": 12596759, "suburb": 0, "state": 2345482, "region": 0, "localadmin": 12623066}, "woe:timezone_id": 28350890, "woe:hash": "u29pemyqsc8w", "woe:centroid": [12.80786, 49.16357], "geom:latitude": 49.16357, "geom:longitude": 12.80786, "geom:hash": "u29pemyqsc8w", "woe:latitude": 49.16357, "geom:centroid": [12.80786, 49.16357], "woe:longitude": 12.80786, "woe:repo": "woeplanet-poi-de"}, "geometry": {"coordinates": [12.80786, 49.16357], "type": "Point"}}