{"type": "Feature", "id": 22265941, "geometry": {"type": "Point", "coordinates": [11.53112, 48.07095]}, "properties": {"woe:id": 22265941, "woe:parent_id": 686199, "woe:name": "Gro\u00dfhesselohe Bahnhof", "woe:placetype": 20, "woe:placetype_name": "POI", "woe:lang": "GER", "iso:country": "DE", "meta:provider": ["geoplanet:7.3.1", "geoplanet:7.3.2", "geoplanet:7.4.0", "geoplanet:7.4.1", "geoplanet:7.5.1", "geoplanet:7.5.2", "geoplanet:7.6.0", "geoplanet:7.8.1", "geoplanet:7.9.0", "geoplanet:7.10.0", "geoplanet:8.0.0", "woeplanet:8.0.0"], "meta:indexed": "2020-08-20T20:51:42.293749", "meta:updated": "2020-10-14T11:50:59.809931", "woe:alias_ENG_S": ["Grosshesselohe Station"], "woe:alias_GER_S": ["Grosshesselohe Bahnhof"], "woe:alias_ENG_P": ["Grosshesselohe Station"], "woe:hierarchy": {"continent": 24865675, "country": 23424829, "town": 0, "planet": 1, "county": 12596963, "suburb": 0, "state": 2345482, "region": 0, "localadmin": 12636085}, "woe:timezone_id": 28350890, "woe:hash": "u281qrh9wdd6", "woe:centroid": [11.53112, 48.07095], "geom:latitude": 48.07095, "geom:longitude": 11.53112, "geom:hash": "u281qrh9wdd6", "woe:latitude": 48.07095, "geom:centroid": [11.53112, 48.07095], "woe:longitude": 11.53112, "woe:repo": "woeplanet-poi-de", "geom:area": 0.0, "woe:scale": 19}}