{"type": "Feature", "id": 22175774, "geometry": {"type": "Point", "coordinates": [9.91004, 53.664089]}, "properties": {"woe:id": 22175774, "woe:parent_id": 640176, "woe:name": "B\u00f6nningstedt Bahnhof", "woe:placetype": 20, "woe:placetype_name": "POI", "woe:lang": "GER", "iso:country": "DE", "meta:provider": ["geoplanet:7.3.1", "geoplanet:7.3.2", "geoplanet:7.4.0", "geoplanet:7.4.1", "geoplanet:7.5.1", "geoplanet:7.5.2", "geoplanet:7.6.0", "geoplanet:7.8.1", "geoplanet:7.9.0", "geoplanet:7.10.0", "geoplanet:8.0.0", "woeplanet:8.0.0"], "meta:indexed": "2020-08-20T20:51:38.640125", "meta:updated": "2020-10-14T11:50:28.030924", "woe:alias_ENG_S": ["Bonningstedt Station"], "woe:alias_GER_S": ["Boenningstedt Bahnhof", "Bonningstedt Bahnhof"], "woe:alias_ENG_P": ["Bonningstedt Station"], "woe:hierarchy": {"continent": 24865675, "country": 23424829, "town": 0, "planet": 1, "county": 12596897, "suburb": 0, "state": 2345490, "region": 0, "localadmin": 12632360}, "woe:timezone_id": 28350890, "woe:hash": "u1x1390rbxm2", "woe:centroid": [9.91004, 53.664089], "geom:latitude": 53.664089, "geom:longitude": 9.91004, "geom:hash": "u1x1390rbxm2", "woe:latitude": 53.664089, "geom:centroid": [9.91004, 53.664089], "woe:longitude": 9.91004, "woe:repo": "woeplanet-poi-de", "geom:area": 0.0, "woe:scale": 19}}