{"type": "Feature", "id": 22294550, "properties": {"woe:id": 22294550, "woe:parent_id": 15002839, "woe:name": "Heimatmuseum Wettenberg", "woe:placetype": 20, "woe:placetype_name": "POI", "woe:lang": "GER", "iso:country": "DE", "meta:provider": ["geoplanet:7.3.1", "geoplanet:7.3.2", "geoplanet:7.4.0", "geoplanet:7.4.1", "geoplanet:7.5.1", "geoplanet:7.5.2", "geoplanet:7.6.0", "geoplanet:7.8.1", "geoplanet:7.9.0", "geoplanet:7.10.0", "geoplanet:8.0.0", "woeplanet:8.0.0"], "meta:indexed": "2020-08-20T20:51:43.622273", "meta:updated": "2020-08-22T01:51:41.655011", "woe:hierarchy": {"continent": 24865675, "country": 23424829, "town": 0, "planet": 1, "county": 12596926, "suburb": 0, "state": 2345485, "region": 0, "localadmin": 12632655}, "woe:timezone_id": 28350890, "woe:hash": "u1n0h2swsqb4", "woe:centroid": [8.63063, 50.628899], "geom:latitude": 50.628899, "geom:longitude": 8.63063, "geom:hash": "u1n0h2swsqb4", "woe:latitude": 50.628899, "geom:centroid": [8.63063, 50.628899], "woe:longitude": 8.63063, "woe:repo": "woeplanet-poi-de"}, "geometry": {"coordinates": [8.63063, 50.628899], "type": "Point"}}