{"type": "Feature", "id": 22153184, "properties": {"woe:id": 22153184, "woe:parent_id": 634976, "woe:name": "Vorgeschichtsmuseum der Oberpfalz", "woe:placetype": 20, "woe:placetype_name": "POI", "woe:lang": "GER", "iso:country": "DE", "meta:provider": ["geoplanet:7.3.1", "geoplanet:7.3.2", "geoplanet:7.4.0", "geoplanet:7.4.1", "geoplanet:7.5.1", "geoplanet:7.5.2", "geoplanet:7.6.0", "geoplanet:7.8.1", "geoplanet:7.9.0", "geoplanet:7.10.0", "geoplanet:8.0.0", "woeplanet:8.0.0"], "meta:indexed": "2020-08-20T20:51:37.918772", "meta:updated": "2020-08-22T01:51:39.086737", "woe:alias_GER_V": ["Vorgeschichtsmuseum Oberpfalz"], "woe:hierarchy": {"continent": 24865675, "country": 23424829, "town": 0, "planet": 1, "county": 12597041, "suburb": 0, "state": 2345482, "region": 0, "localadmin": 12634220}, "woe:timezone_id": 28350890, "woe:hash": "u2b3mc1gj0g1", "woe:centroid": [11.85687, 49.444489], "geom:latitude": 49.444489, "geom:longitude": 11.85687, "geom:hash": "u2b3mc1gj0g1", "woe:latitude": 49.444489, "geom:centroid": [11.85687, 49.444489], "woe:longitude": 11.85687, "woe:repo": "woeplanet-poi-de"}, "geometry": {"coordinates": [11.85687, 49.444489], "type": "Point"}}