{"type": "Feature", "id": 22223623, "properties": {"woe:id": 22223623, "woe:parent_id": 663738, "woe:name": "Iserlohnerheide Bahnhof", "woe:placetype": 20, "woe:placetype_name": "POI", "woe:lang": "GER", "iso:country": "DE", "meta:provider": ["geoplanet:7.3.1", "geoplanet:7.3.2", "geoplanet:7.4.0", "geoplanet:7.4.1", "geoplanet:7.5.1", "geoplanet:7.5.2", "geoplanet:7.6.0", "geoplanet:7.8.1", "geoplanet:7.9.0", "geoplanet:7.10.0", "geoplanet:8.0.0", "woeplanet:8.0.0"], "meta:indexed": "2020-08-20T20:51:40.675970", "meta:updated": "2020-08-22T01:51:40.418762", "woe:alias_ENG_P": ["Iserlohnerheide Station"], "woe:hierarchy": {"continent": 24865675, "country": 23424829, "town": 0, "planet": 1, "county": 12596725, "suburb": 0, "state": 2345487, "region": 0, "localadmin": 12624261}, "woe:timezone_id": 28350890, "woe:hash": "u1jkrj1y7fh9", "woe:centroid": [7.693, 51.40062], "geom:latitude": 51.40062, "geom:longitude": 7.693, "geom:hash": "u1jkrj1y7fh9", "woe:latitude": 51.40062, "geom:centroid": [7.693, 51.40062], "woe:longitude": 7.693, "woe:repo": "woeplanet-poi-de"}, "geometry": {"coordinates": [7.693, 51.40062], "type": "Point"}}