{"type": "Feature", "id": 22277535, "geometry": {"type": "Point", "coordinates": [10.21213, 50.035568]}, "properties": {"woe:id": 22277535, "woe:parent_id": 693838, "woe:name": "Schweinfurt Hauptbahnhof", "woe:placetype": 20, "woe:placetype_name": "POI", "woe:lang": "GER", "iso:country": "DE", "meta:provider": ["geoplanet:7.3.1", "geoplanet:7.3.2", "geoplanet:7.4.0", "geoplanet:7.4.1", "geoplanet:7.5.1", "geoplanet:7.5.2", "geoplanet:7.6.0", "geoplanet:7.8.1", "geoplanet:7.9.0", "geoplanet:7.10.0", "geoplanet:8.0.0", "woeplanet:8.0.0"], "meta:indexed": "2020-08-20T20:51:42.820908", "meta:updated": "2020-10-14T11:50:59.541204", "woe:alias_ENG_P": ["Schweinfurt Central Station"], "woe:alias_ENG_V": ["Schweinfurt Station", "Schweinfurt Railway Station"], "woe:alias_GER_V": ["Schweinfurt Hbf", "Hauptbahnhof Schweinfurt", "Hbf Schweinfurt"], "woe:hierarchy": {"continent": 24865675, "country": 23424829, "town": 0, "planet": 1, "county": 12597113, "suburb": 0, "state": 2345482, "region": 0, "localadmin": 12635654}, "woe:timezone_id": 28350890, "woe:hash": "u0zk8ksnrcuj", "woe:centroid": [10.21213, 50.035568], "geom:latitude": 50.035568, "geom:longitude": 10.21213, "geom:hash": "u0zk8ksnrcuj", "woe:latitude": 50.035568, "geom:centroid": [10.21213, 50.035568], "woe:longitude": 10.21213, "woe:repo": "woeplanet-poi-de", "geom:area": 0.0, "woe:scale": 19}}