{"type": "Feature", "id": 22223043, "geometry": {"type": "Point", "coordinates": [8.72937, 47.936321]}, "properties": {"woe:id": 22223043, "woe:parent_id": 663436, "woe:name": "Immendingen Bahnhof", "woe:placetype": 20, "woe:placetype_name": "POI", "woe:lang": "GER", "iso:country": "DE", "meta:provider": ["geoplanet:7.3.1", "geoplanet:7.3.2", "geoplanet:7.4.0", "geoplanet:7.4.1", "geoplanet:7.5.1", "geoplanet:7.5.2", "geoplanet:7.6.0", "geoplanet:7.8.1", "geoplanet:7.9.0", "geoplanet:7.10.0", "geoplanet:8.0.0", "woeplanet:8.0.0"], "meta:indexed": "2020-08-20T20:51:40.659713", "meta:updated": "2020-10-14T11:50:57.170974", "woe:alias_ENG_P": ["Immendingen Station"], "woe:hierarchy": {"continent": 24865675, "country": 23424829, "town": 0, "planet": 1, "county": 12596922, "suburb": 0, "state": 2345481, "region": 0, "localadmin": 12623494}, "woe:timezone_id": 28350890, "woe:hash": "u0w0wws931fj", "woe:centroid": [8.72937, 47.936321], "geom:latitude": 47.936321, "geom:longitude": 8.72937, "geom:hash": "u0w0wws931fj", "woe:latitude": 47.936321, "geom:centroid": [8.72937, 47.936321], "woe:longitude": 8.72937, "woe:repo": "woeplanet-poi-de", "geom:area": 0.0, "woe:scale": 19}}