{"type": "Feature", "id": 22961592, "properties": {"woe:id": 22961592, "woe:parent_id": 698615, "woe:name": "M\u00fcnchen Bahnhof", "woe:placetype": 20, "woe:placetype_name": "POI", "woe:lang": "GER", "iso:country": "DE", "meta:provider": ["geoplanet:7.3.1", "geoplanet:7.3.2", "geoplanet:7.4.0", "geoplanet:7.4.1", "geoplanet:7.5.1", "geoplanet:7.5.2", "geoplanet:7.6.0", "geoplanet:7.8.1", "geoplanet:7.9.0", "geoplanet:7.10.0", "geoplanet:8.0.0", "woeplanet:8.0.0"], "meta:indexed": "2020-08-20T20:51:44.551699", "meta:updated": "2020-08-22T01:51:42.117393", "woe:alias_ENG_S": ["Munchen Station"], "woe:alias_GER_S": ["Muenchen Bahnhof", "Munchen Bahnhof"], "woe:alias_ENG_P": ["Munchen Station"], "woe:hierarchy": {"continent": 24865675, "country": 23424829, "town": 0, "planet": 1, "county": 12596997, "suburb": 0, "state": 2345495, "region": 0, "localadmin": 12625176}, "woe:timezone_id": 28350890, "woe:hash": "u3012he7pge4", "woe:centroid": [11.2548, 50.86998], "geom:latitude": 50.86998, "geom:longitude": 11.2548, "geom:hash": "u3012he7pge4", "woe:latitude": 50.86998, "geom:centroid": [11.2548, 50.86998], "woe:longitude": 11.2548, "woe:repo": "woeplanet-poi-de"}, "geometry": {"coordinates": [11.2548, 50.86998], "type": "Point"}}