{"type": "Feature", "id": 22948211, "geometry": {"type": "Point", "coordinates": [9.19188, 48.83226]}, "properties": {"woe:id": 22948211, "woe:parent_id": 698064, "woe:name": "F\u00fcrfelder Strasse Bahnhof", "woe:placetype": 20, "woe:placetype_name": "POI", "woe:lang": "GER", "iso:country": "DE", "meta:provider": ["geoplanet:7.3.1", "geoplanet:7.3.2", "geoplanet:7.4.0", "geoplanet:7.4.1", "geoplanet:7.5.1", "geoplanet:7.5.2", "geoplanet:7.6.0", "geoplanet:7.8.1", "geoplanet:7.9.0", "geoplanet:7.10.0", "geoplanet:8.0.0", "woeplanet:8.0.0"], "meta:indexed": "2020-08-20T20:51:44.267601", "meta:updated": "2020-10-14T11:50:28.621822", "woe:alias_ENG_S": ["Furfelder Strasse Station"], "woe:alias_GER_S": ["Fuerfelder Strasse Bahnhof", "Furfelder Strasse Bahnhof"], "woe:alias_ENG_P": ["Furfelder Strasse Station"], "woe:hierarchy": {"continent": 24865675, "country": 23424829, "town": 0, "planet": 1, "county": 12597071, "suburb": 0, "state": 2345481, "region": 0, "localadmin": 26823264}, "woe:timezone_id": 28350890, "woe:hash": "u0wtc1tkd343", "woe:centroid": [9.19188, 48.83226], "geom:latitude": 48.83226, "geom:longitude": 9.19188, "geom:hash": "u0wtc1tkd343", "woe:latitude": 48.83226, "geom:centroid": [9.19188, 48.83226], "woe:longitude": 9.19188, "woe:repo": "woeplanet-poi-de", "geom:area": 0.0, "woe:scale": 19}}