{"type": "Feature", "id": 22223356, "properties": {"woe:id": 22223356, "woe:parent_id": 663545, "woe:name": "Ingolstadt Hauptbahnhof", "woe:placetype": 20, "woe:placetype_name": "POI", "woe:lang": "GER", "iso:country": "DE", "meta:provider": ["geoplanet:7.3.1", "geoplanet:7.3.2", "geoplanet:7.4.0", "geoplanet:7.4.1", "geoplanet:7.5.1", "geoplanet:7.5.2", "geoplanet:7.6.0", "geoplanet:7.8.1", "geoplanet:7.9.0", "geoplanet:7.10.0", "geoplanet:8.0.0", "woeplanet:8.0.0"], "meta:indexed": "2020-08-20T20:51:40.666419", "meta:updated": "2020-08-22T01:51:56.402071", "woe:alias_ENG_P": ["Ingolstadt Central Station"], "woe:alias_ENG_V": ["Ingolstadt Railway Station", "Ingolstadt Station"], "woe:alias_GER_V": ["Ingolstadt Hbf", "Hauptbahnhof Ingolstadt", "Hbf Ingolstadt"], "woe:hierarchy": {"continent": 24865675, "country": 23424829, "town": 0, "planet": 1, "county": 12597077, "suburb": 0, "state": 2345482, "region": 0, "localadmin": 26822668}, "woe:timezone_id": 28350890, "woe:hash": "u28jk38humz6", "woe:centroid": [11.43696, 48.744438], "geom:latitude": 48.744438, "geom:longitude": 11.43696, "geom:hash": "u28jk38humz6", "woe:latitude": 48.744438, "geom:centroid": [11.43696, 48.744438], "woe:longitude": 11.43696, "woe:repo": "woeplanet-poi-de"}, "geometry": {"coordinates": [11.43696, 48.744438], "type": "Point"}}