{"type": "Feature", "id": 22930625, "geometry": {"type": "Point", "coordinates": [9.48195, 49.789398]}, "properties": {"woe:id": 22930625, "woe:parent_id": 657713, "woe:name": "Hasloch Bahnhof", "woe:placetype": 20, "woe:placetype_name": "POI", "woe:lang": "GER", "iso:country": "DE", "meta:provider": ["geoplanet:7.3.1", "geoplanet:7.3.2", "geoplanet:7.4.0", "geoplanet:7.4.1", "geoplanet:7.5.1", "geoplanet:7.5.2", "geoplanet:7.6.0", "geoplanet:7.8.1", "geoplanet:7.9.0", "geoplanet:7.10.0", "geoplanet:8.0.0", "woeplanet:8.0.0"], "meta:indexed": "2020-08-20T20:51:43.998795", "meta:updated": "2020-10-14T11:50:28.663633", "woe:alias_ENG_P": ["Hasloch Station"], "woe:hierarchy": {"continent": 24865675, "country": 23424829, "town": 0, "planet": 1, "county": 12596810, "suburb": 0, "state": 2345482, "region": 0, "localadmin": 12635630}, "woe:timezone_id": 28350890, "woe:hash": "u0yepzbs32qr", "woe:centroid": [9.48195, 49.789398], "geom:latitude": 49.789398, "geom:longitude": 9.48195, "geom:hash": "u0yepzbs32qr", "woe:latitude": 49.789398, "geom:centroid": [9.48195, 49.789398], "woe:longitude": 9.48195, "woe:repo": "woeplanet-poi-de", "geom:area": 0.0, "woe:scale": 19}}