{"type": "Feature", "id": 22232683, "properties": {"woe:id": 22232683, "woe:parent_id": 668213, "woe:name": "Konstanz-Petershausen Bahnhof", "woe:placetype": 20, "woe:placetype_name": "POI", "woe:lang": "GER", "iso:country": "DE", "meta:provider": ["geoplanet:7.3.1", "geoplanet:7.3.2", "geoplanet:7.4.0", "geoplanet:7.4.1", "geoplanet:7.5.1", "geoplanet:7.5.2", "geoplanet:7.6.0", "geoplanet:7.8.1", "geoplanet:7.9.0", "geoplanet:7.10.0", "geoplanet:8.0.0", "woeplanet:8.0.0"], "meta:indexed": "2020-08-20T20:51:41.048444", "meta:updated": "2020-08-22T01:51:40.574252", "woe:alias_ENG_P": ["Konstanz-Petershausen Station"], "woe:hierarchy": {"continent": 24865675, "country": 23424829, "town": 0, "planet": 1, "county": 12596692, "suburb": 0, "state": 2345481, "region": 0, "localadmin": 12623522}, "woe:timezone_id": 28350890, "woe:hash": "u0qx0wykncrn", "woe:centroid": [9.17148, 47.674492], "geom:latitude": 47.674492, "geom:longitude": 9.17148, "geom:hash": "u0qx0wykncrn", "woe:latitude": 47.674492, "geom:centroid": [9.17148, 47.674492], "woe:longitude": 9.17148, "woe:repo": "woeplanet-poi-de"}, "geometry": {"coordinates": [9.17148, 47.674492], "type": "Point"}}