{"type": "Feature", "id": 22153041, "geometry": {"type": "Point", "coordinates": [9.91649, 53.791359]}, "properties": {"woe:id": 22153041, "woe:parent_id": 634905, "woe:name": "Alveslohe Bahnhof", "woe:placetype": 20, "woe:placetype_name": "POI", "woe:lang": "GER", "iso:country": "DE", "meta:provider": ["geoplanet:7.3.1", "geoplanet:7.3.2", "geoplanet:7.4.0", "geoplanet:7.4.1", "geoplanet:7.5.1", "geoplanet:7.5.2", "geoplanet:7.6.0", "geoplanet:7.8.1", "geoplanet:7.9.0", "geoplanet:7.10.0", "geoplanet:8.0.0", "woeplanet:8.0.0"], "meta:indexed": "2020-08-20T20:51:37.910914", "meta:updated": "2020-10-14T11:50:27.157678", "woe:alias_ENG_P": ["Alveslohe Station"], "woe:hierarchy": {"continent": 24865675, "country": 23424829, "town": 0, "planet": 1, "county": 12597010, "suburb": 0, "state": 2345490, "region": 0, "localadmin": 12631655}, "woe:timezone_id": 28350890, "woe:hash": "u1x418kvqung", "woe:centroid": [9.91649, 53.791359], "geom:latitude": 53.791359, "geom:longitude": 9.91649, "geom:hash": "u1x418kvqung", "woe:latitude": 53.791359, "geom:centroid": [9.91649, 53.791359], "woe:longitude": 9.91649, "woe:repo": "woeplanet-poi-de", "geom:area": 0.0, "woe:scale": 19}}