{"type": "Feature", "id": 22175641, "geometry": {"type": "Point", "coordinates": [7.048, 50.73737]}, "properties": {"woe:id": 22175641, "woe:parent_id": 640161, "woe:name": "U Dransdorf Bahnhof", "woe:placetype": 20, "woe:placetype_name": "POI", "woe:lang": "GER", "iso:country": "DE", "meta:provider": ["geoplanet:7.3.1", "geoplanet:7.3.2", "geoplanet:7.4.0", "geoplanet:7.4.1", "geoplanet:7.5.1", "geoplanet:7.5.2", "geoplanet:7.6.0", "geoplanet:7.8.1", "geoplanet:7.9.0", "geoplanet:7.10.0", "geoplanet:8.0.0", "woeplanet:8.0.0"], "meta:indexed": "2020-08-20T20:51:38.622338", "meta:updated": "2020-10-14T11:50:27.896684", "woe:alias_ENG_P": ["U Dransdorf Station"], "woe:hierarchy": {"continent": 24865675, "country": 23424829, "town": 0, "planet": 1, "county": 12597065, "suburb": 0, "state": 2345487, "region": 0, "localadmin": 26822013}, "woe:timezone_id": 28350890, "woe:hash": "u1j08kknw739", "woe:centroid": [7.048, 50.73737], "geom:latitude": 50.73737, "geom:longitude": 7.048, "geom:hash": "u1j08kknw739", "woe:latitude": 50.73737, "geom:centroid": [7.048, 50.73737], "woe:longitude": 7.048, "woe:repo": "woeplanet-poi-de", "geom:area": 0.0, "woe:scale": 19}}