{"type": "Feature", "id": 22196744, "properties": {"woe:id": 22196744, "woe:parent_id": 707592, "woe:name": "Wolfershausen Bahnhof", "woe:placetype": 20, "woe:placetype_name": "POI", "woe:lang": "GER", "iso:country": "DE", "meta:provider": ["geoplanet:7.3.1", "geoplanet:7.3.2", "geoplanet:7.4.0", "geoplanet:7.4.1", "geoplanet:7.5.1", "geoplanet:7.5.2", "geoplanet:7.6.0", "geoplanet:7.8.1", "geoplanet:7.9.0", "geoplanet:7.10.0", "geoplanet:8.0.0", "woeplanet:8.0.0"], "meta:indexed": "2020-08-20T20:51:39.614120", "meta:updated": "2020-08-22T01:51:39.957996", "woe:alias_ENG_P": ["Wolfershausen Station"], "woe:hierarchy": {"continent": 24865675, "country": 23424829, "town": 0, "planet": 1, "county": 12596819, "suburb": 0, "state": 2345485, "region": 0, "localadmin": 12632807}, "woe:timezone_id": 28350890, "woe:hash": "u1nenyr878e4", "woe:centroid": [9.44771, 51.186722], "geom:latitude": 51.186722, "geom:longitude": 9.44771, "geom:hash": "u1nenyr878e4", "woe:latitude": 51.186722, "geom:centroid": [9.44771, 51.186722], "woe:longitude": 9.44771, "woe:repo": "woeplanet-poi-de"}, "geometry": {"coordinates": [9.44771, 51.186722], "type": "Point"}}