{"type": "Feature", "id": 22972613, "geometry": {"type": "Point", "coordinates": [12.92305, 52.167671]}, "properties": {"woe:id": 22972613, "woe:parent_id": 642111, "woe:name": "Buchholz Bahnhof", "woe:placetype": 20, "woe:placetype_name": "POI", "woe:lang": "GER", "iso:country": "DE", "meta:provider": ["geoplanet:7.3.1", "geoplanet:7.3.2", "geoplanet:7.4.0", "geoplanet:7.4.1", "geoplanet:7.5.1", "geoplanet:7.5.2", "geoplanet:7.6.0", "geoplanet:7.8.1", "geoplanet:7.9.0", "geoplanet:7.10.0", "geoplanet:8.0.0", "woeplanet:8.0.0"], "meta:indexed": "2020-08-20T20:51:44.795754", "meta:updated": "2020-10-14T11:50:29.120408", "woe:alias_ENG_P": ["Buchholz Station"], "woe:hierarchy": {"continent": 24865675, "country": 23424829, "town": 0, "planet": 1, "county": 12596947, "suburb": 0, "state": 2345491, "region": 0, "localadmin": 24547374}, "woe:timezone_id": 28350890, "woe:hash": "u330y0f68ysq", "woe:centroid": [12.92305, 52.167671], "geom:latitude": 52.167671, "geom:longitude": 12.92305, "geom:hash": "u330y0f68ysq", "woe:latitude": 52.167671, "geom:centroid": [12.92305, 52.167671], "woe:longitude": 12.92305, "woe:repo": "woeplanet-poi-de", "geom:area": 0.0, "woe:scale": 19}}