{"type": "Feature", "id": 22194578, "geometry": {"type": "Point", "coordinates": [7.02361, 51.422321]}, "properties": {"woe:id": 22194578, "woe:parent_id": 648820, "woe:name": "Essen-Stadtwald Bahnhof", "woe:placetype": 20, "woe:placetype_name": "POI", "woe:lang": "GER", "iso:country": "DE", "meta:provider": ["geoplanet:7.3.1", "geoplanet:7.3.2", "geoplanet:7.4.0", "geoplanet:7.4.1", "geoplanet:7.5.1", "geoplanet:7.5.2", "geoplanet:7.6.0", "geoplanet:7.8.1", "geoplanet:7.9.0", "geoplanet:7.10.0", "geoplanet:8.0.0", "woeplanet:8.0.0"], "meta:indexed": "2020-08-20T20:51:39.544442", "meta:updated": "2020-10-14T11:50:27.628660", "woe:alias_ENG_P": ["Essen-Stadtwald Station"], "woe:hierarchy": {"continent": 24865675, "country": 23424829, "town": 0, "planet": 1, "county": 12597009, "suburb": 0, "state": 2345487, "region": 0, "localadmin": 26822364}, "woe:timezone_id": 28350890, "woe:hash": "u1huxc4ktzrj", "woe:centroid": [7.02361, 51.422321], "geom:latitude": 51.422321, "geom:longitude": 7.02361, "geom:hash": "u1huxc4ktzrj", "woe:latitude": 51.422321, "geom:centroid": [7.02361, 51.422321], "woe:longitude": 7.02361, "woe:repo": "woeplanet-poi-de", "geom:area": 0.0, "woe:scale": 19}}