{"type": "Feature", "id": 22268395, "properties": {"woe:id": 22268395, "woe:parent_id": 687903, "woe:name": "Arp Museum Rolandseck", "woe:placetype": 20, "woe:placetype_name": "POI", "woe:lang": "GER", "iso:country": "DE", "meta:provider": ["geoplanet:7.3.1", "geoplanet:7.3.2", "geoplanet:7.4.0", "geoplanet:7.4.1", "geoplanet:7.5.1", "geoplanet:7.5.2", "geoplanet:7.6.0", "geoplanet:7.8.1", "geoplanet:7.9.0", "geoplanet:7.10.0", "geoplanet:8.0.0", "woeplanet:8.0.0"], "meta:indexed": "2020-08-20T20:51:42.415495", "meta:updated": "2020-08-22T01:51:41.123051", "woe:hierarchy": {"continent": 24865675, "country": 23424829, "town": 0, "planet": 1, "county": 12596824, "suburb": 0, "state": 2345488, "region": 0, "localadmin": 12627793}, "woe:timezone_id": 28350890, "woe:hash": "u0vpsx3q5kzk", "woe:centroid": [7.23087, 50.577991], "geom:latitude": 50.577991, "geom:longitude": 7.23087, "geom:hash": "u0vpsx3q5kzk", "woe:latitude": 50.577991, "geom:centroid": [7.23087, 50.577991], "woe:longitude": 7.23087, "woe:repo": "woeplanet-poi-de"}, "geometry": {"coordinates": [7.23087, 50.577991], "type": "Point"}}