{"type": "Feature", "id": 22234409, "geometry": {"type": "Point", "coordinates": [10.36208, 48.289631]}, "properties": {"woe:id": 22234409, "woe:parent_id": 660379, "woe:name": "Hirschfelden Bahnhof", "woe:placetype": 20, "woe:placetype_name": "POI", "woe:lang": "GER", "iso:country": "DE", "meta:provider": ["geoplanet:7.3.1", "geoplanet:7.3.2", "geoplanet:7.4.0", "geoplanet:7.4.1", "geoplanet:7.5.1", "geoplanet:7.5.2", "geoplanet:7.6.0", "geoplanet:7.8.1", "geoplanet:7.9.0", "geoplanet:7.10.0", "geoplanet:8.0.0", "woeplanet:8.0.0"], "meta:indexed": "2020-08-20T20:51:41.118266", "meta:updated": "2020-10-14T11:50:57.239011", "woe:alias_ENG_P": ["Hirschfelden Station"], "woe:hierarchy": {"continent": 24865675, "country": 23424829, "town": 0, "planet": 1, "county": 12596910, "suburb": 0, "state": 2345482, "region": 0, "localadmin": 12634839}, "woe:timezone_id": 28350890, "woe:hash": "u0x6eyc7mzwv", "woe:centroid": [10.36208, 48.289631], "geom:latitude": 48.289631, "geom:longitude": 10.36208, "geom:hash": "u0x6eyc7mzwv", "woe:latitude": 48.289631, "geom:centroid": [10.36208, 48.289631], "woe:longitude": 10.36208, "woe:repo": "woeplanet-poi-de", "geom:area": 0.0, "woe:scale": 19}}