{"type": "Feature", "id": 22192479, "geometry": {"type": "Point", "coordinates": [7.88606, 48.099751]}, "properties": {"woe:id": 22192479, "woe:parent_id": 667904, "woe:name": "Kollmarsreute Bahnhof", "woe:placetype": 20, "woe:placetype_name": "POI", "woe:lang": "GER", "iso:country": "DE", "meta:provider": ["geoplanet:7.3.1", "geoplanet:7.3.2", "geoplanet:7.4.0", "geoplanet:7.4.1", "geoplanet:7.5.1", "geoplanet:7.5.2", "geoplanet:7.6.0", "geoplanet:7.8.1", "geoplanet:7.9.0", "geoplanet:7.10.0", "geoplanet:8.0.0", "woeplanet:8.0.0"], "meta:indexed": "2020-08-20T20:51:39.441849", "meta:updated": "2020-10-14T11:50:27.466796", "woe:alias_ENG_P": ["Kollmarsreute Station"], "woe:hierarchy": {"continent": 24865675, "country": 23424829, "town": 0, "planet": 1, "county": 12596970, "suburb": 0, "state": 2345481, "region": 0, "localadmin": 12623365}, "woe:timezone_id": 28350890, "woe:hash": "u0t9ekq3qe2w", "woe:centroid": [7.88606, 48.099751], "geom:latitude": 48.099751, "geom:longitude": 7.88606, "geom:hash": "u0t9ekq3qe2w", "woe:latitude": 48.099751, "geom:centroid": [7.88606, 48.099751], "woe:longitude": 7.88606, "woe:repo": "woeplanet-poi-de", "geom:area": 0.0, "woe:scale": 19}}