{"type": "Feature", "id": 22236772, "geometry": {"type": "Point", "coordinates": [9.13885, 48.690159]}, "properties": {"woe:id": 22236772, "woe:parent_id": 20160128, "woe:name": "Deutsches Spielkarten Museum", "woe:placetype": 20, "woe:placetype_name": "POI", "woe:lang": "GER", "iso:country": "DE", "meta:provider": ["geoplanet:7.3.1", "geoplanet:7.3.2", "geoplanet:7.4.0", "geoplanet:7.4.1", "geoplanet:7.5.1", "geoplanet:7.5.2", "geoplanet:7.6.0", "geoplanet:7.8.1", "geoplanet:7.9.0", "geoplanet:7.10.0", "geoplanet:8.0.0", "woeplanet:8.0.0"], "meta:indexed": "2020-08-20T20:51:41.226444", "meta:updated": "2020-10-14T11:51:00.035650", "woe:alias_GER_V": ["Deutsches Spielkartenmuseum"], "woe:hierarchy": {"continent": 24865675, "country": 23424829, "town": 0, "planet": 1, "county": 12596908, "suburb": 0, "state": 2345481, "region": 0, "localadmin": 12623206}, "woe:timezone_id": 28350890, "woe:hash": "u0wkzzy8wxkr", "woe:centroid": [9.13885, 48.690159], "geom:latitude": 48.690159, "geom:longitude": 9.13885, "geom:hash": "u0wkzzy8wxkr", "woe:latitude": 48.690159, "geom:centroid": [9.13885, 48.690159], "woe:longitude": 9.13885, "woe:repo": "woeplanet-poi-de", "geom:area": 0.0, "woe:scale": 19}}