{"type": "Feature", "id": 22246382, "geometry": {"type": "Point", "coordinates": [9.16751, 50.06995]}, "properties": {"woe:id": 22246382, "woe:parent_id": 674804, "woe:name": "M\u00f6mbris-Mensenges\u00e4\u00df Bahnhof", "woe:placetype": 20, "woe:placetype_name": "POI", "woe:lang": "GER", "iso:country": "DE", "meta:provider": ["geoplanet:7.3.1", "geoplanet:7.3.2", "geoplanet:7.4.0", "geoplanet:7.4.1", "geoplanet:7.5.1", "geoplanet:7.5.2", "geoplanet:7.6.0", "geoplanet:7.8.1", "geoplanet:7.9.0", "geoplanet:7.10.0", "geoplanet:8.0.0", "woeplanet:8.0.0"], "meta:indexed": "2020-08-20T20:51:41.682275", "meta:updated": "2020-10-14T11:50:59.585803", "woe:alias_ENG_S": ["Mombris-Mensengesass Station"], "woe:alias_GER_S": ["Moembris-Mensengesaess Bahnhof", "Mombris-Mensengesass Bahnhof"], "woe:alias_ENG_P": ["Mombris-Mensengesass Station"], "woe:hierarchy": {"continent": 24865675, "country": 23424829, "town": 0, "planet": 1, "county": 12596953, "suburb": 0, "state": 2345482, "region": 0, "localadmin": 12635402}, "woe:timezone_id": 28350890, "woe:hash": "u0ysbdgwd7nv", "woe:centroid": [9.16751, 50.06995], "geom:latitude": 50.06995, "geom:longitude": 9.16751, "geom:hash": "u0ysbdgwd7nv", "woe:latitude": 50.06995, "geom:centroid": [9.16751, 50.06995], "woe:longitude": 9.16751, "woe:repo": "woeplanet-poi-de", "geom:area": 0.0, "woe:scale": 19}}