{"type": "Feature", "id": 22192698, "properties": {"woe:id": 22192698, "woe:parent_id": 648049, "woe:name": "Widukind-Museum", "woe:placetype": 20, "woe:placetype_name": "POI", "woe:lang": "GER", "iso:country": "DE", "meta:provider": ["geoplanet:7.3.1", "geoplanet:7.3.2", "geoplanet:7.4.0", "geoplanet:7.4.1", "geoplanet:7.5.1", "geoplanet:7.5.2", "geoplanet:7.6.0", "geoplanet:7.8.1", "geoplanet:7.9.0", "geoplanet:7.10.0", "geoplanet:8.0.0", "woeplanet:8.0.0"], "meta:indexed": "2020-08-20T20:51:39.461445", "meta:updated": "2020-08-22T01:51:39.880408", "woe:alias_GER_V": ["Widukind-Museum Enger"], "woe:hierarchy": {"continent": 24865675, "country": 23424829, "town": 0, "planet": 1, "county": 12596886, "suburb": 0, "state": 2345487, "region": 0, "localadmin": 12624513}, "woe:timezone_id": 28350890, "woe:hash": "u1q0dg8m6zwt", "woe:centroid": [8.55882, 52.139309], "geom:latitude": 52.139309, "geom:longitude": 8.55882, "geom:hash": "u1q0dg8m6zwt", "woe:latitude": 52.139309, "geom:centroid": [8.55882, 52.139309], "woe:longitude": 8.55882, "woe:repo": "woeplanet-poi-de"}, "geometry": {"coordinates": [8.55882, 52.139309], "type": "Point"}}