{"type": "Feature", "id": 22156412, "properties": {"woe:id": 22156412, "woe:parent_id": 700998, "woe:name": "Untergriesheim Bahnhof", "woe:placetype": 20, "woe:placetype_name": "POI", "woe:lang": "GER", "iso:country": "DE", "meta:provider": ["geoplanet:7.3.1", "geoplanet:7.3.2", "geoplanet:7.4.0", "geoplanet:7.4.1", "geoplanet:7.5.1", "geoplanet:7.5.2", "geoplanet:7.6.0", "geoplanet:7.8.1", "geoplanet:7.9.0", "geoplanet:7.10.0", "geoplanet:8.0.0", "woeplanet:8.0.0"], "meta:indexed": "2020-08-20T20:51:38.037534", "meta:updated": "2020-08-22T01:51:39.159206", "woe:alias_ENG_P": ["Untergriesheim Station"], "woe:hierarchy": {"continent": 24865675, "country": 23424829, "town": 0, "planet": 1, "county": 12596745, "suburb": 0, "state": 2345481, "region": 0, "localadmin": 12623271}, "woe:timezone_id": 28350890, "woe:hash": "u0y83b7sk09b", "woe:centroid": [9.22251, 49.264801], "geom:latitude": 49.264801, "geom:longitude": 9.22251, "geom:hash": "u0y83b7sk09b", "woe:latitude": 49.264801, "geom:centroid": [9.22251, 49.264801], "woe:longitude": 9.22251, "woe:repo": "woeplanet-poi-de"}, "geometry": {"coordinates": [9.22251, 49.264801], "type": "Point"}}