{"type": "Feature", "id": 22268598, "geometry": {"type": "Point", "coordinates": [9.43981, 48.805328]}, "properties": {"woe:id": 22268598, "woe:parent_id": 687949, "woe:name": "Geradstetten Bahnhof", "woe:placetype": 20, "woe:placetype_name": "POI", "woe:lang": "GER", "iso:country": "DE", "meta:provider": ["geoplanet:7.3.1", "geoplanet:7.3.2", "geoplanet:7.4.0", "geoplanet:7.4.1", "geoplanet:7.5.1", "geoplanet:7.5.2", "geoplanet:7.6.0", "geoplanet:7.8.1", "geoplanet:7.9.0", "geoplanet:7.10.0", "geoplanet:8.0.0", "woeplanet:8.0.0"], "meta:indexed": "2020-08-20T20:51:42.429184", "meta:updated": "2020-10-14T11:50:58.429200", "woe:alias_ENG_P": ["Geradstetten Station"], "woe:hierarchy": {"continent": 24865675, "country": 23424829, "town": 0, "planet": 1, "county": 12596822, "suburb": 0, "state": 2345481, "region": 0, "localadmin": 12624124}, "woe:timezone_id": 28350890, "woe:hash": "u0wtwu9zes89", "woe:centroid": [9.43981, 48.805328], "geom:latitude": 48.805328, "geom:longitude": 9.43981, "geom:hash": "u0wtwu9zes89", "woe:latitude": 48.805328, "geom:centroid": [9.43981, 48.805328], "woe:longitude": 9.43981, "woe:repo": "woeplanet-poi-de", "geom:area": 0.0, "woe:scale": 19}}