{"type": "Feature", "id": 22159857, "geometry": {"type": "Point", "coordinates": [8.57284, 48.776901]}, "properties": {"woe:id": 22159857, "woe:parent_id": 642987, "woe:name": "Calmbach Bahnhof", "woe:placetype": 20, "woe:placetype_name": "POI", "woe:lang": "GER", "iso:country": "DE", "meta:provider": ["geoplanet:7.3.1", "geoplanet:7.3.2", "geoplanet:7.4.0", "geoplanet:7.4.1", "geoplanet:7.5.1", "geoplanet:7.5.2", "geoplanet:7.6.0", "geoplanet:7.8.1", "geoplanet:7.9.0", "geoplanet:7.10.0", "geoplanet:8.0.0", "woeplanet:8.0.0"], "meta:indexed": "2020-08-20T20:51:38.139297", "meta:updated": "2020-10-14T11:50:28.266144", "woe:alias_ENG_P": ["Calmbach Station"], "woe:hierarchy": {"continent": 24865675, "country": 23424829, "town": 0, "planet": 1, "county": 12596872, "suburb": 0, "state": 2345481, "region": 0, "localadmin": 12624026}, "woe:timezone_id": 28350890, "woe:hash": "u0wj7pdd19ku", "woe:centroid": [8.57284, 48.776901], "geom:latitude": 48.776901, "geom:longitude": 8.57284, "geom:hash": "u0wj7pdd19ku", "woe:latitude": 48.776901, "geom:centroid": [8.57284, 48.776901], "woe:longitude": 8.57284, "woe:repo": "woeplanet-poi-de", "geom:area": 0.0, "woe:scale": 19}}