{"type": "Feature", "id": 22953677, "geometry": {"type": "Point", "coordinates": [10.31843, 48.85741]}, "properties": {"woe:id": 22953677, "woe:parent_id": 636043, "woe:name": "Aufhausen Bahnhof", "woe:placetype": 20, "woe:placetype_name": "POI", "woe:lang": "GER", "iso:country": "DE", "meta:provider": ["geoplanet:7.3.1", "geoplanet:7.3.2", "geoplanet:7.4.0", "geoplanet:7.4.1", "geoplanet:7.5.1", "geoplanet:7.5.2", "geoplanet:7.6.0", "geoplanet:7.8.1", "geoplanet:7.9.0", "geoplanet:7.10.0", "geoplanet:8.0.0", "woeplanet:8.0.0"], "meta:indexed": "2020-08-20T20:51:44.437300", "meta:updated": "2020-10-14T11:50:28.832370", "woe:alias_ENG_P": ["Aufhausen Station"], "woe:hierarchy": {"continent": 24865675, "country": 23424829, "town": 0, "planet": 1, "county": 12596698, "suburb": 0, "state": 2345481, "region": 0, "localadmin": 12624206}, "woe:timezone_id": 28350890, "woe:hash": "u0xmfy1xhc74", "woe:centroid": [10.31843, 48.85741], "geom:latitude": 48.85741, "geom:longitude": 10.31843, "geom:hash": "u0xmfy1xhc74", "woe:latitude": 48.85741, "geom:centroid": [10.31843, 48.85741], "woe:longitude": 10.31843, "woe:repo": "woeplanet-poi-de", "geom:area": 0.0, "woe:scale": 19}}