{"type": "Feature", "id": 22208312, "geometry": {"type": "Point", "coordinates": [11.62217, 49.844292]}, "properties": {"woe:id": 22208312, "woe:parent_id": 643349, "woe:name": "St\u00e4dtisches Kr\u00fcgemuseum", "woe:placetype": 20, "woe:placetype_name": "POI", "woe:lang": "GER", "iso:country": "DE", "meta:provider": ["geoplanet:7.3.1", "geoplanet:7.3.2", "geoplanet:7.4.0", "geoplanet:7.4.1", "geoplanet:7.5.1", "geoplanet:7.5.2", "geoplanet:7.6.0", "geoplanet:7.8.1", "geoplanet:7.9.0", "geoplanet:7.10.0", "geoplanet:8.0.0", "woeplanet:8.0.0"], "meta:indexed": "2020-08-20T20:51:40.122934", "meta:updated": "2020-10-14T11:50:58.192653", "woe:alias_GER_S": ["Staedtisches Kruegemuseum", "Stadtisches Krugemuseum"], "woe:hierarchy": {"continent": 24865675, "country": 23424829, "town": 0, "planet": 1, "county": 12596699, "suburb": 0, "state": 2345482, "region": 0, "localadmin": 12635285}, "woe:timezone_id": 28350890, "woe:hash": "u2b783zh01qp", "woe:centroid": [11.62217, 49.844292], "geom:latitude": 49.844292, "geom:longitude": 11.62217, "geom:hash": "u2b783zh01qp", "woe:latitude": 49.844292, "geom:centroid": [11.62217, 49.844292], "woe:longitude": 11.62217, "woe:repo": "woeplanet-poi-de", "geom:area": 0.0, "woe:scale": 19}}