{"type": "Feature", "id": 22203160, "properties": {"woe:id": 22203160, "woe:parent_id": 652005, "woe:name": "Geldern Bahnhof", "woe:placetype": 20, "woe:placetype_name": "POI", "woe:lang": "GER", "iso:country": "DE", "meta:provider": ["geoplanet:7.3.1", "geoplanet:7.3.2", "geoplanet:7.4.0", "geoplanet:7.4.1", "geoplanet:7.5.1", "geoplanet:7.5.2", "geoplanet:7.6.0", "geoplanet:7.8.1", "geoplanet:7.9.0", "geoplanet:7.10.0", "geoplanet:8.0.0", "woeplanet:8.0.0"], "meta:indexed": "2020-08-20T20:51:39.812419", "meta:updated": "2020-08-22T01:51:40.058598", "woe:alias_ENG_P": ["Geldern Station"], "woe:hierarchy": {"continent": 24865675, "country": 23424829, "town": 0, "planet": 1, "county": 12596784, "suburb": 0, "state": 2345487, "region": 0, "localadmin": 12624399}, "woe:timezone_id": 28350890, "woe:hash": "u1hmpc9w8m22", "woe:centroid": [6.31921, 51.51329], "geom:latitude": 51.51329, "geom:longitude": 6.31921, "geom:hash": "u1hmpc9w8m22", "woe:latitude": 51.51329, "geom:centroid": [6.31921, 51.51329], "woe:longitude": 6.31921, "woe:repo": "woeplanet-poi-de"}, "geometry": {"coordinates": [6.31921, 51.51329], "type": "Point"}}