{"type": "Feature", "id": 22253837, "geometry": {"type": "Point", "coordinates": [14.61266, 50.986591]}, "properties": {"woe:id": 22253837, "woe:parent_id": 678397, "woe:name": "Neugersdorf Bahnhof", "woe:placetype": 20, "woe:placetype_name": "POI", "woe:lang": "GER", "iso:country": "DE", "meta:provider": ["geoplanet:7.3.1", "geoplanet:7.3.2", "geoplanet:7.4.0", "geoplanet:7.4.1", "geoplanet:7.5.1", "geoplanet:7.5.2", "geoplanet:7.6.0", "geoplanet:7.8.1", "geoplanet:7.9.0", "geoplanet:7.10.0", "geoplanet:8.0.0", "woeplanet:8.0.0"], "meta:indexed": "2020-08-20T20:51:41.858918", "meta:updated": "2020-10-14T11:50:57.300610", "woe:alias_ENG_P": ["Neugersdorf Station"], "woe:hierarchy": {"continent": 24865675, "country": 23424829, "town": 0, "planet": 1, "county": 56448173, "suburb": 0, "state": 2345493, "region": 0, "localadmin": 12625804}, "woe:timezone_id": 28350890, "woe:hash": "u346h9bd7tmn", "woe:centroid": [14.61266, 50.986591], "geom:latitude": 50.986591, "geom:longitude": 14.61266, "geom:hash": "u346h9bd7tmn", "woe:latitude": 50.986591, "geom:centroid": [14.61266, 50.986591], "woe:longitude": 14.61266, "woe:repo": "woeplanet-poi-de", "geom:area": 0.0, "woe:scale": 19}}