{"type": "Feature", "id": 22266127, "properties": {"woe:id": 22266127, "woe:parent_id": 686325, "woe:name": "Quakenbr\u00fcck Bahnhof", "woe:placetype": 20, "woe:placetype_name": "POI", "woe:lang": "GER", "iso:country": "DE", "meta:provider": ["geoplanet:7.3.1", "geoplanet:7.3.2", "geoplanet:7.4.0", "geoplanet:7.4.1", "geoplanet:7.5.1", "geoplanet:7.5.2", "geoplanet:7.6.0", "geoplanet:7.8.1", "geoplanet:7.9.0", "geoplanet:7.10.0", "geoplanet:8.0.0", "woeplanet:8.0.0"], "meta:indexed": "2020-08-20T20:51:42.305350", "meta:updated": "2020-08-22T01:51:41.077706", "woe:alias_ENG_S": ["Quakenbruck Station"], "woe:alias_GER_S": ["Quakenbrueck Bahnhof", "Quakenbruck Bahnhof"], "woe:alias_ENG_P": ["Quakenbruck Station"], "woe:hierarchy": {"continent": 24865675, "country": 23424829, "town": 0, "planet": 1, "county": 12596767, "suburb": 0, "state": 2345486, "region": 0, "localadmin": 12630032}, "woe:timezone_id": 28350890, "woe:hash": "u1mesufzduxd", "woe:centroid": [7.94702, 52.673889], "geom:latitude": 52.673889, "geom:longitude": 7.94702, "geom:hash": "u1mesufzduxd", "woe:latitude": 52.673889, "geom:centroid": [7.94702, 52.673889], "woe:longitude": 7.94702, "woe:repo": "woeplanet-poi-de"}, "geometry": {"coordinates": [7.94702, 52.673889], "type": "Point"}}