{"type": "Feature", "id": 22189242, "geometry": {"type": "Point", "coordinates": [6.75755, 51.21059]}, "properties": {"woe:id": 22189242, "woe:parent_id": 646099, "woe:name": "D\u00fcsseldorf-V\u00f6lklinger Stra\u00dfe Bahnhof", "woe:placetype": 20, "woe:placetype_name": "POI", "woe:lang": "GER", "iso:country": "DE", "meta:provider": ["geoplanet:7.3.1", "geoplanet:7.3.2", "geoplanet:7.4.0", "geoplanet:7.4.1", "geoplanet:7.5.1", "geoplanet:7.5.2", "geoplanet:7.6.0", "geoplanet:7.8.1", "geoplanet:7.9.0", "geoplanet:7.10.0", "geoplanet:8.0.0", "woeplanet:8.0.0"], "meta:indexed": "2020-08-20T20:51:39.290864", "meta:updated": "2020-10-14T11:50:26.916724", "woe:alias_ENG_S": ["Dusseldorf-Volklinger Strasse Station"], "woe:alias_GER_S": ["Duesseldorf-Voelklinger Strasse Bahnhof", "Dusseldorf-Volklinger Strasse Bahnhof"], "woe:alias_ENG_P": ["Dusseldorf-Volklinger Strasse Station"], "woe:hierarchy": {"continent": 24865675, "country": 23424829, "town": 0, "planet": 1, "county": 12596700, "suburb": 0, "state": 2345487, "region": 0, "localadmin": 26822261}, "woe:timezone_id": 28350890, "woe:hash": "u1hg3f8eq3fk", "woe:centroid": [6.75755, 51.21059], "geom:latitude": 51.21059, "geom:longitude": 6.75755, "geom:hash": "u1hg3f8eq3fk", "woe:latitude": 51.21059, "geom:centroid": [6.75755, 51.21059], "woe:longitude": 6.75755, "woe:repo": "woeplanet-poi-de", "geom:area": 0.0, "woe:scale": 19}}