{"type": "Feature", "id": 22294830, "geometry": {"type": "Point", "coordinates": [13.00225, 50.606411]}, "properties": {"woe:id": 22294830, "woe:parent_id": 706323, "woe:name": "Sch\u00f6nfeld-Wiesa Bahnhof", "woe:placetype": 20, "woe:placetype_name": "POI", "woe:lang": "GER", "iso:country": "DE", "meta:provider": ["geoplanet:7.3.1", "geoplanet:7.3.2", "geoplanet:7.4.0", "geoplanet:7.4.1", "geoplanet:7.5.1", "geoplanet:7.5.2", "geoplanet:7.6.0", "geoplanet:7.8.1", "geoplanet:7.9.0", "geoplanet:7.10.0", "geoplanet:8.0.0", "woeplanet:8.0.0"], "meta:indexed": "2020-08-20T20:51:43.630365", "meta:updated": "2020-10-14T11:50:58.230864", "woe:alias_ENG_S": ["Schonfeld-Wiesa Station"], "woe:alias_GER_S": ["Schoenfeld-Wiesa Bahnhof", "Schonfeld-Wiesa Bahnhof"], "woe:alias_ENG_P": ["Schonfeld-Wiesa Station"], "woe:hierarchy": {"continent": 24865675, "country": 23424829, "town": 0, "planet": 1, "county": 56448166, "suburb": 0, "state": 2345493, "region": 0, "localadmin": 12636286}, "woe:timezone_id": 28350890, "woe:hash": "u2cpzuegwqu2", "woe:centroid": [13.00225, 50.606411], "geom:latitude": 50.606411, "geom:longitude": 13.00225, "geom:hash": "u2cpzuegwqu2", "woe:latitude": 50.606411, "geom:centroid": [13.00225, 50.606411], "woe:longitude": 13.00225, "woe:repo": "woeplanet-poi-de", "geom:area": 0.0, "woe:scale": 19}}