{"type": "Feature", "id": 22203915, "geometry": {"type": "Point", "coordinates": [8.98044, 49.15324]}, "properties": {"woe:id": 22203915, "woe:parent_id": 652067, "woe:name": "Gemmingen Bahnhof", "woe:placetype": 20, "woe:placetype_name": "POI", "woe:lang": "GER", "iso:country": "DE", "meta:provider": ["geoplanet:7.3.1", "geoplanet:7.3.2", "geoplanet:7.4.0", "geoplanet:7.4.1", "geoplanet:7.5.1", "geoplanet:7.5.2", "geoplanet:7.6.0", "geoplanet:7.8.1", "geoplanet:7.9.0", "geoplanet:7.10.0", "geoplanet:8.0.0", "woeplanet:8.0.0"], "meta:indexed": "2020-08-20T20:51:39.831567", "meta:updated": "2020-10-14T11:50:57.636551", "woe:alias_ENG_P": ["Gemmingen Station"], "woe:hierarchy": {"continent": 24865675, "country": 23424829, "town": 0, "planet": 1, "county": 12596745, "suburb": 0, "state": 2345481, "region": 0, "localadmin": 12623281}, "woe:timezone_id": 28350890, "woe:hash": "u0wrsk567kj3", "woe:centroid": [8.98044, 49.15324], "geom:latitude": 49.15324, "geom:longitude": 8.98044, "geom:hash": "u0wrsk567kj3", "woe:latitude": 49.15324, "geom:centroid": [8.98044, 49.15324], "woe:longitude": 8.98044, "woe:repo": "woeplanet-poi-de", "geom:area": 0.0, "woe:scale": 19}}