{"type": "Feature", "id": 23024905, "properties": {"woe:id": 23024905, "woe:parent_id": 646099, "woe:name": "Kalkumer Schlo\u00dfallee Bahnhof", "woe:placetype": 20, "woe:placetype_name": "POI", "woe:lang": "GER", "iso:country": "DE", "meta:provider": ["geoplanet:7.3.1", "geoplanet:7.3.2", "geoplanet:7.4.0", "geoplanet:7.4.1", "geoplanet:7.5.1", "geoplanet:7.5.2", "geoplanet:7.6.0", "geoplanet:7.8.1", "geoplanet:7.9.0", "geoplanet:7.10.0", "geoplanet:8.0.0", "woeplanet:8.0.0"], "meta:indexed": "2020-08-20T20:51:45.547170", "meta:updated": "2020-08-22T01:51:42.674376", "woe:alias_ENG_S": ["Kalkumer Schlossallee Station"], "woe:alias_GER_S": ["Kalkumer Schlossallee Bahnhof"], "woe:alias_ENG_P": ["Kalkumer Schlossallee Station"], "woe:hierarchy": {"continent": 24865675, "country": 23424829, "town": 0, "planet": 1, "county": 12596700, "suburb": 0, "state": 2345487, "region": 0, "localadmin": 26822252}, "woe:timezone_id": 28350890, "woe:hash": "u1hgc7yezj54", "woe:centroid": [6.74385, 51.30545], "geom:latitude": 51.30545, "geom:longitude": 6.74385, "geom:hash": "u1hgc7yezj54", "woe:latitude": 51.30545, "geom:centroid": [6.74385, 51.30545], "woe:longitude": 6.74385, "woe:repo": "woeplanet-poi-de"}, "geometry": {"coordinates": [6.74385, 51.30545], "type": "Point"}}