{"type": "Feature", "id": 22925309, "geometry": {"type": "Point", "coordinates": [12.96625, 48.832851]}, "properties": {"woe:id": 22925309, "woe:parent_id": 643988, "woe:name": "Zoo-Winnerl", "woe:placetype": 20, "woe:placetype_name": "POI", "woe:lang": "GER", "iso:country": "DE", "meta:provider": ["geoplanet:7.3.1", "geoplanet:7.3.2", "geoplanet:7.4.0", "geoplanet:7.4.1", "geoplanet:7.5.1", "geoplanet:7.5.2", "geoplanet:7.6.0", "geoplanet:7.8.1", "geoplanet:7.9.0", "geoplanet:7.10.0", "geoplanet:8.0.0", "woeplanet:8.0.0"], "meta:indexed": "2020-08-20T20:51:43.929575", "meta:updated": "2020-10-14T11:50:29.176765", "woe:hierarchy": {"continent": 24865675, "country": 23424829, "town": 0, "planet": 1, "county": 12596742, "suburb": 0, "state": 2345482, "region": 0, "localadmin": 12622833}, "woe:timezone_id": 28350890, "woe:hash": "u29jz19xzx0y", "woe:centroid": [12.96625, 48.832851], "geom:latitude": 48.832851, "geom:longitude": 12.96625, "geom:hash": "u29jz19xzx0y", "woe:latitude": 48.832851, "geom:centroid": [12.96625, 48.832851], "woe:longitude": 12.96625, "woe:repo": "woeplanet-poi-de", "geom:area": 0.0, "woe:scale": 19}}