{"type": "Feature", "id": 22234577, "properties": {"woe:id": 22234577, "woe:parent_id": 669549, "woe:name": "Hirschwirtscheuer-Museum", "woe:placetype": 20, "woe:placetype_name": "POI", "woe:lang": "GER", "iso:country": "DE", "meta:provider": ["geoplanet:7.3.1", "geoplanet:7.3.2", "geoplanet:7.4.0", "geoplanet:7.4.1", "geoplanet:7.5.1", "geoplanet:7.5.2", "geoplanet:7.6.0", "geoplanet:7.8.1", "geoplanet:7.9.0", "geoplanet:7.10.0", "geoplanet:8.0.0", "woeplanet:8.0.0"], "meta:indexed": "2020-08-20T20:51:41.131442", "meta:updated": "2020-08-22T01:51:40.610447", "woe:hierarchy": {"continent": 24865675, "country": 23424829, "town": 0, "planet": 1, "county": 12596848, "suburb": 0, "state": 2345481, "region": 0, "localadmin": 12624132}, "woe:timezone_id": 28350890, "woe:hash": "u0ybk6zsqjtf", "woe:centroid": [9.68952, 49.278561], "geom:latitude": 49.278561, "geom:longitude": 9.68952, "geom:hash": "u0ybk6zsqjtf", "woe:latitude": 49.278561, "geom:centroid": [9.68952, 49.278561], "woe:longitude": 9.68952, "woe:repo": "woeplanet-poi-de"}, "geometry": {"coordinates": [9.68952, 49.278561], "type": "Point"}}