{"type": "Feature", "id": 22270670, "properties": {"woe:id": 22270670, "woe:parent_id": 637944, "woe:name": "Berga-Kelbra Bahnhof", "woe:placetype": 20, "woe:placetype_name": "POI", "woe:lang": "GER", "iso:country": "DE", "meta:provider": ["geoplanet:7.3.1", "geoplanet:7.3.2", "geoplanet:7.4.0", "geoplanet:7.4.1", "geoplanet:7.5.1", "geoplanet:7.5.2", "geoplanet:7.6.0", "geoplanet:7.8.1", "geoplanet:7.9.0", "geoplanet:7.10.0", "geoplanet:8.0.0", "woeplanet:8.0.0"], "meta:indexed": "2020-08-20T20:51:42.528095", "meta:updated": "2020-08-22T01:51:41.165735", "woe:alias_ENG_P": ["Berga-Kelbra Station"], "woe:hierarchy": {"continent": 24865675, "country": 23424829, "town": 0, "planet": 1, "county": 12596874, "suburb": 0, "state": 2345494, "region": 0, "localadmin": 12626398}, "woe:timezone_id": 28350890, "woe:hash": "u1pudws4jq2t", "woe:centroid": [11.01402, 51.452099], "geom:latitude": 51.452099, "geom:longitude": 11.01402, "geom:hash": "u1pudws4jq2t", "woe:latitude": 51.452099, "geom:centroid": [11.01402, 51.452099], "woe:longitude": 11.01402, "woe:repo": "woeplanet-poi-de"}, "geometry": {"coordinates": [11.01402, 51.452099], "type": "Point"}}