{"type": "Feature", "id": 22998457, "properties": {"woe:id": 22998457, "woe:parent_id": 708036, "woe:name": "W\u00f6rth Bahnhof", "woe:placetype": 20, "woe:placetype_name": "POI", "woe:lang": "GER", "iso:country": "DE", "meta:provider": ["geoplanet:7.3.1", "geoplanet:7.3.2", "geoplanet:7.4.0", "geoplanet:7.4.1", "geoplanet:7.5.1", "geoplanet:7.5.2", "geoplanet:7.6.0", "geoplanet:7.8.1", "geoplanet:7.9.0", "geoplanet:7.10.0", "geoplanet:8.0.0", "woeplanet:8.0.0"], "meta:indexed": "2020-08-20T20:51:45.317960", "meta:updated": "2020-08-22T01:51:42.550571", "woe:alias_ENG_P": ["Worth Station"], "woe:alias_GER_S": ["Woerth Bahnhof", "Worth Bahnhof"], "woe:hierarchy": {"continent": 24865675, "country": 23424829, "town": 0, "planet": 1, "county": 12597083, "suburb": 0, "state": 2345488, "region": 0, "localadmin": 12627372}, "woe:timezone_id": 28350890, "woe:hash": "u0tzh0x9w91u", "woe:centroid": [8.2723, 49.045979], "geom:latitude": 49.045979, "geom:longitude": 8.2723, "geom:hash": "u0tzh0x9w91u", "woe:latitude": 49.045979, "geom:centroid": [8.2723, 49.045979], "woe:longitude": 8.2723, "woe:repo": "woeplanet-poi-de"}, "geometry": {"coordinates": [8.2723, 49.045979], "type": "Point"}}