{"type": "Feature", "id": 22942527, "geometry": {"type": "Point", "coordinates": [7.98919, 48.113789]}, "properties": {"woe:id": 22942527, "woe:parent_id": 655989, "woe:name": "Gutach Bahnhof", "woe:placetype": 20, "woe:placetype_name": "POI", "woe:lang": "GER", "iso:country": "DE", "meta:provider": ["geoplanet:7.3.1", "geoplanet:7.3.2", "geoplanet:7.4.0", "geoplanet:7.4.1", "geoplanet:7.5.1", "geoplanet:7.5.2", "geoplanet:7.6.0", "geoplanet:7.8.1", "geoplanet:7.9.0", "geoplanet:7.10.0", "geoplanet:8.0.0", "woeplanet:8.0.0"], "meta:indexed": "2020-08-20T20:51:44.183752", "meta:updated": "2020-10-14T11:50:28.519494", "woe:alias_ENG_P": ["Gutach Station"], "woe:hierarchy": {"continent": 24865675, "country": 23424829, "town": 0, "planet": 1, "county": 12596970, "suburb": 0, "state": 2345481, "region": 0, "localadmin": 12623368}, "woe:timezone_id": 28350890, "woe:hash": "u0t9tyce1s7f", "woe:centroid": [7.98919, 48.113789], "geom:latitude": 48.113789, "geom:longitude": 7.98919, "geom:hash": "u0t9tyce1s7f", "woe:latitude": 48.113789, "geom:centroid": [7.98919, 48.113789], "woe:longitude": 7.98919, "woe:repo": "woeplanet-poi-de", "geom:area": 0.0, "woe:scale": 19}}