{"type": "Feature", "id": 22236462, "properties": {"woe:id": 22236462, "woe:parent_id": 670807, "woe:name": "Heimatmuseum Leer", "woe:placetype": 20, "woe:placetype_name": "POI", "woe:lang": "GER", "iso:country": "DE", "meta:provider": ["geoplanet:7.3.1", "geoplanet:7.3.2", "geoplanet:7.4.0", "geoplanet:7.4.1", "geoplanet:7.5.1", "geoplanet:7.5.2", "geoplanet:7.6.0", "geoplanet:7.8.1", "geoplanet:7.9.0", "geoplanet:7.10.0", "geoplanet:8.0.0", "woeplanet:8.0.0"], "meta:indexed": "2020-08-20T20:51:41.207730", "meta:updated": "2020-08-22T01:51:40.644804", "woe:hierarchy": {"continent": 24865675, "country": 23424829, "town": 0, "planet": 1, "county": 12596996, "suburb": 0, "state": 2345486, "region": 0, "localadmin": 12629970}, "woe:timezone_id": 28350890, "woe:hash": "u1mqc92szpcy", "woe:centroid": [7.44972, 53.225498], "geom:latitude": 53.225498, "geom:longitude": 7.44972, "geom:hash": "u1mqc92szpcy", "woe:latitude": 53.225498, "geom:centroid": [7.44972, 53.225498], "woe:longitude": 7.44972, "woe:repo": "woeplanet-poi-de"}, "geometry": {"coordinates": [7.44972, 53.225498], "type": "Point"}}