{"type": "Feature", "id": 22972883, "geometry": {"type": "Point", "coordinates": [12.39149, 52.060669]}, "properties": {"woe:id": 22972883, "woe:parent_id": 674447, "woe:name": "Medewitz Bahnhof", "woe:placetype": 20, "woe:placetype_name": "POI", "woe:lang": "GER", "iso:country": "DE", "meta:provider": ["geoplanet:7.3.1", "geoplanet:7.3.2", "geoplanet:7.4.0", "geoplanet:7.4.1", "geoplanet:7.5.1", "geoplanet:7.5.2", "geoplanet:7.6.0", "geoplanet:7.8.1", "geoplanet:7.9.0", "geoplanet:7.10.0", "geoplanet:8.0.0", "woeplanet:8.0.0"], "meta:indexed": "2020-08-20T20:51:44.803142", "meta:updated": "2020-10-14T11:50:29.583807", "woe:alias_ENG_P": ["Medewitz Station"], "woe:hierarchy": {"continent": 24865675, "country": 23424829, "town": 0, "planet": 1, "county": 12596947, "suburb": 0, "state": 2345491, "region": 0, "localadmin": 24547294}, "woe:timezone_id": 28350890, "woe:hash": "u32b1vr5qshe", "woe:centroid": [12.39149, 52.060669], "geom:latitude": 52.060669, "geom:longitude": 12.39149, "geom:hash": "u32b1vr5qshe", "woe:latitude": 52.060669, "geom:centroid": [12.39149, 52.060669], "woe:longitude": 12.39149, "woe:repo": "woeplanet-poi-de", "geom:area": 0.0, "woe:scale": 19}}