{"type": "Feature", "id": 22203139, "properties": {"woe:id": 22203139, "woe:parent_id": 698733, "woe:name": "Tautenhain Bahnhof", "woe:placetype": 20, "woe:placetype_name": "POI", "woe:lang": "GER", "iso:country": "DE", "meta:provider": ["geoplanet:7.3.1", "geoplanet:7.3.2", "geoplanet:7.4.0", "geoplanet:7.4.1", "geoplanet:7.5.1", "geoplanet:7.5.2", "geoplanet:7.6.0", "geoplanet:7.8.1", "geoplanet:7.9.0", "geoplanet:7.10.0", "geoplanet:8.0.0", "woeplanet:8.0.0"], "meta:indexed": "2020-08-20T20:51:39.811581", "meta:updated": "2020-08-22T01:51:40.058152", "woe:alias_ENG_P": ["Tautenhain Station"], "woe:hierarchy": {"continent": 24865675, "country": 23424829, "town": 0, "planet": 1, "county": 56448169, "suburb": 0, "state": 2345493, "region": 0, "localadmin": 12625693}, "woe:timezone_id": 28350890, "woe:hash": "u3148s8r918y", "woe:centroid": [12.67861, 51.090469], "geom:latitude": 51.090469, "geom:longitude": 12.67861, "geom:hash": "u3148s8r918y", "woe:latitude": 51.090469, "geom:centroid": [12.67861, 51.090469], "woe:longitude": 12.67861, "woe:repo": "woeplanet-poi-de"}, "geometry": {"coordinates": [12.67861, 51.090469], "type": "Point"}}