{"type": "Feature", "id": 22298146, "geometry": {"type": "Point", "coordinates": [13.46922, 52.163269]}, "properties": {"woe:id": 22298146, "woe:parent_id": 708222, "woe:name": "W\u00fcnsdorf Bahnhof", "woe:placetype": 20, "woe:placetype_name": "POI", "woe:lang": "GER", "iso:country": "DE", "meta:provider": ["geoplanet:7.3.1", "geoplanet:7.3.2", "geoplanet:7.4.0", "geoplanet:7.4.1", "geoplanet:7.5.1", "geoplanet:7.5.2", "geoplanet:7.6.0", "geoplanet:7.8.1", "geoplanet:7.9.0", "geoplanet:7.10.0", "geoplanet:8.0.0", "woeplanet:8.0.0"], "meta:indexed": "2020-08-20T20:51:43.753227", "meta:updated": "2020-10-14T11:50:57.654945", "woe:alias_ENG_S": ["Wunsdorf Station"], "woe:alias_GER_S": ["Wuensdorf Bahnhof", "Wunsdorf Bahnhof"], "woe:alias_ENG_P": ["Wunsdorf Station"], "woe:hierarchy": {"continent": 24865675, "country": 23424829, "town": 0, "planet": 1, "county": 12596900, "suburb": 0, "state": 2345491, "region": 0, "localadmin": 12634078}, "woe:timezone_id": 28350890, "woe:hash": "u338f2pcpd4k", "woe:centroid": [13.46922, 52.163269], "geom:latitude": 52.163269, "geom:longitude": 13.46922, "geom:hash": "u338f2pcpd4k", "woe:latitude": 52.163269, "geom:centroid": [13.46922, 52.163269], "woe:longitude": 13.46922, "woe:repo": "woeplanet-poi-de", "geom:area": 0.0, "woe:scale": 19}}