{"type": "Feature", "id": 22233711, "properties": {"woe:id": 22233711, "woe:parent_id": 668736, "woe:name": "Krefelder Zoo", "woe:placetype": 20, "woe:placetype_name": "POI", "woe:lang": "GER", "iso:country": "DE", "meta:provider": ["geoplanet:7.3.1", "geoplanet:7.3.2", "geoplanet:7.4.0", "geoplanet:7.4.1", "geoplanet:7.5.1", "geoplanet:7.5.2", "geoplanet:7.6.0", "geoplanet:7.8.1", "geoplanet:7.9.0", "geoplanet:7.10.0", "geoplanet:8.0.0", "woeplanet:8.0.0"], "meta:indexed": "2020-08-20T20:51:41.091848", "meta:updated": "2020-08-22T01:51:40.592505", "woe:hierarchy": {"continent": 24865675, "country": 23424829, "town": 0, "planet": 1, "county": 12597091, "suburb": 0, "state": 2345487, "region": 0, "localadmin": 26822858}, "woe:timezone_id": 28350890, "woe:hash": "u1hsn4mkssxs", "woe:centroid": [6.59921, 51.341282], "geom:latitude": 51.341282, "geom:longitude": 6.59921, "geom:hash": "u1hsn4mkssxs", "woe:latitude": 51.341282, "geom:centroid": [6.59921, 51.341282], "woe:longitude": 6.59921, "woe:repo": "woeplanet-poi-de"}, "geometry": {"coordinates": [6.59921, 51.341282], "type": "Point"}}