{"type": "Feature", "id": 22261597, "properties": {"woe:id": 22261597, "woe:parent_id": 683147, "woe:name": "Denkmalkomplex Saigerh\u00fctte", "woe:placetype": 20, "woe:placetype_name": "POI", "woe:lang": "GER", "iso:country": "DE", "meta:provider": ["geoplanet:7.3.1", "geoplanet:7.3.2", "geoplanet:7.4.0", "geoplanet:7.4.1", "geoplanet:7.5.1", "geoplanet:7.5.2", "geoplanet:7.6.0", "geoplanet:7.8.1", "geoplanet:7.9.0", "geoplanet:7.10.0", "geoplanet:8.0.0", "woeplanet:8.0.0"], "meta:indexed": "2020-08-20T20:51:42.095752", "meta:updated": "2020-08-22T01:51:40.989498", "woe:alias_GER_S": ["Denkmalkomplex Saigerhuette", "Denkmalkomplex Saigerhutte"], "woe:hierarchy": {"continent": 24865675, "country": 23424829, "town": 0, "planet": 1, "county": 56448166, "suburb": 0, "state": 2345493, "region": 0, "localadmin": 12625634}, "woe:timezone_id": 28350890, "woe:hash": "u3180hw645se", "woe:centroid": [13.36805, 50.650082], "geom:latitude": 50.650082, "geom:longitude": 13.36805, "geom:hash": "u3180hw645se", "woe:latitude": 50.650082, "geom:centroid": [13.36805, 50.650082], "woe:longitude": 13.36805, "woe:repo": "woeplanet-poi-de"}, "geometry": {"coordinates": [13.36805, 50.650082], "type": "Point"}}