{"type": "Feature", "id": 56055639, "properties": {"woe:id": 56055639, "woe:parent_id": 677896, "woe:name": "Universit\u00e4t der Bundeswehr M\u00fcnchen", "woe:placetype": 20, "woe:placetype_name": "POI", "woe:lang": "GER", "iso:country": "DE", "meta:provider": ["geoplanet:7.3.1", "geoplanet:7.3.2", "geoplanet:7.4.0", "geoplanet:7.4.1", "geoplanet:7.5.1", "geoplanet:7.5.2", "geoplanet:7.6.0", "geoplanet:7.8.1", "geoplanet:7.9.0", "geoplanet:7.10.0", "geoplanet:8.0.0", "woeplanet:8.0.0"], "meta:indexed": "2020-08-20T20:51:45.884479", "meta:updated": "2020-08-22T01:51:42.962660", "woe:alias_GER_V": ["Universitat der Bundeswehr Munchen"], "woe:hierarchy": {"continent": 24865675, "country": 23424829, "town": 0, "planet": 1, "county": 12596963, "suburb": 0, "state": 2345482, "region": 0, "localadmin": 12635219}, "woe:timezone_id": 28350890, "woe:hash": "u28389n8dvpz", "woe:centroid": [11.63259, 48.081779], "geom:latitude": 48.081779, "geom:longitude": 11.63259, "geom:hash": "u28389n8dvpz", "woe:latitude": 48.081779, "geom:centroid": [11.63259, 48.081779], "woe:longitude": 11.63259, "woe:repo": "woeplanet-poi-de"}, "geometry": {"coordinates": [11.63259, 48.081779], "type": "Point"}}