{"type": "Feature", "id": 22205996, "geometry": {"type": "Point", "coordinates": [8.77524, 47.737289]}, "properties": {"woe:id": 22205996, "woe:parent_id": 653601, "woe:name": "Gottmadingen Bahnhof", "woe:placetype": 20, "woe:placetype_name": "POI", "woe:lang": "GER", "iso:country": "DE", "meta:provider": ["geoplanet:7.3.1", "geoplanet:7.3.2", "geoplanet:7.4.0", "geoplanet:7.4.1", "geoplanet:7.5.1", "geoplanet:7.5.2", "geoplanet:7.6.0", "geoplanet:7.8.1", "geoplanet:7.9.0", "geoplanet:7.10.0", "geoplanet:8.0.0", "woeplanet:8.0.0"], "meta:indexed": "2020-08-20T20:51:39.949348", "meta:updated": "2020-10-14T11:50:59.575250", "woe:alias_ENG_P": ["Gottmadingen Station"], "woe:hierarchy": {"continent": 24865675, "country": 23424829, "town": 0, "planet": 1, "county": 12596692, "suburb": 0, "state": 2345481, "region": 0, "localadmin": 12623520}, "woe:timezone_id": 28350890, "woe:hash": "u0qpxdmcvgth", "woe:centroid": [8.77524, 47.737289], "geom:latitude": 47.737289, "geom:longitude": 8.77524, "geom:hash": "u0qpxdmcvgth", "woe:latitude": 47.737289, "geom:centroid": [8.77524, 47.737289], "woe:longitude": 8.77524, "woe:repo": "woeplanet-poi-de", "geom:area": 0.0, "woe:scale": 19}}