{"type": "Feature", "id": 22190736, "geometry": {"type": "Point", "coordinates": [9.7889, 50.455921]}, "properties": {"woe:id": 22190736, "woe:parent_id": 15002600, "woe:name": "Schmalnau Bahnhof", "woe:placetype": 20, "woe:placetype_name": "POI", "woe:lang": "GER", "iso:country": "DE", "meta:provider": ["geoplanet:7.3.1", "geoplanet:7.3.2", "geoplanet:7.4.0", "geoplanet:7.4.1", "geoplanet:7.5.1", "geoplanet:7.5.2", "geoplanet:7.6.0", "geoplanet:7.8.1", "geoplanet:7.9.0", "geoplanet:7.10.0", "geoplanet:8.0.0", "woeplanet:8.0.0"], "meta:indexed": "2020-08-20T20:51:39.334241", "meta:updated": "2020-10-14T11:50:27.029167", "woe:alias_ENG_P": ["Schmalnau Station"], "woe:hierarchy": {"continent": 24865675, "country": 23424829, "town": 0, "planet": 1, "county": 12596760, "suburb": 0, "state": 2345485, "region": 0, "localadmin": 12632740}, "woe:timezone_id": 28350890, "woe:hash": "u0yznc0p1cku", "woe:centroid": [9.7889, 50.455921], "geom:latitude": 50.455921, "geom:longitude": 9.7889, "geom:hash": "u0yznc0p1cku", "woe:latitude": 50.455921, "geom:centroid": [9.7889, 50.455921], "woe:longitude": 9.7889, "woe:repo": "woeplanet-poi-de", "geom:area": 0.0, "woe:scale": 19}}