{"type": "Feature", "id": 22272163, "geometry": {"type": "Point", "coordinates": [12.64545, 47.764992]}, "properties": {"woe:id": 22272163, "woe:parent_id": 690357, "woe:name": "Bartholom\u00e4us-Schmucker-Heimatmuseum", "woe:placetype": 20, "woe:placetype_name": "POI", "woe:lang": "GER", "iso:country": "DE", "meta:provider": ["geoplanet:7.3.1", "geoplanet:7.3.2", "geoplanet:7.4.0", "geoplanet:7.4.1", "geoplanet:7.5.1", "geoplanet:7.5.2", "geoplanet:7.6.0", "geoplanet:7.8.1", "geoplanet:7.9.0", "geoplanet:7.10.0", "geoplanet:8.0.0", "woeplanet:8.0.0"], "meta:indexed": "2020-08-20T20:51:42.591971", "meta:updated": "2020-10-14T11:50:58.469223", "woe:alias_GER_S": ["Bartholomaeus-Schmucker-Heimatmuseum", "Bartholomaus-Schmucker-Heimatmuseum"], "woe:hierarchy": {"continent": 24865675, "country": 23424829, "town": 0, "planet": 1, "county": 12596749, "suburb": 0, "state": 2345482, "region": 0, "localadmin": 12622810}, "woe:timezone_id": 28350890, "woe:hash": "u22zxz25hrfg", "woe:centroid": [12.64545, 47.764992], "geom:latitude": 47.764992, "geom:longitude": 12.64545, "geom:hash": "u22zxz25hrfg", "woe:latitude": 47.764992, "geom:centroid": [12.64545, 47.764992], "woe:longitude": 12.64545, "woe:repo": "woeplanet-poi-de", "geom:area": 0.0, "woe:scale": 19}}