{"type": "Feature", "id": 22286740, "geometry": {"type": "Point", "coordinates": [11.87167, 50.740139]}, "properties": {"woe:id": 22286740, "woe:parent_id": 700061, "woe:name": "Triptis Bahnhof", "woe:placetype": 20, "woe:placetype_name": "POI", "woe:lang": "GER", "iso:country": "DE", "meta:provider": ["geoplanet:7.3.1", "geoplanet:7.3.2", "geoplanet:7.4.0", "geoplanet:7.4.1", "geoplanet:7.5.1", "geoplanet:7.5.2", "geoplanet:7.6.0", "geoplanet:7.8.1", "geoplanet:7.9.0", "geoplanet:7.10.0", "geoplanet:8.0.0", "woeplanet:8.0.0"], "meta:indexed": "2020-08-20T20:51:43.208659", "meta:updated": "2020-10-14T11:50:57.399264", "woe:alias_ENG_P": ["Triptis Station"], "woe:hierarchy": {"continent": 24865675, "country": 23424829, "town": 0, "planet": 1, "county": 12596843, "suburb": 0, "state": 2345495, "region": 0, "localadmin": 12625466}, "woe:timezone_id": 28350890, "woe:hash": "u302whuwtzqw", "woe:centroid": [11.87167, 50.740139], "geom:latitude": 50.740139, "geom:longitude": 11.87167, "geom:hash": "u302whuwtzqw", "woe:latitude": 50.740139, "geom:centroid": [11.87167, 50.740139], "woe:longitude": 11.87167, "woe:repo": "woeplanet-poi-de", "geom:area": 0.0, "woe:scale": 19}}