{"type": "Feature", "id": 22270368, "properties": {"woe:id": 22270368, "woe:parent_id": 689527, "woe:name": "R\u00f6nshausen Bahnhof", "woe:placetype": 20, "woe:placetype_name": "POI", "woe:lang": "GER", "iso:country": "DE", "meta:provider": ["geoplanet:7.3.1", "geoplanet:7.3.2", "geoplanet:7.4.0", "geoplanet:7.4.1", "geoplanet:7.5.1", "geoplanet:7.5.2", "geoplanet:7.6.0", "geoplanet:7.8.1", "geoplanet:7.9.0", "geoplanet:7.10.0", "geoplanet:8.0.0", "woeplanet:8.0.0"], "meta:indexed": "2020-08-20T20:51:42.514862", "meta:updated": "2020-08-22T01:51:41.160690", "woe:alias_ENG_P": ["Ronshausen Station"], "woe:alias_GER_S": ["Roenshausen Bahnhof", "Ronshausen Bahnhof"], "woe:hierarchy": {"continent": 24865675, "country": 23424829, "town": 0, "planet": 1, "county": 12596962, "suburb": 0, "state": 2345485, "region": 0, "localadmin": 12632773}, "woe:timezone_id": 28350890, "woe:hash": "u1p1b4w3wevz", "woe:centroid": [9.85262, 50.946629], "geom:latitude": 50.946629, "geom:longitude": 9.85262, "geom:hash": "u1p1b4w3wevz", "woe:latitude": 50.946629, "geom:centroid": [9.85262, 50.946629], "woe:longitude": 9.85262, "woe:repo": "woeplanet-poi-de"}, "geometry": {"coordinates": [9.85262, 50.946629], "type": "Point"}}