{"type": "Feature", "id": 22281913, "properties": {"woe:id": 22281913, "woe:parent_id": 697664, "woe:name": "Heimatmuseum Strasburg", "woe:placetype": 20, "woe:placetype_name": "POI", "woe:lang": "GER", "iso:country": "DE", "meta:provider": ["geoplanet:7.3.1", "geoplanet:7.3.2", "geoplanet:7.4.0", "geoplanet:7.4.1", "geoplanet:7.5.1", "geoplanet:7.5.2", "geoplanet:7.6.0", "geoplanet:7.8.1", "geoplanet:7.9.0", "geoplanet:7.10.0", "geoplanet:8.0.0", "woeplanet:8.0.0"], "meta:indexed": "2020-08-20T20:51:43.041355", "meta:updated": "2020-08-22T01:51:41.368134", "woe:hierarchy": {"continent": 24865675, "country": 23424829, "town": 0, "planet": 1, "county": 12596884, "suburb": 0, "state": 2345492, "region": 0, "localadmin": 12635949}, "woe:timezone_id": 28350890, "woe:hash": "u39b2uc1w693", "woe:centroid": [13.74554, 53.507809], "geom:latitude": 53.507809, "geom:longitude": 13.74554, "geom:hash": "u39b2uc1w693", "woe:latitude": 53.507809, "geom:centroid": [13.74554, 53.507809], "woe:longitude": 13.74554, "woe:repo": "woeplanet-poi-de"}, "geometry": {"coordinates": [13.74554, 53.507809], "type": "Point"}}