{"type": "Feature", "id": 22291049, "geometry": {"type": "Point", "coordinates": [14.65389, 50.876091]}, "properties": {"woe:id": 22291049, "woe:parent_id": 703809, "woe:name": "Volkskunde-Und M\u00fchlenmuseum", "woe:placetype": 20, "woe:placetype_name": "POI", "woe:lang": "GER", "iso:country": "DE", "meta:provider": ["geoplanet:7.3.1", "geoplanet:7.3.2", "geoplanet:7.4.0", "geoplanet:7.4.1", "geoplanet:7.5.1", "geoplanet:7.5.2", "geoplanet:7.6.0", "geoplanet:7.8.1", "geoplanet:7.9.0", "geoplanet:7.10.0", "geoplanet:8.0.0", "woeplanet:8.0.0"], "meta:indexed": "2020-08-20T20:51:43.445202", "meta:updated": "2020-10-14T11:50:58.426144", "woe:alias_GER_S": ["Volkskunde-Und Muehlenmuseum", "Volkskunde-Und Muhlenmuseum"], "woe:hierarchy": {"continent": 24865675, "country": 23424829, "town": 0, "planet": 1, "county": 56448173, "suburb": 0, "state": 2345493, "region": 0, "localadmin": 24547352}, "woe:timezone_id": 28350890, "woe:hash": "u343mmwwsqu2", "woe:centroid": [14.65389, 50.876091], "geom:latitude": 50.876091, "geom:longitude": 14.65389, "geom:hash": "u343mmwwsqu2", "woe:latitude": 50.876091, "geom:centroid": [14.65389, 50.876091], "woe:longitude": 14.65389, "woe:repo": "woeplanet-poi-de", "geom:area": 0.0, "woe:scale": 19}}