{"type": "Feature", "id": 22158613, "properties": {"woe:id": 22158613, "woe:parent_id": 636298, "woe:name": "Babstadt Bahnhof", "woe:placetype": 20, "woe:placetype_name": "POI", "woe:lang": "GER", "iso:country": "DE", "meta:provider": ["geoplanet:7.3.1", "geoplanet:7.3.2", "geoplanet:7.4.0", "geoplanet:7.4.1", "geoplanet:7.5.1", "geoplanet:7.5.2", "geoplanet:7.6.0", "geoplanet:7.8.1", "geoplanet:7.9.0", "geoplanet:7.10.0", "geoplanet:8.0.0", "woeplanet:8.0.0"], "meta:indexed": "2020-08-20T20:51:38.096869", "meta:updated": "2020-08-22T01:51:39.194898", "woe:alias_ENG_P": ["Babstadt Station"], "woe:hierarchy": {"continent": 24865675, "country": 23424829, "town": 0, "planet": 1, "county": 12596745, "suburb": 0, "state": 2345481, "region": 0, "localadmin": 12623272}, "woe:timezone_id": 28350890, "woe:hash": "u0y2n5vjqczn", "woe:centroid": [9.0599, 49.240261], "geom:latitude": 49.240261, "geom:longitude": 9.0599, "geom:hash": "u0y2n5vjqczn", "woe:latitude": 49.240261, "geom:centroid": [9.0599, 49.240261], "woe:longitude": 9.0599, "woe:repo": "woeplanet-poi-de"}, "geometry": {"coordinates": [9.0599, 49.240261], "type": "Point"}}