{"type": "Feature", "id": 22958421, "geometry": {"type": "Point", "coordinates": [8.64506, 48.87513]}, "properties": {"woe:id": 22958421, "woe:parent_id": 639098, "woe:name": "Birkenfeld Bahnhof", "woe:placetype": 20, "woe:placetype_name": "POI", "woe:lang": "GER", "iso:country": "DE", "meta:provider": ["geoplanet:7.3.1", "geoplanet:7.3.2", "geoplanet:7.4.0", "geoplanet:7.4.1", "geoplanet:7.5.1", "geoplanet:7.5.2", "geoplanet:7.6.0", "geoplanet:7.8.1", "geoplanet:7.9.0", "geoplanet:7.10.0", "geoplanet:8.0.0", "woeplanet:8.0.0"], "meta:indexed": "2020-08-20T20:51:44.489338", "meta:updated": "2020-10-14T11:50:29.128174", "woe:alias_ENG_P": ["Birkenfeld Station"], "woe:hierarchy": {"continent": 24865675, "country": 23424829, "town": 0, "planet": 1, "county": 12597058, "suburb": 0, "state": 2345481, "region": 0, "localadmin": 12624030}, "woe:timezone_id": 28350890, "woe:hash": "u0wnh9rnk2xf", "woe:centroid": [8.64506, 48.87513], "geom:latitude": 48.87513, "geom:longitude": 8.64506, "geom:hash": "u0wnh9rnk2xf", "woe:latitude": 48.87513, "geom:centroid": [8.64506, 48.87513], "woe:longitude": 8.64506, "woe:repo": "woeplanet-poi-de", "geom:area": 0.0, "woe:scale": 19}}