{"type": "Feature", "id": 22190422, "geometry": {"type": "Point", "coordinates": [6.7527, 51.265079]}, "properties": {"woe:id": 22190422, "woe:parent_id": 646099, "woe:name": "U Freiligrathplatz Bahnhof", "woe:placetype": 20, "woe:placetype_name": "POI", "woe:lang": "GER", "iso:country": "DE", "meta:provider": ["geoplanet:7.3.1", "geoplanet:7.3.2", "geoplanet:7.4.0", "geoplanet:7.4.1", "geoplanet:7.5.1", "geoplanet:7.5.2", "geoplanet:7.6.0", "geoplanet:7.8.1", "geoplanet:7.9.0", "geoplanet:7.10.0", "geoplanet:8.0.0", "woeplanet:8.0.0"], "meta:indexed": "2020-08-20T20:51:39.308581", "meta:updated": "2020-10-14T11:50:27.767628", "woe:alias_ENG_P": ["U Freiligrathplatz Station"], "woe:hierarchy": {"continent": 24865675, "country": 23424829, "town": 0, "planet": 1, "county": 12596700, "suburb": 0, "state": 2345487, "region": 0, "localadmin": 26822248}, "woe:timezone_id": 28350890, "woe:hash": "u1hg9st0tr65", "woe:centroid": [6.7527, 51.265079], "geom:latitude": 51.265079, "geom:longitude": 6.7527, "geom:hash": "u1hg9st0tr65", "woe:latitude": 51.265079, "geom:centroid": [6.7527, 51.265079], "woe:longitude": 6.7527, "woe:repo": "woeplanet-poi-de", "geom:area": 0.0, "woe:scale": 19}}