{"type": "Feature", "id": 22264117, "properties": {"woe:id": 22264117, "woe:parent_id": 677467, "woe:name": "Nennig Bahnhof", "woe:placetype": 20, "woe:placetype_name": "POI", "woe:lang": "GER", "iso:country": "DE", "meta:provider": ["geoplanet:7.3.1", "geoplanet:7.3.2", "geoplanet:7.4.0", "geoplanet:7.4.1", "geoplanet:7.5.1", "geoplanet:7.5.2", "geoplanet:7.6.0", "geoplanet:7.8.1", "geoplanet:7.9.0", "geoplanet:7.10.0", "geoplanet:8.0.0", "woeplanet:8.0.0"], "meta:indexed": "2020-08-20T20:51:42.208676", "meta:updated": "2020-08-22T01:51:41.038450", "woe:alias_ENG_P": ["Nennig Station"], "woe:hierarchy": {"continent": 24865675, "country": 23424829, "town": 0, "planet": 1, "county": 12597029, "suburb": 0, "state": 2345489, "region": 0, "localadmin": 12627099}, "woe:timezone_id": 28350890, "woe:hash": "u0u9c44xzqec", "woe:centroid": [6.37582, 49.538719], "geom:latitude": 49.538719, "geom:longitude": 6.37582, "geom:hash": "u0u9c44xzqec", "woe:latitude": 49.538719, "geom:centroid": [6.37582, 49.538719], "woe:longitude": 6.37582, "woe:repo": "woeplanet-poi-de"}, "geometry": {"coordinates": [6.37582, 49.538719], "type": "Point"}}