{"type": "Feature", "id": 56055746, "properties": {"woe:id": 56055746, "woe:parent_id": 698064, "woe:name": "Technische Universit\u00e4t Stuttgart", "woe:placetype": 20, "woe:placetype_name": "POI", "woe:lang": "GER", "iso:country": "DE", "meta:provider": ["geoplanet:7.3.1", "geoplanet:7.3.2", "geoplanet:7.4.0", "geoplanet:7.4.1", "geoplanet:7.5.1", "geoplanet:7.5.2", "geoplanet:7.6.0", "geoplanet:7.8.1", "geoplanet:7.9.0", "geoplanet:7.10.0", "geoplanet:8.0.0", "woeplanet:8.0.0"], "meta:indexed": "2020-08-20T20:51:45.976952", "meta:updated": "2020-08-22T01:51:43.000523", "woe:alias_GER_V": ["Technische Universitat Stuttgart"], "woe:hierarchy": {"continent": 24865675, "country": 23424829, "town": 0, "planet": 1, "county": 12597071, "suburb": 0, "state": 2345481, "region": 0, "localadmin": 26823247}, "woe:timezone_id": 28350890, "woe:hash": "u0wmr1mxe9j0", "woe:centroid": [9.10439, 48.743511], "geom:latitude": 48.743511, "geom:longitude": 9.10439, "geom:hash": "u0wmr1mxe9j0", "woe:latitude": 48.743511, "geom:centroid": [9.10439, 48.743511], "woe:longitude": 9.10439, "woe:repo": "woeplanet-poi-de"}, "geometry": {"coordinates": [9.10439, 48.743511], "type": "Point"}}