{"type": "Feature", "id": 22237409, "properties": {"woe:id": 22237409, "woe:parent_id": 649719, "woe:name": "Irfersgr\u00fcn Bahnhof", "woe:placetype": 20, "woe:placetype_name": "POI", "woe:lang": "GER", "iso:country": "DE", "meta:provider": ["geoplanet:7.3.1", "geoplanet:7.3.2", "geoplanet:7.4.0", "geoplanet:7.4.1", "geoplanet:7.5.1", "geoplanet:7.5.2", "geoplanet:7.6.0", "geoplanet:7.8.1", "geoplanet:7.9.0", "geoplanet:7.10.0", "geoplanet:8.0.0", "woeplanet:8.0.0"], "meta:indexed": "2020-08-20T20:51:41.277908", "meta:updated": "2020-08-22T01:51:40.672939", "woe:alias_ENG_S": ["Irfersgrun Station"], "woe:alias_GER_S": ["Irfersgruen Bahnhof", "Irfersgrun Bahnhof"], "woe:alias_ENG_P": ["Irfersgrun Station"], "woe:hierarchy": {"continent": 24865675, "country": 23424829, "town": 0, "planet": 1, "county": 22526000, "suburb": 0, "state": 2345493, "region": 0, "localadmin": 12636513}, "woe:timezone_id": 28350890, "woe:hash": "u2bzfkgfq9jp", "woe:centroid": [12.409, 50.60754], "geom:latitude": 50.60754, "geom:longitude": 12.409, "geom:hash": "u2bzfkgfq9jp", "woe:latitude": 50.60754, "geom:centroid": [12.409, 50.60754], "woe:longitude": 12.409, "woe:repo": "woeplanet-poi-de"}, "geometry": {"coordinates": [12.409, 50.60754], "type": "Point"}}