{"type": "Feature", "id": 22269244, "geometry": {"type": "Point", "coordinates": [7.33338, 50.489738]}, "properties": {"woe:id": 22269244, "woe:parent_id": 688313, "woe:name": "Rheinbrohl Bahnhof", "woe:placetype": 20, "woe:placetype_name": "POI", "woe:lang": "GER", "iso:country": "DE", "meta:provider": ["geoplanet:7.3.1", "geoplanet:7.3.2", "geoplanet:7.4.0", "geoplanet:7.4.1", "geoplanet:7.5.1", "geoplanet:7.5.2", "geoplanet:7.6.0", "geoplanet:7.8.1", "geoplanet:7.9.0", "geoplanet:7.10.0", "geoplanet:8.0.0", "woeplanet:8.0.0"], "meta:indexed": "2020-08-20T20:51:42.453040", "meta:updated": "2020-10-14T11:50:59.286567", "woe:alias_ENG_P": ["Rheinbrohl Station"], "woe:hierarchy": {"continent": 24865675, "country": 23424829, "town": 0, "planet": 1, "county": 12596938, "suburb": 0, "state": 2345488, "region": 0, "localadmin": 12628403}, "woe:timezone_id": 28350890, "woe:hash": "u0vpnzkh01k6", "woe:centroid": [7.33338, 50.489738], "geom:latitude": 50.489738, "geom:longitude": 7.33338, "geom:hash": "u0vpnzkh01k6", "woe:latitude": 50.489738, "geom:centroid": [7.33338, 50.489738], "woe:longitude": 7.33338, "woe:repo": "woeplanet-poi-de", "geom:area": 0.0, "woe:scale": 19}}