{"type": "Feature", "id": 22971557, "geometry": {"type": "Point", "coordinates": [13.287, 52.66954]}, "properties": {"woe:id": 22971557, "woe:parent_id": 661040, "woe:name": "Hohen Neuendorf Bahnhof", "woe:placetype": 20, "woe:placetype_name": "POI", "woe:lang": "GER", "iso:country": "DE", "meta:provider": ["geoplanet:7.3.1", "geoplanet:7.3.2", "geoplanet:7.4.0", "geoplanet:7.4.1", "geoplanet:7.5.1", "geoplanet:7.5.2", "geoplanet:7.6.0", "geoplanet:7.8.1", "geoplanet:7.9.0", "geoplanet:7.10.0", "geoplanet:8.0.0", "woeplanet:8.0.0"], "meta:indexed": "2020-08-20T20:51:44.764266", "meta:updated": "2020-10-14T11:50:28.538682", "woe:alias_ENG_P": ["Hohen Neuendorf Station"], "woe:hierarchy": {"continent": 24865675, "country": 23424829, "town": 0, "planet": 1, "county": 12596942, "suburb": 0, "state": 2345491, "region": 0, "localadmin": 12633337}, "woe:timezone_id": 28350890, "woe:hash": "u337wk5q39ck", "woe:centroid": [13.287, 52.66954], "geom:latitude": 52.66954, "geom:longitude": 13.287, "geom:hash": "u337wk5q39ck", "woe:latitude": 52.66954, "geom:centroid": [13.287, 52.66954], "woe:longitude": 13.287, "woe:repo": "woeplanet-poi-de", "geom:area": 0.0, "woe:scale": 19}}