{"type": "Feature", "id": 22172441, "properties": {"woe:id": 22172441, "woe:parent_id": 639675, "woe:name": "Stadtmuseum Bocholt", "woe:placetype": 20, "woe:placetype_name": "POI", "woe:lang": "GER", "iso:country": "DE", "meta:provider": ["geoplanet:7.3.1", "geoplanet:7.3.2", "geoplanet:7.4.0", "geoplanet:7.4.1", "geoplanet:7.5.1", "geoplanet:7.5.2", "geoplanet:7.6.0", "geoplanet:7.8.1", "geoplanet:7.9.0", "geoplanet:7.10.0", "geoplanet:8.0.0", "woeplanet:8.0.0"], "meta:indexed": "2020-08-20T20:51:38.539818", "meta:updated": "2020-08-22T01:51:39.445827", "woe:hierarchy": {"continent": 24865675, "country": 23424829, "town": 0, "planet": 1, "county": 12596877, "suburb": 0, "state": 2345487, "region": 0, "localadmin": 12624427}, "woe:timezone_id": 28350890, "woe:hash": "u1hwysuvn1rq", "woe:centroid": [6.62056, 51.838482], "geom:latitude": 51.838482, "geom:longitude": 6.62056, "geom:hash": "u1hwysuvn1rq", "woe:latitude": 51.838482, "geom:centroid": [6.62056, 51.838482], "woe:longitude": 6.62056, "woe:repo": "woeplanet-poi-de"}, "geometry": {"coordinates": [6.62056, 51.838482], "type": "Point"}}