{"type": "Feature", "id": 22252852, "properties": {"woe:id": 22252852, "woe:parent_id": 677300, "woe:name": "Heimatmuseum im F\u00fcnfeckingen Turm", "woe:placetype": 20, "woe:placetype_name": "POI", "woe:lang": "GER", "iso:country": "DE", "meta:provider": ["geoplanet:7.3.1", "geoplanet:7.3.2", "geoplanet:7.4.0", "geoplanet:7.4.1", "geoplanet:7.5.1", "geoplanet:7.5.2", "geoplanet:7.6.0", "geoplanet:7.8.1", "geoplanet:7.9.0", "geoplanet:7.10.0", "geoplanet:8.0.0", "woeplanet:8.0.0"], "meta:indexed": "2020-08-20T20:51:41.823016", "meta:updated": "2020-08-22T01:51:40.881355", "woe:alias_GER_S": ["Heimatmuseum im Fuenfeckingen Turm", "Heimatmuseum im Funfeckingen Turm"], "woe:hierarchy": {"continent": 24865675, "country": 23424829, "town": 0, "planet": 1, "county": 12596830, "suburb": 0, "state": 2345481, "region": 0, "localadmin": 12623974}, "woe:timezone_id": 28350890, "woe:hash": "u0y27vhu2tmy", "woe:centroid": [8.96041, 49.29092], "geom:latitude": 49.29092, "geom:longitude": 8.96041, "geom:hash": "u0y27vhu2tmy", "woe:latitude": 49.29092, "geom:centroid": [8.96041, 49.29092], "woe:longitude": 8.96041, "woe:repo": "woeplanet-poi-de"}, "geometry": {"coordinates": [8.96041, 49.29092], "type": "Point"}}