{"type": "Feature", "id": 56055892, "properties": {"woe:id": 56055892, "woe:parent_id": 665077, "woe:name": "Elisabeth-Knipping-Schule", "woe:placetype": 20, "woe:placetype_name": "POI", "woe:lang": "GER", "iso:country": "DE", "meta:provider": ["geoplanet:7.3.1", "geoplanet:7.3.2", "geoplanet:7.4.0", "geoplanet:7.4.1", "geoplanet:7.5.1", "geoplanet:7.5.2", "geoplanet:7.6.0", "geoplanet:7.8.1", "geoplanet:7.9.0", "geoplanet:7.10.0", "geoplanet:8.0.0", "woeplanet:8.0.0"], "meta:indexed": "2020-08-20T20:51:46.072337", "meta:updated": "2020-08-22T01:51:43.040442", "woe:hierarchy": {"continent": 24865675, "country": 23424829, "town": 0, "planet": 1, "county": 20071100, "suburb": 0, "state": 2345485, "region": 0, "localadmin": 26822719}, "woe:timezone_id": 28350890, "woe:hash": "u1ngbpxwy8fv", "woe:centroid": [9.50277, 51.326542], "geom:latitude": 51.326542, "geom:longitude": 9.50277, "geom:hash": "u1ngbpxwy8fv", "woe:latitude": 51.326542, "geom:centroid": [9.50277, 51.326542], "woe:longitude": 9.50277, "woe:repo": "woeplanet-poi-de"}, "geometry": {"coordinates": [9.50277, 51.326542], "type": "Point"}}