{"type": "Feature", "id": 22178982, "geometry": {"type": "Point", "coordinates": [11.67866, 53.40237]}, "properties": {"woe:id": 22178982, "woe:parent_id": 646114, "woe:name": "D\u00fctschow Bahnhof", "woe:placetype": 20, "woe:placetype_name": "POI", "woe:lang": "GER", "iso:country": "DE", "meta:provider": ["geoplanet:7.3.1", "geoplanet:7.3.2", "geoplanet:7.4.0", "geoplanet:7.4.1", "geoplanet:7.5.1", "geoplanet:7.5.2", "geoplanet:7.6.0", "geoplanet:7.8.1", "geoplanet:7.9.0", "geoplanet:7.10.0", "geoplanet:8.0.0", "woeplanet:8.0.0"], "meta:indexed": "2020-08-20T20:51:38.787174", "meta:updated": "2020-10-14T11:50:27.567966", "woe:alias_ENG_S": ["Dutschow Station"], "woe:alias_GER_S": ["Duetschow Bahnhof", "Dutschow Bahnhof"], "woe:alias_ENG_P": ["Dutschow Station"], "woe:hierarchy": {"continent": 24865675, "country": 23424829, "town": 0, "planet": 1, "county": 12596899, "suburb": 0, "state": 2345492, "region": 0, "localadmin": 12631209}, "woe:timezone_id": 28350890, "woe:hash": "u32rcc85ke21", "woe:centroid": [11.67866, 53.40237], "geom:latitude": 53.40237, "geom:longitude": 11.67866, "geom:hash": "u32rcc85ke21", "woe:latitude": 53.40237, "geom:centroid": [11.67866, 53.40237], "woe:longitude": 11.67866, "woe:repo": "woeplanet-poi-de", "geom:area": 0.0, "woe:scale": 19}}