{"type": "Feature", "id": 56055686, "properties": {"woe:id": 56055686, "woe:parent_id": 673361, "woe:name": "Otto-Von-Guericke-Universit\u00e4t", "woe:placetype": 20, "woe:placetype_name": "POI", "woe:lang": "GER", "iso:country": "DE", "meta:provider": ["geoplanet:7.3.1", "geoplanet:7.3.2", "geoplanet:7.4.0", "geoplanet:7.4.1", "geoplanet:7.5.1", "geoplanet:7.5.2", "geoplanet:7.6.0", "geoplanet:7.8.1", "geoplanet:7.9.0", "geoplanet:7.10.0", "geoplanet:8.0.0", "woeplanet:8.0.0"], "meta:indexed": "2020-08-20T20:51:45.924049", "meta:updated": "2020-08-22T01:51:42.978613", "woe:alias_GER_V": ["Otto-Von-Guericke-Universitat"], "woe:hierarchy": {"continent": 24865675, "country": 23424829, "town": 0, "planet": 1, "county": 12597084, "suburb": 0, "state": 2345494, "region": 0, "localadmin": 26822984}, "woe:timezone_id": 28350890, "woe:hash": "u3228uj2udup", "woe:centroid": [11.64193, 52.141258], "geom:latitude": 52.141258, "geom:longitude": 11.64193, "geom:hash": "u3228uj2udup", "woe:latitude": 52.141258, "geom:centroid": [11.64193, 52.141258], "woe:longitude": 11.64193, "woe:repo": "woeplanet-poi-de"}, "geometry": {"coordinates": [11.64193, 52.141258], "type": "Point"}}