{"type": "Feature", "id": 22963214, "geometry": {"type": "Point", "coordinates": [13.41209, 52.542221]}, "properties": {"woe:id": 22963214, "woe:parent_id": 26821872, "woe:name": "Eberswalder Strasse Bahnhof", "woe:placetype": 20, "woe:placetype_name": "POI", "woe:lang": "GER", "iso:country": "DE", "meta:provider": ["geoplanet:7.3.1", "geoplanet:7.3.2", "geoplanet:7.4.0", "geoplanet:7.4.1", "geoplanet:7.5.1", "geoplanet:7.5.2", "geoplanet:7.6.0", "geoplanet:7.8.1", "geoplanet:7.9.0", "geoplanet:7.10.0", "geoplanet:8.0.0", "woeplanet:8.0.0"], "meta:indexed": "2020-08-20T20:51:44.631081", "meta:updated": "2020-10-14T11:50:28.746899", "woe:alias_ENG_P": ["Eberswalder Strasse Station"], "woe:hierarchy": {"continent": 24865675, "country": 23424829, "town": 0, "planet": 1, "county": 12596838, "suburb": 0, "state": 2345496, "region": 0, "localadmin": 26821872}, "woe:timezone_id": 28350890, "woe:hash": "u33dcjn2s7gh", "woe:centroid": [13.41209, 52.542221], "geom:latitude": 52.542221, "geom:longitude": 13.41209, "geom:hash": "u33dcjn2s7gh", "woe:latitude": 52.542221, "geom:centroid": [13.41209, 52.542221], "woe:longitude": 13.41209, "woe:repo": "woeplanet-poi-de", "geom:area": 0.0, "woe:scale": 19}}