{"type": "Feature", "id": 22244868, "properties": {"woe:id": 22244868, "woe:parent_id": 701981, "woe:name": "Vachdorf Bahnhof", "woe:placetype": 20, "woe:placetype_name": "POI", "woe:lang": "GER", "iso:country": "DE", "meta:provider": ["geoplanet:7.3.1", "geoplanet:7.3.2", "geoplanet:7.4.0", "geoplanet:7.4.1", "geoplanet:7.5.1", "geoplanet:7.5.2", "geoplanet:7.6.0", "geoplanet:7.8.1", "geoplanet:7.9.0", "geoplanet:7.10.0", "geoplanet:8.0.0", "woeplanet:8.0.0"], "meta:indexed": "2020-08-20T20:51:41.591433", "meta:updated": "2020-08-22T01:51:40.788211", "woe:alias_ENG_P": ["Vachdorf Station"], "woe:hierarchy": {"continent": 24865675, "country": 23424829, "town": 0, "planet": 1, "county": 12597005, "suburb": 0, "state": 2345495, "region": 0, "localadmin": 12624972}, "woe:timezone_id": 28350890, "woe:hash": "u0zrryd3z00v", "woe:centroid": [10.53928, 50.529171], "geom:latitude": 50.529171, "geom:longitude": 10.53928, "geom:hash": "u0zrryd3z00v", "woe:latitude": 50.529171, "geom:centroid": [10.53928, 50.529171], "woe:longitude": 10.53928, "woe:repo": "woeplanet-poi-de"}, "geometry": {"coordinates": [10.53928, 50.529171], "type": "Point"}}