{"type": "Feature", "id": 22243027, "properties": {"woe:id": 22243027, "woe:parent_id": 673711, "woe:name": "Mannheim-Neckarstadt Bahnhof", "woe:placetype": 20, "woe:placetype_name": "POI", "woe:lang": "GER", "iso:country": "DE", "meta:provider": ["geoplanet:7.3.1", "geoplanet:7.3.2", "geoplanet:7.4.0", "geoplanet:7.4.1", "geoplanet:7.5.1", "geoplanet:7.5.2", "geoplanet:7.6.0", "geoplanet:7.8.1", "geoplanet:7.9.0", "geoplanet:7.10.0", "geoplanet:8.0.0", "woeplanet:8.0.0"], "meta:indexed": "2020-08-20T20:51:41.502701", "meta:updated": "2020-08-22T01:51:40.755961", "woe:alias_ENG_P": ["Mannheim-Neckarstadt Station"], "woe:hierarchy": {"continent": 24865675, "country": 23424829, "town": 0, "planet": 1, "county": 12597108, "suburb": 0, "state": 2345481, "region": 0, "localadmin": 26823003}, "woe:timezone_id": 28350890, "woe:hash": "u0y18ebj79jq", "woe:centroid": [8.45963, 49.503929], "geom:latitude": 49.503929, "geom:longitude": 8.45963, "geom:hash": "u0y18ebj79jq", "woe:latitude": 49.503929, "geom:centroid": [8.45963, 49.503929], "woe:longitude": 8.45963, "woe:repo": "woeplanet-poi-de"}, "geometry": {"coordinates": [8.45963, 49.503929], "type": "Point"}}