{"type": "Feature", "id": 22173308, "properties": {"woe:id": 22173308, "woe:parent_id": 639679, "woe:name": "Ruhrstadion", "woe:placetype": 20, "woe:placetype_name": "POI", "woe:lang": "GER", "iso:country": "DE", "meta:provider": ["geoplanet:7.3.1", "geoplanet:7.3.2", "geoplanet:7.4.0", "geoplanet:7.4.1", "geoplanet:7.5.1", "geoplanet:7.5.2", "geoplanet:7.6.0", "geoplanet:7.8.1", "geoplanet:7.9.0", "geoplanet:7.10.0", "geoplanet:8.0.0", "woeplanet:8.0.0"], "meta:indexed": "2020-08-20T20:51:38.552328", "meta:updated": "2020-08-22T01:51:39.452040", "woe:alias_GER_V": ["Rewirpowerstadion"], "woe:hierarchy": {"continent": 24865675, "country": 23424829, "town": 0, "planet": 1, "county": 12597004, "suburb": 0, "state": 2345487, "region": 0, "localadmin": 26821947}, "woe:timezone_id": 28350890, "woe:hash": "u1jhutqwnvb0", "woe:centroid": [7.23822, 51.489861], "geom:latitude": 51.489861, "geom:longitude": 7.23822, "geom:hash": "u1jhutqwnvb0", "woe:latitude": 51.489861, "geom:centroid": [7.23822, 51.489861], "woe:longitude": 7.23822, "woe:repo": "woeplanet-poi-de"}, "geometry": {"coordinates": [7.23822, 51.489861], "type": "Point"}}