{"type": "Feature", "id": 22252536, "geometry": {"type": "Point", "coordinates": [7.83548, 47.877819]}, "properties": {"woe:id": 22252536, "woe:parent_id": 702829, "woe:name": "Bienenkunde-Museum", "woe:placetype": 20, "woe:placetype_name": "POI", "woe:lang": "GER", "iso:country": "DE", "meta:provider": ["geoplanet:7.3.1", "geoplanet:7.3.2", "geoplanet:7.4.0", "geoplanet:7.4.1", "geoplanet:7.5.1", "geoplanet:7.5.2", "geoplanet:7.6.0", "geoplanet:7.8.1", "geoplanet:7.9.0", "geoplanet:7.10.0", "geoplanet:8.0.0", "woeplanet:8.0.0"], "meta:indexed": "2020-08-20T20:51:41.804042", "meta:updated": "2020-10-14T11:50:58.990342", "woe:alias_GER_V": ["Bienenkundemuseum"], "woe:hierarchy": {"continent": 24865675, "country": 23424829, "town": 0, "planet": 1, "county": 12596773, "suburb": 0, "state": 2345481, "region": 0, "localadmin": 12623356}, "woe:timezone_id": 28350890, "woe:hash": "u0t867csebm7", "woe:centroid": [7.83548, 47.877819], "geom:latitude": 47.877819, "geom:longitude": 7.83548, "geom:hash": "u0t867csebm7", "woe:latitude": 47.877819, "geom:centroid": [7.83548, 47.877819], "woe:longitude": 7.83548, "woe:repo": "woeplanet-poi-de", "geom:area": 0.0, "woe:scale": 19}}