{"type": "Feature", "id": 22229135, "geometry": {"type": "Point", "coordinates": [8.69525, 50.05685]}, "properties": {"woe:id": 22229135, "woe:parent_id": 22528042, "woe:name": "Museum der Stadt Neu-Isenburg", "woe:placetype": 20, "woe:placetype_name": "POI", "woe:lang": "GER", "iso:country": "DE", "meta:provider": ["geoplanet:7.3.1", "geoplanet:7.3.2", "geoplanet:7.4.0", "geoplanet:7.4.1", "geoplanet:7.5.1", "geoplanet:7.5.2", "geoplanet:7.6.0", "geoplanet:7.8.1", "geoplanet:7.9.0", "geoplanet:7.10.0", "geoplanet:8.0.0", "woeplanet:8.0.0"], "meta:indexed": "2020-08-20T20:51:40.881464", "meta:updated": "2020-10-14T11:50:58.876890", "woe:hierarchy": {"continent": 24865675, "country": 23424829, "town": 0, "planet": 1, "county": 12597040, "suburb": 0, "state": 2345485, "region": 0, "localadmin": 12632633}, "woe:timezone_id": 28350890, "woe:hash": "u0yhvbedq10m", "woe:centroid": [8.69525, 50.05685], "geom:latitude": 50.05685, "geom:longitude": 8.69525, "geom:hash": "u0yhvbedq10m", "woe:latitude": 50.05685, "geom:centroid": [8.69525, 50.05685], "woe:longitude": 8.69525, "woe:repo": "woeplanet-poi-de", "geom:area": 0.0, "woe:scale": 19}}