{"type": "Feature", "id": 22287677, "geometry": {"type": "Point", "coordinates": [9.91895, 48.351158]}, "properties": {"woe:id": 22287677, "woe:parent_id": 647282, "woe:name": "Einsingen Bahnhof", "woe:placetype": 20, "woe:placetype_name": "POI", "woe:lang": "GER", "iso:country": "DE", "meta:provider": ["geoplanet:7.3.1", "geoplanet:7.3.2", "geoplanet:7.4.0", "geoplanet:7.4.1", "geoplanet:7.5.1", "geoplanet:7.5.2", "geoplanet:7.6.0", "geoplanet:7.8.1", "geoplanet:7.9.0", "geoplanet:7.10.0", "geoplanet:8.0.0", "woeplanet:8.0.0"], "meta:indexed": "2020-08-20T20:51:43.256987", "meta:updated": "2020-10-14T11:50:58.439876", "woe:alias_ENG_P": ["Einsingen Station"], "woe:hierarchy": {"continent": 24865675, "country": 23424829, "town": 0, "planet": 1, "county": 12596930, "suburb": 0, "state": 2345481, "region": 0, "localadmin": 12623679}, "woe:timezone_id": 28350890, "woe:hash": "u0x51dncbm1h", "woe:centroid": [9.91895, 48.351158], "geom:latitude": 48.351158, "geom:longitude": 9.91895, "geom:hash": "u0x51dncbm1h", "woe:latitude": 48.351158, "geom:centroid": [9.91895, 48.351158], "woe:longitude": 9.91895, "woe:repo": "woeplanet-poi-de", "geom:area": 0.0, "woe:scale": 19}}