{"type": "Feature", "id": 22925833, "geometry": {"type": "Point", "coordinates": [12.19022, 48.7299]}, "properties": {"woe:id": 22925833, "woe:parent_id": 678350, "woe:name": "Neufahrn Bahnhof", "woe:placetype": 20, "woe:placetype_name": "POI", "woe:lang": "GER", "iso:country": "DE", "meta:provider": ["geoplanet:7.3.1", "geoplanet:7.3.2", "geoplanet:7.4.0", "geoplanet:7.4.1", "geoplanet:7.5.1", "geoplanet:7.5.2", "geoplanet:7.6.0", "geoplanet:7.8.1", "geoplanet:7.9.0", "geoplanet:7.10.0", "geoplanet:8.0.0", "woeplanet:8.0.0"], "meta:indexed": "2020-08-20T20:51:43.938442", "meta:updated": "2020-10-14T11:50:28.897738", "woe:alias_ENG_P": ["Neufahrn Station"], "woe:hierarchy": {"continent": 24865675, "country": 23424829, "town": 0, "planet": 1, "county": 12596766, "suburb": 0, "state": 2345482, "region": 0, "localadmin": 12635783}, "woe:timezone_id": 28350890, "woe:hash": "u28tjrh8hxyb", "woe:centroid": [12.19022, 48.7299], "geom:latitude": 48.7299, "geom:longitude": 12.19022, "geom:hash": "u28tjrh8hxyb", "woe:latitude": 48.7299, "geom:centroid": [12.19022, 48.7299], "woe:longitude": 12.19022, "woe:repo": "woeplanet-poi-de", "geom:area": 0.0, "woe:scale": 19}}