{"type": "Feature", "id": 22187271, "geometry": {"type": "Point", "coordinates": [11.87071, 52.143051]}, "properties": {"woe:id": 22187271, "woe:parent_id": 708945, "woe:name": "Ziepel Bahnhof", "woe:placetype": 20, "woe:placetype_name": "POI", "woe:lang": "GER", "iso:country": "DE", "meta:provider": ["geoplanet:7.3.1", "geoplanet:7.3.2", "geoplanet:7.4.0", "geoplanet:7.4.1", "geoplanet:7.5.1", "geoplanet:7.5.2", "geoplanet:7.6.0", "geoplanet:7.8.1", "geoplanet:7.9.0", "geoplanet:7.10.0", "geoplanet:8.0.0", "woeplanet:8.0.0"], "meta:indexed": "2020-08-20T20:51:39.218790", "meta:updated": "2020-10-14T11:50:27.806762", "woe:alias_ENG_P": ["Ziepel Station"], "woe:hierarchy": {"continent": 24865675, "country": 23424829, "town": 0, "planet": 1, "county": 12596990, "suburb": 0, "state": 2345494, "region": 0, "localadmin": 24547380}, "woe:timezone_id": 28350890, "woe:hash": "u322wh7gr94y", "woe:centroid": [11.87071, 52.143051], "geom:latitude": 52.143051, "geom:longitude": 11.87071, "geom:hash": "u322wh7gr94y", "woe:latitude": 52.143051, "geom:centroid": [11.87071, 52.143051], "woe:longitude": 11.87071, "woe:repo": "woeplanet-poi-de", "geom:area": 0.0, "woe:scale": 19}}