{"type": "Feature", "id": 22158302, "properties": {"woe:id": 22158302, "woe:parent_id": 636481, "woe:name": "Bad Oeynhausen Bahnhof", "woe:placetype": 20, "woe:placetype_name": "POI", "woe:lang": "GER", "iso:country": "DE", "meta:provider": ["geoplanet:7.3.1", "geoplanet:7.3.2", "geoplanet:7.4.0", "geoplanet:7.4.1", "geoplanet:7.5.1", "geoplanet:7.5.2", "geoplanet:7.6.0", "geoplanet:7.8.1", "geoplanet:7.9.0", "geoplanet:7.10.0", "geoplanet:8.0.0", "woeplanet:8.0.0"], "meta:indexed": "2020-08-20T20:51:38.090104", "meta:updated": "2020-08-22T01:51:39.190960", "woe:alias_ENG_P": ["Bad Oeynhausen Station"], "woe:hierarchy": {"continent": 24865675, "country": 23424829, "town": 0, "planet": 1, "county": 12596892, "suburb": 0, "state": 2345487, "region": 0, "localadmin": 12624547}, "woe:timezone_id": 28350890, "woe:hash": "u1q2bptmrwhm", "woe:centroid": [8.7966, 52.205219], "geom:latitude": 52.205219, "geom:longitude": 8.7966, "geom:hash": "u1q2bptmrwhm", "woe:latitude": 52.205219, "geom:centroid": [8.7966, 52.205219], "woe:longitude": 8.7966, "woe:repo": "woeplanet-poi-de"}, "geometry": {"coordinates": [8.7966, 52.205219], "type": "Point"}}