{"type": "Feature", "id": 22275824, "properties": {"woe:id": 22275824, "woe:parent_id": 680971, "woe:name": "Obercarsdorf Bahnhof", "woe:placetype": 20, "woe:placetype_name": "POI", "woe:lang": "GER", "iso:country": "DE", "meta:provider": ["geoplanet:7.3.1", "geoplanet:7.3.2", "geoplanet:7.4.0", "geoplanet:7.4.1", "geoplanet:7.5.1", "geoplanet:7.5.2", "geoplanet:7.6.0", "geoplanet:7.8.1", "geoplanet:7.9.0", "geoplanet:7.10.0", "geoplanet:8.0.0", "woeplanet:8.0.0"], "meta:indexed": "2020-08-20T20:51:42.739251", "meta:updated": "2020-08-22T01:51:41.246113", "woe:alias_ENG_P": ["Obercarsdorf Station"], "woe:hierarchy": {"continent": 24865675, "country": 23424829, "town": 0, "planet": 1, "county": 56448172, "suburb": 0, "state": 2345493, "region": 0, "localadmin": 12636493}, "woe:timezone_id": 28350890, "woe:hash": "u319qfytj93r", "woe:centroid": [13.66517, 50.860699], "geom:latitude": 50.860699, "geom:longitude": 13.66517, "geom:hash": "u319qfytj93r", "woe:latitude": 50.860699, "geom:centroid": [13.66517, 50.860699], "woe:longitude": 13.66517, "woe:repo": "woeplanet-poi-de"}, "geometry": {"coordinates": [13.66517, 50.860699], "type": "Point"}}