{"type": "Feature", "id": 22190696, "geometry": {"type": "Point", "coordinates": [9.52358, 48.714329]}, "properties": {"woe:id": 22190696, "woe:parent_id": 646239, "woe:name": "Museum Ebersbach", "woe:placetype": 20, "woe:placetype_name": "POI", "woe:lang": "GER", "iso:country": "DE", "meta:provider": ["geoplanet:7.3.1", "geoplanet:7.3.2", "geoplanet:7.4.0", "geoplanet:7.4.1", "geoplanet:7.5.1", "geoplanet:7.5.2", "geoplanet:7.6.0", "geoplanet:7.8.1", "geoplanet:7.9.0", "geoplanet:7.10.0", "geoplanet:8.0.0", "woeplanet:8.0.0"], "meta:indexed": "2020-08-20T20:51:39.332663", "meta:updated": "2020-10-14T11:50:26.997156", "woe:hierarchy": {"continent": 24865675, "country": 23424829, "town": 0, "planet": 1, "county": 12596800, "suburb": 0, "state": 2345481, "region": 0, "localadmin": 12624071}, "woe:timezone_id": 28350890, "woe:hash": "u0wv0snve3pg", "woe:centroid": [9.52358, 48.714329], "geom:latitude": 48.714329, "geom:longitude": 9.52358, "geom:hash": "u0wv0snve3pg", "woe:latitude": 48.714329, "geom:centroid": [9.52358, 48.714329], "woe:longitude": 9.52358, "woe:repo": "woeplanet-poi-de", "geom:area": 0.0, "woe:scale": 19}}