{"type": "Feature", "id": 56055646, "properties": {"woe:id": 56055646, "woe:parent_id": 677807, "woe:name": "Verwaltungs- U. Wirtschaftsakademie", "woe:placetype": 20, "woe:placetype_name": "POI", "woe:lang": "GER", "iso:country": "DE", "meta:provider": ["geoplanet:7.3.1", "geoplanet:7.3.2", "geoplanet:7.4.0", "geoplanet:7.4.1", "geoplanet:7.5.1", "geoplanet:7.5.2", "geoplanet:7.6.0", "geoplanet:7.8.1", "geoplanet:7.9.0", "geoplanet:7.10.0", "geoplanet:8.0.0", "woeplanet:8.0.0"], "meta:indexed": "2020-08-20T20:51:45.890233", "meta:updated": "2020-08-22T01:51:42.965373", "woe:hierarchy": {"continent": 24865675, "country": 23424829, "town": 0, "planet": 1, "county": 12596930, "suburb": 0, "state": 2345481, "region": 0, "localadmin": 12623679}, "woe:timezone_id": 28350890, "woe:hash": "u0x576qdw5fy", "woe:centroid": [9.99576, 48.396599], "geom:latitude": 48.396599, "geom:longitude": 9.99576, "geom:hash": "u0x576qdw5fy", "woe:latitude": 48.396599, "geom:centroid": [9.99576, 48.396599], "woe:longitude": 9.99576, "woe:repo": "woeplanet-poi-de"}, "geometry": {"coordinates": [9.99576, 48.396599], "type": "Point"}}