{"type": "Feature", "id": 22240136, "properties": {"woe:id": 22240136, "woe:parent_id": 672826, "woe:name": "V\u00f6lkerkunde-Sammlung der Hansestadt L\u00fcbeck", "woe:placetype": 20, "woe:placetype_name": "POI", "woe:lang": "GER", "iso:country": "DE", "meta:provider": ["geoplanet:7.3.1", "geoplanet:7.3.2", "geoplanet:7.4.0", "geoplanet:7.4.1", "geoplanet:7.5.1", "geoplanet:7.5.2", "geoplanet:7.6.0", "geoplanet:7.8.1", "geoplanet:7.9.0", "geoplanet:7.10.0", "geoplanet:8.0.0", "woeplanet:8.0.0"], "meta:indexed": "2020-08-20T20:51:41.391437", "meta:updated": "2020-08-22T01:51:40.715669", "woe:alias_GER_S": ["Voelkerkunde-Sammlung der Hansestadt Luebeck", "Volkerkunde-Sammlung der Hansestadt Lubeck"], "woe:hierarchy": {"continent": 24865675, "country": 23424829, "town": 0, "planet": 1, "county": 12597082, "suburb": 0, "state": 2345490, "region": 0, "localadmin": 26822947}, "woe:timezone_id": 28350890, "woe:hash": "u1xd7jhmfrk6", "woe:centroid": [10.68465, 53.8615], "geom:latitude": 53.8615, "geom:longitude": 10.68465, "geom:hash": "u1xd7jhmfrk6", "woe:latitude": 53.8615, "geom:centroid": [10.68465, 53.8615], "woe:longitude": 10.68465, "woe:repo": "woeplanet-poi-de"}, "geometry": {"coordinates": [10.68465, 53.8615], "type": "Point"}}