{"type": "Feature", "id": 22285254, "geometry": {"type": "Point", "coordinates": [12.26683, 50.730888]}, "properties": {"woe:id": 22285254, "woe:parent_id": 698796, "woe:name": "Teichwolframsdorf Bahnhof", "woe:placetype": 20, "woe:placetype_name": "POI", "woe:lang": "GER", "iso:country": "DE", "meta:provider": ["geoplanet:7.3.1", "geoplanet:7.3.2", "geoplanet:7.4.0", "geoplanet:7.4.1", "geoplanet:7.5.1", "geoplanet:7.5.2", "geoplanet:7.6.0", "geoplanet:7.8.1", "geoplanet:7.9.0", "geoplanet:7.10.0", "geoplanet:8.0.0", "woeplanet:8.0.0"], "meta:indexed": "2020-08-20T20:51:43.132618", "meta:updated": "2020-10-14T11:50:58.207458", "woe:alias_ENG_P": ["Teichwolframsdorf Station"], "woe:hierarchy": {"continent": 24865675, "country": 23424829, "town": 0, "planet": 1, "county": 12596933, "suburb": 0, "state": 2345495, "region": 0, "localadmin": 12636377}, "woe:timezone_id": 28350890, "woe:hash": "u308x5k2vfgq", "woe:centroid": [12.26683, 50.730888], "geom:latitude": 50.730888, "geom:longitude": 12.26683, "geom:hash": "u308x5k2vfgq", "woe:latitude": 50.730888, "geom:centroid": [12.26683, 50.730888], "woe:longitude": 12.26683, "woe:repo": "woeplanet-poi-de", "geom:area": 0.0, "woe:scale": 19}}