{"type": "Feature", "id": 22990431, "geometry": {"type": "Point", "coordinates": [7.82924, 49.763191]}, "properties": {"woe:id": 22990431, "woe:parent_id": 660611, "woe:name": "Hochst\u00e4tten Bahnhof", "woe:placetype": 20, "woe:placetype_name": "POI", "woe:lang": "GER", "iso:country": "DE", "meta:provider": ["geoplanet:7.3.1", "geoplanet:7.3.2", "geoplanet:7.4.0", "geoplanet:7.4.1", "geoplanet:7.5.1", "geoplanet:7.5.2", "geoplanet:7.6.0", "geoplanet:7.8.1", "geoplanet:7.9.0", "geoplanet:7.10.0", "geoplanet:8.0.0", "woeplanet:8.0.0"], "meta:indexed": "2020-08-20T20:51:45.175298", "meta:updated": "2020-10-14T11:50:29.057632", "woe:alias_ENG_S": ["Hochstatten Station"], "woe:alias_GER_S": ["Hochstaetten Bahnhof", "Hochstatten Bahnhof"], "woe:alias_ENG_P": ["Hochstatten Station"], "woe:hierarchy": {"continent": 24865675, "country": 23424829, "town": 0, "planet": 1, "county": 12596762, "suburb": 0, "state": 2345488, "region": 0, "localadmin": 12628007}, "woe:timezone_id": 28350890, "woe:hash": "u0ve45j5de0m", "woe:centroid": [7.82924, 49.763191], "geom:latitude": 49.763191, "geom:longitude": 7.82924, "geom:hash": "u0ve45j5de0m", "woe:latitude": 49.763191, "geom:centroid": [7.82924, 49.763191], "woe:longitude": 7.82924, "woe:repo": "woeplanet-poi-de", "geom:area": 0.0, "woe:scale": 19}}