{"type": "Feature", "id": 22265567, "properties": {"woe:id": 22265567, "woe:parent_id": 55965983, "woe:name": "Potsdam-Drewitz Bahnhof", "woe:placetype": 20, "woe:placetype_name": "POI", "woe:lang": "GER", "iso:country": "DE", "meta:provider": ["geoplanet:7.3.1", "geoplanet:7.3.2", "geoplanet:7.4.0", "geoplanet:7.4.1", "geoplanet:7.5.1", "geoplanet:7.5.2", "geoplanet:7.6.0", "geoplanet:7.8.1", "geoplanet:7.9.0", "geoplanet:7.10.0", "geoplanet:8.0.0", "woeplanet:8.0.0"], "meta:indexed": "2020-08-20T20:51:42.269757", "meta:updated": "2020-08-22T01:51:41.062407", "woe:alias_ENG_P": ["Potsdam-Drewitz Station"], "woe:hierarchy": {"continent": 24865675, "country": 23424829, "town": 0, "planet": 1, "county": 12597070, "suburb": 0, "state": 2345491, "region": 0, "localadmin": 12632873}, "woe:timezone_id": 28350890, "woe:hash": "u333fxgnke2f", "woe:centroid": [13.12199, 52.38253], "geom:latitude": 52.38253, "geom:longitude": 13.12199, "geom:hash": "u333fxgnke2f", "woe:latitude": 52.38253, "geom:centroid": [13.12199, 52.38253], "woe:longitude": 13.12199, "woe:repo": "woeplanet-poi-de"}, "geometry": {"coordinates": [13.12199, 52.38253], "type": "Point"}}