{"type": "Feature", "id": 23013865, "properties": {"woe:id": 23013865, "woe:parent_id": 666874, "woe:name": "Freden Bahnhof", "woe:placetype": 20, "woe:placetype_name": "POI", "woe:lang": "GER", "iso:country": "DE", "meta:provider": ["geoplanet:7.3.1", "geoplanet:7.3.2", "geoplanet:7.4.0", "geoplanet:7.4.1", "geoplanet:7.5.1", "geoplanet:7.5.2", "geoplanet:7.6.0", "geoplanet:7.8.1", "geoplanet:7.9.0", "geoplanet:7.10.0", "geoplanet:8.0.0", "woeplanet:8.0.0"], "meta:indexed": "2020-08-20T20:51:45.470462", "meta:updated": "2020-08-22T01:51:42.634169", "woe:alias_ENG_P": ["Freden Station"], "woe:hierarchy": {"continent": 24865675, "country": 23424829, "town": 0, "planet": 1, "county": 12596788, "suburb": 0, "state": 2345486, "region": 0, "localadmin": 12629489}, "woe:timezone_id": 28350890, "woe:hash": "u1pp3m0j9wdy", "woe:centroid": [9.89875, 51.92786], "geom:latitude": 51.92786, "geom:longitude": 9.89875, "geom:hash": "u1pp3m0j9wdy", "woe:latitude": 51.92786, "geom:centroid": [9.89875, 51.92786], "woe:longitude": 9.89875, "woe:repo": "woeplanet-poi-de"}, "geometry": {"coordinates": [9.89875, 51.92786], "type": "Point"}}