{"type": "Feature", "id": 22293498, "properties": {"woe:id": 22293498, "woe:parent_id": 705515, "woe:name": "Schlo\u00dfmuseum Wernigerode", "woe:placetype": 20, "woe:placetype_name": "POI", "woe:lang": "GER", "iso:country": "DE", "meta:provider": ["geoplanet:7.3.1", "geoplanet:7.3.2", "geoplanet:7.4.0", "geoplanet:7.4.1", "geoplanet:7.5.1", "geoplanet:7.5.2", "geoplanet:7.6.0", "geoplanet:7.8.1", "geoplanet:7.9.0", "geoplanet:7.10.0", "geoplanet:8.0.0", "woeplanet:8.0.0"], "meta:indexed": "2020-08-20T20:51:43.590788", "meta:updated": "2020-08-22T01:51:41.637397", "woe:alias_GER_S": ["Schlossmuseum Wernigerode"], "woe:hierarchy": {"continent": 24865675, "country": 23424829, "town": 0, "planet": 1, "county": 12596713, "suburb": 0, "state": 2345494, "region": 0, "localadmin": 12626935}, "woe:timezone_id": 28350890, "woe:hash": "u1pwven5rpsj", "woe:centroid": [10.79712, 51.828602], "geom:latitude": 51.828602, "geom:longitude": 10.79712, "geom:hash": "u1pwven5rpsj", "woe:latitude": 51.828602, "geom:centroid": [10.79712, 51.828602], "woe:longitude": 10.79712, "woe:repo": "woeplanet-poi-de"}, "geometry": {"coordinates": [10.79712, 51.828602], "type": "Point"}}