{"type": "Feature", "id": 22240264, "geometry": {"type": "Point", "coordinates": [13.65522, 51.856781]}, "properties": {"woe:id": 22240264, "woe:parent_id": 684464, "woe:name": "Z\u00f6llmersdorf Bahnhof", "woe:placetype": 20, "woe:placetype_name": "POI", "woe:lang": "GER", "iso:country": "DE", "meta:provider": ["geoplanet:7.3.1", "geoplanet:7.3.2", "geoplanet:7.4.0", "geoplanet:7.4.1", "geoplanet:7.5.1", "geoplanet:7.5.2", "geoplanet:7.6.0", "geoplanet:7.8.1", "geoplanet:7.9.0", "geoplanet:7.10.0", "geoplanet:8.0.0", "woeplanet:8.0.0"], "meta:indexed": "2020-08-20T20:51:41.399662", "meta:updated": "2020-10-14T11:50:57.787168", "woe:alias_ENG_S": ["Zollmersdorf Station"], "woe:alias_GER_S": ["Zoellmersdorf Bahnhof", "Zollmersdorf Bahnhof"], "woe:alias_ENG_P": ["Zollmersdorf Station"], "woe:hierarchy": {"continent": 24865675, "country": 23424829, "town": 0, "planet": 1, "county": 12596993, "suburb": 0, "state": 2345491, "region": 0, "localadmin": 24547232}, "woe:timezone_id": 28350890, "woe:hash": "u31xn8prtsw5", "woe:centroid": [13.65522, 51.856781], "geom:latitude": 51.856781, "geom:longitude": 13.65522, "geom:hash": "u31xn8prtsw5", "woe:latitude": 51.856781, "geom:centroid": [13.65522, 51.856781], "woe:longitude": 13.65522, "woe:repo": "woeplanet-poi-de", "geom:area": 0.0, "woe:scale": 19}}