{"type": "Feature", "id": 22210042, "properties": {"woe:id": 22210042, "woe:parent_id": 698459, "woe:name": "Sythen Bahnhof", "woe:placetype": 20, "woe:placetype_name": "POI", "woe:lang": "GER", "iso:country": "DE", "meta:provider": ["geoplanet:7.3.1", "geoplanet:7.3.2", "geoplanet:7.4.0", "geoplanet:7.4.1", "geoplanet:7.5.1", "geoplanet:7.5.2", "geoplanet:7.6.0", "geoplanet:7.8.1", "geoplanet:7.9.0", "geoplanet:7.10.0", "geoplanet:8.0.0", "woeplanet:8.0.0"], "meta:indexed": "2020-08-20T20:51:40.182204", "meta:updated": "2020-08-22T01:51:40.224675", "woe:alias_ENG_P": ["Sythen Station"], "woe:hierarchy": {"continent": 24865675, "country": 23424829, "town": 0, "planet": 1, "county": 12596904, "suburb": 0, "state": 2345487, "region": 0, "localadmin": 12624389}, "woe:timezone_id": 28350890, "woe:hash": "u1jns2tzj6bt", "woe:centroid": [7.22614, 51.771542], "geom:latitude": 51.771542, "geom:longitude": 7.22614, "geom:hash": "u1jns2tzj6bt", "woe:latitude": 51.771542, "geom:centroid": [7.22614, 51.771542], "woe:longitude": 7.22614, "woe:repo": "woeplanet-poi-de"}, "geometry": {"coordinates": [7.22614, 51.771542], "type": "Point"}}