{"type": "Feature", "id": 22951705, "geometry": {"type": "Point", "coordinates": [9.26158, 48.81171]}, "properties": {"woe:id": 22951705, "woe:parent_id": 649530, "woe:name": "H\u00f6henstrasse Bahnhof", "woe:placetype": 20, "woe:placetype_name": "POI", "woe:lang": "GER", "iso:country": "DE", "meta:provider": ["geoplanet:7.3.1", "geoplanet:7.3.2", "geoplanet:7.4.0", "geoplanet:7.4.1", "geoplanet:7.5.1", "geoplanet:7.5.2", "geoplanet:7.6.0", "geoplanet:7.8.1", "geoplanet:7.9.0", "geoplanet:7.10.0", "geoplanet:8.0.0", "woeplanet:8.0.0"], "meta:indexed": "2020-08-20T20:51:44.406107", "meta:updated": "2020-10-14T11:50:29.336183", "woe:alias_ENG_P": ["Hohenstrasse Station"], "woe:alias_GER_S": ["Hoehenstrasse Bahnhof", "Hohenstrasse Bahnhof"], "woe:hierarchy": {"continent": 24865675, "country": 23424829, "town": 0, "planet": 1, "county": 12596822, "suburb": 0, "state": 2345481, "region": 0, "localadmin": 12624102}, "woe:timezone_id": 28350890, "woe:hash": "u0wtdvbhf6nx", "woe:centroid": [9.26158, 48.81171], "geom:latitude": 48.81171, "geom:longitude": 9.26158, "geom:hash": "u0wtdvbhf6nx", "woe:latitude": 48.81171, "geom:centroid": [9.26158, 48.81171], "woe:longitude": 9.26158, "woe:repo": "woeplanet-poi-de", "geom:area": 0.0, "woe:scale": 19}}