{"type": "Feature", "id": 23044307, "geometry": {"type": "Point", "coordinates": [9.25922, 51.60965]}, "properties": {"woe:id": 23044307, "woe:parent_id": 643571, "woe:name": "Borgholz Bahnhof", "woe:placetype": 20, "woe:placetype_name": "POI", "woe:lang": "GER", "iso:country": "DE", "meta:provider": ["geoplanet:7.3.1", "geoplanet:7.3.2", "geoplanet:7.4.0", "geoplanet:7.4.1", "geoplanet:7.5.1", "geoplanet:7.5.2", "geoplanet:7.6.0", "geoplanet:7.8.1", "geoplanet:7.9.0", "geoplanet:7.10.0", "geoplanet:8.0.0", "woeplanet:8.0.0"], "meta:indexed": "2020-08-20T20:51:45.710455", "meta:updated": "2020-10-14T11:50:26.623463", "woe:alias_ENG_P": ["Borgholz Station"], "woe:hierarchy": {"continent": 24865675, "country": 23424829, "town": 0, "planet": 1, "county": 12596929, "suburb": 0, "state": 2345487, "region": 0, "localadmin": 12624523}, "woe:timezone_id": 28350890, "woe:hash": "u1ntdeq252nf", "woe:centroid": [9.25922, 51.60965], "geom:latitude": 51.60965, "geom:longitude": 9.25922, "geom:hash": "u1ntdeq252nf", "woe:latitude": 51.60965, "geom:centroid": [9.25922, 51.60965], "woe:longitude": 9.25922, "woe:repo": "woeplanet-poi-de", "geom:area": 0.0, "woe:scale": 19}}