{"type": "Feature", "id": 22231988, "geometry": {"type": "Point", "coordinates": [6.94513, 50.933929]}, "properties": {"woe:id": 22231988, "woe:parent_id": 667931, "woe:name": "U Mauritiuskirche Bahnhof", "woe:placetype": 20, "woe:placetype_name": "POI", "woe:lang": "GER", "iso:country": "DE", "meta:provider": ["geoplanet:7.3.1", "geoplanet:7.3.2", "geoplanet:7.4.0", "geoplanet:7.4.1", "geoplanet:7.5.1", "geoplanet:7.5.2", "geoplanet:7.6.0", "geoplanet:7.8.1", "geoplanet:7.9.0", "geoplanet:7.10.0", "geoplanet:8.0.0", "woeplanet:8.0.0"], "meta:indexed": "2020-08-20T20:51:40.981568", "meta:updated": "2020-10-14T11:50:57.261642", "woe:alias_ENG_P": ["U Mauritiuskirche Station"], "woe:hierarchy": {"continent": 24865675, "country": 23424829, "town": 0, "planet": 1, "county": 12597059, "suburb": 0, "state": 2345487, "region": 0, "localadmin": 26822796}, "woe:timezone_id": 28350890, "woe:hash": "u1hcy01r9k83", "woe:centroid": [6.94513, 50.933929], "geom:latitude": 50.933929, "geom:longitude": 6.94513, "geom:hash": "u1hcy01r9k83", "woe:latitude": 50.933929, "geom:centroid": [6.94513, 50.933929], "woe:longitude": 6.94513, "woe:repo": "woeplanet-poi-de", "geom:area": 0.0, "woe:scale": 19}}