{"type": "Feature", "id": 22234461, "properties": {"woe:id": 22234461, "woe:parent_id": 640649, "woe:name": "Brahlstorf Bahnhof", "woe:placetype": 20, "woe:placetype_name": "POI", "woe:lang": "GER", "iso:country": "DE", "meta:provider": ["geoplanet:7.3.1", "geoplanet:7.3.2", "geoplanet:7.4.0", "geoplanet:7.4.1", "geoplanet:7.5.1", "geoplanet:7.5.2", "geoplanet:7.6.0", "geoplanet:7.8.1", "geoplanet:7.9.0", "geoplanet:7.10.0", "geoplanet:8.0.0", "woeplanet:8.0.0"], "meta:indexed": "2020-08-20T20:51:41.122226", "meta:updated": "2020-08-22T01:51:40.605616", "woe:alias_ENG_P": ["Brahlstorf Station"], "woe:hierarchy": {"continent": 24865675, "country": 23424829, "town": 0, "planet": 1, "county": 12596989, "suburb": 0, "state": 2345492, "region": 0, "localadmin": 12630713}, "woe:timezone_id": 28350890, "woe:hash": "u1rz94wwe7bu", "woe:centroid": [10.95145, 53.364479], "geom:latitude": 53.364479, "geom:longitude": 10.95145, "geom:hash": "u1rz94wwe7bu", "woe:latitude": 53.364479, "geom:centroid": [10.95145, 53.364479], "woe:longitude": 10.95145, "woe:repo": "woeplanet-poi-de"}, "geometry": {"coordinates": [10.95145, 53.364479], "type": "Point"}}