{"type": "Feature", "id": 22236654, "properties": {"woe:id": 22236654, "woe:parent_id": 670975, "woe:name": "Leichlingen Bahnhof", "woe:placetype": 20, "woe:placetype_name": "POI", "woe:lang": "GER", "iso:country": "DE", "meta:provider": ["geoplanet:7.3.1", "geoplanet:7.3.2", "geoplanet:7.4.0", "geoplanet:7.4.1", "geoplanet:7.5.1", "geoplanet:7.5.2", "geoplanet:7.6.0", "geoplanet:7.8.1", "geoplanet:7.9.0", "geoplanet:7.10.0", "geoplanet:8.0.0", "woeplanet:8.0.0"], "meta:indexed": "2020-08-20T20:51:41.221878", "meta:updated": "2020-08-22T01:51:40.650598", "woe:alias_ENG_P": ["Leichlingen Station"], "woe:hierarchy": {"continent": 24865675, "country": 23424829, "town": 0, "planet": 1, "county": 12596889, "suburb": 0, "state": 2345487, "region": 0, "localadmin": 12624357}, "woe:timezone_id": 28350890, "woe:hash": "u1hfxrv6wyz4", "woe:centroid": [7.0058, 51.107491], "geom:latitude": 51.107491, "geom:longitude": 7.0058, "geom:hash": "u1hfxrv6wyz4", "woe:latitude": 51.107491, "geom:centroid": [7.0058, 51.107491], "woe:longitude": 7.0058, "woe:repo": "woeplanet-poi-de"}, "geometry": {"coordinates": [7.0058, 51.107491], "type": "Point"}}