{"type": "Feature", "id": 22170494, "properties": {"woe:id": 22170494, "woe:parent_id": 668117, "woe:name": "K\u00f6nigsborn Bahnhof", "woe:placetype": 20, "woe:placetype_name": "POI", "woe:lang": "GER", "iso:country": "DE", "meta:provider": ["geoplanet:7.3.1", "geoplanet:7.3.2", "geoplanet:7.4.0", "geoplanet:7.4.1", "geoplanet:7.5.1", "geoplanet:7.5.2", "geoplanet:7.6.0", "geoplanet:7.8.1", "geoplanet:7.9.0", "geoplanet:7.10.0", "geoplanet:8.0.0", "woeplanet:8.0.0"], "meta:indexed": "2020-08-20T20:51:38.474651", "meta:updated": "2020-08-22T01:51:39.409330", "woe:alias_ENG_S": ["Konigsborn Station"], "woe:alias_GER_S": ["Koenigsborn Bahnhof", "Konigsborn Bahnhof"], "woe:alias_ENG_P": ["Konigsborn Station"], "woe:hierarchy": {"continent": 24865675, "country": 23424829, "town": 0, "planet": 1, "county": 12596990, "suburb": 0, "state": 2345494, "region": 0, "localadmin": 12626626}, "woe:timezone_id": 28350890, "woe:hash": "u322ed8ww7g5", "woe:centroid": [11.75633, 52.13401], "geom:latitude": 52.13401, "geom:longitude": 11.75633, "geom:hash": "u322ed8ww7g5", "woe:latitude": 52.13401, "geom:centroid": [11.75633, 52.13401], "woe:longitude": 11.75633, "woe:repo": "woeplanet-poi-de"}, "geometry": {"coordinates": [11.75633, 52.13401], "type": "Point"}}