{"type": "Feature", "id": 22970414, "properties": {"woe:id": 22970414, "woe:parent_id": 20173540, "woe:name": "Brand Bahnhof", "woe:placetype": 20, "woe:placetype_name": "POI", "woe:lang": "GER", "iso:country": "DE", "meta:provider": ["geoplanet:7.3.1", "geoplanet:7.3.2", "geoplanet:7.4.0", "geoplanet:7.4.1", "geoplanet:7.5.1", "geoplanet:7.5.2", "geoplanet:7.6.0", "geoplanet:7.8.1", "geoplanet:7.9.0", "geoplanet:7.10.0", "geoplanet:8.0.0", "woeplanet:8.0.0"], "meta:indexed": "2020-08-20T20:51:44.734643", "meta:updated": "2020-08-22T01:51:42.217609", "woe:alias_ENG_P": ["Brand Station"], "woe:hierarchy": {"continent": 24865675, "country": 23424829, "town": 0, "planet": 1, "county": 12596993, "suburb": 0, "state": 2345491, "region": 0, "localadmin": 12632990}, "woe:timezone_id": 28350890, "woe:hash": "u31zbpxry5n2", "woe:centroid": [13.72116, 52.02985], "geom:latitude": 52.02985, "geom:longitude": 13.72116, "geom:hash": "u31zbpxry5n2", "woe:latitude": 52.02985, "geom:centroid": [13.72116, 52.02985], "woe:longitude": 13.72116, "woe:repo": "woeplanet-poi-de"}, "geometry": {"coordinates": [13.72116, 52.02985], "type": "Point"}}