{"type": "Feature", "id": 22297266, "geometry": {"type": "Point", "coordinates": [10.72382, 52.727779]}, "properties": {"woe:id": 22297266, "woe:parent_id": 707347, "woe:name": "Wittingen Bahnhof", "woe:placetype": 20, "woe:placetype_name": "POI", "woe:lang": "GER", "iso:country": "DE", "meta:provider": ["geoplanet:7.3.1", "geoplanet:7.3.2", "geoplanet:7.4.0", "geoplanet:7.4.1", "geoplanet:7.5.1", "geoplanet:7.5.2", "geoplanet:7.6.0", "geoplanet:7.8.1", "geoplanet:7.9.0", "geoplanet:7.10.0", "geoplanet:8.0.0", "woeplanet:8.0.0"], "meta:indexed": "2020-08-20T20:51:43.703145", "meta:updated": "2020-10-14T11:50:58.719414", "woe:alias_ENG_P": ["Wittingen Station"], "woe:hierarchy": {"continent": 24865675, "country": 23424829, "town": 0, "planet": 1, "county": 12596827, "suburb": 0, "state": 2345486, "region": 0, "localadmin": 12630319}, "woe:timezone_id": 28350890, "woe:hash": "u1reunbce47v", "woe:centroid": [10.72382, 52.727779], "geom:latitude": 52.727779, "geom:longitude": 10.72382, "geom:hash": "u1reunbce47v", "woe:latitude": 52.727779, "geom:centroid": [10.72382, 52.727779], "woe:longitude": 10.72382, "woe:repo": "woeplanet-poi-de", "geom:area": 0.0, "woe:scale": 19}}