{"type": "Feature", "id": 22205809, "geometry": {"type": "Point", "coordinates": [9.93479, 51.528938]}, "properties": {"woe:id": 22205809, "woe:parent_id": 653592, "woe:name": "Anthropologische Sammlung der Universit\u00e4t G\u00f6ttingen", "woe:placetype": 20, "woe:placetype_name": "POI", "woe:lang": "GER", "iso:country": "DE", "meta:provider": ["geoplanet:7.3.1", "geoplanet:7.3.2", "geoplanet:7.4.0", "geoplanet:7.4.1", "geoplanet:7.5.1", "geoplanet:7.5.2", "geoplanet:7.6.0", "geoplanet:7.8.1", "geoplanet:7.9.0", "geoplanet:7.10.0", "geoplanet:8.0.0", "woeplanet:8.0.0"], "meta:indexed": "2020-08-20T20:51:39.940688", "meta:updated": "2020-10-14T11:50:59.305252", "woe:alias_GER_S": ["Anthropologische Sammlung der Universitaet Goettingen", "Anthropologische Sammlung der Universitat Gottingen"], "woe:hierarchy": {"continent": 24865675, "country": 23424829, "town": 0, "planet": 1, "county": 12596802, "suburb": 0, "state": 2345486, "region": 0, "localadmin": 12630332}, "woe:timezone_id": 28350890, "woe:hash": "u1pj4hd3c6k2", "woe:centroid": [9.93479, 51.528938], "geom:latitude": 51.528938, "geom:longitude": 9.93479, "geom:hash": "u1pj4hd3c6k2", "woe:latitude": 51.528938, "geom:centroid": [9.93479, 51.528938], "woe:longitude": 9.93479, "woe:repo": "woeplanet-poi-de", "geom:area": 0.0, "woe:scale": 19}}