{"type": "Feature", "id": 22267141, "geometry": {"type": "Point", "coordinates": [11.03762, 50.396591]}, "properties": {"woe:id": 22267141, "woe:parent_id": 655419, "woe:name": "Gr\u00fcmpen Bahnhof", "woe:placetype": 20, "woe:placetype_name": "POI", "woe:lang": "GER", "iso:country": "DE", "meta:provider": ["geoplanet:7.3.1", "geoplanet:7.3.2", "geoplanet:7.4.0", "geoplanet:7.4.1", "geoplanet:7.5.1", "geoplanet:7.5.2", "geoplanet:7.6.0", "geoplanet:7.8.1", "geoplanet:7.9.0", "geoplanet:7.10.0", "geoplanet:8.0.0", "woeplanet:8.0.0"], "meta:indexed": "2020-08-20T20:51:42.365116", "meta:updated": "2020-10-14T11:50:58.537995", "woe:alias_ENG_S": ["Grumpen Station"], "woe:alias_GER_S": ["Gruempen Bahnhof", "Grumpen Bahnhof"], "woe:alias_ENG_P": ["Grumpen Station"], "woe:hierarchy": {"continent": 24865675, "country": 23424829, "town": 0, "planet": 1, "county": 12596974, "suburb": 0, "state": 2345495, "region": 0, "localadmin": 12625250}, "woe:timezone_id": 28350890, "woe:hash": "u0zyenmm7jmz", "woe:centroid": [11.03762, 50.396591], "geom:latitude": 50.396591, "geom:longitude": 11.03762, "geom:hash": "u0zyenmm7jmz", "woe:latitude": 50.396591, "geom:centroid": [11.03762, 50.396591], "woe:longitude": 11.03762, "woe:repo": "woeplanet-poi-de", "geom:area": 0.0, "woe:scale": 19}}