{"type": "Feature", "id": 22206131, "geometry": {"type": "Point", "coordinates": [10.77745, 50.780369]}, "properties": {"woe:id": 22206131, "woe:parent_id": 643338, "woe:name": "Crawinkel Bahnhof", "woe:placetype": 20, "woe:placetype_name": "POI", "woe:lang": "GER", "iso:country": "DE", "meta:provider": ["geoplanet:7.3.1", "geoplanet:7.3.2", "geoplanet:7.4.0", "geoplanet:7.4.1", "geoplanet:7.5.1", "geoplanet:7.5.2", "geoplanet:7.6.0", "geoplanet:7.8.1", "geoplanet:7.9.0", "geoplanet:7.10.0", "geoplanet:8.0.0", "woeplanet:8.0.0"], "meta:indexed": "2020-08-20T20:51:39.968542", "meta:updated": "2020-10-14T11:50:58.741067", "woe:alias_ENG_P": ["Crawinkel Station"], "woe:hierarchy": {"continent": 24865675, "country": 23424829, "town": 0, "planet": 1, "county": 12597003, "suburb": 0, "state": 2345495, "region": 0, "localadmin": 12624988}, "woe:timezone_id": 28350890, "woe:hash": "u1p8vhrchfch", "woe:centroid": [10.77745, 50.780369], "geom:latitude": 50.780369, "geom:longitude": 10.77745, "geom:hash": "u1p8vhrchfch", "woe:latitude": 50.780369, "geom:centroid": [10.77745, 50.780369], "woe:longitude": 10.77745, "woe:repo": "woeplanet-poi-de", "geom:area": 0.0, "woe:scale": 19}}