{"type": "Feature", "id": 22279337, "properties": {"woe:id": 22279337, "woe:parent_id": 655156, "woe:name": "Gro\u00dfpostwitz Bahnhof", "woe:placetype": 20, "woe:placetype_name": "POI", "woe:lang": "GER", "iso:country": "DE", "meta:provider": ["geoplanet:7.3.1", "geoplanet:7.3.2", "geoplanet:7.4.0", "geoplanet:7.4.1", "geoplanet:7.5.1", "geoplanet:7.5.2", "geoplanet:7.6.0", "geoplanet:7.8.1", "geoplanet:7.9.0", "geoplanet:7.10.0", "geoplanet:8.0.0", "woeplanet:8.0.0"], "meta:indexed": "2020-08-20T20:51:42.920631", "meta:updated": "2020-08-22T01:51:41.316115", "woe:alias_ENG_S": ["Grosspostwitz Station"], "woe:alias_GER_S": ["Grosspostwitz Bahnhof"], "woe:alias_ENG_P": ["Grosspostwitz Station"], "woe:hierarchy": {"continent": 24865675, "country": 23424829, "town": 0, "planet": 1, "county": 56448174, "suburb": 0, "state": 2345493, "region": 0, "localadmin": 12636310}, "woe:timezone_id": 28350890, "woe:hash": "u346bd0kb98h", "woe:centroid": [14.4364, 51.120209], "geom:latitude": 51.120209, "geom:longitude": 14.4364, "geom:hash": "u346bd0kb98h", "woe:latitude": 51.120209, "geom:centroid": [14.4364, 51.120209], "woe:longitude": 14.4364, "woe:repo": "woeplanet-poi-de"}, "geometry": {"coordinates": [14.4364, 51.120209], "type": "Point"}}