{"type": "Feature", "id": 22293773, "geometry": {"type": "Point", "coordinates": [6.48967, 51.677818]}, "properties": {"woe:id": 22293773, "woe:parent_id": 20170675, "woe:name": "Heimatmuseum Bislich", "woe:placetype": 20, "woe:placetype_name": "POI", "woe:lang": "GER", "iso:country": "DE", "meta:provider": ["geoplanet:7.3.1", "geoplanet:7.3.2", "geoplanet:7.4.0", "geoplanet:7.4.1", "geoplanet:7.5.1", "geoplanet:7.5.2", "geoplanet:7.6.0", "geoplanet:7.8.1", "geoplanet:7.9.0", "geoplanet:7.10.0", "geoplanet:8.0.0", "woeplanet:8.0.0"], "meta:indexed": "2020-08-20T20:51:43.602199", "meta:updated": "2020-10-14T11:51:00.067184", "woe:hierarchy": {"continent": 24865675, "country": 23424829, "town": 0, "planet": 1, "county": 12596976, "suburb": 0, "state": 2345487, "region": 0, "localadmin": 12624424}, "woe:timezone_id": 28350890, "woe:hash": "u1htgxtth72x", "woe:centroid": [6.48967, 51.677818], "geom:latitude": 51.677818, "geom:longitude": 6.48967, "geom:hash": "u1htgxtth72x", "woe:latitude": 51.677818, "geom:centroid": [6.48967, 51.677818], "woe:longitude": 6.48967, "woe:repo": "woeplanet-poi-de", "geom:area": 0.0, "woe:scale": 19}}