{"type": "Feature", "id": 22975631, "geometry": {"type": "Point", "coordinates": [12.8138, 51.051189]}, "properties": {"woe:id": 22975631, "woe:parent_id": 688973, "woe:name": "D\u00f6hlen Bahnhof", "woe:placetype": 20, "woe:placetype_name": "POI", "woe:lang": "GER", "iso:country": "DE", "meta:provider": ["geoplanet:7.3.1", "geoplanet:7.3.2", "geoplanet:7.4.0", "geoplanet:7.4.1", "geoplanet:7.5.1", "geoplanet:7.5.2", "geoplanet:7.6.0", "geoplanet:7.8.1", "geoplanet:7.9.0", "geoplanet:7.10.0", "geoplanet:8.0.0", "woeplanet:8.0.0"], "meta:indexed": "2020-08-20T20:51:44.885532", "meta:updated": "2020-10-14T11:50:29.157830", "woe:alias_ENG_S": ["Dohlen Station"], "woe:alias_GER_S": ["Doehlen Bahnhof", "Dohlen Bahnhof"], "woe:alias_ENG_P": ["Dohlen Station"], "woe:hierarchy": {"continent": 24865675, "country": 23424829, "town": 0, "planet": 1, "county": 56448168, "suburb": 0, "state": 2345493, "region": 0, "localadmin": 12625643}, "woe:timezone_id": 28350890, "woe:hash": "u3147tddxpmu", "woe:centroid": [12.8138, 51.051189], "geom:latitude": 51.051189, "geom:longitude": 12.8138, "geom:hash": "u3147tddxpmu", "woe:latitude": 51.051189, "geom:centroid": [12.8138, 51.051189], "woe:longitude": 12.8138, "woe:repo": "woeplanet-poi-de", "geom:area": 0.0, "woe:scale": 19}}