{"type": "Feature", "id": 22155910, "geometry": {"type": "Point", "coordinates": [9.75188, 50.305191]}, "properties": {"woe:id": 22155910, "woe:parent_id": 696139, "woe:name": "Heimat-Und Regionalmuseum", "woe:placetype": 20, "woe:placetype_name": "POI", "woe:lang": "GER", "iso:country": "DE", "meta:provider": ["geoplanet:7.3.1", "geoplanet:7.3.2", "geoplanet:7.4.0", "geoplanet:7.4.1", "geoplanet:7.5.1", "geoplanet:7.5.2", "geoplanet:7.6.0", "geoplanet:7.8.1", "geoplanet:7.9.0", "geoplanet:7.10.0", "geoplanet:8.0.0", "woeplanet:8.0.0"], "meta:indexed": "2020-08-20T20:51:38.014874", "meta:updated": "2020-10-14T11:50:27.549349", "woe:hierarchy": {"continent": 24865675, "country": 23424829, "town": 0, "planet": 1, "county": 12596941, "suburb": 0, "state": 2345482, "region": 0, "localadmin": 12635492}, "woe:timezone_id": 28350890, "woe:hash": "u0yyjvv0gr2c", "woe:centroid": [9.75188, 50.305191], "geom:latitude": 50.305191, "geom:longitude": 9.75188, "geom:hash": "u0yyjvv0gr2c", "woe:latitude": 50.305191, "geom:centroid": [9.75188, 50.305191], "woe:longitude": 9.75188, "woe:repo": "woeplanet-poi-de", "geom:area": 0.0, "woe:scale": 19}}