{"type": "Feature", "id": 22239877, "geometry": {"type": "Point", "coordinates": [10.61274, 53.835121]}, "properties": {"woe:id": 22239877, "woe:parent_id": 20164601, "woe:name": "L\u00fcbeck-Niendorf Bahnhof", "woe:placetype": 20, "woe:placetype_name": "POI", "woe:lang": "GER", "iso:country": "DE", "meta:provider": ["geoplanet:7.3.1", "geoplanet:7.3.2", "geoplanet:7.4.0", "geoplanet:7.4.1", "geoplanet:7.5.1", "geoplanet:7.5.2", "geoplanet:7.6.0", "geoplanet:7.8.1", "geoplanet:7.9.0", "geoplanet:7.10.0", "geoplanet:8.0.0", "woeplanet:8.0.0"], "meta:indexed": "2020-08-20T20:51:41.382230", "meta:updated": "2020-10-14T11:51:00.258928", "woe:alias_ENG_S": ["Lubeck-Niendorf Station"], "woe:alias_GER_S": ["Luebeck-Niendorf Bahnhof", "Lubeck-Niendorf Bahnhof"], "woe:alias_ENG_P": ["Lubeck-Niendorf Station"], "woe:hierarchy": {"continent": 24865675, "country": 23424829, "town": 0, "planet": 1, "county": 12597082, "suburb": 0, "state": 2345490, "region": 0, "localadmin": 26822952}, "woe:timezone_id": 28350890, "woe:hash": "u1xd32ruqcbt", "woe:centroid": [10.61274, 53.835121], "geom:latitude": 53.835121, "geom:longitude": 10.61274, "geom:hash": "u1xd32ruqcbt", "woe:latitude": 53.835121, "geom:centroid": [10.61274, 53.835121], "woe:longitude": 10.61274, "woe:repo": "woeplanet-poi-de", "geom:area": 0.0, "woe:scale": 19}}