{"type": "Feature", "id": 22180907, "geometry": {"type": "Point", "coordinates": [12.91039, 50.86829]}, "properties": {"woe:id": 22180907, "woe:parent_id": 643134, "woe:name": "Chemnitz-Gl\u00f6sa Bahnhof", "woe:placetype": 20, "woe:placetype_name": "POI", "woe:lang": "GER", "iso:country": "DE", "meta:provider": ["geoplanet:7.3.1", "geoplanet:7.3.2", "geoplanet:7.4.0", "geoplanet:7.4.1", "geoplanet:7.5.1", "geoplanet:7.5.2", "geoplanet:7.6.0", "geoplanet:7.8.1", "geoplanet:7.9.0", "geoplanet:7.10.0", "geoplanet:8.0.0", "woeplanet:8.0.0"], "meta:indexed": "2020-08-20T20:51:38.874355", "meta:updated": "2020-10-14T11:50:27.743248", "woe:alias_ENG_S": ["Chemnitz-Glosa Station"], "woe:alias_GER_S": ["Chemnitz-Gloesa Bahnhof", "Chemnitz-Glosa Bahnhof"], "woe:alias_ENG_P": ["Chemnitz-Glosa Station"], "woe:hierarchy": {"continent": 24865675, "country": 23424829, "town": 0, "planet": 1, "county": 12596812, "suburb": 0, "state": 2345493, "region": 0, "localadmin": 26822087}, "woe:timezone_id": 28350890, "woe:hash": "u311mu313bs9", "woe:centroid": [12.91039, 50.86829], "geom:latitude": 50.86829, "geom:longitude": 12.91039, "geom:hash": "u311mu313bs9", "woe:latitude": 50.86829, "geom:centroid": [12.91039, 50.86829], "woe:longitude": 12.91039, "woe:repo": "woeplanet-poi-de", "geom:area": 0.0, "woe:scale": 19}}