{"type": "Feature", "id": 22290623, "geometry": {"type": "Point", "coordinates": [12.40808, 48.202862]}, "properties": {"woe:id": 22290623, "woe:parent_id": 703523, "woe:name": "Waldkraiburg Bahnhof", "woe:placetype": 20, "woe:placetype_name": "POI", "woe:lang": "GER", "iso:country": "DE", "meta:provider": ["geoplanet:7.3.1", "geoplanet:7.3.2", "geoplanet:7.4.0", "geoplanet:7.4.1", "geoplanet:7.5.1", "geoplanet:7.5.2", "geoplanet:7.6.0", "geoplanet:7.8.1", "geoplanet:7.9.0", "geoplanet:7.10.0", "geoplanet:8.0.0", "woeplanet:8.0.0"], "meta:indexed": "2020-08-20T20:51:43.420940", "meta:updated": "2020-10-14T11:50:57.355781", "woe:alias_ENG_P": ["Waldkraiburg Station"], "woe:hierarchy": {"continent": 24865675, "country": 23424829, "town": 0, "planet": 1, "county": 12596907, "suburb": 0, "state": 2345482, "region": 0, "localadmin": 12622757}, "woe:timezone_id": 28350890, "woe:hash": "u28f4r5610z0", "woe:centroid": [12.40808, 48.202862], "geom:latitude": 48.202862, "geom:longitude": 12.40808, "geom:hash": "u28f4r5610z0", "woe:latitude": 48.202862, "geom:centroid": [12.40808, 48.202862], "woe:longitude": 12.40808, "woe:repo": "woeplanet-poi-de", "geom:area": 0.0, "woe:scale": 19}}