{"type": "Feature", "id": 22939351, "geometry": {"type": "Point", "coordinates": [11.04828, 49.434132]}, "properties": {"woe:id": 22939351, "woe:parent_id": 680564, "woe:name": "Schweinau Bahnhof", "woe:placetype": 20, "woe:placetype_name": "POI", "woe:lang": "GER", "iso:country": "DE", "meta:provider": ["geoplanet:7.3.1", "geoplanet:7.3.2", "geoplanet:7.4.0", "geoplanet:7.4.1", "geoplanet:7.5.1", "geoplanet:7.5.2", "geoplanet:7.6.0", "geoplanet:7.8.1", "geoplanet:7.9.0", "geoplanet:7.10.0", "geoplanet:8.0.0", "woeplanet:8.0.0"], "meta:indexed": "2020-08-20T20:51:44.123618", "meta:updated": "2020-10-14T11:50:28.945152", "woe:alias_ENG_P": ["Schweinau Station"], "woe:hierarchy": {"continent": 24865675, "country": 23424829, "town": 0, "planet": 1, "county": 12596973, "suburb": 0, "state": 2345482, "region": 0, "localadmin": 26823116}, "woe:timezone_id": 28350890, "woe:hash": "u0zc5rjnew4e", "woe:centroid": [11.04828, 49.434132], "geom:latitude": 49.434132, "geom:longitude": 11.04828, "geom:hash": "u0zc5rjnew4e", "woe:latitude": 49.434132, "geom:centroid": [11.04828, 49.434132], "woe:longitude": 11.04828, "woe:repo": "woeplanet-poi-de", "geom:area": 0.0, "woe:scale": 19}}