{"type": "Feature", "id": 22964838, "properties": {"woe:id": 22964838, "woe:parent_id": 26821919, "woe:name": "Rathaus Neuk\u00f6lln Bahnhof", "woe:placetype": 20, "woe:placetype_name": "POI", "woe:lang": "GER", "iso:country": "DE", "meta:provider": ["geoplanet:7.3.1", "geoplanet:7.3.2", "geoplanet:7.4.0", "geoplanet:7.4.1", "geoplanet:7.5.1", "geoplanet:7.5.2", "geoplanet:7.6.0", "geoplanet:7.8.1", "geoplanet:7.9.0", "geoplanet:7.10.0", "geoplanet:8.0.0", "woeplanet:8.0.0"], "meta:indexed": "2020-08-20T20:51:44.653796", "meta:updated": "2020-08-22T01:51:42.168853", "woe:alias_ENG_S": ["Rathaus Neukolln Station"], "woe:alias_GER_S": ["Rathaus Neukoelln Bahnhof", "Rathaus Neukolln Bahnhof"], "woe:alias_ENG_P": ["Rathaus Neukolln Station"], "woe:hierarchy": {"continent": 24865675, "country": 23424829, "town": 0, "planet": 1, "county": 12596838, "suburb": 0, "state": 2345496, "region": 0, "localadmin": 26821919}, "woe:timezone_id": 28350890, "woe:hash": "u33d9djdnge4", "woe:centroid": [13.43314, 52.482052], "geom:latitude": 52.482052, "geom:longitude": 13.43314, "geom:hash": "u33d9djdnge4", "woe:latitude": 52.482052, "geom:centroid": [13.43314, 52.482052], "woe:longitude": 13.43314, "woe:repo": "woeplanet-poi-de"}, "geometry": {"coordinates": [13.43314, 52.482052], "type": "Point"}}