{"type": "Feature", "id": 22252971, "geometry": {"type": "Point", "coordinates": [9.13799, 49.316219]}, "properties": {"woe:id": 22252971, "woe:parent_id": 677324, "woe:name": "Neckarzimmern Bahnhof", "woe:placetype": 20, "woe:placetype_name": "POI", "woe:lang": "GER", "iso:country": "DE", "meta:provider": ["geoplanet:7.3.1", "geoplanet:7.3.2", "geoplanet:7.4.0", "geoplanet:7.4.1", "geoplanet:7.5.1", "geoplanet:7.5.2", "geoplanet:7.6.0", "geoplanet:7.8.1", "geoplanet:7.9.0", "geoplanet:7.10.0", "geoplanet:8.0.0", "woeplanet:8.0.0"], "meta:indexed": "2020-08-20T20:51:41.827987", "meta:updated": "2020-10-14T11:50:59.908587", "woe:alias_ENG_P": ["Neckarzimmern Station"], "woe:hierarchy": {"continent": 24865675, "country": 23424829, "town": 0, "planet": 1, "county": 12596820, "suburb": 0, "state": 2345481, "region": 0, "localadmin": 12623940}, "woe:timezone_id": 28350890, "woe:hash": "u0y2xcwpf9e1", "woe:centroid": [9.13799, 49.316219], "geom:latitude": 49.316219, "geom:longitude": 9.13799, "geom:hash": "u0y2xcwpf9e1", "woe:latitude": 49.316219, "geom:centroid": [9.13799, 49.316219], "woe:longitude": 9.13799, "woe:repo": "woeplanet-poi-de", "geom:area": 0.0, "woe:scale": 19}}