{"type": "Feature", "id": 28289358, "properties": {"woe:id": 28289358, "woe:parent_id": 650272, "woe:name": "Frankfurt R\u00f6mer", "woe:placetype": 20, "woe:placetype_name": "POI", "woe:lang": "GER", "iso:country": "DE", "meta:provider": ["geoplanet:7.3.1", "geoplanet:7.3.2", "geoplanet:7.4.0", "geoplanet:7.4.1", "geoplanet:7.5.1", "geoplanet:7.5.2", "geoplanet:7.6.0", "geoplanet:7.8.1", "geoplanet:7.9.0", "geoplanet:7.10.0", "geoplanet:8.0.0", "woeplanet:8.0.0"], "meta:indexed": "2020-08-20T20:51:45.857743", "meta:updated": "2020-08-22T01:51:42.951164", "woe:alias_GER_S": ["Frankfurt Roemer", "Frankfurt Romer"], "woe:hierarchy": {"continent": 24865675, "country": 23424829, "town": 0, "planet": 1, "county": 12597087, "suburb": 0, "state": 2345485, "region": 0, "localadmin": 26822422}, "woe:timezone_id": 28350890, "woe:hash": "u0yjjd6551k4", "woe:centroid": [8.68208, 50.110538], "geom:latitude": 50.110538, "geom:longitude": 8.68208, "geom:hash": "u0yjjd6551k4", "woe:latitude": 50.110538, "geom:centroid": [8.68208, 50.110538], "woe:longitude": 8.68208, "woe:repo": "woeplanet-poi-de"}, "geometry": {"coordinates": [8.68208, 50.110538], "type": "Point"}}