{"type": "Feature", "id": 22190411, "geometry": {"type": "Point", "coordinates": [6.739, 51.289291]}, "properties": {"woe:id": 22190411, "woe:parent_id": 646099, "woe:name": "U Alte Landstra\u00dfe Bahnhof", "woe:placetype": 20, "woe:placetype_name": "POI", "woe:lang": "GER", "iso:country": "DE", "meta:provider": ["geoplanet:7.3.1", "geoplanet:7.3.2", "geoplanet:7.4.0", "geoplanet:7.4.1", "geoplanet:7.5.1", "geoplanet:7.5.2", "geoplanet:7.6.0", "geoplanet:7.8.1", "geoplanet:7.9.0", "geoplanet:7.10.0", "geoplanet:8.0.0", "woeplanet:8.0.0"], "meta:indexed": "2020-08-20T20:51:39.301566", "meta:updated": "2020-10-14T11:50:27.769065", "woe:alias_ENG_S": ["U Alte Landstrasse Station"], "woe:alias_GER_S": ["U Alte Landstrasse Bahnhof"], "woe:alias_ENG_P": ["U Alte Landstrasse Station"], "woe:hierarchy": {"continent": 24865675, "country": 23424829, "town": 0, "planet": 1, "county": 12596700, "suburb": 0, "state": 2345487, "region": 0, "localadmin": 26822249}, "woe:timezone_id": 28350890, "woe:hash": "u1hgc2gjy0fd", "woe:centroid": [6.739, 51.289291], "geom:latitude": 51.289291, "geom:longitude": 6.739, "geom:hash": "u1hgc2gjy0fd", "woe:latitude": 51.289291, "geom:centroid": [6.739, 51.289291], "woe:longitude": 6.739, "woe:repo": "woeplanet-poi-de", "geom:area": 0.0, "woe:scale": 19}}