{"type": "Feature", "id": 22232906, "geometry": {"type": "Point", "coordinates": [9.18001, 48.862339]}, "properties": {"woe:id": 22232906, "woe:parent_id": 668327, "woe:name": "Kornwestheim Pbf Bahnhof", "woe:placetype": 20, "woe:placetype_name": "POI", "woe:lang": "GER", "iso:country": "DE", "meta:provider": ["geoplanet:7.3.1", "geoplanet:7.3.2", "geoplanet:7.4.0", "geoplanet:7.4.1", "geoplanet:7.5.1", "geoplanet:7.5.2", "geoplanet:7.6.0", "geoplanet:7.8.1", "geoplanet:7.9.0", "geoplanet:7.10.0", "geoplanet:8.0.0", "woeplanet:8.0.0"], "meta:indexed": "2020-08-20T20:51:41.060935", "meta:updated": "2020-10-14T11:50:58.233888", "woe:alias_ENG_P": ["Kornwestheim Pbf Station"], "woe:hierarchy": {"continent": 24865675, "country": 23424829, "town": 0, "planet": 1, "county": 12596746, "suburb": 0, "state": 2345481, "region": 0, "localadmin": 12623226}, "woe:timezone_id": 28350890, "woe:hash": "u0wtbzhev8pt", "woe:centroid": [9.18001, 48.862339], "geom:latitude": 48.862339, "geom:longitude": 9.18001, "geom:hash": "u0wtbzhev8pt", "woe:latitude": 48.862339, "geom:centroid": [9.18001, 48.862339], "woe:longitude": 9.18001, "woe:repo": "woeplanet-poi-de", "geom:area": 0.0, "woe:scale": 19}}