{"type": "Feature", "id": 22961537, "geometry": {"type": "Point", "coordinates": [10.90713, 50.866989]}, "properties": {"woe:id": 22961537, "woe:parent_id": 23410863, "woe:name": "Haarhausen Bahnhof", "woe:placetype": 20, "woe:placetype_name": "POI", "woe:lang": "GER", "iso:country": "DE", "meta:provider": ["geoplanet:7.3.1", "geoplanet:7.3.2", "geoplanet:7.4.0", "geoplanet:7.4.1", "geoplanet:7.5.1", "geoplanet:7.5.2", "geoplanet:7.6.0", "geoplanet:7.8.1", "geoplanet:7.9.0", "geoplanet:7.10.0", "geoplanet:8.0.0", "woeplanet:8.0.0"], "meta:indexed": "2020-08-20T20:51:44.550077", "meta:updated": "2020-10-14T11:50:28.954875", "woe:alias_ENG_P": ["Haarhausen Station"], "woe:hierarchy": {"continent": 24865675, "country": 23424829, "town": 0, "planet": 1, "county": 12596768, "suburb": 0, "state": 2345495, "region": 0, "localadmin": 12625163}, "woe:timezone_id": 28350890, "woe:hash": "u1pc2hn3dw18", "woe:centroid": [10.90713, 50.866989], "geom:latitude": 50.866989, "geom:longitude": 10.90713, "geom:hash": "u1pc2hn3dw18", "woe:latitude": 50.866989, "geom:centroid": [10.90713, 50.866989], "woe:longitude": 10.90713, "woe:repo": "woeplanet-poi-de", "geom:area": 0.0, "woe:scale": 19}}