{"type": "Feature", "id": 22202597, "geometry": {"type": "Point", "coordinates": [12.57275, 48.130322]}, "properties": {"woe:id": 22202597, "woe:parent_id": 651522, "woe:name": "Garching Bahnhof", "woe:placetype": 20, "woe:placetype_name": "POI", "woe:lang": "GER", "iso:country": "DE", "meta:provider": ["geoplanet:7.3.1", "geoplanet:7.3.2", "geoplanet:7.4.0", "geoplanet:7.4.1", "geoplanet:7.5.1", "geoplanet:7.5.2", "geoplanet:7.6.0", "geoplanet:7.8.1", "geoplanet:7.9.0", "geoplanet:7.10.0", "geoplanet:8.0.0", "woeplanet:8.0.0"], "meta:indexed": "2020-08-20T20:51:39.787008", "meta:updated": "2020-10-14T11:50:59.226229", "woe:alias_ENG_P": ["Garching Station"], "woe:hierarchy": {"continent": 24865675, "country": 23424829, "town": 0, "planet": 1, "county": 12596913, "suburb": 0, "state": 2345482, "region": 0, "localadmin": 12635754}, "woe:timezone_id": 28350890, "woe:hash": "u28cy1g5qq3f", "woe:centroid": [12.57275, 48.130322], "geom:latitude": 48.130322, "geom:longitude": 12.57275, "geom:hash": "u28cy1g5qq3f", "woe:latitude": 48.130322, "geom:centroid": [12.57275, 48.130322], "woe:longitude": 12.57275, "woe:repo": "woeplanet-poi-de", "geom:area": 0.0, "woe:scale": 19}}