{"type": "Feature", "id": 22236576, "geometry": {"type": "Point", "coordinates": [10.28247, 54.23687]}, "properties": {"woe:id": 22236576, "woe:parent_id": 685878, "woe:name": "Erstes Circusmuseum in Deutschland", "woe:placetype": 20, "woe:placetype_name": "POI", "woe:lang": "GER", "iso:country": "DE", "meta:provider": ["geoplanet:7.3.1", "geoplanet:7.3.2", "geoplanet:7.4.0", "geoplanet:7.4.1", "geoplanet:7.5.1", "geoplanet:7.5.2", "geoplanet:7.6.0", "geoplanet:7.8.1", "geoplanet:7.9.0", "geoplanet:7.10.0", "geoplanet:8.0.0", "woeplanet:8.0.0"], "meta:indexed": "2020-08-20T20:51:41.217298", "meta:updated": "2020-10-14T11:50:57.350770", "woe:hierarchy": {"continent": 24865675, "country": 23424829, "town": 0, "planet": 1, "county": 12597018, "suburb": 0, "state": 2345490, "region": 0, "localadmin": 12632425}, "woe:timezone_id": 28350890, "woe:hash": "u1xk9cx2wvm7", "woe:centroid": [10.28247, 54.23687], "geom:latitude": 54.23687, "geom:longitude": 10.28247, "geom:hash": "u1xk9cx2wvm7", "woe:latitude": 54.23687, "geom:centroid": [10.28247, 54.23687], "woe:longitude": 10.28247, "woe:repo": "woeplanet-poi-de", "geom:area": 0.0, "woe:scale": 19}}