{"type": "Feature", "id": 22192558, "geometry": {"type": "Point", "coordinates": [7.53066, 52.17276]}, "properties": {"woe:id": 22192558, "woe:parent_id": 647901, "woe:name": "August Holl\u00e4nder Museum", "woe:placetype": 20, "woe:placetype_name": "POI", "woe:lang": "GER", "iso:country": "DE", "meta:provider": ["geoplanet:7.3.1", "geoplanet:7.3.2", "geoplanet:7.4.0", "geoplanet:7.4.1", "geoplanet:7.5.1", "geoplanet:7.5.2", "geoplanet:7.6.0", "geoplanet:7.8.1", "geoplanet:7.9.0", "geoplanet:7.10.0", "geoplanet:8.0.0", "woeplanet:8.0.0"], "meta:indexed": "2020-08-20T20:51:39.450391", "meta:updated": "2020-10-14T11:50:27.071973", "woe:alias_GER_S": ["August Hollaender Museum", "August Hollander Museum"], "woe:hierarchy": {"continent": 24865675, "country": 23424829, "town": 0, "planet": 1, "county": 12596690, "suburb": 0, "state": 2345487, "region": 0, "localadmin": 12624302}, "woe:timezone_id": 28350890, "woe:hash": "u1m2g3g8m57h", "woe:centroid": [7.53066, 52.17276], "geom:latitude": 52.17276, "geom:longitude": 7.53066, "geom:hash": "u1m2g3g8m57h", "woe:latitude": 52.17276, "geom:centroid": [7.53066, 52.17276], "woe:longitude": 7.53066, "woe:repo": "woeplanet-poi-de", "geom:area": 0.0, "woe:scale": 19}}