{"type": "Feature", "id": 22184555, "properties": {"woe:id": 22184555, "woe:parent_id": 645141, "woe:name": "Donauw\u00f6rth Bahnhof", "woe:placetype": 20, "woe:placetype_name": "POI", "woe:lang": "GER", "iso:country": "DE", "meta:provider": ["geoplanet:7.3.1", "geoplanet:7.3.2", "geoplanet:7.4.0", "geoplanet:7.4.1", "geoplanet:7.5.1", "geoplanet:7.5.2", "geoplanet:7.6.0", "geoplanet:7.8.1", "geoplanet:7.9.0", "geoplanet:7.10.0", "geoplanet:8.0.0", "woeplanet:8.0.0"], "meta:indexed": "2020-08-20T20:51:39.061281", "meta:updated": "2020-08-22T01:51:39.690811", "woe:alias_ENG_S": ["Donauworth Station"], "woe:alias_GER_S": ["Donauwoerth Bahnhof", "Donauworth Bahnhof"], "woe:alias_ENG_P": ["Donauworth Station"], "woe:hierarchy": {"continent": 24865675, "country": 23424829, "town": 0, "planet": 1, "county": 12596957, "suburb": 0, "state": 2345482, "region": 0, "localadmin": 12634989}, "woe:timezone_id": 28350890, "woe:hash": "u0xtjh4vpbwy", "woe:centroid": [10.77072, 48.714241], "geom:latitude": 48.714241, "geom:longitude": 10.77072, "geom:hash": "u0xtjh4vpbwy", "woe:latitude": 48.714241, "geom:centroid": [10.77072, 48.714241], "woe:longitude": 10.77072, "woe:repo": "woeplanet-poi-de"}, "geometry": {"coordinates": [10.77072, 48.714241], "type": "Point"}}