{"type": "Feature", "id": 22228707, "geometry": {"type": "Point", "coordinates": [7.22662, 49.286121]}, "properties": {"woe:id": 22228707, "woe:parent_id": 20163826, "woe:name": "Kirkel Bahnhof", "woe:placetype": 20, "woe:placetype_name": "POI", "woe:lang": "GER", "iso:country": "DE", "meta:provider": ["geoplanet:7.3.1", "geoplanet:7.3.2", "geoplanet:7.4.0", "geoplanet:7.4.1", "geoplanet:7.5.1", "geoplanet:7.5.2", "geoplanet:7.6.0", "geoplanet:7.8.1", "geoplanet:7.9.0", "geoplanet:7.10.0", "geoplanet:8.0.0", "woeplanet:8.0.0"], "meta:indexed": "2020-08-20T20:51:40.857494", "meta:updated": "2020-10-14T11:50:57.210566", "woe:alias_ENG_P": ["Kirkel Station"], "woe:hierarchy": {"continent": 24865675, "country": 23424829, "town": 0, "planet": 1, "county": 12596978, "suburb": 0, "state": 2345489, "region": 0, "localadmin": 12627123}, "woe:timezone_id": 28350890, "woe:hash": "u0v0kkq22qy7", "woe:centroid": [7.22662, 49.286121], "geom:latitude": 49.286121, "geom:longitude": 7.22662, "geom:hash": "u0v0kkq22qy7", "woe:latitude": 49.286121, "geom:centroid": [7.22662, 49.286121], "woe:longitude": 7.22662, "woe:repo": "woeplanet-poi-de", "geom:area": 0.0, "woe:scale": 19}}