{"type": "Feature", "id": 22279704, "geometry": {"type": "Point", "coordinates": [6.99319, 51.167171]}, "properties": {"woe:id": 22279704, "woe:parent_id": 695336, "woe:name": "Solingen Vogelpark Bahnhof", "woe:placetype": 20, "woe:placetype_name": "POI", "woe:lang": "GER", "iso:country": "DE", "meta:provider": ["geoplanet:7.3.1", "geoplanet:7.3.2", "geoplanet:7.4.0", "geoplanet:7.4.1", "geoplanet:7.5.1", "geoplanet:7.5.2", "geoplanet:7.6.0", "geoplanet:7.8.1", "geoplanet:7.9.0", "geoplanet:7.10.0", "geoplanet:8.0.0", "woeplanet:8.0.0"], "meta:indexed": "2020-08-20T20:51:42.943860", "meta:updated": "2020-10-14T11:51:00.218431", "woe:alias_ENG_P": ["Solingen Vogelpark Station"], "woe:hierarchy": {"continent": 24865675, "country": 23424829, "town": 0, "planet": 1, "county": 12597079, "suburb": 0, "state": 2345487, "region": 0, "localadmin": 26823245}, "woe:timezone_id": 28350890, "woe:hash": "u1hgp4sq35ur", "woe:centroid": [6.99319, 51.167171], "geom:latitude": 51.167171, "geom:longitude": 6.99319, "geom:hash": "u1hgp4sq35ur", "woe:latitude": 51.167171, "geom:centroid": [6.99319, 51.167171], "woe:longitude": 6.99319, "woe:repo": "woeplanet-poi-de", "geom:area": 0.0, "woe:scale": 19}}