{"type": "Feature", "id": 22300725, "properties": {"woe:id": 22300725, "woe:parent_id": 645212, "woe:name": "Dorfchemnitz Bahnhof", "woe:placetype": 20, "woe:placetype_name": "POI", "woe:lang": "GER", "iso:country": "DE", "meta:provider": ["geoplanet:7.3.1", "geoplanet:7.3.2", "geoplanet:7.4.0", "geoplanet:7.4.1", "geoplanet:7.5.1", "geoplanet:7.5.2", "geoplanet:7.6.0", "geoplanet:7.8.1", "geoplanet:7.9.0", "geoplanet:7.10.0", "geoplanet:8.0.0", "woeplanet:8.0.0"], "meta:indexed": "2020-08-20T20:51:43.833214", "meta:updated": "2020-08-22T01:51:41.767315", "woe:alias_ENG_P": ["Dorfchemnitz Station"], "woe:hierarchy": {"continent": 24865675, "country": 23424829, "town": 0, "planet": 1, "county": 56448166, "suburb": 0, "state": 2345493, "region": 0, "localadmin": 12636550}, "woe:timezone_id": 28350890, "woe:hash": "u310hpymt48f", "woe:centroid": [12.84083, 50.66853], "geom:latitude": 50.66853, "geom:longitude": 12.84083, "geom:hash": "u310hpymt48f", "woe:latitude": 50.66853, "geom:centroid": [12.84083, 50.66853], "woe:longitude": 12.84083, "woe:repo": "woeplanet-poi-de"}, "geometry": {"coordinates": [12.84083, 50.66853], "type": "Point"}}