{"type": "Feature", "id": 22195964, "properties": {"woe:id": 22195964, "woe:parent_id": 654856, "woe:name": "Gro\u00dfb\u00fcllesheim Bahnhof", "woe:placetype": 20, "woe:placetype_name": "POI", "woe:lang": "GER", "iso:country": "DE", "meta:provider": ["geoplanet:7.3.1", "geoplanet:7.3.2", "geoplanet:7.4.0", "geoplanet:7.4.1", "geoplanet:7.5.1", "geoplanet:7.5.2", "geoplanet:7.6.0", "geoplanet:7.8.1", "geoplanet:7.9.0", "geoplanet:7.10.0", "geoplanet:8.0.0", "woeplanet:8.0.0"], "meta:indexed": "2020-08-20T20:51:39.587126", "meta:updated": "2020-08-22T01:51:39.944021", "woe:alias_ENG_S": ["Grossbullesheim Station"], "woe:alias_GER_S": ["Grossbuellesheim Bahnhof", "Grossbullesheim Bahnhof"], "woe:alias_ENG_P": ["Grossbullesheim Station"], "woe:hierarchy": {"continent": 24865675, "country": 23424829, "town": 0, "planet": 1, "county": 12596895, "suburb": 0, "state": 2345487, "region": 0, "localadmin": 12624593}, "woe:timezone_id": 28350890, "woe:hash": "u1hb755x33uz", "woe:centroid": [6.81639, 50.68668], "geom:latitude": 50.68668, "geom:longitude": 6.81639, "geom:hash": "u1hb755x33uz", "woe:latitude": 50.68668, "geom:centroid": [6.81639, 50.68668], "woe:longitude": 6.81639, "woe:repo": "woeplanet-poi-de"}, "geometry": {"coordinates": [6.81639, 50.68668], "type": "Point"}}