{"type": "Feature", "id": 22930571, "properties": {"woe:id": 22930571, "woe:parent_id": 708031, "woe:name": "W\u00f6rth Bahnhof", "woe:placetype": 20, "woe:placetype_name": "POI", "woe:lang": "GER", "iso:country": "DE", "meta:provider": ["geoplanet:7.3.1", "geoplanet:7.3.2", "geoplanet:7.4.0", "geoplanet:7.4.1", "geoplanet:7.5.1", "geoplanet:7.5.2", "geoplanet:7.6.0", "geoplanet:7.8.1", "geoplanet:7.9.0", "geoplanet:7.10.0", "geoplanet:8.0.0", "woeplanet:8.0.0"], "meta:indexed": "2020-08-20T20:51:43.996883", "meta:updated": "2020-08-22T01:51:41.854072", "woe:alias_ENG_P": ["Worth Station"], "woe:alias_GER_S": ["Woerth Bahnhof", "Worth Bahnhof"], "woe:hierarchy": {"continent": 24865675, "country": 23424829, "town": 0, "planet": 1, "county": 12597044, "suburb": 0, "state": 2345482, "region": 0, "localadmin": 12636133}, "woe:timezone_id": 28350890, "woe:hash": "u0ye22fctds8", "woe:centroid": [9.15563, 49.79443], "geom:latitude": 49.79443, "geom:longitude": 9.15563, "geom:hash": "u0ye22fctds8", "woe:latitude": 49.79443, "geom:centroid": [9.15563, 49.79443], "woe:longitude": 9.15563, "woe:repo": "woeplanet-poi-de"}, "geometry": {"coordinates": [9.15563, 49.79443], "type": "Point"}}