{"type": "Feature", "id": 22241673, "geometry": {"type": "Point", "coordinates": [8.97027, 50.016109]}, "properties": {"woe:id": 22241673, "woe:parent_id": 708715, "woe:name": "Zellhausen Bahnhof", "woe:placetype": 20, "woe:placetype_name": "POI", "woe:lang": "GER", "iso:country": "DE", "meta:provider": ["geoplanet:7.3.1", "geoplanet:7.3.2", "geoplanet:7.4.0", "geoplanet:7.4.1", "geoplanet:7.5.1", "geoplanet:7.5.2", "geoplanet:7.6.0", "geoplanet:7.8.1", "geoplanet:7.9.0", "geoplanet:7.10.0", "geoplanet:8.0.0", "woeplanet:8.0.0"], "meta:indexed": "2020-08-20T20:51:41.469274", "meta:updated": "2020-10-14T11:51:00.180527", "woe:alias_ENG_P": ["Zellhausen Station"], "woe:hierarchy": {"continent": 24865675, "country": 23424829, "town": 0, "planet": 1, "county": 12597040, "suburb": 0, "state": 2345485, "region": 0, "localadmin": 12632631}, "woe:timezone_id": 28350890, "woe:hash": "u0yks15uyqqp", "woe:centroid": [8.97027, 50.016109], "geom:latitude": 50.016109, "geom:longitude": 8.97027, "geom:hash": "u0yks15uyqqp", "woe:latitude": 50.016109, "geom:centroid": [8.97027, 50.016109], "woe:longitude": 8.97027, "woe:repo": "woeplanet-poi-de", "geom:area": 0.0, "woe:scale": 19}}