{"type": "Feature", "id": 22288147, "properties": {"woe:id": 22288147, "woe:parent_id": 641616, "woe:name": "Brucken Bahnhof", "woe:placetype": 20, "woe:placetype_name": "POI", "woe:lang": "GER", "iso:country": "DE", "meta:provider": ["geoplanet:7.3.1", "geoplanet:7.3.2", "geoplanet:7.4.0", "geoplanet:7.4.1", "geoplanet:7.5.1", "geoplanet:7.5.2", "geoplanet:7.6.0", "geoplanet:7.8.1", "geoplanet:7.9.0", "geoplanet:7.10.0", "geoplanet:8.0.0", "woeplanet:8.0.0"], "meta:indexed": "2020-08-20T20:51:43.276202", "meta:updated": "2020-08-22T01:51:41.481666", "woe:alias_ENG_P": ["Brucken Station"], "woe:hierarchy": {"continent": 24865675, "country": 23424829, "town": 0, "planet": 1, "county": 12596908, "suburb": 0, "state": 2345481, "region": 0, "localadmin": 12623207}, "woe:timezone_id": 28350890, "woe:hash": "u0wsr4ee2qzg", "woe:centroid": [9.45307, 48.573898], "geom:latitude": 48.573898, "geom:longitude": 9.45307, "geom:hash": "u0wsr4ee2qzg", "woe:latitude": 48.573898, "geom:centroid": [9.45307, 48.573898], "woe:longitude": 9.45307, "woe:repo": "woeplanet-poi-de"}, "geometry": {"coordinates": [9.45307, 48.573898], "type": "Point"}}