{"type": "Feature", "id": 22170466, "geometry": {"type": "Point", "coordinates": [8.53021, 50.90937]}, "properties": {"woe:id": 22170466, "woe:parent_id": 638786, "woe:name": "Biedenkopf Bahnhof", "woe:placetype": 20, "woe:placetype_name": "POI", "woe:lang": "GER", "iso:country": "DE", "meta:provider": ["geoplanet:7.3.1", "geoplanet:7.3.2", "geoplanet:7.4.0", "geoplanet:7.4.1", "geoplanet:7.5.1", "geoplanet:7.5.2", "geoplanet:7.6.0", "geoplanet:7.8.1", "geoplanet:7.9.0", "geoplanet:7.10.0", "geoplanet:8.0.0", "woeplanet:8.0.0"], "meta:indexed": "2020-08-20T20:51:38.471127", "meta:updated": "2020-10-14T11:50:27.107941", "woe:alias_ENG_P": ["Biedenkopf Station"], "woe:hierarchy": {"continent": 24865675, "country": 23424829, "town": 0, "planet": 1, "county": 12596951, "suburb": 0, "state": 2345485, "region": 0, "localadmin": 12632700}, "woe:timezone_id": 28350890, "woe:hash": "u1n1d5g8863t", "woe:centroid": [8.53021, 50.90937], "geom:latitude": 50.90937, "geom:longitude": 8.53021, "geom:hash": "u1n1d5g8863t", "woe:latitude": 50.90937, "geom:centroid": [8.53021, 50.90937], "woe:longitude": 8.53021, "woe:repo": "woeplanet-poi-de", "geom:area": 0.0, "woe:scale": 19}}