{"type": "Feature", "id": 22292309, "geometry": {"type": "Point", "coordinates": [11.344, 50.965759]}, "properties": {"woe:id": 22292309, "woe:parent_id": 704770, "woe:name": "Deutsches Bienenmuseum", "woe:placetype": 20, "woe:placetype_name": "POI", "woe:lang": "GER", "iso:country": "DE", "meta:provider": ["geoplanet:7.3.1", "geoplanet:7.3.2", "geoplanet:7.4.0", "geoplanet:7.4.1", "geoplanet:7.5.1", "geoplanet:7.5.2", "geoplanet:7.6.0", "geoplanet:7.8.1", "geoplanet:7.9.0", "geoplanet:7.10.0", "geoplanet:8.0.0", "woeplanet:8.0.0"], "meta:indexed": "2020-08-20T20:51:43.524105", "meta:updated": "2020-10-14T11:50:59.057537", "woe:hierarchy": {"continent": 24865675, "country": 23424829, "town": 0, "planet": 1, "county": 12597105, "suburb": 0, "state": 2345495, "region": 0, "localadmin": 12624639}, "woe:timezone_id": 28350890, "woe:hash": "u301fnh3n656", "woe:centroid": [11.344, 50.965759], "geom:latitude": 50.965759, "geom:longitude": 11.344, "geom:hash": "u301fnh3n656", "woe:latitude": 50.965759, "geom:centroid": [11.344, 50.965759], "woe:longitude": 11.344, "woe:repo": "woeplanet-poi-de", "geom:area": 0.0, "woe:scale": 19}}