{"type": "Feature", "id": 22197426, "properties": {"woe:id": 22197426, "woe:parent_id": 691129, "woe:name": "S\u00e4ttelst\u00e4dt Bahnhof", "woe:placetype": 20, "woe:placetype_name": "POI", "woe:lang": "GER", "iso:country": "DE", "meta:provider": ["geoplanet:7.3.1", "geoplanet:7.3.2", "geoplanet:7.4.0", "geoplanet:7.4.1", "geoplanet:7.5.1", "geoplanet:7.5.2", "geoplanet:7.6.0", "geoplanet:7.8.1", "geoplanet:7.9.0", "geoplanet:7.10.0", "geoplanet:8.0.0", "woeplanet:8.0.0"], "meta:indexed": "2020-08-20T20:51:39.651493", "meta:updated": "2020-08-22T01:51:39.975424", "woe:alias_ENG_S": ["Sattelstadt Station"], "woe:alias_GER_S": ["Saettelstaedt Bahnhof", "Sattelstadt Bahnhof"], "woe:alias_ENG_P": ["Sattelstadt Station"], "woe:hierarchy": {"continent": 24865675, "country": 23424829, "town": 0, "planet": 1, "county": 12596750, "suburb": 0, "state": 2345495, "region": 0, "localadmin": 12636517}, "woe:timezone_id": 28350890, "woe:hash": "u1p3yd2u7y38", "woe:centroid": [10.48215, 50.94574], "geom:latitude": 50.94574, "geom:longitude": 10.48215, "geom:hash": "u1p3yd2u7y38", "woe:latitude": 50.94574, "geom:centroid": [10.48215, 50.94574], "woe:longitude": 10.48215, "woe:repo": "woeplanet-poi-de"}, "geometry": {"coordinates": [10.48215, 50.94574], "type": "Point"}}