{"type": "Feature", "id": 22286201, "properties": {"woe:id": 22286201, "woe:parent_id": 701910, "woe:name": "Museum Langes Tannen", "woe:placetype": 20, "woe:placetype_name": "POI", "woe:lang": "GER", "iso:country": "DE", "meta:provider": ["geoplanet:7.3.1", "geoplanet:7.3.2", "geoplanet:7.4.0", "geoplanet:7.4.1", "geoplanet:7.5.1", "geoplanet:7.5.2", "geoplanet:7.6.0", "geoplanet:7.8.1", "geoplanet:7.9.0", "geoplanet:7.10.0", "geoplanet:8.0.0", "woeplanet:8.0.0"], "meta:indexed": "2020-08-20T20:51:43.171258", "meta:updated": "2020-08-22T01:51:41.434530", "woe:alias_GER_V": ["Heimatmuseum Langes Tannen"], "woe:hierarchy": {"continent": 24865675, "country": 23424829, "town": 0, "planet": 1, "county": 12596897, "suburb": 0, "state": 2345490, "region": 0, "localadmin": 12632332}, "woe:timezone_id": 28350890, "woe:hash": "u1wcknmux9f1", "woe:centroid": [9.67619, 53.692341], "geom:latitude": 53.692341, "geom:longitude": 9.67619, "geom:hash": "u1wcknmux9f1", "woe:latitude": 53.692341, "geom:centroid": [9.67619, 53.692341], "woe:longitude": 9.67619, "woe:repo": "woeplanet-poi-de"}, "geometry": {"coordinates": [9.67619, 53.692341], "type": "Point"}}