{"type": "Feature", "id": 22152105, "geometry": {"type": "Point", "coordinates": [10.14489, 49.763592]}, "properties": {"woe:id": 22152105, "woe:parent_id": 673512, "woe:name": "Buchbrunn-Mainstockheim Bahnhof", "woe:placetype": 20, "woe:placetype_name": "POI", "woe:lang": "GER", "iso:country": "DE", "meta:provider": ["geoplanet:7.3.1", "geoplanet:7.3.2", "geoplanet:7.4.0", "geoplanet:7.4.1", "geoplanet:7.5.1", "geoplanet:7.5.2", "geoplanet:7.6.0", "geoplanet:7.8.1", "geoplanet:7.9.0", "geoplanet:7.10.0", "geoplanet:8.0.0", "woeplanet:8.0.0"], "meta:indexed": "2020-08-20T20:51:37.863171", "meta:updated": "2020-10-14T11:50:28.002231", "woe:alias_ENG_P": ["Buchbrunn-Mainstockheim Station"], "woe:hierarchy": {"continent": 24865675, "country": 23424829, "town": 0, "planet": 1, "county": 12596761, "suburb": 0, "state": 2345482, "region": 0, "localadmin": 12635566}, "woe:timezone_id": 28350890, "woe:hash": "u0z5ng5mcjfm", "woe:centroid": [10.14489, 49.763592], "geom:latitude": 49.763592, "geom:longitude": 10.14489, "geom:hash": "u0z5ng5mcjfm", "woe:latitude": 49.763592, "geom:centroid": [10.14489, 49.763592], "woe:longitude": 10.14489, "woe:repo": "woeplanet-poi-de", "geom:area": 0.0, "woe:scale": 19}}