{"type": "Feature", "id": 22292363, "geometry": {"type": "Point", "coordinates": [11.34518, 51.01321]}, "properties": {"woe:id": 22292363, "woe:parent_id": 692948, "woe:name": "Schlo\u00df Tiefurt", "woe:placetype": 20, "woe:placetype_name": "POI", "woe:lang": "GER", "iso:country": "DE", "meta:provider": ["geoplanet:7.3.1", "geoplanet:7.3.2", "geoplanet:7.4.0", "geoplanet:7.4.1", "geoplanet:7.5.1", "geoplanet:7.5.2", "geoplanet:7.6.0", "geoplanet:7.8.1", "geoplanet:7.9.0", "geoplanet:7.10.0", "geoplanet:8.0.0", "woeplanet:8.0.0"], "meta:indexed": "2020-08-20T20:51:43.529285", "meta:updated": "2020-10-14T11:50:59.061358", "woe:alias_GER_S": ["Schloss Tiefurt"], "woe:hierarchy": {"continent": 24865675, "country": 23424829, "town": 0, "planet": 1, "county": 12597105, "suburb": 0, "state": 2345495, "region": 0, "localadmin": 12624639}, "woe:timezone_id": 28350890, "woe:hash": "u3044ntm3ze6", "woe:centroid": [11.34518, 51.01321], "geom:latitude": 51.01321, "geom:longitude": 11.34518, "geom:hash": "u3044ntm3ze6", "woe:latitude": 51.01321, "geom:centroid": [11.34518, 51.01321], "woe:longitude": 11.34518, "woe:repo": "woeplanet-poi-de", "geom:area": 0.0, "woe:scale": 19}}