{"type": "Feature", "id": 22287983, "geometry": {"type": "Point", "coordinates": [7.21975, 50.602669]}, "properties": {"woe:id": 22287983, "woe:parent_id": 700608, "woe:name": "Unkel Bahnhof", "woe:placetype": 20, "woe:placetype_name": "POI", "woe:lang": "GER", "iso:country": "DE", "meta:provider": ["geoplanet:7.3.1", "geoplanet:7.3.2", "geoplanet:7.4.0", "geoplanet:7.4.1", "geoplanet:7.5.1", "geoplanet:7.5.2", "geoplanet:7.6.0", "geoplanet:7.8.1", "geoplanet:7.9.0", "geoplanet:7.10.0", "geoplanet:8.0.0", "woeplanet:8.0.0"], "meta:indexed": "2020-08-20T20:51:43.264743", "meta:updated": "2020-10-14T11:50:57.132617", "woe:alias_ENG_P": ["Unkel Station"], "woe:hierarchy": {"continent": 24865675, "country": 23424829, "town": 0, "planet": 1, "county": 12596938, "suburb": 0, "state": 2345488, "region": 0, "localadmin": 12628412}, "woe:timezone_id": 28350890, "woe:hash": "u0vpu7cmbm5y", "woe:centroid": [7.21975, 50.602669], "geom:latitude": 50.602669, "geom:longitude": 7.21975, "geom:hash": "u0vpu7cmbm5y", "woe:latitude": 50.602669, "geom:centroid": [7.21975, 50.602669], "woe:longitude": 7.21975, "woe:repo": "woeplanet-poi-de", "geom:area": 0.0, "woe:scale": 19}}