{"type": "Feature", "id": 22287562, "properties": {"woe:id": 22287562, "woe:parent_id": 700414, "woe:name": "Uelzen Bahnhof", "woe:placetype": 20, "woe:placetype_name": "POI", "woe:lang": "GER", "iso:country": "DE", "meta:provider": ["geoplanet:7.3.1", "geoplanet:7.3.2", "geoplanet:7.4.0", "geoplanet:7.4.1", "geoplanet:7.5.1", "geoplanet:7.5.2", "geoplanet:7.6.0", "geoplanet:7.8.1", "geoplanet:7.9.0", "geoplanet:7.10.0", "geoplanet:8.0.0", "woeplanet:8.0.0"], "meta:indexed": "2020-08-20T20:51:43.248462", "meta:updated": "2020-08-22T01:51:41.469185", "woe:alias_ENG_P": ["Uelzen Station"], "woe:hierarchy": {"continent": 24865675, "country": 23424829, "town": 0, "planet": 1, "county": 12596707, "suburb": 0, "state": 2345486, "region": 0, "localadmin": 12629798}, "woe:timezone_id": 28350890, "woe:hash": "u1rt24y0qtkw", "woe:centroid": [10.5554, 52.96928], "geom:latitude": 52.96928, "geom:longitude": 10.5554, "geom:hash": "u1rt24y0qtkw", "woe:latitude": 52.96928, "geom:centroid": [10.5554, 52.96928], "woe:longitude": 10.5554, "woe:repo": "woeplanet-poi-de"}, "geometry": {"coordinates": [10.5554, 52.96928], "type": "Point"}}