{"type": "Feature", "id": 22262037, "properties": {"woe:id": 22262037, "woe:parent_id": 683326, "woe:name": "Deutsches Weinbaumuseum", "woe:placetype": 20, "woe:placetype_name": "POI", "woe:lang": "GER", "iso:country": "DE", "meta:provider": ["geoplanet:7.3.1", "geoplanet:7.3.2", "geoplanet:7.4.0", "geoplanet:7.4.1", "geoplanet:7.5.1", "geoplanet:7.5.2", "geoplanet:7.6.0", "geoplanet:7.8.1", "geoplanet:7.9.0", "geoplanet:7.10.0", "geoplanet:8.0.0", "woeplanet:8.0.0"], "meta:indexed": "2020-08-20T20:51:42.109663", "meta:updated": "2020-08-22T01:51:40.995584", "woe:hierarchy": {"continent": 24865675, "country": 23424829, "town": 0, "planet": 1, "county": 12597054, "suburb": 0, "state": 2345488, "region": 0, "localadmin": 12627668}, "woe:timezone_id": 28350890, "woe:hash": "u0vgw5hnce43", "woe:centroid": [8.35517, 49.851639], "geom:latitude": 49.851639, "geom:longitude": 8.35517, "geom:hash": "u0vgw5hnce43", "woe:latitude": 49.851639, "geom:centroid": [8.35517, 49.851639], "woe:longitude": 8.35517, "woe:repo": "woeplanet-poi-de"}, "geometry": {"coordinates": [8.35517, 49.851639], "type": "Point"}}