{"type": "Feature", "id": 22182359, "geometry": {"type": "Point", "coordinates": [12.61654, 52.20541]}, "properties": {"woe:id": 22182359, "woe:parent_id": 673196, "woe:name": "L\u00fctte Bahnhof", "woe:placetype": 20, "woe:placetype_name": "POI", "woe:lang": "GER", "iso:country": "DE", "meta:provider": ["geoplanet:7.3.1", "geoplanet:7.3.2", "geoplanet:7.4.0", "geoplanet:7.4.1", "geoplanet:7.5.1", "geoplanet:7.5.2", "geoplanet:7.6.0", "geoplanet:7.8.1", "geoplanet:7.9.0", "geoplanet:7.10.0", "geoplanet:8.0.0", "woeplanet:8.0.0"], "meta:indexed": "2020-08-20T20:51:38.947553", "meta:updated": "2020-10-14T11:50:27.625479", "woe:alias_ENG_S": ["Lutte Station"], "woe:alias_GER_S": ["Luette Bahnhof", "Lutte Bahnhof"], "woe:alias_ENG_P": ["Lutte Station"], "woe:hierarchy": {"continent": 24865675, "country": 23424829, "town": 0, "planet": 1, "county": 12596947, "suburb": 0, "state": 2345491, "region": 0, "localadmin": 24547285}, "woe:timezone_id": 28350890, "woe:hash": "u32bzpend9y0", "woe:centroid": [12.61654, 52.20541], "geom:latitude": 52.20541, "geom:longitude": 12.61654, "geom:hash": "u32bzpend9y0", "woe:latitude": 52.20541, "geom:centroid": [12.61654, 52.20541], "woe:longitude": 12.61654, "woe:repo": "woeplanet-poi-de", "geom:area": 0.0, "woe:scale": 19}}