{"type": "Feature", "id": 22948600, "geometry": {"type": "Point", "coordinates": [9.20053, 48.792259]}, "properties": {"woe:id": 22948600, "woe:parent_id": 698064, "woe:name": "Metzstrasse Bahnhof", "woe:placetype": 20, "woe:placetype_name": "POI", "woe:lang": "GER", "iso:country": "DE", "meta:provider": ["geoplanet:7.3.1", "geoplanet:7.3.2", "geoplanet:7.4.0", "geoplanet:7.4.1", "geoplanet:7.5.1", "geoplanet:7.5.2", "geoplanet:7.6.0", "geoplanet:7.8.1", "geoplanet:7.9.0", "geoplanet:7.10.0", "geoplanet:8.0.0", "woeplanet:8.0.0"], "meta:indexed": "2020-08-20T20:51:44.287854", "meta:updated": "2020-10-14T11:50:29.490871", "woe:alias_ENG_P": ["Metzstrasse Station"], "woe:hierarchy": {"continent": 24865675, "country": 23424829, "town": 0, "planet": 1, "county": 12597071, "suburb": 0, "state": 2345481, "region": 0, "localadmin": 26823268}, "woe:timezone_id": 28350890, "woe:hash": "u0wt967eebk6", "woe:centroid": [9.20053, 48.792259], "geom:latitude": 48.792259, "geom:longitude": 9.20053, "geom:hash": "u0wt967eebk6", "woe:latitude": 48.792259, "geom:centroid": [9.20053, 48.792259], "woe:longitude": 9.20053, "woe:repo": "woeplanet-poi-de", "geom:area": 0.0, "woe:scale": 19}}