{"type": "Feature", "id": 22275195, "geometry": {"type": "Point", "coordinates": [7.11992, 49.35252]}, "properties": {"woe:id": 22275195, "woe:parent_id": 669999, "woe:name": "Landsweiler-Reden Bahnhof", "woe:placetype": 20, "woe:placetype_name": "POI", "woe:lang": "GER", "iso:country": "DE", "meta:provider": ["geoplanet:7.3.1", "geoplanet:7.3.2", "geoplanet:7.4.0", "geoplanet:7.4.1", "geoplanet:7.5.1", "geoplanet:7.5.2", "geoplanet:7.6.0", "geoplanet:7.8.1", "geoplanet:7.9.0", "geoplanet:7.10.0", "geoplanet:8.0.0", "woeplanet:8.0.0"], "meta:indexed": "2020-08-20T20:51:42.699960", "meta:updated": "2020-10-14T11:51:00.161276", "woe:alias_ENG_P": ["Landsweiler-Reden Station"], "woe:hierarchy": {"continent": 24865675, "country": 23424829, "town": 0, "planet": 1, "county": 12597099, "suburb": 0, "state": 2345489, "region": 0, "localadmin": 12627107}, "woe:timezone_id": 28350890, "woe:hash": "u0v0f02e60t1", "woe:centroid": [7.11992, 49.35252], "geom:latitude": 49.35252, "geom:longitude": 7.11992, "geom:hash": "u0v0f02e60t1", "woe:latitude": 49.35252, "geom:centroid": [7.11992, 49.35252], "woe:longitude": 7.11992, "woe:repo": "woeplanet-poi-de", "geom:area": 0.0, "woe:scale": 19}}