{"type": "Feature", "id": 22280904, "properties": {"woe:id": 22280904, "woe:parent_id": 696229, "woe:name": "Stadtoldendorf Bahnhof", "woe:placetype": 20, "woe:placetype_name": "POI", "woe:lang": "GER", "iso:country": "DE", "meta:provider": ["geoplanet:7.3.1", "geoplanet:7.3.2", "geoplanet:7.4.0", "geoplanet:7.4.1", "geoplanet:7.5.1", "geoplanet:7.5.2", "geoplanet:7.6.0", "geoplanet:7.8.1", "geoplanet:7.9.0", "geoplanet:7.10.0", "geoplanet:8.0.0", "woeplanet:8.0.0"], "meta:indexed": "2020-08-20T20:51:43.001069", "meta:updated": "2020-08-22T01:51:41.349535", "woe:alias_ENG_P": ["Stadtoldendorf Station"], "woe:hierarchy": {"continent": 24865675, "country": 23424829, "town": 0, "planet": 1, "county": 12596967, "suburb": 0, "state": 2345486, "region": 0, "localadmin": 12629543}, "woe:timezone_id": 28350890, "woe:hash": "u1nz4utgf5b2", "woe:centroid": [9.62102, 51.880852], "geom:latitude": 51.880852, "geom:longitude": 9.62102, "geom:hash": "u1nz4utgf5b2", "woe:latitude": 51.880852, "geom:centroid": [9.62102, 51.880852], "woe:longitude": 9.62102, "woe:repo": "woeplanet-poi-de"}, "geometry": {"coordinates": [9.62102, 51.880852], "type": "Point"}}