{"type": "Feature", "id": 22978753, "geometry": {"type": "Point", "coordinates": [14.34005, 51.378689]}, "properties": {"woe:id": 22978753, "woe:parent_id": 667676, "woe:name": "Koblenz Bahnhof", "woe:placetype": 20, "woe:placetype_name": "POI", "woe:lang": "GER", "iso:country": "DE", "meta:provider": ["geoplanet:7.3.1", "geoplanet:7.3.2", "geoplanet:7.4.0", "geoplanet:7.4.1", "geoplanet:7.5.1", "geoplanet:7.5.2", "geoplanet:7.6.0", "geoplanet:7.8.1", "geoplanet:7.9.0", "geoplanet:7.10.0", "geoplanet:8.0.0", "woeplanet:8.0.0"], "meta:indexed": "2020-08-20T20:51:44.940878", "meta:updated": "2020-10-14T11:50:29.234120", "woe:alias_ENG_P": ["Koblenz Station"], "woe:hierarchy": {"continent": 24865675, "country": 23424829, "town": 0, "planet": 1, "county": 56448174, "suburb": 0, "state": 2345493, "region": 0, "localadmin": 12625848}, "woe:timezone_id": 28350890, "woe:hash": "u34hq34ne3u6", "woe:centroid": [14.34005, 51.378689], "geom:latitude": 51.378689, "geom:longitude": 14.34005, "geom:hash": "u34hq34ne3u6", "woe:latitude": 51.378689, "geom:centroid": [14.34005, 51.378689], "woe:longitude": 14.34005, "woe:repo": "woeplanet-poi-de", "geom:area": 0.0, "woe:scale": 19}}