{"type": "Feature", "id": 22232919, "geometry": {"type": "Point", "coordinates": [9.18885, 48.867069]}, "properties": {"woe:id": 22232919, "woe:parent_id": 668327, "woe:name": "Schulmuseum Nordw\u00fcrttemberg", "woe:placetype": 20, "woe:placetype_name": "POI", "woe:lang": "GER", "iso:country": "DE", "meta:provider": ["geoplanet:7.3.1", "geoplanet:7.3.2", "geoplanet:7.4.0", "geoplanet:7.4.1", "geoplanet:7.5.1", "geoplanet:7.5.2", "geoplanet:7.6.0", "geoplanet:7.8.1", "geoplanet:7.9.0", "geoplanet:7.10.0", "geoplanet:8.0.0", "woeplanet:8.0.0"], "meta:indexed": "2020-08-20T20:51:41.061740", "meta:updated": "2020-10-14T11:50:58.232478", "woe:alias_GER_S": ["Schulmuseum Nordwuerttemberg", "Schulmuseum Nordwurttemberg"], "woe:hierarchy": {"continent": 24865675, "country": 23424829, "town": 0, "planet": 1, "county": 12596746, "suburb": 0, "state": 2345481, "region": 0, "localadmin": 12623226}, "woe:timezone_id": 28350890, "woe:hash": "u0wtcpgp79zj", "woe:centroid": [9.18885, 48.867069], "geom:latitude": 48.867069, "geom:longitude": 9.18885, "geom:hash": "u0wtcpgp79zj", "woe:latitude": 48.867069, "geom:centroid": [9.18885, 48.867069], "woe:longitude": 9.18885, "woe:repo": "woeplanet-poi-de", "geom:area": 0.0, "woe:scale": 19}}