{"type": "Feature", "id": 22193556, "geometry": {"type": "Point", "coordinates": [6.96549, 51.21624]}, "properties": {"woe:id": 22193556, "woe:parent_id": 660502, "woe:name": "Hochdahl-Millrath Bahnhof", "woe:placetype": 20, "woe:placetype_name": "POI", "woe:lang": "GER", "iso:country": "DE", "meta:provider": ["geoplanet:7.3.1", "geoplanet:7.3.2", "geoplanet:7.4.0", "geoplanet:7.4.1", "geoplanet:7.5.1", "geoplanet:7.5.2", "geoplanet:7.6.0", "geoplanet:7.8.1", "geoplanet:7.9.0", "geoplanet:7.10.0", "geoplanet:8.0.0", "woeplanet:8.0.0"], "meta:indexed": "2020-08-20T20:51:39.500228", "meta:updated": "2020-10-14T11:50:28.063421", "woe:alias_ENG_P": ["Hochdahl-Millrath Station"], "woe:hierarchy": {"continent": 24865675, "country": 23424829, "town": 0, "planet": 1, "county": 12597055, "suburb": 0, "state": 2345487, "region": 0, "localadmin": 12624468}, "woe:timezone_id": 28350890, "woe:hash": "u1hgqe8h5xjg", "woe:centroid": [6.96549, 51.21624], "geom:latitude": 51.21624, "geom:longitude": 6.96549, "geom:hash": "u1hgqe8h5xjg", "woe:latitude": 51.21624, "geom:centroid": [6.96549, 51.21624], "woe:longitude": 6.96549, "woe:repo": "woeplanet-poi-de", "geom:area": 0.0, "woe:scale": 19}}