{"type": "Feature", "id": 22204533, "properties": {"woe:id": 22204533, "woe:parent_id": 667559, "woe:name": "Gevelsberg-Knapp Bahnhof", "woe:placetype": 20, "woe:placetype_name": "POI", "woe:lang": "GER", "iso:country": "DE", "meta:provider": ["geoplanet:7.3.1", "geoplanet:7.3.2", "geoplanet:7.4.0", "geoplanet:7.4.1", "geoplanet:7.5.1", "geoplanet:7.5.2", "geoplanet:7.6.0", "geoplanet:7.8.1", "geoplanet:7.9.0", "geoplanet:7.10.0", "geoplanet:8.0.0", "woeplanet:8.0.0"], "meta:indexed": "2020-08-20T20:51:39.872712", "meta:updated": "2020-08-22T01:51:40.088828", "woe:alias_ENG_P": ["Gevelsberg-Knapp Station"], "woe:hierarchy": {"continent": 24865675, "country": 23424829, "town": 0, "planet": 1, "county": 12596887, "suburb": 0, "state": 2345487, "region": 0, "localadmin": 12624483}, "woe:timezone_id": 28350890, "woe:hash": "u1jhpcs7bmuu", "woe:centroid": [7.37768, 51.33704], "geom:latitude": 51.33704, "geom:longitude": 7.37768, "geom:hash": "u1jhpcs7bmuu", "woe:latitude": 51.33704, "geom:centroid": [7.37768, 51.33704], "woe:longitude": 7.37768, "woe:repo": "woeplanet-poi-de"}, "geometry": {"coordinates": [7.37768, 51.33704], "type": "Point"}}