{"type": "Feature", "id": 22200024, "geometry": {"type": "Point", "coordinates": [13.52523, 50.740978]}, "properties": {"woe:id": 22200024, "woe:parent_id": 677953, "woe:name": "Bienenm\u00fchle Bahnhof", "woe:placetype": 20, "woe:placetype_name": "POI", "woe:lang": "GER", "iso:country": "DE", "meta:provider": ["geoplanet:7.3.1", "geoplanet:7.3.2", "geoplanet:7.4.0", "geoplanet:7.4.1", "geoplanet:7.5.1", "geoplanet:7.5.2", "geoplanet:7.6.0", "geoplanet:7.8.1", "geoplanet:7.9.0", "geoplanet:7.10.0", "geoplanet:8.0.0", "woeplanet:8.0.0"], "meta:indexed": "2020-08-20T20:51:39.691453", "meta:updated": "2020-10-14T11:50:58.218627", "woe:alias_ENG_S": ["Bienenmuhle Station"], "woe:alias_GER_S": ["Bienenmuehle Bahnhof", "Bienenmuhle Bahnhof"], "woe:alias_ENG_P": ["Bienenmuhle Station"], "woe:hierarchy": {"continent": 24865675, "country": 23424829, "town": 0, "planet": 1, "county": 56448168, "suburb": 0, "state": 2345493, "region": 0, "localadmin": 12625597}, "woe:timezone_id": 28350890, "woe:hash": "u318ev0g8ey7", "woe:centroid": [13.52523, 50.740978], "geom:latitude": 50.740978, "geom:longitude": 13.52523, "geom:hash": "u318ev0g8ey7", "woe:latitude": 50.740978, "geom:centroid": [13.52523, 50.740978], "woe:longitude": 13.52523, "woe:repo": "woeplanet-poi-de", "geom:area": 0.0, "woe:scale": 19}}