{"type": "Feature", "id": 22243887, "geometry": {"type": "Point", "coordinates": [10.58184, 47.74559]}, "properties": {"woe:id": 22243887, "woe:parent_id": 689522, "woe:name": "Leuterschach Bahnhof", "woe:placetype": 20, "woe:placetype_name": "POI", "woe:lang": "GER", "iso:country": "DE", "meta:provider": ["geoplanet:7.3.1", "geoplanet:7.3.2", "geoplanet:7.4.0", "geoplanet:7.4.1", "geoplanet:7.5.1", "geoplanet:7.5.2", "geoplanet:7.6.0", "geoplanet:7.8.1", "geoplanet:7.9.0", "geoplanet:7.10.0", "geoplanet:8.0.0", "woeplanet:8.0.0"], "meta:indexed": "2020-08-20T20:51:41.529643", "meta:updated": "2020-10-14T11:50:57.893898", "woe:alias_ENG_P": ["Leuterschach Station"], "woe:hierarchy": {"continent": 24865675, "country": 23424829, "town": 0, "planet": 1, "county": 12596920, "suburb": 0, "state": 2345482, "region": 0, "localadmin": 12634908}, "woe:timezone_id": 28350890, "woe:hash": "u0rx8gc6nxpf", "woe:centroid": [10.58184, 47.74559], "geom:latitude": 47.74559, "geom:longitude": 10.58184, "geom:hash": "u0rx8gc6nxpf", "woe:latitude": 47.74559, "geom:centroid": [10.58184, 47.74559], "woe:longitude": 10.58184, "woe:repo": "woeplanet-poi-de", "geom:area": 0.0, "woe:scale": 19}}