{"type": "Feature", "id": 22156183, "geometry": {"type": "Point", "coordinates": [8.15031, 49.460739]}, "properties": {"woe:id": 22156183, "woe:parent_id": 636411, "woe:name": "Pfalzmuseum F\u00fcr Naturkunde", "woe:placetype": 20, "woe:placetype_name": "POI", "woe:lang": "GER", "iso:country": "DE", "meta:provider": ["geoplanet:7.3.1", "geoplanet:7.3.2", "geoplanet:7.4.0", "geoplanet:7.4.1", "geoplanet:7.5.1", "geoplanet:7.5.2", "geoplanet:7.6.0", "geoplanet:7.8.1", "geoplanet:7.9.0", "geoplanet:7.10.0", "geoplanet:8.0.0", "woeplanet:8.0.0"], "meta:indexed": "2020-08-20T20:51:38.026466", "meta:updated": "2020-10-14T11:50:28.140092", "woe:alias_GER_S": ["Pfalzmuseum Fuer Naturkunde", "Pfalzmuseum Fur Naturkunde"], "woe:hierarchy": {"continent": 24865675, "country": 23424829, "town": 0, "planet": 1, "county": 12596952, "suburb": 0, "state": 2345488, "region": 0, "localadmin": 12627213}, "woe:timezone_id": 28350890, "woe:hash": "u0vc3knceyp8", "woe:centroid": [8.15031, 49.460739], "geom:latitude": 49.460739, "geom:longitude": 8.15031, "geom:hash": "u0vc3knceyp8", "woe:latitude": 49.460739, "geom:centroid": [8.15031, 49.460739], "woe:longitude": 8.15031, "woe:repo": "woeplanet-poi-de", "geom:area": 0.0, "woe:scale": 19}}