{"type": "Feature", "id": 22196024, "geometry": {"type": "Point", "coordinates": [6.81302, 50.65591]}, "properties": {"woe:id": 22196024, "woe:parent_id": 649055, "woe:name": "Zuckerfabrik Bahnhof", "woe:placetype": 20, "woe:placetype_name": "POI", "woe:lang": "GER", "iso:country": "DE", "meta:provider": ["geoplanet:7.3.1", "geoplanet:7.3.2", "geoplanet:7.4.0", "geoplanet:7.4.1", "geoplanet:7.5.1", "geoplanet:7.5.2", "geoplanet:7.6.0", "geoplanet:7.8.1", "geoplanet:7.9.0", "geoplanet:7.10.0", "geoplanet:8.0.0", "woeplanet:8.0.0"], "meta:indexed": "2020-08-20T20:51:39.589870", "meta:updated": "2020-10-14T11:50:28.186014", "woe:alias_ENG_P": ["Zuckerfabrik Station"], "woe:hierarchy": {"continent": 24865675, "country": 23424829, "town": 0, "planet": 1, "county": 12596895, "suburb": 0, "state": 2345487, "region": 0, "localadmin": 12624593}, "woe:timezone_id": 28350890, "woe:hash": "u1hb5j9h4f5c", "woe:centroid": [6.81302, 50.65591], "geom:latitude": 50.65591, "geom:longitude": 6.81302, "geom:hash": "u1hb5j9h4f5c", "woe:latitude": 50.65591, "geom:centroid": [6.81302, 50.65591], "woe:longitude": 6.81302, "woe:repo": "woeplanet-poi-de", "geom:area": 0.0, "woe:scale": 19}}