{"type": "Feature", "id": 22228211, "geometry": {"type": "Point", "coordinates": [14.18908, 51.235909]}, "properties": {"woe:id": 22228211, "woe:parent_id": 684166, "woe:name": "Cisinski-Gedenkst\u00e4tte", "woe:placetype": 20, "woe:placetype_name": "POI", "woe:lang": "GER", "iso:country": "DE", "meta:provider": ["geoplanet:7.3.1", "geoplanet:7.3.2", "geoplanet:7.4.0", "geoplanet:7.4.1", "geoplanet:7.5.1", "geoplanet:7.5.2", "geoplanet:7.6.0", "geoplanet:7.8.1", "geoplanet:7.9.0", "geoplanet:7.10.0", "geoplanet:8.0.0", "woeplanet:8.0.0"], "meta:indexed": "2020-08-20T20:51:40.828677", "meta:updated": "2020-10-14T11:50:58.577952", "woe:alias_GER_S": ["Cisinski-Gedenkstaette", "Cisinski-Gedenkstatte"], "woe:hierarchy": {"continent": 24865675, "country": 23424829, "town": 0, "planet": 1, "county": 56448174, "suburb": 0, "state": 2345493, "region": 0, "localadmin": 12625852}, "woe:timezone_id": 28350890, "woe:hash": "u3456zhnv98y", "woe:centroid": [14.18908, 51.235909], "geom:latitude": 51.235909, "geom:longitude": 14.18908, "geom:hash": "u3456zhnv98y", "woe:latitude": 51.235909, "geom:centroid": [14.18908, 51.235909], "woe:longitude": 14.18908, "woe:repo": "woeplanet-poi-de", "geom:area": 0.0, "woe:scale": 19}}