{"type": "Feature", "id": 56055765, "geometry": {"type": "Point", "coordinates": [12.95619, 48.8288]}, "properties": {"woe:id": 56055765, "woe:parent_id": 643988, "woe:name": "Fachhochschule Deggendorf", "woe:placetype": 20, "woe:placetype_name": "POI", "woe:lang": "GER", "iso:country": "DE", "meta:provider": ["geoplanet:7.3.1", "geoplanet:7.3.2", "geoplanet:7.4.0", "geoplanet:7.4.1", "geoplanet:7.5.1", "geoplanet:7.5.2", "geoplanet:7.6.0", "geoplanet:7.8.1", "geoplanet:7.9.0", "geoplanet:7.10.0", "geoplanet:8.0.0", "woeplanet:8.0.0"], "meta:indexed": "2020-08-20T20:51:45.993637", "meta:updated": "2020-10-14T11:50:35.562535", "woe:hierarchy": {"continent": 24865675, "country": 23424829, "town": 0, "planet": 1, "county": 12596742, "suburb": 0, "state": 2345482, "region": 0, "localadmin": 12622833}, "woe:timezone_id": 28350890, "woe:hash": "u29jyc42mh53", "woe:centroid": [12.95619, 48.8288], "geom:latitude": 48.8288, "geom:longitude": 12.95619, "geom:hash": "u29jyc42mh53", "woe:latitude": 48.8288, "geom:centroid": [12.95619, 48.8288], "woe:longitude": 12.95619, "woe:repo": "woeplanet-poi-de", "geom:area": 0.0, "woe:scale": 19}}