{"type": "Feature", "id": 22270348, "properties": {"woe:id": 22270348, "woe:parent_id": 708651, "woe:name": "Zell-Romrod Bahnhof", "woe:placetype": 20, "woe:placetype_name": "POI", "woe:lang": "GER", "iso:country": "DE", "meta:provider": ["geoplanet:7.3.1", "geoplanet:7.3.2", "geoplanet:7.4.0", "geoplanet:7.4.1", "geoplanet:7.5.1", "geoplanet:7.5.2", "geoplanet:7.6.0", "geoplanet:7.8.1", "geoplanet:7.9.0", "geoplanet:7.10.0", "geoplanet:8.0.0", "woeplanet:8.0.0"], "meta:indexed": "2020-08-20T20:51:42.511698", "meta:updated": "2020-08-22T01:51:41.159436", "woe:alias_ENG_P": ["Zell-Romrod Station"], "woe:hierarchy": {"continent": 24865675, "country": 23424829, "town": 0, "planet": 1, "county": 12596971, "suburb": 0, "state": 2345485, "region": 0, "localadmin": 12632730}, "woe:timezone_id": 28350890, "woe:hash": "u1n896dvp0hb", "woe:centroid": [9.19964, 50.727482], "geom:latitude": 50.727482, "geom:longitude": 9.19964, "geom:hash": "u1n896dvp0hb", "woe:latitude": 50.727482, "geom:centroid": [9.19964, 50.727482], "woe:longitude": 9.19964, "woe:repo": "woeplanet-poi-de"}, "geometry": {"coordinates": [9.19964, 50.727482], "type": "Point"}}