{"type": "Feature", "id": 22274531, "geometry": {"type": "Point", "coordinates": [7.16766, 49.468079]}, "properties": {"woe:id": 22274531, "woe:parent_id": 696123, "woe:name": "Museum St. Wendel", "woe:placetype": 20, "woe:placetype_name": "POI", "woe:lang": "GER", "iso:country": "DE", "meta:provider": ["geoplanet:7.3.1", "geoplanet:7.3.2", "geoplanet:7.4.0", "geoplanet:7.4.1", "geoplanet:7.5.1", "geoplanet:7.5.2", "geoplanet:7.6.0", "geoplanet:7.8.1", "geoplanet:7.9.0", "geoplanet:7.10.0", "geoplanet:8.0.0", "woeplanet:8.0.0"], "meta:indexed": "2020-08-20T20:51:42.653903", "meta:updated": "2020-10-14T11:50:59.627571", "woe:hierarchy": {"continent": 24865675, "country": 23424829, "town": 0, "planet": 1, "county": 12596979, "suburb": 0, "state": 2345489, "region": 0, "localadmin": 12635916}, "woe:timezone_id": 28350890, "woe:hash": "u0v17j7k6w69", "woe:centroid": [7.16766, 49.468079], "geom:latitude": 49.468079, "geom:longitude": 7.16766, "geom:hash": "u0v17j7k6w69", "woe:latitude": 49.468079, "geom:centroid": [7.16766, 49.468079], "woe:longitude": 7.16766, "woe:repo": "woeplanet-poi-de", "geom:area": 0.0, "woe:scale": 19}}