{"type": "Feature", "id": 22220915, "properties": {"woe:id": 22220915, "woe:parent_id": 660599, "woe:name": "H\u00f6chst\u00e4dt an der Donau Bahnhof", "woe:placetype": 20, "woe:placetype_name": "POI", "woe:lang": "GER", "iso:country": "DE", "meta:provider": ["geoplanet:7.3.1", "geoplanet:7.3.2", "geoplanet:7.4.0", "geoplanet:7.4.1", "geoplanet:7.5.1", "geoplanet:7.5.2", "geoplanet:7.6.0", "geoplanet:7.8.1", "geoplanet:7.9.0", "geoplanet:7.10.0", "geoplanet:8.0.0", "woeplanet:8.0.0"], "meta:indexed": "2020-08-20T20:51:40.534967", "meta:updated": "2020-08-22T01:51:40.368847", "woe:alias_ENG_S": ["Hochstadt an der Donau Station"], "woe:alias_GER_S": ["Hoechstaedt an der Donau Bahnhof", "Hochstadt an der Donau Bahnhof"], "woe:alias_ENG_P": ["Hochstadt an der Donau Station"], "woe:hierarchy": {"continent": 24865675, "country": 23424829, "town": 0, "planet": 1, "county": 12596918, "suburb": 0, "state": 2345482, "region": 0, "localadmin": 12636055}, "woe:timezone_id": 28350890, "woe:hash": "u0xs86wm23gt", "woe:centroid": [10.56646, 48.61816], "geom:latitude": 48.61816, "geom:longitude": 10.56646, "geom:hash": "u0xs86wm23gt", "woe:latitude": 48.61816, "geom:centroid": [10.56646, 48.61816], "woe:longitude": 10.56646, "woe:repo": "woeplanet-poi-de"}, "geometry": {"coordinates": [10.56646, 48.61816], "type": "Point"}}