{"type": "Feature", "id": 23007897, "geometry": {"type": "Point", "coordinates": [10.92806, 53.853291]}, "properties": {"woe:id": 23007897, "woe:parent_id": 692868, "woe:name": "Sch\u00f6nberg Bahnhof", "woe:placetype": 20, "woe:placetype_name": "POI", "woe:lang": "GER", "iso:country": "DE", "meta:provider": ["geoplanet:7.3.1", "geoplanet:7.3.2", "geoplanet:7.4.0", "geoplanet:7.4.1", "geoplanet:7.5.1", "geoplanet:7.5.2", "geoplanet:7.6.0", "geoplanet:7.8.1", "geoplanet:7.9.0", "geoplanet:7.10.0", "geoplanet:8.0.0", "woeplanet:8.0.0"], "meta:indexed": "2020-08-20T20:51:45.420392", "meta:updated": "2020-10-14T11:50:26.690268", "woe:alias_ENG_P": ["Schonberg Station"], "woe:alias_GER_S": ["Schoenberg Bahnhof", "Schonberg Bahnhof"], "woe:hierarchy": {"continent": 24865675, "country": 23424829, "town": 0, "planet": 1, "county": 12596988, "suburb": 0, "state": 2345492, "region": 0, "localadmin": 12631079}, "woe:timezone_id": 28350890, "woe:hash": "u1xf2etw4m01", "woe:centroid": [10.92806, 53.853291], "geom:latitude": 53.853291, "geom:longitude": 10.92806, "geom:hash": "u1xf2etw4m01", "woe:latitude": 53.853291, "geom:centroid": [10.92806, 53.853291], "woe:longitude": 10.92806, "woe:repo": "woeplanet-poi-de", "geom:area": 0.0, "woe:scale": 19}}