{"type": "Feature", "id": 22185288, "geometry": {"type": "Point", "coordinates": [7.60792, 51.529671]}, "properties": {"woe:id": 22185288, "woe:parent_id": 645458, "woe:name": "Dortmund-Wickede West Bahnhof", "woe:placetype": 20, "woe:placetype_name": "POI", "woe:lang": "GER", "iso:country": "DE", "meta:provider": ["geoplanet:7.3.1", "geoplanet:7.3.2", "geoplanet:7.4.0", "geoplanet:7.4.1", "geoplanet:7.5.1", "geoplanet:7.5.2", "geoplanet:7.6.0", "geoplanet:7.8.1", "geoplanet:7.9.0", "geoplanet:7.10.0", "geoplanet:8.0.0", "woeplanet:8.0.0"], "meta:indexed": "2020-08-20T20:51:39.117823", "meta:updated": "2020-10-14T11:50:27.370357", "woe:alias_ENG_P": ["Dortmund-Wickede West Station"], "woe:hierarchy": {"continent": 24865675, "country": 23424829, "town": 0, "planet": 1, "county": 12596991, "suburb": 0, "state": 2345487, "region": 0, "localadmin": 26822127}, "woe:timezone_id": 28350890, "woe:hash": "u1jmjheyj6uk", "woe:centroid": [7.60792, 51.529671], "geom:latitude": 51.529671, "geom:longitude": 7.60792, "geom:hash": "u1jmjheyj6uk", "woe:latitude": 51.529671, "geom:centroid": [7.60792, 51.529671], "woe:longitude": 7.60792, "woe:repo": "woeplanet-poi-de", "geom:area": 0.0, "woe:scale": 19}}