{"type": "Feature", "id": 22236006, "geometry": {"type": "Point", "coordinates": [13.74368, 51.47414]}, "properties": {"woe:id": 22236006, "woe:parent_id": 670544, "woe:name": "Lauchhammer-West Bahnhof", "woe:placetype": 20, "woe:placetype_name": "POI", "woe:lang": "GER", "iso:country": "DE", "meta:provider": ["geoplanet:7.3.1", "geoplanet:7.3.2", "geoplanet:7.4.0", "geoplanet:7.4.1", "geoplanet:7.5.1", "geoplanet:7.5.2", "geoplanet:7.6.0", "geoplanet:7.8.1", "geoplanet:7.9.0", "geoplanet:7.10.0", "geoplanet:8.0.0", "woeplanet:8.0.0"], "meta:indexed": "2020-08-20T20:51:41.195456", "meta:updated": "2020-10-14T11:50:59.784051", "woe:alias_ENG_P": ["Lauchhammer-West Station"], "woe:hierarchy": {"continent": 24865675, "country": 23424829, "town": 0, "planet": 1, "county": 12596972, "suburb": 0, "state": 2345491, "region": 0, "localadmin": 12633392}, "woe:timezone_id": 28350890, "woe:hash": "u31ubdxfdgnt", "woe:centroid": [13.74368, 51.47414], "geom:latitude": 51.47414, "geom:longitude": 13.74368, "geom:hash": "u31ubdxfdgnt", "woe:latitude": 51.47414, "geom:centroid": [13.74368, 51.47414], "woe:longitude": 13.74368, "woe:repo": "woeplanet-poi-de", "geom:area": 0.0, "woe:scale": 19}}