{"type": "Feature", "id": 22180485, "geometry": {"type": "Point", "coordinates": [7.32398, 51.52837]}, "properties": {"woe:id": 22180485, "woe:parent_id": 674876, "woe:name": "Castrop-Rauxel-Merklinde Bahnhof", "woe:placetype": 20, "woe:placetype_name": "POI", "woe:lang": "GER", "iso:country": "DE", "meta:provider": ["geoplanet:7.3.1", "geoplanet:7.3.2", "geoplanet:7.4.0", "geoplanet:7.4.1", "geoplanet:7.5.1", "geoplanet:7.5.2", "geoplanet:7.6.0", "geoplanet:7.8.1", "geoplanet:7.9.0", "geoplanet:7.10.0", "geoplanet:8.0.0", "woeplanet:8.0.0"], "meta:indexed": "2020-08-20T20:51:38.864900", "meta:updated": "2020-10-14T11:50:27.016798", "woe:alias_ENG_P": ["Castrop-Rauxel-Merklinde Station"], "woe:hierarchy": {"continent": 24865675, "country": 23424829, "town": 0, "planet": 1, "county": 12596904, "suburb": 0, "state": 2345487, "region": 0, "localadmin": 12624385}, "woe:timezone_id": 28350890, "woe:hash": "u1jjnsmnt077", "woe:centroid": [7.32398, 51.52837], "geom:latitude": 51.52837, "geom:longitude": 7.32398, "geom:hash": "u1jjnsmnt077", "woe:latitude": 51.52837, "geom:centroid": [7.32398, 51.52837], "woe:longitude": 7.32398, "woe:repo": "woeplanet-poi-de", "geom:area": 0.0, "woe:scale": 19}}