{"type": "Feature", "id": 22953375, "geometry": {"type": "Point", "coordinates": [9.72445, 49.545448]}, "properties": {"woe:id": 22953375, "woe:parent_id": 22662212, "woe:name": "K\u00f6nigshofen Bahnhof", "woe:placetype": 20, "woe:placetype_name": "POI", "woe:lang": "GER", "iso:country": "DE", "meta:provider": ["geoplanet:7.3.1", "geoplanet:7.3.2", "geoplanet:7.4.0", "geoplanet:7.4.1", "geoplanet:7.5.1", "geoplanet:7.5.2", "geoplanet:7.6.0", "geoplanet:7.8.1", "geoplanet:7.9.0", "geoplanet:7.10.0", "geoplanet:8.0.0", "woeplanet:8.0.0"], "meta:indexed": "2020-08-20T20:51:44.430356", "meta:updated": "2020-10-14T11:50:28.704206", "woe:alias_ENG_P": ["Konigshofen Station"], "woe:alias_GER_S": ["Koenigshofen Bahnhof", "Konigshofen Bahnhof"], "woe:hierarchy": {"continent": 24865675, "country": 23424829, "town": 0, "planet": 1, "county": 12596849, "suburb": 0, "state": 2345481, "region": 0, "localadmin": 12624190}, "woe:timezone_id": 28350890, "woe:hash": "u0ycv73phhgm", "woe:centroid": [9.72445, 49.545448], "geom:latitude": 49.545448, "geom:longitude": 9.72445, "geom:hash": "u0ycv73phhgm", "woe:latitude": 49.545448, "geom:centroid": [9.72445, 49.545448], "woe:longitude": 9.72445, "woe:repo": "woeplanet-poi-de", "geom:area": 0.0, "woe:scale": 19}}