{"type": "Feature", "id": 23034688, "geometry": {"type": "Point", "coordinates": [7.66927, 51.301521]}, "properties": {"woe:id": 23034688, "woe:parent_id": 634308, "woe:name": "Altena Bahnhof", "woe:placetype": 20, "woe:placetype_name": "POI", "woe:lang": "GER", "iso:country": "DE", "meta:provider": ["geoplanet:7.3.1", "geoplanet:7.3.2", "geoplanet:7.4.0", "geoplanet:7.4.1", "geoplanet:7.5.1", "geoplanet:7.5.2", "geoplanet:7.6.0", "geoplanet:7.8.1", "geoplanet:7.9.0", "geoplanet:7.10.0", "geoplanet:8.0.0", "woeplanet:8.0.0"], "meta:indexed": "2020-08-20T20:51:45.638690", "meta:updated": "2020-10-14T11:50:26.607173", "woe:alias_ENG_P": ["Altena Station"], "woe:hierarchy": {"continent": 24865675, "country": 23424829, "town": 0, "planet": 1, "county": 12596725, "suburb": 0, "state": 2345487, "region": 0, "localadmin": 12624256}, "woe:timezone_id": 28350890, "woe:hash": "u1j7ye0t4bwh", "woe:centroid": [7.66927, 51.301521], "geom:latitude": 51.301521, "geom:longitude": 7.66927, "geom:hash": "u1j7ye0t4bwh", "woe:latitude": 51.301521, "geom:centroid": [7.66927, 51.301521], "woe:longitude": 7.66927, "woe:repo": "woeplanet-poi-de", "geom:area": 0.0, "woe:scale": 19}}