{"type": "Feature", "id": 56055881, "geometry": {"type": "Point", "coordinates": [7.56689, 50.335571]}, "properties": {"woe:id": 56055881, "woe:parent_id": 667675, "woe:name": "Fachhochschule Koblenz (bereich 2)", "woe:placetype": 20, "woe:placetype_name": "POI", "woe:lang": "GER", "iso:country": "DE", "meta:provider": ["geoplanet:7.3.1", "geoplanet:7.3.2", "geoplanet:7.4.0", "geoplanet:7.4.1", "geoplanet:7.5.1", "geoplanet:7.5.2", "geoplanet:7.6.0", "geoplanet:7.8.1", "geoplanet:7.9.0", "geoplanet:7.10.0", "geoplanet:8.0.0", "woeplanet:8.0.0"], "meta:indexed": "2020-08-20T20:51:46.062792", "meta:updated": "2020-10-14T11:50:35.503366", "woe:alias_GER_V": ["Fachhochschule Koblenz"], "woe:hierarchy": {"continent": 24865675, "country": 23424829, "town": 0, "planet": 1, "county": 12597056, "suburb": 0, "state": 2345488, "region": 0, "localadmin": 12627769}, "woe:timezone_id": 28350890, "woe:hash": "u0vqk5q1cqd0", "woe:centroid": [7.56689, 50.335571], "geom:latitude": 50.335571, "geom:longitude": 7.56689, "geom:hash": "u0vqk5q1cqd0", "woe:latitude": 50.335571, "geom:centroid": [7.56689, 50.335571], "woe:longitude": 7.56689, "woe:repo": "woeplanet-poi-de", "geom:area": 0.0, "woe:scale": 19}}