{"type": "Feature", "id": 22187604, "properties": {"woe:id": 22187604, "woe:parent_id": 645877, "woe:name": "Duisburg-Ruhrort Bahnhof", "woe:placetype": 20, "woe:placetype_name": "POI", "woe:lang": "GER", "iso:country": "DE", "meta:provider": ["geoplanet:7.3.1", "geoplanet:7.3.2", "geoplanet:7.4.0", "geoplanet:7.4.1", "geoplanet:7.5.1", "geoplanet:7.5.2", "geoplanet:7.6.0", "geoplanet:7.8.1", "geoplanet:7.9.0", "geoplanet:7.10.0", "geoplanet:8.0.0", "woeplanet:8.0.0"], "meta:indexed": "2020-08-20T20:51:39.235666", "meta:updated": "2020-08-22T01:51:39.765497", "woe:alias_ENG_P": ["Duisburg-Ruhrort Station"], "woe:hierarchy": {"continent": 24865675, "country": 23424829, "town": 0, "planet": 1, "county": 12596956, "suburb": 0, "state": 2345487, "region": 0, "localadmin": 26822215}, "woe:timezone_id": 28350890, "woe:hash": "u1hu9r2zf9de", "woe:centroid": [6.73576, 51.45718], "geom:latitude": 51.45718, "geom:longitude": 6.73576, "geom:hash": "u1hu9r2zf9de", "woe:latitude": 51.45718, "geom:centroid": [6.73576, 51.45718], "woe:longitude": 6.73576, "woe:repo": "woeplanet-poi-de"}, "geometry": {"coordinates": [6.73576, 51.45718], "type": "Point"}}