{"type": "Feature", "id": 22242001, "geometry": {"type": "Point", "coordinates": [8.21402, 49.997742]}, "properties": {"woe:id": 22242001, "woe:parent_id": 673515, "woe:name": "Mainz-Gonsenheim Bahnhof", "woe:placetype": 20, "woe:placetype_name": "POI", "woe:lang": "GER", "iso:country": "DE", "meta:provider": ["geoplanet:7.3.1", "geoplanet:7.3.2", "geoplanet:7.4.0", "geoplanet:7.4.1", "geoplanet:7.5.1", "geoplanet:7.5.2", "geoplanet:7.6.0", "geoplanet:7.8.1", "geoplanet:7.9.0", "geoplanet:7.10.0", "geoplanet:8.0.0", "woeplanet:8.0.0"], "meta:indexed": "2020-08-20T20:51:41.477680", "meta:updated": "2020-10-14T11:50:59.560948", "woe:alias_ENG_P": ["Mainz-Gonsenheim Station"], "woe:hierarchy": {"continent": 24865675, "country": 23424829, "town": 0, "planet": 1, "county": 12597097, "suburb": 0, "state": 2345488, "region": 0, "localadmin": 12627137}, "woe:timezone_id": 28350890, "woe:hash": "u0vu6vv3bw9h", "woe:centroid": [8.21402, 49.997742], "geom:latitude": 49.997742, "geom:longitude": 8.21402, "geom:hash": "u0vu6vv3bw9h", "woe:latitude": 49.997742, "geom:centroid": [8.21402, 49.997742], "woe:longitude": 8.21402, "woe:repo": "woeplanet-poi-de", "geom:area": 0.0, "woe:scale": 19}}