{"type": "Feature", "id": 22262716, "geometry": {"type": "Point", "coordinates": [13.73769, 54.345779]}, "properties": {"woe:id": 22262716, "woe:parent_id": 653094, "woe:name": "M\u00f6nchguter Museum", "woe:placetype": 20, "woe:placetype_name": "POI", "woe:lang": "GER", "iso:country": "DE", "meta:provider": ["geoplanet:7.3.1", "geoplanet:7.3.2", "geoplanet:7.4.0", "geoplanet:7.4.1", "geoplanet:7.5.1", "geoplanet:7.5.2", "geoplanet:7.6.0", "geoplanet:7.8.1", "geoplanet:7.9.0", "geoplanet:7.10.0", "geoplanet:8.0.0", "woeplanet:8.0.0"], "meta:indexed": "2020-08-20T20:51:42.139149", "meta:updated": "2020-10-14T11:50:58.604737", "woe:alias_GER_S": ["Moenchguter Museum", "Monchguter Museum"], "woe:hierarchy": {"continent": 24865675, "country": 23424829, "town": 0, "planet": 1, "county": 12596987, "suburb": 0, "state": 2345492, "region": 0, "localadmin": 12631282}, "woe:timezone_id": 28350890, "woe:hash": "u39v0t77p7kp", "woe:centroid": [13.73769, 54.345779], "geom:latitude": 54.345779, "geom:longitude": 13.73769, "geom:hash": "u39v0t77p7kp", "woe:latitude": 54.345779, "geom:centroid": [13.73769, 54.345779], "woe:longitude": 13.73769, "woe:repo": "woeplanet-poi-de", "geom:area": 0.0, "woe:scale": 19}}