{"type": "Feature", "id": 22978637, "geometry": {"type": "Point", "coordinates": [13.78241, 50.851742]}, "properties": {"woe:id": 22978637, "woe:parent_id": 652738, "woe:name": "Glash\u00fctte Bahnhof", "woe:placetype": 20, "woe:placetype_name": "POI", "woe:lang": "GER", "iso:country": "DE", "meta:provider": ["geoplanet:7.3.1", "geoplanet:7.3.2", "geoplanet:7.4.0", "geoplanet:7.4.1", "geoplanet:7.5.1", "geoplanet:7.5.2", "geoplanet:7.6.0", "geoplanet:7.8.1", "geoplanet:7.9.0", "geoplanet:7.10.0", "geoplanet:8.0.0", "woeplanet:8.0.0"], "meta:indexed": "2020-08-20T20:51:44.937851", "meta:updated": "2020-10-14T11:50:29.154734", "woe:alias_ENG_S": ["Glashutte Station"], "woe:alias_GER_S": ["Glashuette Bahnhof", "Glashutte Bahnhof"], "woe:alias_ENG_P": ["Glashutte Station"], "woe:hierarchy": {"continent": 24865675, "country": 23424829, "town": 0, "planet": 1, "county": 56448172, "suburb": 0, "state": 2345493, "region": 0, "localadmin": 12636491}, "woe:timezone_id": 28350890, "woe:hash": "u31c39k0c7vb", "woe:centroid": [13.78241, 50.851742], "geom:latitude": 50.851742, "geom:longitude": 13.78241, "geom:hash": "u31c39k0c7vb", "woe:latitude": 50.851742, "geom:centroid": [13.78241, 50.851742], "woe:longitude": 13.78241, "woe:repo": "woeplanet-poi-de", "geom:area": 0.0, "woe:scale": 19}}