{"type": "Feature", "id": 22292604, "properties": {"woe:id": 22292604, "woe:parent_id": 20160284, "woe:name": "Wei\u00dfbach Traube Bahnhof", "woe:placetype": 20, "woe:placetype_name": "POI", "woe:lang": "GER", "iso:country": "DE", "meta:provider": ["geoplanet:7.3.1", "geoplanet:7.3.2", "geoplanet:7.4.0", "geoplanet:7.4.1", "geoplanet:7.5.1", "geoplanet:7.5.2", "geoplanet:7.6.0", "geoplanet:7.8.1", "geoplanet:7.9.0", "geoplanet:7.10.0", "geoplanet:8.0.0", "woeplanet:8.0.0"], "meta:indexed": "2020-08-20T20:51:43.549848", "meta:updated": "2020-08-22T01:51:41.614559", "woe:alias_ENG_S": ["Weissbach Traube Station"], "woe:alias_GER_S": ["Weissbach Traube Bahnhof"], "woe:alias_ENG_P": ["Weissbach Traube Station"], "woe:hierarchy": {"continent": 24865675, "country": 23424829, "town": 0, "planet": 1, "county": 12596848, "suburb": 0, "state": 2345481, "region": 0, "localadmin": 12624141}, "woe:timezone_id": 28350890, "woe:hash": "u0yb6nn3sehn", "woe:centroid": [9.58886, 49.295929], "geom:latitude": 49.295929, "geom:longitude": 9.58886, "geom:hash": "u0yb6nn3sehn", "woe:latitude": 49.295929, "geom:centroid": [9.58886, 49.295929], "woe:longitude": 9.58886, "woe:repo": "woeplanet-poi-de"}, "geometry": {"coordinates": [9.58886, 49.295929], "type": "Point"}}