{"type": "Feature", "id": 22299577, "geometry": {"type": "Point", "coordinates": [10.72397, 53.374939]}, "properties": {"woe:id": 22299577, "woe:parent_id": 639975, "woe:name": "Heimatmuseum Boizenburg", "woe:placetype": 20, "woe:placetype_name": "POI", "woe:lang": "GER", "iso:country": "DE", "meta:provider": ["geoplanet:7.3.1", "geoplanet:7.3.2", "geoplanet:7.4.0", "geoplanet:7.4.1", "geoplanet:7.5.1", "geoplanet:7.5.2", "geoplanet:7.6.0", "geoplanet:7.8.1", "geoplanet:7.9.0", "geoplanet:7.10.0", "geoplanet:8.0.0", "woeplanet:8.0.0"], "meta:indexed": "2020-08-20T20:51:43.789898", "meta:updated": "2020-10-14T11:50:58.677357", "woe:hierarchy": {"continent": 24865675, "country": 23424829, "town": 0, "planet": 1, "county": 12596989, "suburb": 0, "state": 2345492, "region": 0, "localadmin": 12630712}, "woe:timezone_id": 28350890, "woe:hash": "u1rxsh8gw9g9", "woe:centroid": [10.72397, 53.374939], "geom:latitude": 53.374939, "geom:longitude": 10.72397, "geom:hash": "u1rxsh8gw9g9", "woe:latitude": 53.374939, "geom:centroid": [10.72397, 53.374939], "woe:longitude": 10.72397, "woe:repo": "woeplanet-poi-de", "geom:area": 0.0, "woe:scale": 19}}