{"type": "Feature", "id": 22153255, "properties": {"woe:id": 22153255, "woe:parent_id": 635067, "woe:name": "Ampfing Bahnhof", "woe:placetype": 20, "woe:placetype_name": "POI", "woe:lang": "GER", "iso:country": "DE", "meta:provider": ["geoplanet:7.3.1", "geoplanet:7.3.2", "geoplanet:7.4.0", "geoplanet:7.4.1", "geoplanet:7.5.1", "geoplanet:7.5.2", "geoplanet:7.6.0", "geoplanet:7.8.1", "geoplanet:7.9.0", "geoplanet:7.10.0", "geoplanet:8.0.0", "woeplanet:8.0.0"], "meta:indexed": "2020-08-20T20:51:37.927276", "meta:updated": "2020-08-22T01:51:39.091593", "woe:alias_ENG_P": ["Ampfing Station"], "woe:hierarchy": {"continent": 24865675, "country": 23424829, "town": 0, "planet": 1, "county": 12596907, "suburb": 0, "state": 2345482, "region": 0, "localadmin": 12622731}, "woe:timezone_id": 28350890, "woe:hash": "u28fd2qkur21", "woe:centroid": [12.41233, 48.254181], "geom:latitude": 48.254181, "geom:longitude": 12.41233, "geom:hash": "u28fd2qkur21", "woe:latitude": 48.254181, "geom:centroid": [12.41233, 48.254181], "woe:longitude": 12.41233, "woe:repo": "woeplanet-poi-de"}, "geometry": {"coordinates": [12.41233, 48.254181], "type": "Point"}}