{"type": "Feature", "id": 22264258, "geometry": {"type": "Point", "coordinates": [10.15951, 48.354771]}, "properties": {"woe:id": 22264258, "woe:parent_id": 684793, "woe:name": "Hermann K\u00f6hl-Museum", "woe:placetype": 20, "woe:placetype_name": "POI", "woe:lang": "GER", "iso:country": "DE", "meta:provider": ["geoplanet:7.3.1", "geoplanet:7.3.2", "geoplanet:7.4.0", "geoplanet:7.4.1", "geoplanet:7.5.1", "geoplanet:7.5.2", "geoplanet:7.6.0", "geoplanet:7.8.1", "geoplanet:7.9.0", "geoplanet:7.10.0", "geoplanet:8.0.0", "woeplanet:8.0.0"], "meta:indexed": "2020-08-20T20:51:42.220334", "meta:updated": "2020-10-14T11:50:58.436842", "woe:alias_GER_S": ["Hermann Koehl-Museum", "Hermann Kohl-Museum"], "woe:hierarchy": {"continent": 24865675, "country": 23424829, "town": 0, "planet": 1, "county": 12597020, "suburb": 0, "state": 2345482, "region": 0, "localadmin": 12634863}, "woe:timezone_id": 28350890, "woe:hash": "u0x5p4tyvwxs", "woe:centroid": [10.15951, 48.354771], "geom:latitude": 48.354771, "geom:longitude": 10.15951, "geom:hash": "u0x5p4tyvwxs", "woe:latitude": 48.354771, "geom:centroid": [10.15951, 48.354771], "woe:longitude": 10.15951, "woe:repo": "woeplanet-poi-de", "geom:area": 0.0, "woe:scale": 19}}