{"type": "Feature", "id": 22292590, "geometry": {"type": "Point", "coordinates": [9.35216, 48.81181]}, "properties": {"woe:id": 22292590, "woe:parent_id": 704842, "woe:name": "Stetten-Beinstein Bahnhof", "woe:placetype": 20, "woe:placetype_name": "POI", "woe:lang": "GER", "iso:country": "DE", "meta:provider": ["geoplanet:7.3.1", "geoplanet:7.3.2", "geoplanet:7.4.0", "geoplanet:7.4.1", "geoplanet:7.5.1", "geoplanet:7.5.2", "geoplanet:7.6.0", "geoplanet:7.8.1", "geoplanet:7.9.0", "geoplanet:7.10.0", "geoplanet:8.0.0", "woeplanet:8.0.0"], "meta:indexed": "2020-08-20T20:51:43.548971", "meta:updated": "2020-10-14T11:50:57.573634", "woe:alias_ENG_P": ["Stetten-Beinstein Station"], "woe:hierarchy": {"continent": 24865675, "country": 23424829, "town": 0, "planet": 1, "county": 12596822, "suburb": 0, "state": 2345481, "region": 0, "localadmin": 12624125}, "woe:timezone_id": 28350890, "woe:hash": "u0wtsvfj3hgu", "woe:centroid": [9.35216, 48.81181], "geom:latitude": 48.81181, "geom:longitude": 9.35216, "geom:hash": "u0wtsvfj3hgu", "woe:latitude": 48.81181, "geom:centroid": [9.35216, 48.81181], "woe:longitude": 9.35216, "woe:repo": "woeplanet-poi-de", "geom:area": 0.0, "woe:scale": 19}}