{"type": "Feature", "id": 22947848, "properties": {"woe:id": 22947848, "woe:parent_id": 703894, "woe:name": "Wangen Bahnhof", "woe:placetype": 20, "woe:placetype_name": "POI", "woe:lang": "GER", "iso:country": "DE", "meta:provider": ["geoplanet:7.3.1", "geoplanet:7.3.2", "geoplanet:7.4.0", "geoplanet:7.4.1", "geoplanet:7.5.1", "geoplanet:7.5.2", "geoplanet:7.6.0", "geoplanet:7.8.1", "geoplanet:7.9.0", "geoplanet:7.10.0", "geoplanet:8.0.0", "woeplanet:8.0.0"], "meta:indexed": "2020-08-20T20:51:44.250525", "meta:updated": "2020-08-22T01:51:41.973612", "woe:alias_ENG_P": ["Wangen Station"], "woe:hierarchy": {"continent": 24865675, "country": 23424829, "town": 0, "planet": 1, "county": 12596733, "suburb": 0, "state": 2345481, "region": 0, "localadmin": 12623832}, "woe:timezone_id": 28350890, "woe:hash": "u0qzr9w397h7", "woe:centroid": [9.83042, 47.689178], "geom:latitude": 47.689178, "geom:longitude": 9.83042, "geom:hash": "u0qzr9w397h7", "woe:latitude": 47.689178, "geom:centroid": [9.83042, 47.689178], "woe:longitude": 9.83042, "woe:repo": "woeplanet-poi-de"}, "geometry": {"coordinates": [9.83042, 47.689178], "type": "Point"}}