{"type": "Feature", "id": 22179468, "properties": {"woe:id": 22179468, "woe:parent_id": 708243, "woe:name": "W\u00fcrgendorf-Ort Bahnhof", "woe:placetype": 20, "woe:placetype_name": "POI", "woe:lang": "GER", "iso:country": "DE", "meta:provider": ["geoplanet:7.3.1", "geoplanet:7.3.2", "geoplanet:7.4.0", "geoplanet:7.4.1", "geoplanet:7.5.1", "geoplanet:7.5.2", "geoplanet:7.6.0", "geoplanet:7.8.1", "geoplanet:7.9.0", "geoplanet:7.10.0", "geoplanet:8.0.0", "woeplanet:8.0.0"], "meta:indexed": "2020-08-20T20:51:38.806618", "meta:updated": "2020-08-22T01:51:39.572046", "woe:alias_ENG_S": ["Wurgendorf-Ort Station"], "woe:alias_GER_S": ["Wuergendorf-Ort Bahnhof", "Wurgendorf-Ort Bahnhof"], "woe:alias_ENG_P": ["Wurgendorf-Ort Station"], "woe:hierarchy": {"continent": 24865675, "country": 23424829, "town": 0, "planet": 1, "county": 12596770, "suburb": 0, "state": 2345487, "region": 0, "localadmin": 12624279}, "woe:timezone_id": 28350890, "woe:hash": "u1jbbbnd6er6", "woe:centroid": [8.12794, 50.75724], "geom:latitude": 50.75724, "geom:longitude": 8.12794, "geom:hash": "u1jbbbnd6er6", "woe:latitude": 50.75724, "geom:centroid": [8.12794, 50.75724], "woe:longitude": 8.12794, "woe:repo": "woeplanet-poi-de"}, "geometry": {"coordinates": [8.12794, 50.75724], "type": "Point"}}