{"type": "Feature", "id": 22979885, "geometry": {"type": "Point", "coordinates": [12.59788, 51.589642]}, "properties": {"woe:id": 22979885, "woe:parent_id": 636410, "woe:name": "Bad D\u00fcben Bahnhof", "woe:placetype": 20, "woe:placetype_name": "POI", "woe:lang": "GER", "iso:country": "DE", "meta:provider": ["geoplanet:7.3.1", "geoplanet:7.3.2", "geoplanet:7.4.0", "geoplanet:7.4.1", "geoplanet:7.5.1", "geoplanet:7.5.2", "geoplanet:7.6.0", "geoplanet:7.8.1", "geoplanet:7.9.0", "geoplanet:7.10.0", "geoplanet:8.0.0", "woeplanet:8.0.0"], "meta:indexed": "2020-08-20T20:51:44.948167", "meta:updated": "2020-10-14T11:50:29.461915", "woe:alias_ENG_S": ["Bad Duben Station"], "woe:alias_GER_S": ["Bad Dueben Bahnhof", "Bad Duben Bahnhof"], "woe:alias_ENG_P": ["Bad Duben Station"], "woe:hierarchy": {"continent": 24865675, "country": 23424829, "town": 0, "planet": 1, "county": 56448170, "suburb": 0, "state": 2345493, "region": 0, "localadmin": 12636575}, "woe:timezone_id": 28350890, "woe:hash": "u30vqxt7ryk1", "woe:centroid": [12.59788, 51.589642], "geom:latitude": 51.589642, "geom:longitude": 12.59788, "geom:hash": "u30vqxt7ryk1", "woe:latitude": 51.589642, "geom:centroid": [12.59788, 51.589642], "woe:longitude": 12.59788, "woe:repo": "woeplanet-poi-de", "geom:area": 0.0, "woe:scale": 19}}