{"type": "Feature", "id": 22273176, "properties": {"woe:id": 22273176, "woe:parent_id": 29348933, "woe:name": "Schafbr\u00fccke Bahnhof", "woe:placetype": 20, "woe:placetype_name": "POI", "woe:lang": "GER", "iso:country": "DE", "meta:provider": ["geoplanet:7.3.1", "geoplanet:7.3.2", "geoplanet:7.4.0", "geoplanet:7.4.1", "geoplanet:7.5.1", "geoplanet:7.5.2", "geoplanet:7.6.0", "geoplanet:7.8.1", "geoplanet:7.9.0", "geoplanet:7.10.0", "geoplanet:8.0.0", "woeplanet:8.0.0"], "meta:indexed": "2020-08-20T20:51:42.611989", "meta:updated": "2020-08-22T01:51:41.199615", "woe:alias_ENG_S": ["Schafbrucke Station"], "woe:alias_GER_S": ["Schafbruecke Bahnhof", "Schafbrucke Bahnhof"], "woe:alias_ENG_P": ["Schafbrucke Station"], "woe:hierarchy": {"continent": 24865675, "country": 23424829, "town": 0, "planet": 1, "county": 12597017, "suburb": 0, "state": 2345489, "region": 0, "localadmin": 26823204}, "woe:timezone_id": 28350890, "woe:hash": "u0v003v0p1mp", "woe:centroid": [7.04941, 49.228371], "geom:latitude": 49.228371, "geom:longitude": 7.04941, "geom:hash": "u0v003v0p1mp", "woe:latitude": 49.228371, "geom:centroid": [7.04941, 49.228371], "woe:longitude": 7.04941, "woe:repo": "woeplanet-poi-de"}, "geometry": {"coordinates": [7.04941, 49.228371], "type": "Point"}}