{"type": "Feature", "id": 22931866, "properties": {"woe:id": 22931866, "woe:parent_id": 646958, "woe:name": "Eichenau Bahnhof", "woe:placetype": 20, "woe:placetype_name": "POI", "woe:lang": "GER", "iso:country": "DE", "meta:provider": ["geoplanet:7.3.1", "geoplanet:7.3.2", "geoplanet:7.4.0", "geoplanet:7.4.1", "geoplanet:7.5.1", "geoplanet:7.5.2", "geoplanet:7.6.0", "geoplanet:7.8.1", "geoplanet:7.9.0", "geoplanet:7.10.0", "geoplanet:8.0.0", "woeplanet:8.0.0"], "meta:indexed": "2020-08-20T20:51:44.018717", "meta:updated": "2020-08-22T01:51:41.864003", "woe:alias_ENG_P": ["Eichenau Station"], "woe:hierarchy": {"continent": 24865675, "country": 23424829, "town": 0, "planet": 1, "county": 12596821, "suburb": 0, "state": 2345482, "region": 0, "localadmin": 12635088}, "woe:timezone_id": 28350890, "woe:hash": "u2841fbbq9jn", "woe:centroid": [11.32822, 48.179218], "geom:latitude": 48.179218, "geom:longitude": 11.32822, "geom:hash": "u2841fbbq9jn", "woe:latitude": 48.179218, "geom:centroid": [11.32822, 48.179218], "woe:longitude": 11.32822, "woe:repo": "woeplanet-poi-de"}, "geometry": {"coordinates": [11.32822, 48.179218], "type": "Point"}}