{"type": "Feature", "id": 22996103, "properties": {"woe:id": 22996103, "woe:parent_id": 639363, "woe:name": "Blankenburg Bahnhof", "woe:placetype": 20, "woe:placetype_name": "POI", "woe:lang": "GER", "iso:country": "DE", "meta:provider": ["geoplanet:7.3.1", "geoplanet:7.3.2", "geoplanet:7.4.0", "geoplanet:7.4.1", "geoplanet:7.5.1", "geoplanet:7.5.2", "geoplanet:7.6.0", "geoplanet:7.8.1", "geoplanet:7.9.0", "geoplanet:7.10.0", "geoplanet:8.0.0", "woeplanet:8.0.0"], "meta:indexed": "2020-08-20T20:51:45.290326", "meta:updated": "2020-08-22T01:51:42.535355", "woe:alias_ENG_P": ["Blankenburg Station"], "woe:hierarchy": {"continent": 24865675, "country": 23424829, "town": 0, "planet": 1, "county": 12596713, "suburb": 0, "state": 2345494, "region": 0, "localadmin": 12635909}, "woe:timezone_id": 28350890, "woe:hash": "u1py9mjv9bqg", "woe:centroid": [10.96135, 51.79599], "geom:latitude": 51.79599, "geom:longitude": 10.96135, "geom:hash": "u1py9mjv9bqg", "woe:latitude": 51.79599, "geom:centroid": [10.96135, 51.79599], "woe:longitude": 10.96135, "woe:repo": "woeplanet-poi-de"}, "geometry": {"coordinates": [10.96135, 51.79599], "type": "Point"}}