{"type": "Feature", "id": 22265817, "properties": {"woe:id": 22265817, "woe:parent_id": 654574, "woe:name": "Gro\u00df Langerwisch Bahnhof", "woe:placetype": 20, "woe:placetype_name": "POI", "woe:lang": "GER", "iso:country": "DE", "meta:provider": ["geoplanet:7.3.1", "geoplanet:7.3.2", "geoplanet:7.4.0", "geoplanet:7.4.1", "geoplanet:7.5.1", "geoplanet:7.5.2", "geoplanet:7.6.0", "geoplanet:7.8.1", "geoplanet:7.9.0", "geoplanet:7.10.0", "geoplanet:8.0.0", "woeplanet:8.0.0"], "meta:indexed": "2020-08-20T20:51:42.287581", "meta:updated": "2020-08-22T01:51:41.069680", "woe:alias_ENG_S": ["Gross Langerwisch Station"], "woe:alias_GER_S": ["Gross Langerwisch Bahnhof"], "woe:alias_ENG_P": ["Gross Langerwisch Station"], "woe:hierarchy": {"continent": 24865675, "country": 23424829, "town": 0, "planet": 1, "county": 12596708, "suburb": 0, "state": 2345491, "region": 0, "localadmin": 24547180}, "woe:timezone_id": 28350890, "woe:hash": "u32w7ps4dp80", "woe:centroid": [12.09054, 53.171551], "geom:latitude": 53.171551, "geom:longitude": 12.09054, "geom:hash": "u32w7ps4dp80", "woe:latitude": 53.171551, "geom:centroid": [12.09054, 53.171551], "woe:longitude": 12.09054, "woe:repo": "woeplanet-poi-de"}, "geometry": {"coordinates": [12.09054, 53.171551], "type": "Point"}}