{"type": "Feature", "id": 22289298, "geometry": {"type": "Point", "coordinates": [12.42557, 53.680882]}, "properties": {"woe:id": 22289298, "woe:parent_id": 670318, "woe:name": "Langhagen Bahnhof", "woe:placetype": 20, "woe:placetype_name": "POI", "woe:lang": "GER", "iso:country": "DE", "meta:provider": ["geoplanet:7.3.1", "geoplanet:7.3.2", "geoplanet:7.4.0", "geoplanet:7.4.1", "geoplanet:7.5.1", "geoplanet:7.5.2", "geoplanet:7.6.0", "geoplanet:7.8.1", "geoplanet:7.9.0", "geoplanet:7.10.0", "geoplanet:8.0.0", "woeplanet:8.0.0"], "meta:indexed": "2020-08-20T20:51:43.354210", "meta:updated": "2020-10-14T11:50:57.204013", "woe:alias_ENG_P": ["Langhagen Station"], "woe:hierarchy": {"continent": 24865675, "country": 23424829, "town": 0, "planet": 1, "county": 12596903, "suburb": 0, "state": 2345492, "region": 0, "localadmin": 12630699}, "woe:timezone_id": 28350890, "woe:hash": "u38c6u21bc8w", "woe:centroid": [12.42557, 53.680882], "geom:latitude": 53.680882, "geom:longitude": 12.42557, "geom:hash": "u38c6u21bc8w", "woe:latitude": 53.680882, "geom:centroid": [12.42557, 53.680882], "woe:longitude": 12.42557, "woe:repo": "woeplanet-poi-de", "geom:area": 0.0, "woe:scale": 19}}