{"type": "Feature", "id": 22268850, "geometry": {"type": "Point", "coordinates": [11.94384, 50.432629]}, "properties": {"woe:id": 22268850, "woe:parent_id": 654283, "woe:name": "Grobau Bahnhof", "woe:placetype": 20, "woe:placetype_name": "POI", "woe:lang": "GER", "iso:country": "DE", "meta:provider": ["geoplanet:7.3.1", "geoplanet:7.3.2", "geoplanet:7.4.0", "geoplanet:7.4.1", "geoplanet:7.5.1", "geoplanet:7.5.2", "geoplanet:7.6.0", "geoplanet:7.8.1", "geoplanet:7.9.0", "geoplanet:7.10.0", "geoplanet:8.0.0", "woeplanet:8.0.0"], "meta:indexed": "2020-08-20T20:51:42.436866", "meta:updated": "2020-10-14T11:50:57.516467", "woe:alias_ENG_P": ["Grobau Station"], "woe:hierarchy": {"continent": 24865675, "country": 23424829, "town": 0, "planet": 1, "county": 22526000, "suburb": 0, "state": 2345493, "region": 0, "localadmin": 12636504}, "woe:timezone_id": 28350890, "woe:hash": "u2bqzucprekw", "woe:centroid": [11.94384, 50.432629], "geom:latitude": 50.432629, "geom:longitude": 11.94384, "geom:hash": "u2bqzucprekw", "woe:latitude": 50.432629, "geom:centroid": [11.94384, 50.432629], "woe:longitude": 11.94384, "woe:repo": "woeplanet-poi-de", "geom:area": 0.0, "woe:scale": 19}}