{"type": "Feature", "id": 22285516, "geometry": {"type": "Point", "coordinates": [13.50168, 50.926262]}, "properties": {"woe:id": 22285516, "woe:parent_id": 667373, "woe:name": "Klingenberg-Colmnitz Bahnhof", "woe:placetype": 20, "woe:placetype_name": "POI", "woe:lang": "GER", "iso:country": "DE", "meta:provider": ["geoplanet:7.3.1", "geoplanet:7.3.2", "geoplanet:7.4.0", "geoplanet:7.4.1", "geoplanet:7.5.1", "geoplanet:7.5.2", "geoplanet:7.6.0", "geoplanet:7.8.1", "geoplanet:7.9.0", "geoplanet:7.10.0", "geoplanet:8.0.0", "woeplanet:8.0.0"], "meta:indexed": "2020-08-20T20:51:43.146605", "meta:updated": "2020-10-14T11:50:59.671185", "woe:alias_ENG_P": ["Klingenberg-Colmnitz Station"], "woe:hierarchy": {"continent": 24865675, "country": 23424829, "town": 0, "planet": 1, "county": 56448172, "suburb": 0, "state": 2345493, "region": 0, "localadmin": 12636485}, "woe:timezone_id": 28350890, "woe:hash": "u319enzdgzq3", "woe:centroid": [13.50168, 50.926262], "geom:latitude": 50.926262, "geom:longitude": 13.50168, "geom:hash": "u319enzdgzq3", "woe:latitude": 50.926262, "geom:centroid": [13.50168, 50.926262], "woe:longitude": 13.50168, "woe:repo": "woeplanet-poi-de", "geom:area": 0.0, "woe:scale": 19}}