{"type": "Feature", "id": 22234727, "properties": {"woe:id": 22234727, "woe:parent_id": 669672, "woe:name": "Kutzenhausen Bahnhof", "woe:placetype": 20, "woe:placetype_name": "POI", "woe:lang": "GER", "iso:country": "DE", "meta:provider": ["geoplanet:7.3.1", "geoplanet:7.3.2", "geoplanet:7.4.0", "geoplanet:7.4.1", "geoplanet:7.5.1", "geoplanet:7.5.2", "geoplanet:7.6.0", "geoplanet:7.8.1", "geoplanet:7.9.0", "geoplanet:7.10.0", "geoplanet:8.0.0", "woeplanet:8.0.0"], "meta:indexed": "2020-08-20T20:51:41.141087", "meta:updated": "2020-08-22T01:51:40.615451", "woe:alias_ENG_P": ["Kutzenhausen Station"], "woe:hierarchy": {"continent": 24865675, "country": 23424829, "town": 0, "planet": 1, "county": 12596778, "suburb": 0, "state": 2345482, "region": 0, "localadmin": 12634776}, "woe:timezone_id": 28350890, "woe:hash": "u0xdgr5f68s4", "woe:centroid": [10.69496, 48.33474], "geom:latitude": 48.33474, "geom:longitude": 10.69496, "geom:hash": "u0xdgr5f68s4", "woe:latitude": 48.33474, "geom:centroid": [10.69496, 48.33474], "woe:longitude": 10.69496, "woe:repo": "woeplanet-poi-de"}, "geometry": {"coordinates": [10.69496, 48.33474], "type": "Point"}}