{"type": "Feature", "id": 22981749, "geometry": {"type": "Point", "coordinates": [8.70147, 50.123051]}, "properties": {"woe:id": 22981749, "woe:parent_id": 650272, "woe:name": "H\u00f6henstrasse Bahnhof", "woe:placetype": 20, "woe:placetype_name": "POI", "woe:lang": "GER", "iso:country": "DE", "meta:provider": ["geoplanet:7.3.1", "geoplanet:7.3.2", "geoplanet:7.4.0", "geoplanet:7.4.1", "geoplanet:7.5.1", "geoplanet:7.5.2", "geoplanet:7.6.0", "geoplanet:7.8.1", "geoplanet:7.9.0", "geoplanet:7.10.0", "geoplanet:8.0.0", "woeplanet:8.0.0"], "meta:indexed": "2020-08-20T20:51:45.025801", "meta:updated": "2020-10-14T11:50:29.257515", "woe:alias_ENG_P": ["Hohenstrasse Station"], "woe:alias_GER_S": ["Hoehenstrasse Bahnhof", "Hohenstrasse Bahnhof"], "woe:hierarchy": {"continent": 24865675, "country": 23424829, "town": 0, "planet": 1, "county": 12597087, "suburb": 0, "state": 2345485, "region": 0, "localadmin": 26822426}, "woe:timezone_id": 28350890, "woe:hash": "u0yjnh85yvym", "woe:centroid": [8.70147, 50.123051], "geom:latitude": 50.123051, "geom:longitude": 8.70147, "geom:hash": "u0yjnh85yvym", "woe:latitude": 50.123051, "geom:centroid": [8.70147, 50.123051], "woe:longitude": 8.70147, "woe:repo": "woeplanet-poi-de", "geom:area": 0.0, "woe:scale": 19}}