{"type": "Feature", "id": 22254176, "geometry": {"type": "Point", "coordinates": [11.3214, 49.520309]}, "properties": {"woe:id": 22254176, "woe:parent_id": 678856, "woe:name": "Neunkirchen am Sand Bahnhof", "woe:placetype": 20, "woe:placetype_name": "POI", "woe:lang": "GER", "iso:country": "DE", "meta:provider": ["geoplanet:7.3.1", "geoplanet:7.3.2", "geoplanet:7.4.0", "geoplanet:7.4.1", "geoplanet:7.5.1", "geoplanet:7.5.2", "geoplanet:7.6.0", "geoplanet:7.8.1", "geoplanet:7.9.0", "geoplanet:7.10.0", "geoplanet:8.0.0", "woeplanet:8.0.0"], "meta:indexed": "2020-08-20T20:51:41.869763", "meta:updated": "2020-10-14T11:50:59.551634", "woe:alias_ENG_P": ["Neunkirchen Am Sand Station"], "woe:hierarchy": {"continent": 24865675, "country": 23424829, "town": 0, "planet": 1, "county": 12596808, "suburb": 0, "state": 2345482, "region": 0, "localadmin": 12636033}, "woe:timezone_id": 28350890, "woe:hash": "u2b19wguxwxt", "woe:centroid": [11.3214, 49.520309], "geom:latitude": 49.520309, "geom:longitude": 11.3214, "geom:hash": "u2b19wguxwxt", "woe:latitude": 49.520309, "geom:centroid": [11.3214, 49.520309], "woe:longitude": 11.3214, "woe:repo": "woeplanet-poi-de", "geom:area": 0.0, "woe:scale": 19}}