{"type": "Feature", "id": 22267686, "properties": {"woe:id": 22267686, "woe:parent_id": 687337, "woe:name": "Wachsziehermuseum Dunzinger", "woe:placetype": 20, "woe:placetype_name": "POI", "woe:lang": "GER", "iso:country": "DE", "meta:provider": ["geoplanet:7.3.1", "geoplanet:7.3.2", "geoplanet:7.4.0", "geoplanet:7.4.1", "geoplanet:7.5.1", "geoplanet:7.5.2", "geoplanet:7.6.0", "geoplanet:7.8.1", "geoplanet:7.9.0", "geoplanet:7.10.0", "geoplanet:8.0.0", "woeplanet:8.0.0"], "meta:indexed": "2020-08-20T20:51:42.386857", "meta:updated": "2020-08-22T01:51:41.110849", "woe:hierarchy": {"continent": 24865675, "country": 23424829, "town": 0, "planet": 1, "county": 20071089, "suburb": 0, "state": 2345482, "region": 0, "localadmin": 12623063}, "woe:timezone_id": 28350890, "woe:hash": "u28wg70ykfws", "woe:centroid": [12.09719, 49.01659], "geom:latitude": 49.01659, "geom:longitude": 12.09719, "geom:hash": "u28wg70ykfws", "woe:latitude": 49.01659, "geom:centroid": [12.09719, 49.01659], "woe:longitude": 12.09719, "woe:repo": "woeplanet-poi-de"}, "geometry": {"coordinates": [12.09719, 49.01659], "type": "Point"}}