{"type": "Feature", "id": 23685990, "geometry": {"type": "Point", "coordinates": [13.3684, 52.508331]}, "properties": {"woe:id": 23685990, "woe:parent_id": 26821854, "woe:name": "Kulturforum", "woe:placetype": 20, "woe:placetype_name": "POI", "woe:lang": "GER", "iso:country": "DE", "meta:provider": ["geoplanet:7.3.1", "geoplanet:7.3.2", "geoplanet:7.4.0", "geoplanet:7.4.1", "geoplanet:7.5.1", "geoplanet:7.5.2", "geoplanet:7.6.0", "geoplanet:7.8.1", "geoplanet:7.9.0", "geoplanet:7.10.0", "geoplanet:8.0.0", "woeplanet:8.0.0"], "meta:indexed": "2020-08-20T20:51:45.742942", "meta:updated": "2020-10-14T11:50:28.373789", "woe:alias_ENG_P": ["Cultural Forum"], "woe:hierarchy": {"continent": 24865675, "country": 23424829, "town": 0, "planet": 1, "county": 12596838, "suburb": 0, "state": 2345496, "region": 0, "localadmin": 26821854}, "woe:timezone_id": 28350890, "woe:hash": "u33d8nye4q3e", "woe:centroid": [13.3684, 52.508331], "geom:latitude": 52.508331, "geom:longitude": 13.3684, "geom:hash": "u33d8nye4q3e", "woe:latitude": 52.508331, "geom:centroid": [13.3684, 52.508331], "woe:longitude": 13.3684, "woe:repo": "woeplanet-poi-de", "geom:area": 0.0, "woe:scale": 19}}