{"type": "Feature", "id": 56055733, "geometry": {"type": "Point", "coordinates": [8.66776, 49.417568]}, "properties": {"woe:id": 56055733, "woe:parent_id": 658421, "woe:name": "Universit\u00e4t Heidelberg", "woe:placetype": 20, "woe:placetype_name": "POI", "woe:lang": "GER", "iso:country": "DE", "meta:provider": ["geoplanet:7.3.1", "geoplanet:7.3.2", "geoplanet:7.4.0", "geoplanet:7.4.1", "geoplanet:7.5.1", "geoplanet:7.5.2", "geoplanet:7.6.0", "geoplanet:7.8.1", "geoplanet:7.9.0", "geoplanet:7.10.0", "geoplanet:8.0.0", "woeplanet:8.0.0"], "meta:indexed": "2020-08-20T20:51:45.965271", "meta:updated": "2020-10-14T11:50:35.568758", "woe:alias_GER_V": ["Universitat Heidelberg"], "woe:hierarchy": {"continent": 24865675, "country": 23424829, "town": 0, "planet": 1, "county": 12597109, "suburb": 0, "state": 2345481, "region": 0, "localadmin": 12623922}, "woe:timezone_id": 28350890, "woe:hash": "u0y1jhpwjqq7", "woe:centroid": [8.66776, 49.417568], "geom:latitude": 49.417568, "geom:longitude": 8.66776, "geom:hash": "u0y1jhpwjqq7", "woe:latitude": 49.417568, "geom:centroid": [8.66776, 49.417568], "woe:longitude": 8.66776, "woe:repo": "woeplanet-poi-de", "geom:area": 0.0, "woe:scale": 19}}