{"type": "Feature", "id": 22258774, "properties": {"woe:id": 22258774, "woe:parent_id": 680979, "woe:name": "Oberdachstetten Bahnhof", "woe:placetype": 20, "woe:placetype_name": "POI", "woe:lang": "GER", "iso:country": "DE", "meta:provider": ["geoplanet:7.3.1", "geoplanet:7.3.2", "geoplanet:7.4.0", "geoplanet:7.4.1", "geoplanet:7.5.1", "geoplanet:7.5.2", "geoplanet:7.6.0", "geoplanet:7.8.1", "geoplanet:7.9.0", "geoplanet:7.10.0", "geoplanet:8.0.0", "woeplanet:8.0.0"], "meta:indexed": "2020-08-20T20:51:42.025515", "meta:updated": "2020-08-22T01:51:40.961791", "woe:alias_ENG_P": ["Oberdachstetten Station"], "woe:hierarchy": {"continent": 24865675, "country": 23424829, "town": 0, "planet": 1, "county": 12596809, "suburb": 0, "state": 2345482, "region": 0, "localadmin": 12634417}, "woe:timezone_id": 28350890, "woe:hash": "u0z3jhm4hc2k", "woe:centroid": [10.42211, 49.418228], "geom:latitude": 49.418228, "geom:longitude": 10.42211, "geom:hash": "u0z3jhm4hc2k", "woe:latitude": 49.418228, "geom:centroid": [10.42211, 49.418228], "woe:longitude": 10.42211, "woe:repo": "woeplanet-poi-de"}, "geometry": {"coordinates": [10.42211, 49.418228], "type": "Point"}}