{"type": "Feature", "id": 22266422, "geometry": {"type": "Point", "coordinates": [13.72791, 51.209759]}, "properties": {"woe:id": 22266422, "woe:parent_id": 686526, "woe:name": "Radeburg Bahnhof", "woe:placetype": 20, "woe:placetype_name": "POI", "woe:lang": "GER", "iso:country": "DE", "meta:provider": ["geoplanet:7.3.1", "geoplanet:7.3.2", "geoplanet:7.4.0", "geoplanet:7.4.1", "geoplanet:7.5.1", "geoplanet:7.5.2", "geoplanet:7.6.0", "geoplanet:7.8.1", "geoplanet:7.9.0", "geoplanet:7.10.0", "geoplanet:8.0.0", "woeplanet:8.0.0"], "meta:indexed": "2020-08-20T20:51:42.326829", "meta:updated": "2020-10-14T11:50:59.616442", "woe:alias_ENG_P": ["Radeburg Station"], "woe:hierarchy": {"continent": 24865675, "country": 23424829, "town": 0, "planet": 1, "county": 56448171, "suburb": 0, "state": 2345493, "region": 0, "localadmin": 12636499}, "woe:timezone_id": 28350890, "woe:hash": "u31g26kq7qzx", "woe:centroid": [13.72791, 51.209759], "geom:latitude": 51.209759, "geom:longitude": 13.72791, "geom:hash": "u31g26kq7qzx", "woe:latitude": 51.209759, "geom:centroid": [13.72791, 51.209759], "woe:longitude": 13.72791, "woe:repo": "woeplanet-poi-de", "geom:area": 0.0, "woe:scale": 19}}