{"type": "Feature", "id": 22285469, "geometry": {"type": "Point", "coordinates": [7.60466, 49.259251]}, "properties": {"woe:id": 22285469, "woe:parent_id": 699023, "woe:name": "Pirmasens Nord Bahnhof", "woe:placetype": 20, "woe:placetype_name": "POI", "woe:lang": "GER", "iso:country": "DE", "meta:provider": ["geoplanet:7.3.1", "geoplanet:7.3.2", "geoplanet:7.4.0", "geoplanet:7.4.1", "geoplanet:7.5.1", "geoplanet:7.5.2", "geoplanet:7.6.0", "geoplanet:7.8.1", "geoplanet:7.9.0", "geoplanet:7.10.0", "geoplanet:8.0.0", "woeplanet:8.0.0"], "meta:indexed": "2020-08-20T20:51:43.144935", "meta:updated": "2020-10-14T11:50:57.487758", "woe:alias_ENG_P": ["Pirmasens Nord Station"], "woe:hierarchy": {"continent": 24865675, "country": 23424829, "town": 0, "planet": 1, "county": 12597026, "suburb": 0, "state": 2345488, "region": 0, "localadmin": 12627734}, "woe:timezone_id": 28350890, "woe:hash": "u0v2jp3ecmvm", "woe:centroid": [7.60466, 49.259251], "geom:latitude": 49.259251, "geom:longitude": 7.60466, "geom:hash": "u0v2jp3ecmvm", "woe:latitude": 49.259251, "geom:centroid": [7.60466, 49.259251], "woe:longitude": 7.60466, "woe:repo": "woeplanet-poi-de", "geom:area": 0.0, "woe:scale": 19}}