{"type": "Feature", "id": 22204194, "geometry": {"type": "Point", "coordinates": [12.58791, 51.353771]}, "properties": {"woe:id": 22204194, "woe:parent_id": 652237, "woe:name": "Gerichshain Bahnhof", "woe:placetype": 20, "woe:placetype_name": "POI", "woe:lang": "GER", "iso:country": "DE", "meta:provider": ["geoplanet:7.3.1", "geoplanet:7.3.2", "geoplanet:7.4.0", "geoplanet:7.4.1", "geoplanet:7.5.1", "geoplanet:7.5.2", "geoplanet:7.6.0", "geoplanet:7.8.1", "geoplanet:7.9.0", "geoplanet:7.10.0", "geoplanet:8.0.0", "woeplanet:8.0.0"], "meta:indexed": "2020-08-20T20:51:39.852736", "meta:updated": "2020-10-14T11:50:58.024515", "woe:alias_ENG_P": ["Gerichshain Station"], "woe:hierarchy": {"continent": 24865675, "country": 23424829, "town": 0, "planet": 1, "county": 56448169, "suburb": 0, "state": 2345493, "region": 0, "localadmin": 12625708}, "woe:timezone_id": 28350890, "woe:hash": "u30unkwjrsf0", "woe:centroid": [12.58791, 51.353771], "geom:latitude": 51.353771, "geom:longitude": 12.58791, "geom:hash": "u30unkwjrsf0", "woe:latitude": 51.353771, "geom:centroid": [12.58791, 51.353771], "woe:longitude": 12.58791, "woe:repo": "woeplanet-poi-de", "geom:area": 0.0, "woe:scale": 19}}