{"type": "Feature", "id": 22208662, "geometry": {"type": "Point", "coordinates": [7.47262, 51.356529]}, "properties": {"woe:id": 22208662, "woe:parent_id": 656385, "woe:name": "Karl-Ernst-Osthaus-Museum", "woe:placetype": 20, "woe:placetype_name": "POI", "woe:lang": "GER", "iso:country": "DE", "meta:provider": ["geoplanet:7.3.1", "geoplanet:7.3.2", "geoplanet:7.4.0", "geoplanet:7.4.1", "geoplanet:7.5.1", "geoplanet:7.5.2", "geoplanet:7.6.0", "geoplanet:7.8.1", "geoplanet:7.9.0", "geoplanet:7.10.0", "geoplanet:8.0.0", "woeplanet:8.0.0"], "meta:indexed": "2020-08-20T20:51:40.140478", "meta:updated": "2020-10-14T11:50:58.568056", "woe:alias_GER_V": ["Karl Ernst Osthaus-Museum", "Osthaus-Museum"], "woe:hierarchy": {"continent": 24865675, "country": 23424829, "town": 0, "planet": 1, "county": 12596856, "suburb": 0, "state": 2345487, "region": 0, "localadmin": 26822479}, "woe:timezone_id": 28350890, "woe:hash": "u1jk4j1mkwvk", "woe:centroid": [7.47262, 51.356529], "geom:latitude": 51.356529, "geom:longitude": 7.47262, "geom:hash": "u1jk4j1mkwvk", "woe:latitude": 51.356529, "geom:centroid": [7.47262, 51.356529], "woe:longitude": 7.47262, "woe:repo": "woeplanet-poi-de", "geom:area": 0.0, "woe:scale": 19}}