{"type": "Feature", "id": 56055793, "geometry": {"type": "Point", "coordinates": [7.87216, 47.988251]}, "properties": {"woe:id": 56055793, "woe:parent_id": 650437, "woe:name": "Staatliche Hochschule F\u00fcr Musik", "woe:placetype": 20, "woe:placetype_name": "POI", "woe:lang": "GER", "iso:country": "DE", "meta:provider": ["geoplanet:7.3.1", "geoplanet:7.3.2", "geoplanet:7.4.0", "geoplanet:7.4.1", "geoplanet:7.5.1", "geoplanet:7.5.2", "geoplanet:7.6.0", "geoplanet:7.8.1", "geoplanet:7.9.0", "geoplanet:7.10.0", "geoplanet:8.0.0", "woeplanet:8.0.0"], "meta:indexed": "2020-08-20T20:51:46.017391", "meta:updated": "2020-10-14T11:50:35.571550", "woe:alias_GER_V": ["Staatliche Hochschule Fur Musik"], "woe:hierarchy": {"continent": 24865675, "country": 23424829, "town": 0, "planet": 1, "county": 12597085, "suburb": 0, "state": 2345481, "region": 0, "localadmin": 12623313}, "woe:timezone_id": 28350890, "woe:hash": "u0t8gpurfd7g", "woe:centroid": [7.87216, 47.988251], "geom:latitude": 47.988251, "geom:longitude": 7.87216, "geom:hash": "u0t8gpurfd7g", "woe:latitude": 47.988251, "geom:centroid": [7.87216, 47.988251], "woe:longitude": 7.87216, "woe:repo": "woeplanet-poi-de", "geom:area": 0.0, "woe:scale": 19}}