{"type": "Feature", "id": 22190425, "geometry": {"type": "Point", "coordinates": [6.81195, 51.198318]}, "properties": {"woe:id": 22190425, "woe:parent_id": 646099, "woe:name": "U Harffstra\u00dfe Bahnhof", "woe:placetype": 20, "woe:placetype_name": "POI", "woe:lang": "GER", "iso:country": "DE", "meta:provider": ["geoplanet:7.3.1", "geoplanet:7.3.2", "geoplanet:7.4.0", "geoplanet:7.4.1", "geoplanet:7.5.1", "geoplanet:7.5.2", "geoplanet:7.6.0", "geoplanet:7.8.1", "geoplanet:7.9.0", "geoplanet:7.10.0", "geoplanet:8.0.0", "woeplanet:8.0.0"], "meta:indexed": "2020-08-20T20:51:39.311085", "meta:updated": "2020-10-14T11:50:27.762251", "woe:alias_ENG_S": ["U Harffstrasse Station"], "woe:alias_GER_S": ["U Harffstrasse Bahnhof"], "woe:alias_ENG_P": ["U Harffstrasse Station"], "woe:hierarchy": {"continent": 24865675, "country": 23424829, "town": 0, "planet": 1, "county": 12596700, "suburb": 0, "state": 2345487, "region": 0, "localadmin": 26822271}, "woe:timezone_id": 28350890, "woe:hash": "u1hg7027cfnp", "woe:centroid": [6.81195, 51.198318], "geom:latitude": 51.198318, "geom:longitude": 6.81195, "geom:hash": "u1hg7027cfnp", "woe:latitude": 51.198318, "geom:centroid": [6.81195, 51.198318], "woe:longitude": 6.81195, "woe:repo": "woeplanet-poi-de", "geom:area": 0.0, "woe:scale": 19}}