{"type": "Feature", "id": 22180400, "geometry": {"type": "Point", "coordinates": [9.05771, 53.768349]}, "properties": {"woe:id": 22180400, "woe:parent_id": 642964, "woe:name": "Cadenberge Bahnhof", "woe:placetype": 20, "woe:placetype_name": "POI", "woe:lang": "GER", "iso:country": "DE", "meta:provider": ["geoplanet:7.3.1", "geoplanet:7.3.2", "geoplanet:7.4.0", "geoplanet:7.4.1", "geoplanet:7.5.1", "geoplanet:7.5.2", "geoplanet:7.6.0", "geoplanet:7.8.1", "geoplanet:7.9.0", "geoplanet:7.10.0", "geoplanet:8.0.0", "woeplanet:8.0.0"], "meta:indexed": "2020-08-20T20:51:38.854920", "meta:updated": "2020-10-14T11:50:27.009136", "woe:alias_ENG_P": ["Cadenberge Station"], "woe:hierarchy": {"continent": 24865675, "country": 23424829, "town": 0, "planet": 1, "county": 12596716, "suburb": 0, "state": 2345486, "region": 0, "localadmin": 12630146}, "woe:timezone_id": 28350890, "woe:hash": "u1w3yh5x7fwp", "woe:centroid": [9.05771, 53.768349], "geom:latitude": 53.768349, "geom:longitude": 9.05771, "geom:hash": "u1w3yh5x7fwp", "woe:latitude": 53.768349, "geom:centroid": [9.05771, 53.768349], "woe:longitude": 9.05771, "woe:repo": "woeplanet-poi-de", "geom:area": 0.0, "woe:scale": 19}}