{"type": "Feature", "id": 23046402, "geometry": {"type": "Point", "coordinates": [7.37781, 51.562092]}, "properties": {"woe:id": 23046402, "woe:parent_id": 26822122, "woe:name": "Dortmund-Nette Bahnhof", "woe:placetype": 20, "woe:placetype_name": "POI", "woe:lang": "GER", "iso:country": "DE", "meta:provider": ["geoplanet:7.3.1", "geoplanet:7.3.2", "geoplanet:7.4.0", "geoplanet:7.4.1", "geoplanet:7.5.1", "geoplanet:7.5.2", "geoplanet:7.6.0", "geoplanet:7.8.1", "geoplanet:7.9.0", "geoplanet:7.10.0", "geoplanet:8.0.0", "woeplanet:8.0.0"], "meta:indexed": "2020-08-20T20:51:45.722528", "meta:updated": "2020-10-14T11:50:26.460756", "woe:alias_ENG_P": ["Dortmund-Nette Station"], "woe:hierarchy": {"continent": 24865675, "country": 23424829, "town": 0, "planet": 1, "county": 12596991, "suburb": 0, "state": 2345487, "region": 0, "localadmin": 26822122}, "woe:timezone_id": 28350890, "woe:hash": "u1jjrfs6gqtg", "woe:centroid": [7.37781, 51.562092], "geom:latitude": 51.562092, "geom:longitude": 7.37781, "geom:hash": "u1jjrfs6gqtg", "woe:latitude": 51.562092, "geom:centroid": [7.37781, 51.562092], "woe:longitude": 7.37781, "woe:repo": "woeplanet-poi-de", "geom:area": 0.0, "woe:scale": 19}}