{"type": "Feature", "id": 22972241, "geometry": {"type": "Point", "coordinates": [14.37918, 52.164848]}, "properties": {"woe:id": 22972241, "woe:parent_id": 655594, "woe:name": "Grunow Bahnhof", "woe:placetype": 20, "woe:placetype_name": "POI", "woe:lang": "GER", "iso:country": "DE", "meta:provider": ["geoplanet:7.3.1", "geoplanet:7.3.2", "geoplanet:7.4.0", "geoplanet:7.4.1", "geoplanet:7.5.1", "geoplanet:7.5.2", "geoplanet:7.6.0", "geoplanet:7.8.1", "geoplanet:7.9.0", "geoplanet:7.10.0", "geoplanet:8.0.0", "woeplanet:8.0.0"], "meta:indexed": "2020-08-20T20:51:44.778435", "meta:updated": "2020-10-14T11:50:28.858124", "woe:alias_ENG_P": ["Grunow Station"], "woe:hierarchy": {"continent": 24865675, "country": 23424829, "town": 0, "planet": 1, "county": 12596901, "suburb": 0, "state": 2345491, "region": 0, "localadmin": 28350200}, "woe:timezone_id": 28350890, "woe:hash": "u360z0qd70mx", "woe:centroid": [14.37918, 52.164848], "geom:latitude": 52.164848, "geom:longitude": 14.37918, "geom:hash": "u360z0qd70mx", "woe:latitude": 52.164848, "geom:centroid": [14.37918, 52.164848], "woe:longitude": 14.37918, "woe:repo": "woeplanet-poi-de", "geom:area": 0.0, "woe:scale": 19}}