{"type": "Feature", "id": 22282163, "properties": {"woe:id": 22282163, "woe:parent_id": 709155, "woe:name": "Z\u00f6rbig Bahnhof", "woe:placetype": 20, "woe:placetype_name": "POI", "woe:lang": "GER", "iso:country": "DE", "meta:provider": ["geoplanet:7.3.1", "geoplanet:7.3.2", "geoplanet:7.4.0", "geoplanet:7.4.1", "geoplanet:7.5.1", "geoplanet:7.5.2", "geoplanet:7.6.0", "geoplanet:7.8.1", "geoplanet:7.9.0", "geoplanet:7.10.0", "geoplanet:8.0.0", "woeplanet:8.0.0"], "meta:indexed": "2020-08-20T20:51:43.054938", "meta:updated": "2020-08-22T01:51:41.374717", "woe:alias_ENG_S": ["Zorbig Station"], "woe:alias_GER_S": ["Zoerbig Bahnhof", "Zorbig Bahnhof"], "woe:alias_ENG_P": ["Zorbig Station"], "woe:hierarchy": {"continent": 24865675, "country": 23424829, "town": 0, "planet": 1, "county": 12597028, "suburb": 0, "state": 2345494, "region": 0, "localadmin": 12625998}, "woe:timezone_id": 28350890, "woe:hash": "u30texpf8p6t", "woe:centroid": [12.11758, 51.630718], "geom:latitude": 51.630718, "geom:longitude": 12.11758, "geom:hash": "u30texpf8p6t", "woe:latitude": 51.630718, "geom:centroid": [12.11758, 51.630718], "woe:longitude": 12.11758, "woe:repo": "woeplanet-poi-de"}, "geometry": {"coordinates": [12.11758, 51.630718], "type": "Point"}}