{"type": "Feature", "id": 22239278, "properties": {"woe:id": 22239278, "woe:parent_id": 672683, "woe:name": "L\u00f6rrach Hauptbahnhof", "woe:placetype": 20, "woe:placetype_name": "POI", "woe:lang": "GER", "iso:country": "DE", "meta:provider": ["geoplanet:7.3.1", "geoplanet:7.3.2", "geoplanet:7.4.0", "geoplanet:7.4.1", "geoplanet:7.5.1", "geoplanet:7.5.2", "geoplanet:7.6.0", "geoplanet:7.8.1", "geoplanet:7.9.0", "geoplanet:7.10.0", "geoplanet:8.0.0", "woeplanet:8.0.0"], "meta:indexed": "2020-08-20T20:51:41.362749", "meta:updated": "2020-08-22T01:51:56.408727", "woe:alias_ENG_S": ["Lorrach Station"], "woe:alias_GER_S": ["Lorrach Bahnhof", "Loerrach Bahnhof"], "woe:alias_ENG_V": ["Lorrach Railway Station", "Lorrach Station"], "woe:alias_ENG_P": ["Lorrach Central Station"], "woe:alias_GER_V": ["Hbf L\u00f6rrach", "Hauptbahnhof L\u00f6rrach", "L\u00f6rrach Hbf"], "woe:hierarchy": {"continent": 24865675, "country": 23424829, "town": 0, "planet": 1, "county": 12596804, "suburb": 0, "state": 2345481, "region": 0, "localadmin": 12623567}, "woe:timezone_id": 28350890, "woe:hash": "u0mqy7vdmzxh", "woe:centroid": [7.66528, 47.6138], "geom:latitude": 47.6138, "geom:longitude": 7.66528, "geom:hash": "u0mqy7vdmzxh", "woe:latitude": 47.6138, "geom:centroid": [7.66528, 47.6138], "woe:longitude": 7.66528, "woe:repo": "woeplanet-poi-de"}, "geometry": {"coordinates": [7.66528, 47.6138], "type": "Point"}}