{"type": "Feature", "id": 22291956, "properties": {"woe:id": 22291956, "woe:parent_id": 704661, "woe:name": "Tauberl\u00e4nder Dorfmuseum", "woe:placetype": 20, "woe:placetype_name": "POI", "woe:lang": "GER", "iso:country": "DE", "meta:provider": ["geoplanet:7.3.1", "geoplanet:7.3.2", "geoplanet:7.4.0", "geoplanet:7.4.1", "geoplanet:7.5.1", "geoplanet:7.5.2", "geoplanet:7.6.0", "geoplanet:7.8.1", "geoplanet:7.9.0", "geoplanet:7.10.0", "geoplanet:8.0.0", "woeplanet:8.0.0"], "meta:indexed": "2020-08-20T20:51:43.508005", "meta:updated": "2020-08-22T01:51:41.595095", "woe:alias_GER_S": ["Tauberlaender Dorfmuseum", "Tauberlander Dorfmuseum"], "woe:hierarchy": {"continent": 24865675, "country": 23424829, "town": 0, "planet": 1, "county": 12596849, "suburb": 0, "state": 2345481, "region": 0, "localadmin": 12624185}, "woe:timezone_id": 28350890, "woe:hash": "u0z13pxm8pqh", "woe:centroid": [9.89766, 49.480659], "geom:latitude": 49.480659, "geom:longitude": 9.89766, "geom:hash": "u0z13pxm8pqh", "woe:latitude": 49.480659, "geom:centroid": [9.89766, 49.480659], "woe:longitude": 9.89766, "woe:repo": "woeplanet-poi-de"}, "geometry": {"coordinates": [9.89766, 49.480659], "type": "Point"}}