{"type": "Feature", "id": 22161399, "geometry": {"type": "Point", "coordinates": [9.4362, 52.323292]}, "properties": {"woe:id": 22161399, "woe:parent_id": 707065, "woe:name": "Winninghausen Bahnhof", "woe:placetype": 20, "woe:placetype_name": "POI", "woe:lang": "GER", "iso:country": "DE", "meta:provider": ["geoplanet:7.3.1", "geoplanet:7.3.2", "geoplanet:7.4.0", "geoplanet:7.4.1", "geoplanet:7.5.1", "geoplanet:7.5.2", "geoplanet:7.6.0", "geoplanet:7.8.1", "geoplanet:7.9.0", "geoplanet:7.10.0", "geoplanet:8.0.0", "woeplanet:8.0.0"], "meta:indexed": "2020-08-20T20:51:38.204996", "meta:updated": "2020-10-14T11:50:28.101518", "woe:alias_ENG_P": ["Winninghausen Station"], "woe:hierarchy": {"continent": 24865675, "country": 23424829, "town": 0, "planet": 1, "county": 20071101, "suburb": 0, "state": 2345486, "region": 0, "localadmin": 12629454}, "woe:timezone_id": 28350890, "woe:hash": "u1q9wtpjr2sd", "woe:centroid": [9.4362, 52.323292], "geom:latitude": 52.323292, "geom:longitude": 9.4362, "geom:hash": "u1q9wtpjr2sd", "woe:latitude": 52.323292, "geom:centroid": [9.4362, 52.323292], "woe:longitude": 9.4362, "woe:repo": "woeplanet-poi-de", "geom:area": 0.0, "woe:scale": 19}}