{"type": "Feature", "id": 22981473, "geometry": {"type": "Point", "coordinates": [8.65555, 50.159271]}, "properties": {"woe:id": 22981473, "woe:parent_id": 650272, "woe:name": "Frankfurt-Eschersheim Bahnhof", "woe:placetype": 20, "woe:placetype_name": "POI", "woe:lang": "GER", "iso:country": "DE", "meta:provider": ["geoplanet:7.3.1", "geoplanet:7.3.2", "geoplanet:7.4.0", "geoplanet:7.4.1", "geoplanet:7.5.1", "geoplanet:7.5.2", "geoplanet:7.6.0", "geoplanet:7.8.1", "geoplanet:7.9.0", "geoplanet:7.10.0", "geoplanet:8.0.0", "woeplanet:8.0.0"], "meta:indexed": "2020-08-20T20:51:44.984497", "meta:updated": "2020-10-14T11:50:28.660556", "woe:alias_ENG_P": ["Frankfurt-Eschersheim Station"], "woe:hierarchy": {"continent": 24865675, "country": 23424829, "town": 0, "planet": 1, "county": 12597087, "suburb": 0, "state": 2345485, "region": 0, "localadmin": 26822408}, "woe:timezone_id": 28350890, "woe:hash": "u0yjkgnybvvf", "woe:centroid": [8.65555, 50.159271], "geom:latitude": 50.159271, "geom:longitude": 8.65555, "geom:hash": "u0yjkgnybvvf", "woe:latitude": 50.159271, "geom:centroid": [8.65555, 50.159271], "woe:longitude": 8.65555, "woe:repo": "woeplanet-poi-de", "geom:area": 0.0, "woe:scale": 19}}