{"type": "Feature", "id": 22244872, "properties": {"woe:id": 22244872, "woe:parent_id": 707594, "woe:name": "W\u00f6lfershausen Bahnhof", "woe:placetype": 20, "woe:placetype_name": "POI", "woe:lang": "GER", "iso:country": "DE", "meta:provider": ["geoplanet:7.3.1", "geoplanet:7.3.2", "geoplanet:7.4.0", "geoplanet:7.4.1", "geoplanet:7.5.1", "geoplanet:7.5.2", "geoplanet:7.6.0", "geoplanet:7.8.1", "geoplanet:7.9.0", "geoplanet:7.10.0", "geoplanet:8.0.0", "woeplanet:8.0.0"], "meta:indexed": "2020-08-20T20:51:41.592025", "meta:updated": "2020-08-22T01:51:40.788541", "woe:alias_ENG_P": ["Wolfershausen Station"], "woe:alias_GER_S": ["Woelfershausen Bahnhof", "Wolfershausen Bahnhof"], "woe:hierarchy": {"continent": 24865675, "country": 23424829, "town": 0, "planet": 1, "county": 12597005, "suburb": 0, "state": 2345495, "region": 0, "localadmin": 12624977}, "woe:timezone_id": 28350890, "woe:hash": "u0zrjxbh87je", "woe:centroid": [10.43703, 50.49258], "geom:latitude": 50.49258, "geom:longitude": 10.43703, "geom:hash": "u0zrjxbh87je", "woe:latitude": 50.49258, "geom:centroid": [10.43703, 50.49258], "woe:longitude": 10.43703, "woe:repo": "woeplanet-poi-de"}, "geometry": {"coordinates": [10.43703, 50.49258], "type": "Point"}}