{"type": "Feature", "id": 22236636, "geometry": {"type": "Point", "coordinates": [10.08483, 52.39164]}, "properties": {"woe:id": 22236636, "woe:parent_id": 635529, "woe:name": "Immensen-Arpke Bahnhof", "woe:placetype": 20, "woe:placetype_name": "POI", "woe:lang": "GER", "iso:country": "DE", "meta:provider": ["geoplanet:7.3.1", "geoplanet:7.3.2", "geoplanet:7.4.0", "geoplanet:7.4.1", "geoplanet:7.5.1", "geoplanet:7.5.2", "geoplanet:7.6.0", "geoplanet:7.8.1", "geoplanet:7.9.0", "geoplanet:7.10.0", "geoplanet:8.0.0", "woeplanet:8.0.0"], "meta:indexed": "2020-08-20T20:51:41.221275", "meta:updated": "2020-10-14T11:50:59.443715", "woe:alias_ENG_P": ["Immensen-Arpke Station"], "woe:hierarchy": {"continent": 24865675, "country": 23424829, "town": 0, "planet": 1, "county": 20071101, "suburb": 0, "state": 2345486, "region": 0, "localadmin": 12629463}, "woe:timezone_id": 28350890, "woe:hash": "u1r4j3xe3td6", "woe:centroid": [10.08483, 52.39164], "geom:latitude": 52.39164, "geom:longitude": 10.08483, "geom:hash": "u1r4j3xe3td6", "woe:latitude": 52.39164, "geom:centroid": [10.08483, 52.39164], "woe:longitude": 10.08483, "woe:repo": "woeplanet-poi-de", "geom:area": 0.0, "woe:scale": 19}}