{"type": "Feature", "id": 22193653, "geometry": {"type": "Point", "coordinates": [10.99609, 49.553829]}, "properties": {"woe:id": 22193653, "woe:parent_id": 647781, "woe:name": "Eltersdorf Bahnhof", "woe:placetype": 20, "woe:placetype_name": "POI", "woe:lang": "GER", "iso:country": "DE", "meta:provider": ["geoplanet:7.3.1", "geoplanet:7.3.2", "geoplanet:7.4.0", "geoplanet:7.4.1", "geoplanet:7.5.1", "geoplanet:7.5.2", "geoplanet:7.6.0", "geoplanet:7.8.1", "geoplanet:7.9.0", "geoplanet:7.10.0", "geoplanet:8.0.0", "woeplanet:8.0.0"], "meta:indexed": "2020-08-20T20:51:39.501061", "meta:updated": "2020-10-14T11:50:27.605022", "woe:alias_ENG_P": ["Eltersdorf Station"], "woe:hierarchy": {"continent": 24865675, "country": 23424829, "town": 0, "planet": 1, "county": 12597023, "suburb": 0, "state": 2345482, "region": 0, "localadmin": 12634383}, "woe:timezone_id": 28350890, "woe:hash": "u0zcfhzpgrqb", "woe:centroid": [10.99609, 49.553829], "geom:latitude": 49.553829, "geom:longitude": 10.99609, "geom:hash": "u0zcfhzpgrqb", "woe:latitude": 49.553829, "geom:centroid": [10.99609, 49.553829], "woe:longitude": 10.99609, "woe:repo": "woeplanet-poi-de", "geom:area": 0.0, "woe:scale": 19}}