{"type": "Feature", "id": 22271841, "properties": {"woe:id": 22271841, "woe:parent_id": 700447, "woe:name": "Uftrungen Bahnhof", "woe:placetype": 20, "woe:placetype_name": "POI", "woe:lang": "GER", "iso:country": "DE", "meta:provider": ["geoplanet:7.3.1", "geoplanet:7.3.2", "geoplanet:7.4.0", "geoplanet:7.4.1", "geoplanet:7.5.1", "geoplanet:7.5.2", "geoplanet:7.6.0", "geoplanet:7.8.1", "geoplanet:7.9.0", "geoplanet:7.10.0", "geoplanet:8.0.0", "woeplanet:8.0.0"], "meta:indexed": "2020-08-20T20:51:42.578417", "meta:updated": "2020-08-22T01:51:41.187066", "woe:alias_ENG_P": ["Uftrungen Station"], "woe:hierarchy": {"continent": 24865675, "country": 23424829, "town": 0, "planet": 1, "county": 12596874, "suburb": 0, "state": 2345494, "region": 0, "localadmin": 12626435}, "woe:timezone_id": 28350890, "woe:hash": "u1pucww5f7wj", "woe:centroid": [10.9727, 51.49633], "geom:latitude": 51.49633, "geom:longitude": 10.9727, "geom:hash": "u1pucww5f7wj", "woe:latitude": 51.49633, "geom:centroid": [10.9727, 51.49633], "woe:longitude": 10.9727, "woe:repo": "woeplanet-poi-de"}, "geometry": {"coordinates": [10.9727, 51.49633], "type": "Point"}}