{"type": "Feature", "id": 22219920, "geometry": {"type": "Point", "coordinates": [9.98061, 52.114491]}, "properties": {"woe:id": 22219920, "woe:parent_id": 646614, "woe:name": "Dom\u00e4ne Marienburg", "woe:placetype": 20, "woe:placetype_name": "POI", "woe:lang": "GER", "iso:country": "DE", "meta:provider": ["geoplanet:7.3.1", "geoplanet:7.3.2", "geoplanet:7.4.0", "geoplanet:7.4.1", "geoplanet:7.5.1", "geoplanet:7.5.2", "geoplanet:7.6.0", "geoplanet:7.8.1", "geoplanet:7.9.0", "geoplanet:7.10.0", "geoplanet:8.0.0", "woeplanet:8.0.0"], "meta:indexed": "2020-08-20T20:51:40.511739", "meta:updated": "2020-10-14T11:50:57.914574", "woe:alias_GER_S": ["Domaene Marienburg", "Domane Marienburg"], "woe:hierarchy": {"continent": 24865675, "country": 23424829, "town": 0, "planet": 1, "county": 12596788, "suburb": 0, "state": 2345486, "region": 0, "localadmin": 26822659}, "woe:timezone_id": 28350890, "woe:hash": "u1r07p5svj4p", "woe:centroid": [9.98061, 52.114491], "geom:latitude": 52.114491, "geom:longitude": 9.98061, "geom:hash": "u1r07p5svj4p", "woe:latitude": 52.114491, "geom:centroid": [9.98061, 52.114491], "woe:longitude": 9.98061, "woe:repo": "woeplanet-poi-de", "geom:area": 0.0, "woe:scale": 19}}