{"type": "Feature", "id": 56055682, "properties": {"woe:id": 56055682, "woe:parent_id": 26821864, "woe:name": "Humboldt-Universit\u00e4t Zu Berlin", "woe:placetype": 20, "woe:placetype_name": "POI", "woe:lang": "GER", "iso:country": "DE", "meta:provider": ["geoplanet:7.3.1", "geoplanet:7.3.2", "geoplanet:7.4.0", "geoplanet:7.4.1", "geoplanet:7.5.1", "geoplanet:7.5.2", "geoplanet:7.6.0", "geoplanet:7.8.1", "geoplanet:7.9.0", "geoplanet:7.10.0", "geoplanet:8.0.0", "woeplanet:8.0.0"], "meta:indexed": "2020-08-20T20:51:45.920881", "meta:updated": "2020-08-22T01:51:42.977394", "woe:alias_GER_V": ["Humboldt-Universitat Zu Berlin"], "woe:hierarchy": {"continent": 24865675, "country": 23424829, "town": 0, "planet": 1, "county": 12596838, "suburb": 0, "state": 2345496, "region": 0, "localadmin": 26821864}, "woe:timezone_id": 28350890, "woe:hash": "u33dbb3pbfbq", "woe:centroid": [13.39374, 52.517368], "geom:latitude": 52.517368, "geom:longitude": 13.39374, "geom:hash": "u33dbb3pbfbq", "woe:latitude": 52.517368, "geom:centroid": [13.39374, 52.517368], "woe:longitude": 13.39374, "woe:repo": "woeplanet-poi-de"}, "geometry": {"coordinates": [13.39374, 52.517368], "type": "Point"}}