{"type": "Feature", "id": 22278724, "properties": {"woe:id": 22278724, "woe:parent_id": 700399, "woe:name": "Uebernthal Bahnhof", "woe:placetype": 20, "woe:placetype_name": "POI", "woe:lang": "GER", "iso:country": "DE", "meta:provider": ["geoplanet:7.3.1", "geoplanet:7.3.2", "geoplanet:7.4.0", "geoplanet:7.4.1", "geoplanet:7.5.1", "geoplanet:7.5.2", "geoplanet:7.6.0", "geoplanet:7.8.1", "geoplanet:7.9.0", "geoplanet:7.10.0", "geoplanet:8.0.0", "woeplanet:8.0.0"], "meta:indexed": "2020-08-20T20:51:42.896180", "meta:updated": "2020-08-22T01:51:41.306175", "woe:alias_ENG_P": ["Uebernthal Station"], "woe:hierarchy": {"continent": 24865675, "country": 23424829, "town": 0, "planet": 1, "county": 12596769, "suburb": 0, "state": 2345485, "region": 0, "localadmin": 12632675}, "woe:timezone_id": 28350890, "woe:hash": "u1jbxc6uvcd4", "woe:centroid": [8.43054, 50.720581], "geom:latitude": 50.720581, "geom:longitude": 8.43054, "geom:hash": "u1jbxc6uvcd4", "woe:latitude": 50.720581, "geom:centroid": [8.43054, 50.720581], "woe:longitude": 8.43054, "woe:repo": "woeplanet-poi-de"}, "geometry": {"coordinates": [8.43054, 50.720581], "type": "Point"}}