{"type": "Feature", "id": 22202982, "properties": {"woe:id": 22202982, "woe:parent_id": 671164, "woe:name": "Lemmie Bahnhof", "woe:placetype": 20, "woe:placetype_name": "POI", "woe:lang": "GER", "iso:country": "DE", "meta:provider": ["geoplanet:7.3.1", "geoplanet:7.3.2", "geoplanet:7.4.0", "geoplanet:7.4.1", "geoplanet:7.5.1", "geoplanet:7.5.2", "geoplanet:7.6.0", "geoplanet:7.8.1", "geoplanet:7.9.0", "geoplanet:7.10.0", "geoplanet:8.0.0", "woeplanet:8.0.0"], "meta:indexed": "2020-08-20T20:51:39.800730", "meta:updated": "2020-08-22T01:51:40.052496", "woe:alias_ENG_P": ["Lemmie Station"], "woe:hierarchy": {"continent": 24865675, "country": 23424829, "town": 0, "planet": 1, "county": 20071101, "suburb": 0, "state": 2345486, "region": 0, "localadmin": 12629458}, "woe:timezone_id": 28350890, "woe:hash": "u1qc6wjx8t7k", "woe:centroid": [9.60963, 52.285252], "geom:latitude": 52.285252, "geom:longitude": 9.60963, "geom:hash": "u1qc6wjx8t7k", "woe:latitude": 52.285252, "geom:centroid": [9.60963, 52.285252], "woe:longitude": 9.60963, "woe:repo": "woeplanet-poi-de"}, "geometry": {"coordinates": [9.60963, 52.285252], "type": "Point"}}