{"type": "Feature", "id": 22227413, "properties": {"woe:id": 22227413, "woe:parent_id": 662401, "woe:name": "Horrem Bahnhof", "woe:placetype": 20, "woe:placetype_name": "POI", "woe:lang": "GER", "iso:country": "DE", "meta:provider": ["geoplanet:7.3.1", "geoplanet:7.3.2", "geoplanet:7.4.0", "geoplanet:7.4.1", "geoplanet:7.5.1", "geoplanet:7.5.2", "geoplanet:7.6.0", "geoplanet:7.8.1", "geoplanet:7.9.0", "geoplanet:7.10.0", "geoplanet:8.0.0", "woeplanet:8.0.0"], "meta:indexed": "2020-08-20T20:51:40.818457", "meta:updated": "2020-08-22T01:51:40.478365", "woe:alias_ENG_P": ["Horrem Station"], "woe:hierarchy": {"continent": 24865675, "country": 23424829, "town": 0, "planet": 1, "county": 12596882, "suburb": 0, "state": 2345487, "region": 0, "localadmin": 12624587}, "woe:timezone_id": 28350890, "woe:hash": "u1hc8v11553p", "woe:centroid": [6.71415, 50.916328], "geom:latitude": 50.916328, "geom:longitude": 6.71415, "geom:hash": "u1hc8v11553p", "woe:latitude": 50.916328, "geom:centroid": [6.71415, 50.916328], "woe:longitude": 6.71415, "woe:repo": "woeplanet-poi-de"}, "geometry": {"coordinates": [6.71415, 50.916328], "type": "Point"}}