{"type": "Feature", "id": 22951911, "geometry": {"type": "Point", "coordinates": [9.57441, 48.80508]}, "properties": {"woe:id": 22951911, "woe:parent_id": 701646, "woe:name": "Urbach Bahnhof", "woe:placetype": 20, "woe:placetype_name": "POI", "woe:lang": "GER", "iso:country": "DE", "meta:provider": ["geoplanet:7.3.1", "geoplanet:7.3.2", "geoplanet:7.4.0", "geoplanet:7.4.1", "geoplanet:7.5.1", "geoplanet:7.5.2", "geoplanet:7.6.0", "geoplanet:7.8.1", "geoplanet:7.9.0", "geoplanet:7.10.0", "geoplanet:8.0.0", "woeplanet:8.0.0"], "meta:indexed": "2020-08-20T20:51:44.411789", "meta:updated": "2020-10-14T11:50:29.183521", "woe:alias_ENG_P": ["Urbach Station"], "woe:hierarchy": {"continent": 24865675, "country": 23424829, "town": 0, "planet": 1, "county": 12596822, "suburb": 0, "state": 2345481, "region": 0, "localadmin": 12624116}, "woe:timezone_id": 28350890, "woe:hash": "u0wv9uey5ymd", "woe:centroid": [9.57441, 48.80508], "geom:latitude": 48.80508, "geom:longitude": 9.57441, "geom:hash": "u0wv9uey5ymd", "woe:latitude": 48.80508, "geom:centroid": [9.57441, 48.80508], "woe:longitude": 9.57441, "woe:repo": "woeplanet-poi-de", "geom:area": 0.0, "woe:scale": 19}}