{"type": "Feature", "id": 22224442, "geometry": {"type": "Point", "coordinates": [13.50908, 53.117378]}, "properties": {"woe:id": 22224442, "woe:parent_id": 698831, "woe:name": "Templin Stadt Bahnhof", "woe:placetype": 20, "woe:placetype_name": "POI", "woe:lang": "GER", "iso:country": "DE", "meta:provider": ["geoplanet:7.3.1", "geoplanet:7.3.2", "geoplanet:7.4.0", "geoplanet:7.4.1", "geoplanet:7.5.1", "geoplanet:7.5.2", "geoplanet:7.6.0", "geoplanet:7.8.1", "geoplanet:7.9.0", "geoplanet:7.10.0", "geoplanet:8.0.0", "woeplanet:8.0.0"], "meta:indexed": "2020-08-20T20:51:40.725068", "meta:updated": "2020-10-14T11:50:58.323689", "woe:alias_ENG_P": ["Templin Stadt Station"], "woe:hierarchy": {"continent": 24865675, "country": 23424829, "town": 0, "planet": 1, "county": 12596890, "suburb": 0, "state": 2345491, "region": 0, "localadmin": 12634174}, "woe:timezone_id": 28350890, "woe:hash": "u33w5mtp0kuj", "woe:centroid": [13.50908, 53.117378], "geom:latitude": 53.117378, "geom:longitude": 13.50908, "geom:hash": "u33w5mtp0kuj", "woe:latitude": 53.117378, "geom:centroid": [13.50908, 53.117378], "woe:longitude": 13.50908, "woe:repo": "woeplanet-poi-de", "geom:area": 0.0, "woe:scale": 19}}