{"type": "Feature", "id": 22240832, "properties": {"woe:id": 22240832, "woe:parent_id": 698748, "woe:name": "Mahn-Und Gedenkst\u00e4tten", "woe:placetype": 20, "woe:placetype_name": "POI", "woe:lang": "GER", "iso:country": "DE", "meta:provider": ["geoplanet:7.3.1", "geoplanet:7.3.2", "geoplanet:7.4.0", "geoplanet:7.4.1", "geoplanet:7.5.1", "geoplanet:7.5.2", "geoplanet:7.6.0", "geoplanet:7.8.1", "geoplanet:7.9.0", "geoplanet:7.10.0", "geoplanet:8.0.0", "woeplanet:8.0.0"], "meta:indexed": "2020-08-20T20:51:41.415032", "meta:updated": "2020-08-22T01:51:40.724512", "woe:alias_GER_S": ["Mahn-Und Gedenkstaetten", "Mahn-Und Gedenkstatten"], "woe:hierarchy": {"continent": 24865675, "country": 23424829, "town": 0, "planet": 1, "county": 12596989, "suburb": 0, "state": 2345492, "region": 0, "localadmin": 12630764}, "woe:timezone_id": 28350890, "woe:hash": "u32pm94qusmz", "woe:centroid": [11.49499, 53.31234], "geom:latitude": 53.31234, "geom:longitude": 11.49499, "geom:hash": "u32pm94qusmz", "woe:latitude": 53.31234, "geom:centroid": [11.49499, 53.31234], "woe:longitude": 11.49499, "woe:repo": "woeplanet-poi-de"}, "geometry": {"coordinates": [11.49499, 53.31234], "type": "Point"}}