{"type": "Feature", "id": 22224118, "geometry": {"type": "Point", "coordinates": [10.44379, 48.399792]}, "properties": {"woe:id": 22224118, "woe:parent_id": 691708, "woe:name": "Jettingen Bahnhof", "woe:placetype": 20, "woe:placetype_name": "POI", "woe:lang": "GER", "iso:country": "DE", "meta:provider": ["geoplanet:7.3.1", "geoplanet:7.3.2", "geoplanet:7.4.0", "geoplanet:7.4.1", "geoplanet:7.5.1", "geoplanet:7.5.2", "geoplanet:7.6.0", "geoplanet:7.8.1", "geoplanet:7.9.0", "geoplanet:7.10.0", "geoplanet:8.0.0", "woeplanet:8.0.0"], "meta:indexed": "2020-08-20T20:51:40.697145", "meta:updated": "2020-10-14T11:50:57.161136", "woe:alias_ENG_P": ["Jettingen Station"], "woe:hierarchy": {"continent": 24865675, "country": 23424829, "town": 0, "planet": 1, "county": 12596910, "suburb": 0, "state": 2345482, "region": 0, "localadmin": 12634836}, "woe:timezone_id": 28350890, "woe:hash": "u0x7mduvjznm", "woe:centroid": [10.44379, 48.399792], "geom:latitude": 48.399792, "geom:longitude": 10.44379, "geom:hash": "u0x7mduvjznm", "woe:latitude": 48.399792, "geom:centroid": [10.44379, 48.399792], "woe:longitude": 10.44379, "woe:repo": "woeplanet-poi-de", "geom:area": 0.0, "woe:scale": 19}}