{"type": "Feature", "id": 22203396, "geometry": {"type": "Point", "coordinates": [7.04164, 51.58445]}, "properties": {"woe:id": 22203396, "woe:parent_id": 29349204, "woe:name": "Gelsenkirchen-Buer Nord Bahnhof", "woe:placetype": 20, "woe:placetype_name": "POI", "woe:lang": "GER", "iso:country": "DE", "meta:provider": ["geoplanet:7.3.1", "geoplanet:7.3.2", "geoplanet:7.4.0", "geoplanet:7.4.1", "geoplanet:7.5.1", "geoplanet:7.5.2", "geoplanet:7.6.0", "geoplanet:7.8.1", "geoplanet:7.9.0", "geoplanet:7.10.0", "geoplanet:8.0.0", "woeplanet:8.0.0"], "meta:indexed": "2020-08-20T20:51:39.816307", "meta:updated": "2020-10-14T11:50:58.320693", "woe:alias_ENG_P": ["Gelsenkirchen-Buer Nord Station"], "woe:hierarchy": {"continent": 24865675, "country": 23424829, "town": 0, "planet": 1, "county": 12597080, "suburb": 0, "state": 2345487, "region": 0, "localadmin": 26822453}, "woe:timezone_id": 28350890, "woe:hash": "u1jj2nxt4n7q", "woe:centroid": [7.04164, 51.58445], "geom:latitude": 51.58445, "geom:longitude": 7.04164, "geom:hash": "u1jj2nxt4n7q", "woe:latitude": 51.58445, "geom:centroid": [7.04164, 51.58445], "woe:longitude": 7.04164, "woe:repo": "woeplanet-poi-de", "geom:area": 0.0, "woe:scale": 19}}