{"type": "Feature", "id": 22970562, "properties": {"woe:id": 22970562, "woe:parent_id": 693156, "woe:name": "Sch\u00f6nwalde Bahnhof", "woe:placetype": 20, "woe:placetype_name": "POI", "woe:lang": "GER", "iso:country": "DE", "meta:provider": ["geoplanet:7.3.1", "geoplanet:7.3.2", "geoplanet:7.4.0", "geoplanet:7.4.1", "geoplanet:7.5.1", "geoplanet:7.5.2", "geoplanet:7.6.0", "geoplanet:7.8.1", "geoplanet:7.9.0", "geoplanet:7.10.0", "geoplanet:8.0.0", "woeplanet:8.0.0"], "meta:indexed": "2020-08-20T20:51:44.737097", "meta:updated": "2020-08-22T01:51:42.219345", "woe:alias_ENG_P": ["Schonwalde Station"], "woe:alias_GER_S": ["Schoenwalde Bahnhof", "Schonwalde Bahnhof"], "woe:hierarchy": {"continent": 24865675, "country": 23424829, "town": 0, "planet": 1, "county": 12596993, "suburb": 0, "state": 2345491, "region": 0, "localadmin": 24547209}, "woe:timezone_id": 28350890, "woe:hash": "u31zc88j9s84", "woe:centroid": [13.77692, 51.99102], "geom:latitude": 51.99102, "geom:longitude": 13.77692, "geom:hash": "u31zc88j9s84", "woe:latitude": 51.99102, "geom:centroid": [13.77692, 51.99102], "woe:longitude": 13.77692, "woe:repo": "woeplanet-poi-de"}, "geometry": {"coordinates": [13.77692, 51.99102], "type": "Point"}}