{"type": "Feature", "id": 23010093, "geometry": {"type": "Point", "coordinates": [10.42716, 52.456291]}, "properties": {"woe:id": 23010093, "woe:parent_id": 670997, "woe:name": "Leiferde Bahnhof", "woe:placetype": 20, "woe:placetype_name": "POI", "woe:lang": "GER", "iso:country": "DE", "meta:provider": ["geoplanet:7.3.1", "geoplanet:7.3.2", "geoplanet:7.4.0", "geoplanet:7.4.1", "geoplanet:7.5.1", "geoplanet:7.5.2", "geoplanet:7.6.0", "geoplanet:7.8.1", "geoplanet:7.9.0", "geoplanet:7.10.0", "geoplanet:8.0.0", "woeplanet:8.0.0"], "meta:indexed": "2020-08-20T20:51:45.443354", "meta:updated": "2020-10-14T11:50:26.517336", "woe:alias_ENG_P": ["Leiferde Station"], "woe:hierarchy": {"continent": 24865675, "country": 23424829, "town": 0, "planet": 1, "county": 12596827, "suburb": 0, "state": 2345486, "region": 0, "localadmin": 12630294}, "woe:timezone_id": 28350890, "woe:hash": "u1r6mm2u43qh", "woe:centroid": [10.42716, 52.456291], "geom:latitude": 52.456291, "geom:longitude": 10.42716, "geom:hash": "u1r6mm2u43qh", "woe:latitude": 52.456291, "geom:centroid": [10.42716, 52.456291], "woe:longitude": 10.42716, "woe:repo": "woeplanet-poi-de", "geom:area": 0.0, "woe:scale": 19}}